Workbook
Name \0: #REF!
Name \0: #REF!
Name \1: #REF!
Name \1: #REF!
Name \a: #REF!
Name \a: #REF!
Name \AA: #REF!
Name \b: #REF!
Name \C: #REF!
Name \d: #N/A
Name \e: #N/A
Name \f: #N/A
Name \g: #N/A
Name \H: #REF!
Name \H: #REF!
Name \i: #N/A
Name \j: #N/A
Name \k: #N/A
Name \KWS123: #N/A
Name \M: #REF!
Name \M: #REF!
Name \N: #REF!
Name \N: #REF!
Name \nbvf: #REF!
Name \P: #REF!
Name \P: #REF!
Name \R: #REF!
Name \R: #REF!
Name \s: #REF!
Name \s: #REF!
Name \t: #N/A
Name \U: #REF!
Name \V: #REF!
Name \x: #REF!
Name \x: #REF!
Name \z: #REF!
Name _: #REF!
Name _: #REF!
Name ____________________________________________________________________sw1: #REF!
Name ____________________________________________________________________sw1: #REF!
Name ____________________________________________________________________sw2: #REF!
Name ____________________________________________________________________sw2: #REF!
Name ____________________________________________________________________sw3: #REF!
Name ____________________________________________________________________sw3: #REF!
Name ____________________________________________________________________sw4: #REF!
Name ____________________________________________________________________sw5: #REF!
Name ____________________________________________________________________sw6: #REF!
Name ____________________________________________________________________sw7: #REF!
Name ____________________________________________________________________sw8: #REF!
Name ___________________________________________________________________sw1: #REF!
Name ___________________________________________________________________sw2: #REF!
Name ___________________________________________________________________sw3: #REF!
Name ___________________________________________________________________sw4: #REF!
Name ___________________________________________________________________sw5: #REF!
Name ___________________________________________________________________sw6: #REF!
Name ___________________________________________________________________sw7: #REF!
Name ___________________________________________________________________sw8: #REF!
Name __________________________________________________________________sw1: #REF!
Name __________________________________________________________________sw2: #REF!
Name __________________________________________________________________sw3: #REF!

Sheet Cover Page
C10: Bakreswar FSPV Financial Model- DPR

Sheet RA
A1: PVSyst File | L1: SolarGIS
B2: GlobHor | C2: DiffHor | D2: T_Amb | E2: GlobInc | F2: GlobEff | G2: EArray | H2: E_Grid
B3: kWh/m² | C3: kWh/m² | D3: °C | E3: kWh/m² | F3: kWh/m² | G3: MWh | H3: MWh | I3: PR | J3: Capacity (MW) | K3: Days | L3: CUF
A4: January | B4: 121.6 | C4: 63.7 | D4: 17.1 | E4: 129.4 | F4: 120.5 | G4: 26234 | H4: 24195 | I4: 0.767 | J4: 180.418 | K4: 31 | L4: =H4/J4/(24*K4) -> 0.18024898
A5: February | B5: 137.5 | C5: 61.8 | D5: 21 | E5: 144.6 | F5: 135.4 | G5: 29173 | H5: 28629 | I5: 0.812 | J5: =J4 -> 180.418 | K5: 28 | L5: =H5/J5/(24*K5) -> 0.23613319
A6: March | B6: 182.8 | C6: 77.6 | D6: 26.1 | E6: 188.7 | F6: 177.3 | G6: 37507 | H6: 36770 | I6: 0.799 | J6: =J5 -> 180.418 | K6: 31 | L6: =H6/J6/(24*K6) -> 0.27393078
A7: April | B7: 189.6 | C7: 87.2 | D7: 29.9 | E7: 191.9 | F7: 180.4 | G7: 37626 | H7: 36889 | I7: 0.788 | J7: =J6 -> 180.418 | K7: 30 | L7: =H7/J7/(24*K7) -> 0.28397789
A8: May | B8: 182.3 | C8: 101.1 | D8: 30.7 | E8: 181.9 | F8: 170.6 | G8: 35441 | H8: 34791 | I8: 0.784 | J8: =J7 -> 180.418 | K8: 31 | L8: =H8/J8/(24*K8) -> 0.25918754
A9: June | B9: 150.3 | C9: 95.4 | D9: 30.3 | E9: 149 | F9: 139.3 | G9: 28999 | H9: 28494 | I9: 0.784 | J9: =J8 -> 180.418 | K9: 30 | L9: =H9/J9/(24*K9) -> 0.21935173
A10: July | B10: 139.5 | C10: 91.3 | D10: 29.1 | E10: 138.7 | F10: 129.6 | G10: 27101 | H10: 26626 | I10: 0.787 | J10: =J9 -> 180.418 | K10: 31 | L10: =H10/J10/(24*K10) -> 0.19835956
A11: August | B11: 143.4 | C11: 89.7 | D11: 29 | E11: 143.9 | F11: 134.6 | G11: 28175 | H11: 27673 | I11: 0.789 | J11: =J10 -> 180.418 | K11: 31 | L11: =H11/J11/(24*K11) -> 0.20615954
A12: September | B12: 135.7 | C12: 80.1 | D12: 28.5 | E12: 137.9 | F12: 129.1 | G12: 27085 | H12: 26592 | I12: 0.79 | J12: =J11 -> 180.418 | K12: 30 | L12: =H12/J12/(24*K12) -> 0.2047098
A13: October | B13: 143.3 | C13: 73.6 | D13: 26.9 | E13: 148.8 | F13: 139.1 | G13: 29351 | H13: 28821 | I13: 0.794 | J13: =J12 -> 180.418 | K13: 31 | L13: =H13/J13/(24*K13) -> 0.21471196
A14: November | B14: 124.3 | C14: 64.9 | D14: 22.8 | E14: 131.5 | F14: 122.8 | G14: 26247 | H14: 22840 | I14: 0.712 | J14: =J13 -> 180.418 | K14: 30 | L14: =H14/J14/(24*K14) -> 0.17582626
A15: December | B15: 111.2 | C15: 62.5 | D15: 18.49 | E15: 118.3 | F15: 110.1 | G15: 23819 | H15: 21441 | I15: 0.743 | J15: =J14 -> 180.418 | K15: 31 | L15: =H15/J15/(24*K15) -> 0.15973211
A16: Year | B16: =SUM(B4:B15) -> 1761.5 | C16: =SUM(C4:C15) -> 948.9 | D16: 25.84 | E16: =SUM(E4:E15) -> 1804.6 | F16: =SUM(F4:F15) -> 1688.8 | G16: =SUM(G4:G15) -> 356758 | H16: =SUM(H4:H15) -> 343761 | I16: 0.781 | J16: =J15 -> 180.418 | K16: =SUM(K4:K15) -> 365 | L16: =H16/J16/(24*K16) -> 0.2175067
A18: Option 2
B19: GlobHor | C19: DiffHor | D19: T_Amb | E19: GlobInc | F19: GlobEff | G19: EArray | H19: E_Grid
B20: kWh/m² | C20: kWh/m² | D20: °C | E20: kWh/m² | F20: kWh/m² | G20: MWh | H20: MWh | I20: PR | J20: Capacity (MW) | K20: Days | L20: CUF
A21: January | B21: 121.6 | C21: 63.7 | D21: 17.1 | E21: 129.4 | F21: 120.5 | G21: 26662 | H21: 25367 | I21: 0.804 | J21: 199.6 | K21: 31 | L21: =H21/J21/(24*K21) -> 0.17081879
A22: February | B22: 137.5 | C22: 61.8 | D22: 21 | E22: 144.6 | F22: 135.4 | G22: 29646 | H22: 29198 | I22: 0.828 | J22: =J21 -> 199.6 | K22: 28 | L22: =H22/J22/(24*K22) -> 0.21768239
A23: March | B23: 182.8 | C23: 77.6 | D23: 26.1 | E23: 188.7 | F23: 177.3 | G23: 38108 | H23: 37512 | I23: 0.815 | J23: =J22 -> 199.6 | K23: 31 | L23: =H23/J23/(24*K23) -> 0.25260198
A24: April | B24: 189.6 | C24: 87.2 | D24: 29.9 | E24: 191.9 | F24: 180.4 | G24: 38230 | H24: 37634 | I24: 0.804 | J24: =J23 -> 199.6 | K24: 30 | L24: =H24/J24/(24*K24) -> 0.26187096
A25: May | B25: 182.3 | C25: 101.1 | D25: 30.7 | E25: 181.9 | F25: 170.6 | G25: 36021 | H25: 35482 | I25: 0.8 | J25: =J24 -> 199.6 | K25: 31 | L25: =H25/J25/(24*K25) -> 0.23893217
A26: June | B26: 150.3 | C26: 95.4 | D26: 30.3 | E26: 149 | F26: 139.3 | G26: 29471 | H26: 29042 | I26: 0.799 | J26: =J25 -> 199.6 | K26: 30 | L26: =H26/J26/(24*K26) -> 0.20208473
A27: July | B27: 139.5 | C27: 91.3 | D27: 29.1 | E27: 138.7 | F27: 129.6 | G27: 27533 | H27: 26983 | I27: 0.798 | J27: =J26 -> 199.6 | K27: 31 | L27: =H27/J27/(24*K27) -> 0.18170077
A28: August | B28: 143.4 | C28: 89.7 | D28: 29 | E28: 143.9 | F28: 134.6 | G28: 28631 | H28: 28209 | I28: 0.804 | J28: =J27 -> 199.6 | K28: 31 | L28: =H28/J28/(24*K28) -> 0.18995653
A29: September | B29: 135.7 | C29: 80.1 | D29: 28.5 | E29: 137.9 | F29: 129.1 | G29: 27520 | H29: 27107 | I29: 0.806 | J29: =J28 -> 199.6 | K29: 30 | L29: =H29/J29/(24*K29) -> 0.1886203
A30: October | B30: 143.3 | C30: 73.6 | D30: 26.9 | E30: 148.8 | F30: 139.1 | G30: 29829 | H30: 29384 | I30: 0.81 | J30: =J29 -> 199.6 | K30: 31 | L30: =H30/J30/(24*K30) -> 0.19786886
A31: November | B31: 124.3 | C31: 64.9 | D31: 22.8 | E31: 131.5 | F31: 122.8 | G31: 26672 | H31: 25980 | I31: 0.81 | J31: =J30 -> 199.6 | K31: 30 | L31: =H31/J31/(24*K31) -> 0.18077822
A32: December | B32: 111.2 | C32: 62.5 | D32: 18.49 | E32: 118.3 | F32: 110.1 | G32: 24207 | H32: 23859 | I32: 0.827 | J32: =J31 -> 199.6 | K32: 31 | L32: =H32/J32/(24*K32) -> 0.16066407
A33: Year | B33: =SUM(B21:B32) -> 1761.5 | C33: =SUM(C21:C32) -> 948.9 | D33: 25.84 | E33: =SUM(E21:E32) -> 1804.6 | F33: =SUM(F21:F32) -> 1688.8 | G33: 362529 | H33: 355757 | I33: 0.808 | J33: =J32 -> 199.6 | K33: =SUM(K21:K32) -> 365 | L33: =H33/J33/(24*K33) -> 0.20346458
A35: Option 2
B36: GlobHor | C36: DiffHor | D36: T_Amb | E36: GlobInc | F36: GlobEff | G36: EArray | H36: E_Grid
B37: kWh/m² | C37: kWh/m² | D37: °C | E37: kWh/m² | F37: kWh/m² | G37: MWh | H37: MWh | I37: PR | J37: Capacity (MW) | K37: Days | L37: CUF
A38: January | B38: 121.6 | C38: 63.7 | D38: 17.1 | E38: 129.4 | F38: 120.5 | G38: 26234 | H38: 24204 | I38: 0.767 | J38: 203.24 | K38: 31 | L38: =H38/J38/(24*K38) -> 0.16006819
A39: February | B39: 137.5 | C39: 61.8 | D39: 21 | E39: 144.6 | F39: 135.4 | G39: 29173 | H39: 28645 | I39: 0.812 | J39: =J38 -> 203.24 | K39: 28 | L39: =H39/J39/(24*K39) -> 0.20973474
A40: March | B40: 182.8 | C40: 77.6 | D40: 26.1 | E40: 188.7 | F40: 177.3 | G40: 37507 | H40: 36795 | I40: 0.8 | J40: =J39 -> 203.24 | K40: 31 | L40: =H40/J40/(24*K40) -> 0.24333618
A41: April | B41: 189.6 | C41: 87.2 | D41: 29.9 | E41: 191.9 | F41: 180.4 | G41: 37648 | H41: 36935 | I41: 0.789 | J41: =J40 -> 203.24 | K41: 30 | L41: =H42/J41/(24*K41) -> 0.23802592
A42: May | B42: 182.3 | C42: 101.1 | D42: 30.7 | E42: 181.9 | F42: 170.6 | G42: 35463 | H42: 34831 | I42: 0.785 | J42: =J41 -> 203.24 | K42: 31 | L42: =H43/J42/(24*K42) -> 0.18851197
A43: June | B43: 150.3 | C43: 95.4 | D43: 30.3 | E43: 149 | F43: 139.3 | G43: 28999 | H43: 28505 | I43: 0.784 | J43: =J42 -> 203.24 | K43: 30 | L43: =H44/J43/(24*K43) -> 0.18202344
A44: July | B44: 139.5 | C44: 91.3 | D44: 29.1 | E44: 138.7 | F44: 129.6 | G44: 27106 | H44: 26636 | I44: 0.787 | J44: =J43 -> 203.24 | K44: 31 | L44: =H45/J44/(24*K44) -> 0.18277824
A45: August | B45: 143.4 | C45: 89.7 | D45: 29 | E45: 143.9 | F45: 134.6 | G45: 28175 | H45: 27638 | I45: 0.789 | J45: =J44 -> 203.24 | K45: 31 | L45: =H46/J45/(24*K45) -> 0.17600623
A46: September | B46: 135.7 | C46: 80.1 | D46: 28.5 | E46: 137.9 | F46: 129.1 | G46: 27095 | H46: 26614 | I46: 0.791 | J46: =J45 -> 203.24 | K46: 30 | L46: =H46/J46/(24*K46) -> 0.1818731
A47: October | B47: 143.3 | C47: 73.6 | D47: 26.9 | E47: 148.8 | F47: 139.1 | G47: 29351 | H47: 28838 | I47: 0.795 | J47: =J46 -> 203.24 | K47: 31 | L47: =H47/J47/(24*K47) -> 0.19071419
A48: November | B48: 124.3 | C48: 64.9 | D48: 22.8 | E48: 131.5 | F48: 122.8 | G48: 26247 | H48: 22846 | I48: 0.712 | J48: =J47 -> 203.24 | K48: 30 | L48: =H48/J48/(24*K48) -> 0.15612358
A49: December | B49: 111.2 | C49: 62.5 | D49: 18.49 | E49: 118.3 | F49: 110.1 | G49: 23819 | H49: 21444 | I49: 0.743 | J49: =J48 -> 203.24 | K49: 31 | L49: =H49/J49/(24*K49) -> 0.14181549
A50: Year | B50: =SUM(B38:B49) -> 1761.5 | C50: =SUM(C38:C49) -> 948.9 | D50: 25.84 | E50: =SUM(E38:E49) -> 1804.6 | F50: =SUM(F38:F49) -> 1688.8 | G50: =SUM(G38:G49) -> 356817 | H50: =SUM(H38:H49) -> 343931 | I50: 0.808 | J50: =J49 -> 203.24 | K50: =SUM(K38:K49) -> 365 | L50: =H50/J50/(24*K50) -> 0.19317816

Sheet Input
L1: Circularity
C2: Units | D2: Rate | E2: Quantity | I2: Levelized Tariff (Rs/ kWh) | J2: =Working!D276 -> 5.2535517 | L2: TRUE | M2: =L2 -> TRUE
B3: Technical | I3: FIRR | J3: =Working!D421 -> 0.087955957
B4: DC Capacity | C4: MWp | E4: =(D11*D15)+(E11*E15) -> 243.888 | I4: EIRR | J4: =Working!D482 -> 0.19492022 | L4: Option 2
B5: Conversion Factor | E5: =IF($F$5=$H$17,I17,I18) -> 1.2 | F5: Option 2 | I5: WACC | J5: =Input!$E$228 -> 0.07476 | L5: 705 | M5: 25% Overloading
B6: AC Capacity - Project | C6: MW | E6: =(D15*D12)+(E15*E12) -> 203.24 | I6: Rs.Crore/MW | J6: =Output!J6 -> 6.1137671
B7: CUF of the project | C7: % | E7: =RA!L50 -> 0.19317816 | I7: Rs.Crore/MWp | J7: =Output!I6 -> 5.0948059
B8: If Transmission Cost Included | C8: # | E8: Yes
B9: Water Depth- 73.5m | C9: # | E9: Yes | H9: Senstivity | I9: Change
D10: Island 1 | E10: Island 2 | H10: Project Cost | I10: 0
B11: Island unit capacity - DC | C11: MWp | D11: =6.087 -> 6.087 | E11: 4.092 | H11: CUF | I11: 0
B12: Island unit capacity - AC | C12: MW | D12: =D11/$E$5 -> 5.0725 | E12: =E11/$E$5 -> 3.41 | H12: Interest Rate | I12: 0
B13: Module Size | C13: Wp | D13: 580 | E13: 580 | H13: Overloading Factor | I13: =E5 -> 1.2
B14: Inverter size | C14: MW | D14: 4.4 | E14: 1.1
B15: No of islands | C15: # | D15: =IF($E$9="Yes",32,23) -> 32 | E15: =IF($E$9="Yes",12,15) -> 12
B16: No of Inverters | C16: # | D16: =D15+E15 -> 44 | E16: =E15 -> 12 | I16: Overloading
B17: No of Inverters per island | C17: # | D17: 1 | E17: 1 | H17: Option 1 | I17: 1.352
B18: No of modules per string | C18: # | D18: 28 | E18: 28 | H18: Option 2 | I18: 1.2
B20: Total Modules per island | C20: # | D20: =D22+D24 -> 336544 | E20: =E22+E24 -> 84841
B21: No of Module Floats per Sub Plot | C21: # | D21: 10496 | E21: 7056
B22: No of modules per island | C22: # | D22: =D15*D21 -> 335872 | E22: =E15*E21 -> 84672
B23: Spare Modules | C23: % | D23: 0.002 | E23: =D23 -> 0.002
B24: Spare Modules | C24: # | D24: =ROUND(D23*D22,0) -> 672 | E24: =ROUND(E23*E22,0) -> 169
B25: No of Main walkway Floats per Island | C25: # | D25: 1180 | E25: 856
B26: No of Long Secondary Float per Island | C26: # | D26: 4092 | E26: 2697
B27: No of Short Secondary Float per Island | C27: # | D27: 3712 | E27: 2436
B28: No of Secondary Walkway per Island | C28: # | D28: 597 | E28: 416
B29: No of Cable Float-DC | C29: # | D29: 20695 | E29: 7761
B30: No of Cable Float-AC | C30: # | D30: 24803 | E30: 9301
B31: Rigid Mooring Line | C31: KM | D31: =68320/1000 -> 68.32 | E31: =19320/1000 -> 19.32
B32: Flexible Mooring Line | C32: KM | D32: =55360/1000 -> 55.36 | E32: =15480/1000 -> 15.48
B33: Inverter Barge- Mooring Line | C33: KM | D33: =5940/1000 -> 5.94 | E33: =5940/1000 -> 5.94
A34: BOQ Assumptions | D34: Unit Rate | E34: No of Units
A35: A | B35: PV System
B36: PV Module | C36: # | D36: =14.4*1.1 -> 15.84 | E36: =IF($E$9="Yes",D20+E20,E36*0.95) -> 421385 | F36: 0
B37: EL Testing | C37: # | D37: 1000000 | E37: 1
B38: Thermography | C38: # | D38: 500000 | E38: 1
B39: Inverter 4.4 MW | C39: # | D39: 5700000 | E39: =D16 -> 44
B40: Inverter 1.1 MW | C40: # | D40: 1187500 | E40: =E16 -> 12
B42: Solar Project | H42: For 73.5 m | I42: For 72.5 m
B43: Float Devices | D43: Rate | E43: Quantity | F43: As per Design
B44: Floats - Panel Platform | C44: # | D44: 1045 | E44: =IF($E$9="Yes",H44,I44) -> 420544 | F44: As per Design | H44: 420544 | I44: =H44*(1-17%) -> 349051.52
B45: Floats - Main walkway | C45: # | D45: 4018.5 | E45: =IF($E$9="Yes",H45,I45) -> 48032 | F45: As per Design | H45: 48032 | I45: =H45*(1-17%) -> 39866.56
B46: Floats-Long Secondary | C46: # | D46: 2411.1 | E46: =IF($E$9="Yes",H46,I46) -> 163308 | F46: As per Design | H46: 163308 | I46: =H46*(1-17%) -> 135545.64
B47: Floats- Short Secondary | C47: # | D47: 1607.4 | E47: =IF($E$9="Yes",H47,I47) -> 148016 | F47: As per Design | H47: 148016 | I47: =H47*(1-17%) -> 122853.28
B48: Floats- Secondary Walkway | C48: # | D48: 7968.125 | E48: =IF($E$9="Yes",H48,I48) -> 24096 | F48: As per Design | H48: 24096 | I48: =H48*(1-17%) -> 19999.68
B49: No of Cable Float-DC | C49: # | D49: 126.35 | E49: =IF($E$9="Yes",H49,I49) -> 755372 | F49: As per Design | H49: 755372 | I49: =H49*(1-17%) -> 626958.76
B50: No of Cable Float-AC | C50: # | D50: 105.45 | E50: =IF($E$9="Yes",H50,I50) -> 905308 | F50: As per Design | H50: 905308 | I50: =H50*(1-17%) -> 751405.64
B54: Mooring Line | D54: Cost | E54: Unit
B55: Mooring Line - Rigid | C55: Rs per KM | D55: 5878028.1 | E55: =IF($E$9="Yes",H55,I55) -> 87.64 | H55: =D31+E31 -> 87.64 | I55: =H55*(1-17%) -> 72.7412
B56: Mooring Line - Flexible | C56: Rs per KM | D56: 5878028.1 | E56: =IF($E$9="Yes",H56,I56) -> 70.84 | H56: =D32+E32 -> 70.84 | I56: =H56*(1-17%) -> 58.7972
B57: Mooring Accessories | C57: Rs per unit | D57: 7505 | E57: =IF($E$9="Yes",H57,I57) -> 2400 | H57: 2400 | I57: =H57*(1-17%) -> 1992
B58: Inverter Barge | C58: Rs. Per KM | D58: 1055716.3 | E58: =IF($E$9="Yes",H58,I58) -> 11.88 | H58: =SUM(D33:E33) -> 11.88 | I58: =H58*(1-17%) -> 9.8604
B59: Anchors
B60: Anchor Type - Gravity | C60: Rs per Anchor | D60: 17307.1 | E60: =IF($E$9="Yes",H60,I60) -> 5536 | H60: 5536 | I60: =H60*(1-17%) -> 4594.88
B62: Inverter-Transformer Platform
B63: Transformer of Size 5.5 MVA | C63: Rs per unit | D63: 5790250 | E63: =E15 -> 12 | F63: 15% erection included
B64: Transformer of Size 6.5 MVA | C64: Rs per unit | D64: 6992000 | E64: =D15 -> 32 | F64: 15% erection included
B65: Ferrocement Platform | C65: Lum Sum Cost | D65: 5500000 | E65: =IF($E$9="Yes",H65,I65) -> 52 | H65: 52 | I65: 38
B66: Service Cost/Installation Cost
B67: Panel Platform - Floats | C67: % of Hard cost | D67: 0.15
B68: Floats- Main Walkways | C68: % of Hard cost | D68: 0.15
B69: Floats-Long Secondary | C69: % of Hard cost | D69: 0.15
B70: Floats- Short Secondary | C70: % of Hard cost | D70: 0.15
B71: Floats- Secondary Walkways | C71: % of Hard cost | D71: 0.15
B72: Floats- Cables | C72: % of Hard cost | D72: 0.15
B73: Mooring | C73: % of Hard cost | D73: 0.15
B74: Anchoring | C74: % of Hard cost | D74: 0.15
A75: III | B75: General
A76: A | B76: Land Area | E76: Area (Acre) | F76: Av Length (m) | H76: Av Width (m)
A77: 1 | B77: 220/33 kV Sub Station | C77: Rs Lakh/ acre | D77: 0 | E77: =(F77*H77)/4000 -> 10.125 | F77: 225 | H77: 180
A78: 2 | B78: Sub station Control Room | C78: Rs Lakh/ acre | D78: 0 | E78: =(F78*H78)/4000 -> 1 | F78: 80 | H78: 50
A79: 3 | B79: Approach Road | C79: Rs Lakh/ acre | D79: 0 | E79: =(F79*H79)/4000 -> 0.6125 | F79: 700 | H79: 3.5
A80: 4 | B80: Master Control Room - FSPV | C80: Rs Lakh/ acre | D80: 0 | E80: =(F80*H80)/4000 -> 3.8955 | F80: 147 | H80: 106
A81: 5 | B81: Storage Space | C81: Rs Lakh/ acre | D81: 0 | E81: =(F81*H81)/4000 -> 4.125 | F81: 165 | H81: 100
B82: Total Land Area | E82: =SUM(E77:E81) -> 19.758
A83: B | B83: Site Development
B84: Site Development | C84: Rs Lakh per Acre | D84: 100 | E84: =SUM(Input!E77:E78,E80) -> 15.0205
A85: C | B85: Road Infrastructure
A86: 1 | B86: Access Roads | C86: Rs Lakh per kM | D86: 120 | E86: =E79 -> 0.6125
A87: D | B87: Building and Civil Infrastructure
A88: 1 | B88: Master Control Room - FSPV | C88: Rs per sq m | D88: 676 | E88: =E80*4000 -> 15582
A89: 2 | B89: Offices | C89: Rs per sq m | D89: 676 | E89: 20000
A90: 3 | B90: Housing | C90: Rs per sq m | D90: 0 | E90: 0
A91: 4 | B91: Common Infrastructure | C91: Rs per sq m | D91: 676 | E91: 10000
A92: 5 | B92: Medical facilities | C92: Rs per sq m | D92: 0 | E92: 0
A93: E | B93: Other Infrastructure
A94: 1 | B94: Lighting | C94: Rs per Unit | D94: 3000 | E94: 2000
B95: Security | C95: Rs per Unit | D95: 5000 | E95: 400
A96: 3 | B96: Drainage System | C96: Rs per kM | D96: 0 | E96: 0
A97: 4 | B97: Fencing | C97: Rs per kM | D97: 0 | E97: 0
A98: 5 | B98: Gates | C98: Rs per m | D98: 0 | E98: 0
A99: 7 | B99: Waste disposal and liquid sewage treatment plant | C99: Rs per unit | D99: 0 | E99: 0
A100: 8 | B100: Solid waste collection, recycling and storage | C100: Rs per sq m | D100: 0 | E100: 0
A101: 9 | B101: Cost of Green Belt | C101: Rs per sq m | D101: 0 | E101: 0
A102: 10 | B102: Any other envisaged | C102: Rs Lakh per Unit | D102: 0 | E102: 0
A103: F | B103: Other Infrastructure
B104: Enviromental Mitigation Charges | C104: Rs Lakh | E104: 1000
A106: G | B106: Other Charges
A107: 1 | B107: Local Area Development Charges | C107: Rs per MW | D107: 100000 | E107: =$E$6 -> 203.24
...

Sheet BOQ_G
B1: Summary | C1: Unit | D1: Unit Costs | E1: Quantity | F1: Cost (Rs Lakh) | G1: Tax (Rs Lakh) | H1: Cost with Tax (Rs Lakh) | N1: Equipment Cost (Rs Lakhs) | O1: Installation Cost (Rs Lakhs) | P1: Total Cost (Rs per Wp) | Q1: Tax (Rs per Wp) | R1: Gross Cost (Rs per Wp) | S1: Cost (Rs Cr/ MW) | U1: Equipment Cost (Rs Lakhs) | V1: Installation Cost (Rs Lakhs) | W1: Total Cost (Rs Lakhs) | X1: Tax (Rs Lakhs) | Y1: Gross Cost (Rs Lakhs) | AA1: Equipment Cost | AB1: Installation Cost
A2: A | B2: PV Modules | C2: Lot | D2: =ROUND(F2/E2,0) -> 159 | E2: =Input!$E$4 -> 243.888 | F2: =SUM(F$36:F$39) -> 38728.483 | G2: =SUM(G$36:G$39) -> 5344.5306 | H2: =SUM(F2:G2) -> 44073.013 | N2: =ROUND($F2*$AA$2/Input!$E$4/10,2) -> 13.5 | O2: =ROUND($F2*(100%-$AA$2)/Input!$E$4/10,2) -> 2.38 | P2: =SUM(N2:O2) -> 15.88 | Q2: =N2*$AA$3+$O2*$AB$3 -> 2.0484 | R2: =P2+Q2 -> 17.9284 | S2: =H2/$E$27/100 -> 2.1685206 | U2: =F2*$AA$2 -> 32919.21 | V2: =F2*$AB$2 -> 4647.4179 | W2: =U2+V2 -> 37566.628 | X2: =G2 -> 5344.5306 | Y2: =H2 -> 44073.013 | AA2: 0.85 | AB2: 0.12
A3: B | B3: Inverters | C3: Lot | D3: =ROUND(F3/E3,0) -> 13 | E3: =Input!$E$6 -> 203.24 | F3: =SUM(F41:F42) -> 2650.5 | G3: =SUM(G41:G42) -> 365.769 | H3: =SUM(F3:G3) -> 3016.269 | N3: =ROUND($F3*$AA$2/Input!$E$4/10,2) -> 0.92 | O3: =ROUND($F3*(100%-$AA$2)/Input!$E$4/10,2) -> 0.16 | P3: =SUM(N3:O3) -> 1.08 | Q3: =N3*$AA$3+$O3*$AB$3 -> 0.1392 | R3: =P3+Q3 -> 1.2192 | S3: =H3/$E$27/100 -> 0.14840922 | U3: =F3*$AA$2 -> 2252.925 | V3: =F3*$AB$2 -> 318.06 | W3: =U3+V3 -> 2570.985 | X3: =G3 -> 365.769 | Y3: =H3 -> 3016.269 | AA3: =Input!F225 -> 0.12 | AB3: =Input!H225 -> 0.18
A4: C | B4: Floating Structures and Installation | C4: Lot | D4: =ROUND(F4/E4,0) -> 135 | E4: =Input!$E$4 -> 243.888 | F4: =SUM(F45:F60) -> 32929.861 | G4: =SUM(G45:G60) -> 4544.3208 | H4: =SUM(F4:G4) -> 37474.182 | N4: =ROUND($F4*$AA$2/Input!$E$4/10,2) -> 11.48 | O4: =ROUND($F4*(100%-$AA$2)/Input!$E$4/10,2) -> 2.03 | P4: =SUM(N4:O4) -> 13.51 | Q4: =N4*$AA$3+$O4*$AB$3 -> 1.743 | R4: =P4+Q4 -> 15.253 | S4: =H4/$E$27/100 -> 1.8438389 | U4: =F4*$AA$2 -> 27990.382 | V4: =F4*$AB$2 -> 3951.5833 | W4: =U4+V4 -> 31941.965 | X4: =G4 -> 4544.3208 | Y4: =H4 -> 37474.182 | AA4: =AA2*AA3+AB2*AB3 -> 0.1236
A5: 1 | B5: Float Structures | D5: =ROUND(F5/E5,0) -> 68 | E5: =Input!$E$4 -> 243.888 | F5: =SUM(F45:F51) -> 16470.638 | G5: =SUM(G45:G51) -> 2272.9481 | H5: =SUM(F5:G5) -> 18743.586 | N5: =ROUND($F5*$AA$2/Input!$E$4/10,2) -> 5.74 | O5: =ROUND($F5*(100%-$AA$2)/Input!$E$4/10,2) -> 1.01 | P5: =SUM(N5:O5) -> 6.75 | Q5: =ROUND(N5*$AA$3+$O5*$AB$3,2) -> 0.87 | R5: =P5+Q5 -> 7.62 | S5: =H5/$E$27/100 -> 0.92223905 | U5: =F5*$AA$2 -> 14000.043 | V5: =F5*$AB$2 -> 1976.4766 | W5: =U5+V5 -> 15976.519 | X5: =G5 -> 2272.9481 | Y5: =H5 -> 18743.586
A6: 2 | B6: Inverter Transformer System | D6: =ROUND(F6/E6,0) -> 25 | E6: =Input!$E$4 -> 243.888 | F6: =SUM(F53:F56) -> 6005.4825 | G6: =SUM(G53:G56) -> 828.75658 | H6: =SUM(F6:G6) -> 6834.239 | N6: =ROUND($F6*$AA$2/Input!$E$4/10,2) -> 2.09 | O6: =ROUND($F6*(100%-$AA$2)/Input!$E$4/10,2) -> 0.37 | P6: =SUM(N6:O6) -> 2.46 | Q6: =ROUND(N6*$AA$3+$O6*$AB$3,2) -> 0.32 | R6: =P6+Q6 -> 2.78 | S6: =H6/$E$27/100 -> 0.33626447 | U6: =F6*$AA$2 -> 5104.6601 | V6: =F6*$AB$2 -> 720.6579 | W6: =U6+V6 -> 5825.318 | X6: =G6 -> 828.75658 | Y6: =H6 -> 6834.239
A7: 3 | B7: Anchoring & Mooring | D7: =ROUND(F7/E7,0) -> 43 | E7: =Input!$E$4 -> 243.888 | F7: =SUM(F57:F60) -> 10453.74 | G7: =SUM(G57:G60) -> 1442.6161 | H7: =SUM(F7:G7) -> 11896.356 | N7: =ROUND($F7*$AA$2/Input!$E$4/10,2) -> 3.64 | O7: =ROUND($F7*(100%-$AA$2)/Input!$E$4/10,2) -> 0.64 | P7: =SUM(N7:O7) -> 4.28 | Q7: =ROUND(N7*$AA$3+$O7*$AB$3,2) -> 0.55 | R7: =P7+Q7 -> 4.83 | S7: =H7/$E$27/100 -> 0.58533537 | U7: =F7*$AA$2 -> 8885.679 | V7: =F7*$AB$2 -> 1254.4488 | W7: =U7+V7 -> 10140.128 | X7: =G7 -> 1442.6161 | Y7: =H7 -> 11896.356
A8: D | B8: Balance of System | C8: Lot | D8: =ROUND(F8/E8,0) -> 40 | E8: =Input!$E$4 -> 243.888 | F8: =SUM(F62:F193) -> 9694.1833 | G8: =SUM(G62:G193) -> 1337.7973 | H8: =SUM(F8:G8) -> 11031.981 | N8: =ROUND($F8*$AA$2/Input!$E$4/10,2) -> 3.38 | O8: =ROUND($F8*(100%-$AA$2)/Input!$E$4/10,2) -> 0.6 | P8: =SUM(N8:O8) -> 3.98 | Q8: =N8*$AA$3+$O8*$AB$3 -> 0.5136 | R8: =P8+Q8 -> 4.4936 | S8: =H8/$E$27/100 -> 0.54280558 | U8: =F8*$AA$2 -> 8240.0558 | V8: =F8*$AB$2 -> 1163.302 | W8: =U8+V8 -> 9403.3578 | X8: =G8 -> 1337.7973 | Y8: =H8 -> 11031.981
A9: 1 | B9: DC - Cables, SCB, Accessories | D9: =ROUND(F9/E9,0) -> 17 | E9: =Input!$E$4 -> 243.888 | F9: =SUM(F62:F80) -> 4077.46 | G9: =SUM(G62:G80) -> 562.68949 | H9: =SUM(F9:G9) -> 4640.1495 | N9: =ROUND($F9*$AA$2/Input!$E$4/10,2) -> 1.42 | O9: =ROUND($F9*(100%-$AA$2)/Input!$E$4/10,2) -> 0.25 | P9: =SUM(N9:O9) -> 1.67 | Q9: =N9*$AA$3+$O9*$AB$3 -> 0.2154 | R9: =P9+Q9 -> 1.8854 | S9: =H9/$E$27/100 -> 0.22830887 | U9: =F9*$AA$2 -> 3465.841 | V9: =F9*$AB$2 -> 489.2952 | W9: =U9+V9 -> 3955.1362 | X9: =G9 -> 562.68949 | Y9: =H9 -> 4640.1495
A10: 2 | B10: AC Cables | D10: =ROUND(F10/E10,0) -> 1 | E10: =Input!$E$4 -> 243.888 | F10: =SUM(F82:F112) -> 219.31885 | G10: =SUM(G82:G112) -> 30.266001 | H10: =SUM(F10:G10) -> 249.58485 | N10: =ROUND($F10*$AA$2/Input!$E$4/10,2) -> 0.08 | O10: =ROUND($F10*(100%-$AA$2)/Input!$E$4/10,2) -> 0.01 | P10: =SUM(N10:O10) -> 0.09 | Q10: =N10*$AA$3+$O10*$AB$3 -> 0.0114 | R10: =P10+Q10 -> 0.1014 | S10: =H10/$E$27/100 -> 0.012280302 | U10: =F10*$AA$2 -> 186.42102 | V10: =F10*$AB$2 -> 26.318262 | W10: =U10+V10 -> 212.73928 | X10: =G10 -> 30.266001 | Y10: =H10 -> 249.58485
A11: 3 | B11: Inverter Transformers, Switchgear and Panels | D11: =ROUND(F11/E11,0) -> 16 | E11: =Input!$E$4 -> 243.888 | F11: =SUM(F114:F154) -> 3922.9529 | G11: =SUM(G114:G154) -> 541.3675 | H11: =SUM(F11:G11) -> 4464.3204 | N11: =ROUND($F11*$AA$2/Input!$E$4/10,2) -> 1.37 | O11: =ROUND($F11*(100%-$AA$2)/Input!$E$4/10,2) -> 0.24 | P11: =SUM(N11:O11) -> 1.61 | Q11: =N11*$AA$3+$O11*$AB$3 -> 0.2076 | R11: =P11+Q11 -> 1.8176 | S11: =H11/$E$27/100 -> 0.21965757 | U11: =F11*$AA$2 -> 3334.51 | V11: =F11*$AB$2 -> 470.75435 | W11: =U11+V11 -> 3805.2643 | X11: =G11 -> 541.3675 | Y11: =H11 -> 4464.3204
A12: 4 | B12: Illumination System, Earthing | D12: =ROUND(F12/E12,0) -> 4 | E12: =Input!$E$4 -> 243.888 | F12: =SUM(F155:F177) -> 1034.4515 | G12: =SUM(G155:G177) -> 142.75431 | H12: =SUM(F12:G12) -> 1177.2058 | N12: =ROUND($F12*$AA$2/Input!$E$4/10,2) -> 0.36 | O12: =ROUND($F12*(100%-$AA$2)/Input!$E$4/10,2) -> 0.06 | P12: =SUM(N12:O12) -> 0.42 | Q12: =N12*$AA$3+$O12*$AB$3 -> 0.054 | R12: =P12+Q12 -> 0.474 | S12: =H12/$E$27/100 -> 0.057921955 | U12: =F12*$AA$2 -> 879.28379 | V12: =F12*$AB$2 -> 124.13418 | W12: =U12+V12 -> 1003.418 | X12: =G12 -> 142.75431 | Y12: =H12 -> 1177.2058
A13: 5 | B13: SCADA and Master Control Room | D13: =ROUND(F13/E13,0) -> 2 | E13: =Input!$E$4 -> 243.888 | F13: =SUM(F179:F193) -> 440 | G13: =SUM(G155:G164) -> 60.504101 | H13: =SUM(F13:G13) -> 500.5041 | N13: =ROUND($F13*$AA$2/Input!$E$4/10,2) -> 0.15 | O13: =ROUND($F13*(100%-$AA$2)/Input!$E$4/10,2) -> 0.03 | P13: =SUM(N13:O13) -> 0.18 | Q13: =N13*$AA$3+$O13*$AB$3 -> 0.0234 | R13: =P13+Q13 -> 0.2034 | S13: =H13/$E$27/100 -> 0.02462626 | U13: =F13*$AA$2 -> 374 | V13: =F13*$AB$2 -> 52.8 | W13: =U13+V13 -> 426.8 | X13: =G13 -> 60.504101 | Y13: =H13 -> 500.5041
A14: E | B14: Civil Infrastructure | C14: Lot | D14: =ROUND(F14/E14,0) -> 7 | E14: =Input!$E$4 -> 243.888 | F14: =SUM(F15:F17) -> 1663.1343 | G14: =SUM(G15:G17) -> 229.51254 | H14: =SUM(F14:G14) -> 1892.6469 | N14: =ROUND($F14*$AA$2/Input!$E$4/10,2) -> 0.58 | O14: =ROUND($F14*(100%-$AA$2)/Input!$E$4/10,2) -> 0.1 | P14: =SUM(N14:O14) -> 0.68 | Q14: =N14*$AA$3+$O14*$AB$3 -> 0.0876 | R14: =P14+Q14 -> 0.7676 | S14: =H14/$E$27/100 -> 0.093123738 | U14: =F14*$AA$2 -> 1413.6642 | V14: =F14*$AB$2 -> 199.57612 | W14: =U14+V14 -> 1613.2403 | X14: =G14 -> 229.51254 | Y14: =H14 -> 1892.6469
B15: Building and Civil Infrastructure | F15: =SUM(F196:F200) -> 308.13432 | G15: =SUM(G196:G200) -> 42.522536 | H15: =SUM(H196:H200) -> 350.65686 | N15: =ROUND($F15*$AA$2/Input!$E$4/10,2) -> 0.11 | O15: =ROUND($F15*(100%-$AA$2)/Input!$E$4/10,2) -> 0.02 | P15: =SUM(N15:O15) -> 0.13 | Q15: =N15*$AA$3+$O15*$AB$3 -> 0.0168 | R15: =P15+Q15 -> 0.1468 | S15: =H15/$E$27/100 -> 0.017253339 | U15: =F15*$AA$2 -> 261.91417 | V15: =F15*$AB$2 -> 36.976118 | W15: =U15+V15 -> 298.89029 | X15: =G15 -> 42.522536 | Y15: =H15 -> 350.65686
B16: Marine Infrastructure | F16: =SUM(F202:F204) -> 280 | G16: =SUM(G202:G204) -> 38.64 | H16: =SUM(H202:H204) -> 318.64 | N16: =ROUND($F16*$AA$2/Input!$E$4/10,2) -> 0.1 | O16: =ROUND($F16*(100%-$AA$2)/Input!$E$4/10,2) -> 0.02 | P16: =SUM(N16:O16) -> 0.12 | Q16: =N16*$AA$3+$O16*$AB$3 -> 0.0156 | R16: =P16+Q16 -> 0.1356 | S16: =H16/$E$27/100 -> 0.015678016 | U16: =F16*$AA$2 -> 238 | V16: =F16*$AB$2 -> 33.6 | W16: =U16+V16 -> 271.6 | X16: =G16 -> 38.64 | Y16: =H16 -> 318.64
B17: Other Infrastructure | F17: =SUM(F206:F214) -> 1075 | G17: =SUM(G206:G214) -> 148.35 | H17: =SUM(H206:H214) -> 1223.35 | N17: =ROUND($F17*$AA$2/Input!$E$4/10,2) -> 0.37 | O17: =ROUND($F17*(100%-$AA$2)/Input!$E$4/10,2) -> 0.07 | P17: =SUM(N17:O17) -> 0.44 | Q17: =N17*$AA$3+$O17*$AB$3 -> 0.057 | R17: =P17+Q17 -> 0.497 | S17: =H17/$E$27/100 -> 0.060192383 | U17: =F17*$AA$2 -> 913.75 | V17: =F17*$AB$2 -> 129 | W17: =U17+V17 -> 1042.75 | X17: =G17 -> 148.35 | Y17: =H17 -> 1223.35
B18: FSP Project Capital Cost | F18: =SUM(F2,F3,F4,F8,F14) -> 85666.161 | G18: =SUM(G2,G3,G4,G8,G14) -> 11821.93 | H18: =SUM(H2,H3,H4,H8,H14) -> 97488.091 | N18: =SUM(N2,N3,N4,N8,N14) -> 29.86 | O18: =SUM(O2,O3,O4,O8,O14) -> 5.27 | P18: =SUM(P2,P3,P4,P8,P14) -> 35.13 | Q18: =SUM(Q2,Q3,Q4,Q8,Q14) -> 4.5318 | R18: =SUM(R2,R3,R4,R8,R14) -> 39.6618 | S18: =H18/$E$27/100 -> 4.7966981 | U18: =F18*$AA$2 -> 72816.237 | V18: =F18*$AB$2 -> 10279.939 | W18: =U18+V18 -> 83096.176 | X18: =G18 -> 11821.93 | Y18: =H18 -> 97488.091
B19: Other Costs (Designs, Survey, Insurance, Warranty, etc) | F19: =SUM(F216:F220) -> 2941.3852 | G19: =SUM(G216:G220) -> 405.91116 | H19: =SUM(F19:G19) -> 3347.2964 | N19: =ROUND($F19*$AA$2/Input!$E$4/10,2) -> 1.03 | O19: =ROUND($F19*(100%-$AA$2)/Input!$E$4/10,2) -> 0.18 | P19: =SUM(N19:O19) -> 1.21 | Q19: =N19*$AA$3+$O19*$AB$3 -> 0.156 | R19: =P19+Q19 -> 1.366 | S19: =H19/$E$27/100 -> 0.16469673 | U19: =F19*$AA$2 -> 2500.1775 | V19: =F19*$AB$2 -> 352.96623 | W19: =U19+V19 -> 2853.1437 | X19: =G19 -> 405.91116 | Y19: =H19 -> 3347.2964
B20: Grand Total | F20: =F18+F19 -> 88607.546 | G20: =G18+G19 -> 12227.841 | H20: =SUM(F20:G20) -> 100835.39 | N20: =ROUND($F20*$AA$2/Input!$E$4/10,2) -> 30.88 | O20: =ROUND($F20*(100%-$AA$2)/Input!$E$4/10,2) -> 5.45 | P20: =SUM(N20:O20) -> 36.33 | Q20: =N20*$AA$3+$O20*$AB$3 -> 4.6866 | R20: =P20+Q20 -> 41.0166 | S20: =H20/$E$27/100 -> 4.9613948 | U20: =F20*$AA$2 -> 75316.414 | V20: =F20*$AB$2 -> 10632.906 | W20: =U20+V20 -> 85949.32 | X20: =G20 -> 12227.841 | Y20: =H20 -> 100835.39
B21: Profit Margin | F21: =F221 -> 6508.2021 | G21: =G221 -> 898.1319 | H21: =SUM(F21:G21) -> 7406.334 | N21: =ROUND($F21*$AA$2/Input!$E$4/10,2) -> 2.27 | O21: =ROUND($F21*(100%-$AA$2)/Input!$E$4/10,2) -> 0.4 | P21: =SUM(N21:O21) -> 2.67 | Q21: =N21*$AA$3+$O21*$AB$3 -> 0.3444 | R21: =P21+Q21 -> 3.0144 | S21: =H21/$E$27/100 -> 0.36441321 | U21: =F21*$AA$2 -> 5531.9718 | V21: =F21*$AB$2 -> 780.98426 | W21: =U21+V21 -> 6312.9561 | X21: =G21 -> 898.1319 | Y21: =H21 -> 7406.334
B22: FSPV Total | F22: =F20+F21 -> 95115.748 | G22: =G20+G21 -> 13125.973 | H22: =H20+H21 -> 108241.72 | N22: =N20+N21 -> 33.15 | O22: =O20+O21 -> 5.85 | P22: =P20+P21 -> 39 | Q22: =Q20+Q21 -> 5.031 | R22: =R20+R21 -> 44.031 | S22: =H22/$E$27/100 -> 5.325808 | U22: =F22*$AA$2 -> 80848.386 | V22: =F22*$AB$2 -> 11413.89 | W22: =U22+V22 -> 92262.276 | X22: =G22 -> 13125.973 | Y22: =H22 -> 108241.72
B23: Optional | F23: =SUM(F222:F227) -> 638.8 | G23: =SUM(G222:G227) -> 88.1544 | H23: =SUM(F23:G23) -> 726.9544 | N23: =ROUND($F23*$AA$2/Input!$E$4/10,2) -> 0.22 | O23: =ROUND($F23*(100%-$AA$2)/Input!$E$4/10,2) -> 0.04 | P23: =SUM(N23:O23) -> 0.26 | Q23: =N23*$AA$3+$O23*$AB$3 -> 0.0336 | R23: =P23+Q23 -> 0.2936 | S23: =H23/$E$27/100 -> 0.035768274 | U23: =F23*$AA$2 -> 542.98 | V23: =F23*$AB$2 -> 76.656 | W23: =U23+V23 -> 619.636 | X23: =G23 -> 88.1544 | Y23: =H23 -> 726.9544
Y24: =H24 -> 0
B25: General | E25: #
B26: Project Capacity | C26: MW DC | E26: =Input!E4 -> 243.888
B27: Project Capacity | C27: MW AC | E27: =Input!E6 -> 203.24
B28: Inverter Rating (in kW) & Qty (At 50ᵒ C Temp) | C28: 4400 | E28: =Input!D16 -> 44
B29: Inverter Rating (in kW) & Qty (At 50ᵒ C Temp) | C29: 1100 | E29: =Input!E16 -> 12
B30: Total Modules | C30: # | E30: =Input!E22+Input!D22 -> 420544
B31: Module rating | C31: Wp | E31: =Input!D13 -> 580
B32: # Module per string | C32: # | E32: =Input!D18 -> 28 | O32: =SUM(O36:O39)+(O41+O42)+SUM(O53:O56) -> 2.91
B34: BOQ | S34: Tax Rate
A35: A | B35: PV Modules
A36: 1 | B36: PV Modules | C36: # | D36: =Input!$D$36*$E$31 -> 9187.2 | E36: =Input!D22+Input!E22 -> 420544 | F36: =D36*E36/10^5 -> 38636.218 | G36: =$F36*$S36 -> 5331.7981 | H36: =F36+G36 -> 43968.017 | N36: =ROUND($F36*$AA$2/Input!$E$4/10,2) -> 13.47 | O36: =ROUND($F36*(100%-$AA$2)/Input!$E$4/10,2) -> 2.38 | P36: =SUM(N36:O36) -> 15.85 | Q36: =N36*$AA$3+$O36*$AB$3 -> 2.0448 | R36: =P36+Q36 -> 17.8948 | S36: 0.138 | U36: =F36*$AA$2 -> 32840.786 | V36: =F36*$AB$2 -> 4636.3462 | W36: =U36+V36 -> 37477.132 | X36: =G36 -> 5331.7981 | Y36: =H36 -> 43968.017
A37: 2 | B37: Spare Modules | C37: # | D37: =Input!$D$36*$E$31 -> 9187.2 | E37: =Input!D24+Input!E24 -> 841 | F37: =D37*E37/10^5 -> 77.264352 | G37: =$F37*$S37 -> 10.662481 | H37: =F37+G37 -> 87.926833 | N37: =ROUND($F37*$AA$2/Input!$E$4/10,2) -> 0.03 | O37: =ROUND($F37*(100%-$AA$2)/Input!$E$4/10,2) -> 0 | P37: =SUM(N37:O37) -> 0.03 | Q37: =N37*$AA$3+$O37*$AB$3 -> 0.0036 | R37: =P37+Q37 -> 0.0336 | S37: 0.138 | U37: =F37*$AA$2 -> 65.674699 | V37: =F37*$AB$2 -> 9.2717222 | W37: =U37+V37 -> 74.946421 | X37: =G37 -> 10.662481 | Y37: =H37 -> 87.926833
A38: 3 | B38: EL Testing | C38: # | D38: =Input!D37 -> 1000000 | E38: =Input!E37 -> 1 | F38: =D38*E38/10^5 -> 10 | G38: =$F38*$S38 -> 1.38 | H38: =F38+G38 -> 11.38 | N38: =ROUND($F38*$AA$2/Input!$E$4/10,2) -> 0 | O38: =ROUND($F38*(100%-$AA$2)/Input!$E$4/10,2) -> 0 | P38: =SUM(N38:O38) -> 0 | Q38: =N38*$AA$3+$O38*$AB$3 -> 0 | R38: =P38+Q38 -> 0 | S38: 0.138 | U38: =F38*$AA$2 -> 8.5 | V38: =F38*$AB$2 -> 1.2 | W38: =U38+V38 -> 9.7 | X38: =G38 -> 1.38 | Y38: =H38 -> 11.38
A39: 4 | B39: Thermography | C39: # | D39: =Input!D38 -> 500000 | E39: =Input!E38 -> 1 | F39: =D39*E39/10^5 -> 5 | G39: =$F39*$S39 -> 0.69 | H39: =F39+G39 -> 5.69 | N39: =ROUND($F39*$AA$2/Input!$E$4/10,2) -> 0 | O39: =ROUND($F39*(100%-$AA$2)/Input!$E$4/10,2) -> 0 | P39: =SUM(N39:O39) -> 0 | Q39: =N39*$AA$3+$O39*$AB$3 -> 0 | R39: =P39+Q39 -> 0 | S39: 0.138 | U39: =F39*$AA$2 -> 4.25 | V39: =F39*$AB$2 -> 0.6 | W39: =U39+V39 -> 4.85 | X39: =G39 -> 0.69 | Y39: =H39 -> 5.69
A40: B | B40: Inverters
A41: 1 | B41: Inverter 4.4 MW | C41: # | D41: =Input!D39 -> 5700000 | E41: =E28 -> 44 | F41: =D41*E41/10^5 -> 2508 | G41: =$F41*$S41 -> 346.104 | H41: =F41+G41 -> 2854.104 | N41: =ROUND($F41*$AA$2/Input!$E$4/10,2) -> 0.87 | O41: =ROUND($F41*(100%-$AA$2)/Input!$E$4/10,2) -> 0.15 | P41: =SUM(N41:O41) -> 1.02 | Q41: =N41*$AA$3+$O41*$AB$3 -> 0.1314 | R41: =P41+Q41 -> 1.1514 | S41: 0.138 | U41: =F41*$AA$2 -> 2131.8 | V41: =F41*$AB$2 -> 300.96 | W41: =U41+V41 -> 2432.76 | X41: =G41 -> 346.104 | Y41: =H41 -> 2854.104
A42: 2 | B42: Inverter 1.1 MW | C42: # | D42: =Input!D40 -> 1187500 | E42: =E29 -> 12 | F42: =D42*E42/10^5 -> 142.5 | G42: =$F42*$S42 -> 19.665 | H42: =F42+G42 -> 162.165 | N42: =ROUND($F42*$AA$2/Input!$E$4/10,2) -> 0.05 | O42: =ROUND($F42*(100%-$AA$2)/Input!$E$4/10,2) -> 0.01 | P42: =SUM(N42:O42) -> 0.06 | Q42: =N42*$AA$3+$O42*$AB$3 -> 0.0078 | R42: =P42+Q42 -> 0.0678 | S42: 0.138 | U42: =F42*$AA$2 -> 121.125 | V42: =F42*$AB$2 -> 17.1 | W42: =U42+V42 -> 138.225 | X42: =G42 -> 19.665 | Y42: =H42 -> 162.165
A43: C | B43: Floating Module Mounting Structure
A44: C1 | B44: Floating Structures | N44: =ROUND($F44*$AA$2/Input!$E$4/10,2) -> 0 | O44: =ROUND($F44*(100%-$AA$2)/Input!$E$4/10,2) -> 0 | P44: =SUM(N44:O44) -> 0 | Q44: =N44*$AA$3+$O44*$AB$3 -> 0 | R44: =P44+Q44 -> 0 | S44: 0.138 | U44: =F44*$AA$2 -> 0 | V44: =F44*$AB$2 -> 0 | W44: =U44+V44 -> 0 | X44: =G44 -> 0 | Y44: =H44 -> 0
A45: 1 | B45: OMF (Module Float) | C45: Rs per float | D45: =Input!D44 -> 1045 | E45: =Input!E44 -> 420544 | F45: =D45*E45/10^5 -> 4394.6848 | G45: =$F45*$S45 -> 606.4665 | H45: =F45+G45 -> 5001.1513 | N45: =ROUND($F45*$AA$2/Input!$E$4/10,2) -> 1.53 | O45: =ROUND($F45*(100%-$AA$2)/Input!$E$4/10,2) -> 0.27 | P45: =SUM(N45:O45) -> 1.8 | Q45: =N45*$AA$3+$O45*$AB$3 -> 0.2322 | R45: =P45+Q45 -> 2.0322 | S45: 0.138 | U45: =F45*$AA$2 -> 3735.4821 | V45: =F45*$AB$2 -> 527.36218 | W45: =U45+V45 -> 4262.8443 | X45: =G45 -> 606.4665 | Y45: =H45 -> 5001.1513
A46: 2 | B46: OMWF (Main Walkway Float) | C46: Rs per float | D46: =Input!D45 -> 4018.5 | E46: =Input!E45 -> 48032 | F46: =D46*E46/10^5 -> 1930.1659 | G46: =$F46*$S46 -> 266.3629 | H46: =F46+G46 -> 2196.5288 | N46: =ROUND($F46*$AA$2/Input!$E$4/10,2) -> 0.67 | O46: =ROUND($F46*(100%-$AA$2)/Input!$E$4/10,2) -> 0.12 | P46: =SUM(N46:O46) -> 0.79 | Q46: =N46*$AA$3+$O46*$AB$3 -> 0.102 | R46: =P46+Q46 -> 0.892 | S46: 0.138 | U46: =F46*$AA$2 -> 1640.641 | V46: =F46*$AB$2 -> 231.61991 | W46: =U46+V46 -> 1872.2609 | X46: =G46 -> 266.3629 | Y46: =H46 -> 2196.5288
A47: 3 | B47: OLSF (Long Secondary Float) | C47: Rs per float | D47: =Input!D46 -> 2411.1 | E47: =Input!E46 -> 163308 | F47: =D47*E47/10^5 -> 3937.5192 | G47: =$F47*$S47 -> 543.37765 | H47: =F47+G47 -> 4480.8968 | N47: =ROUND($F47*$AA$2/Input!$E$4/10,2) -> 1.37 | O47: =ROUND($F47*(100%-$AA$2)/Input!$E$4/10,2) -> 0.24 | P47: =SUM(N47:O47) -> 1.61 | Q47: =N47*$AA$3+$O47*$AB$3 -> 0.2076 | R47: =P47+Q47 -> 1.8176 | S47: 0.138 | U47: =F47*$AA$2 -> 3346.8913 | V47: =F47*$AB$2 -> 472.5023 | W47: =U47+V47 -> 3819.3936 | X47: =G47 -> 543.37765 | Y47: =H47 -> 4480.8968
A48: 4 | B48: OSSF (Small Secondary Float) | C48: Rs per float | D48: =Input!D47 -> 1607.4 | E48: =Input!E47 -> 148016 | F48: =D48*E48/10^5 -> 2379.2092 | G48: =$F48*$S48 -> 328.33087 | H48: =F48+G48 -> 2707.5401 | N48: =ROUND($F48*$AA$2/Input!$E$4/10,2) -> 0.83 | O48: =ROUND($F48*(100%-$AA$2)/Input!$E$4/10,2) -> 0.15 | P48: =SUM(N48:O48) -> 0.98 | Q48: =N48*$AA$3+$O48*$AB$3 -> 0.1266 | R48: =P48+Q48 -> 1.1066 | S48: 0.138 | U48: =F48*$AA$2 -> 2022.3278 | V48: =F48*$AB$2 -> 285.5051 | W48: =U48+V48 -> 2307.8329 | X48: =G48 -> 328.33087 | Y48: =H48 -> 2707.5401
A49: 5 | B49: OSSFx (Small Secondary Walkway Float) | C49: Rs per float | D49: =Input!D48 -> 7968.125 | E49: =Input!E48 -> 24096 | F49: =D49*E49/10^5 -> 1919.9994 | G49: =$F49*$S49 -> 264.95992 | H49: =F49+G49 -> 2184.9593 | N49: =ROUND($F49*$AA$2/Input!$E$4/10,2) -> 0.67 | O49: =ROUND($F49*(100%-$AA$2)/Input!$E$4/10,2) -> 0.12 | P49: =SUM(N49:O49) -> 0.79 | Q49: =N49*$AA$3+$O49*$AB$3 -> 0.102 | R49: =P49+Q49 -> 0.892 | S49: 0.138 | U49: =F49*$AA$2 -> 1631.9995 | V49: =F49*$AB$2 -> 230.39993 | W49: =U49+V49 -> 1862.3994 | X49: =G49 -> 264.95992 | Y49: =H49 -> 2184.9593
A50: 6 | B50: OCF (Cable Float)-DC | C50: Rs per float | D50: =Input!D49 -> 126.35 | E50: =Input!E49 -> 755372 | F50: =D50*E50/10^5 -> 954.41252 | G50: =$F50*$S50 -> 131.70893 | H50: =F50+G50 -> 1086.1215 | N50: =ROUND($F50*$AA$2/Input!$E$4/10,2) -> 0.33 | O50: =ROUND($F50*(100%-$AA$2)/Input!$E$4/10,2) -> 0.06 | P50: =SUM(N50:O50) -> 0.39 | Q50: =N50*$AA$3+$O50*$AB$3 -> 0.0504 | R50: =P50+Q50 -> 0.4404 | S50: 0.138 | U50: =F50*$AA$2 -> 811.25064 | V50: =F50*$AB$2 -> 114.5295 | W50: =U50+V50 -> 925.78015 | X50: =G50 -> 131.70893 | Y50: =H50 -> 1086.1215
A51: 7 | B51: OCF (Cable Float)-AC | C51: Rs per float | D51: =Input!D50 -> 105.45 | E51: =Input!E50 -> 905308 | F51: =D51*E51/10^5 -> 954.64729 | G51: =$F51*$S51 -> 131.74133 | H51: =F51+G51 -> 1086.3886 | N51: =ROUND($F51*$AA$2/Input!$E$4/10,2) -> 0.33 | O51: =ROUND($F51*(100%-$AA$2)/Input!$E$4/10,2) -> 0.06 | P51: =SUM(N51:O51) -> 0.39 | Q51: =N51*$AA$3+$O51*$AB$3 -> 0.0504 | R51: =P51+Q51 -> 0.4404 | S51: 0.138 | U51: =F51*$AA$2 -> 811.45019 | V51: =F51*$AB$2 -> 114.55767 | W51: =U51+V51 -> 926.00787 | X51: =G51 -> 131.74133 | Y51: =H51 -> 1086.3886
A52: C2 | B52: Inverter Transformer Platforms
A53: 1 | B53: Transformer of Size 5.5 MVA | C53: Rs per Transformer | D53: =Input!D63 -> 5790250 | E53: =Input!E63 -> 12 | F53: =D53*E53/10^5 -> 694.83 | G53: =$F53*$S53 -> 95.88654 | H53: =F53+G53 -> 790.71654 | N53: =ROUND($F53*$AA$2/Input!$E$4/10,2) -> 0.24 | O53: =ROUND($F53*(100%-$AA$2)/Input!$E$4/10,2) -> 0.04 | P53: =SUM(N53:O53) -> 0.28 | Q53: =N53*$AA$3+$O53*$AB$3 -> 0.036 | R53: =P53+Q53 -> 0.316 | S53: 0.138 | U53: =F53*$AA$2 -> 590.6055 | V53: =F53*$AB$2 -> 83.3796 | W53: =U53+V53 -> 673.9851 | X53: =G53 -> 95.88654 | Y53: =H53 -> 790.71654
A54: 2 | B54: Transformer of Size 6.5 MVA | C54: Rs per Transformer | D54: =Input!D64 -> 6992000 | E54: =Input!E64 -> 32 | F54: =D54*E54/10^5 -> 2237.44 | G54: =$F54*$S54 -> 308.76672 | H54: =F54+G54 -> 2546.2067 | N54: =ROUND($F54*$AA$2/Input!$E$4/10,2) -> 0.78 | O54: =ROUND($F54*(100%-$AA$2)/Input!$E$4/10,2) -> 0.14 | P54: =SUM(N54:O54) -> 0.92 | Q54: =N54*$AA$3+$O54*$AB$3 -> 0.1188 | R54: =P54+Q54 -> 1.0388 | S54: 0.138 | U54: =F54*$AA$2 -> 1901.824 | V54: =F54*$AB$2 -> 268.4928 | W54: =U54+V54 -> 2170.3168 | X54: =G54 -> 308.76672 | Y54: =H54 -> 2546.2067
A55: 3 | B55: Platform-Ferro Cement | C55: Rs per Platform | D55: =Input!D65 -> 5500000 | E55: =Input!E65 -> 52 | F55: =D55*E55/10^5 -> 2860 | G55: =$F55*$S55 -> 394.68 | H55: =F55+G55 -> 3254.68 | N55: =ROUND($F55*$AA$2/Input!$E$4/10,2) -> 1 | O55: =ROUND($F55*(100%-$AA$2)/Input!$E$4/10,2) -> 0.18 | P55: =SUM(N55:O55) -> 1.18 | Q55: =N55*$AA$3+$O55*$AB$3 -> 0.1524 | R55: =P55+Q55 -> 1.3324 | S55: 0.138
A56: 4 | B56: Inverter Barge- Mooring Line length | C56: Rs. Per KM | D56: =Input!D58 -> 1055716.3 | E56: =Input!E58 -> 11.88 | F56: =D56*E56/10^5*1.7 -> 213.21246 | G56: =$F56*$S56 -> 29.42332 | H56: =F56+G56 -> 242.63578 | N56: =ROUND($F56*$AA$2/Input!$E$4/10,2) -> 0.07 | O56: =ROUND($F56*(100%-$AA$2)/Input!$E$4/10,2) -> 0.01 | P56: =SUM(N56:O56) -> 0.08 | Q56: =N56*$AA$3+$O56*$AB$3 -> 0.0102 | R56: =P56+Q56 -> 0.0902 | S56: 0.138 | U56: =F56*$AA$2 -> 181.23059 | V56: =F56*$AB$2 -> 25.585495 | W56: =U56+V56 -> 206.81609 | X56: =G56 -> 29.42332 | Y56: =H56 -> 242.63578
A57: C3 | B57: Anchoring and Mooring System
A58: 1 | B58: Mooring System | C58: Rs per KM | D58: =Input!D55 -> 5878028.1 | E58: =Input!E55+Input!E56 -> 158.48 | F58: =D58*E58/10^5 -> 9315.4989 | G58: =$F58*$S58 -> 1285.5389 | H58: =F58+G58 -> 10601.038 | N58: =ROUND($F58*$AA$2/Input!$E$4/10,2) -> 3.25 | O58: =ROUND($F58*(100%-$AA$2)/Input!$E$4/10,2) -> 0.57 | P58: =SUM(N58:O58) -> 3.82 | Q58: =N58*$AA$3+$O58*$AB$3 -> 0.4926 | R58: =P58+Q58 -> 4.3126 | S58: 0.138 | U58: =F58*$AA$2 -> 7918.1741 | V58: =F58*$AB$2 -> 1117.8599 | W58: =U58+V58 -> 9036.034 | X58: =G58 -> 1285.5389 | Y58: =H58 -> 10601.038
A59: 2 | B59: Mooring Line Accessories | C59: Rs per unit | D59: =Input!D57 -> 7505 | E59: =Input!E57 -> 2400 | F59: =D59*E59/10^5 -> 180.12 | G59: =$F59*$S59 -> 24.85656 | H59: =F59+G59 -> 204.97656 | N59: =ROUND($F59*$AA$2/Input!$E$4/10,2) -> 0.06 | O59: =ROUND($F59*(100%-$AA$2)/Input!$E$4/10,2) -> 0.01 | P59: =SUM(N59:O59) -> 0.07 | Q59: =N59*$AA$3+$O59*$AB$3 -> 0.009 | R59: =P59+Q59 -> 0.079 | S59: 0.138 | U59: =F59*$AA$2 -> 153.102 | V59: =F59*$AB$2 -> 21.6144 | W59: =U59+V59 -> 174.7164 | X59: =G59 -> 24.85656 | Y59: =H59 -> 204.97656
A60: 3 | B60: Anchor System | C60: Rs per Anchor | D60: =Input!D60 -> 17307.1 | E60: =Input!E60 -> 5536 | F60: =D60*E60/10^5 -> 958.12106 | G60: =$F60*$S60 -> 132.22071 | H60: =F60+G60 -> 1090.3418 | N60: =ROUND($F60*$AA$2/Input!$E$4/10,2) -> 0.33 | O60: =ROUND($F60*(100%-$AA$2)/Input!$E$4/10,2) -> 0.06 | P60: =SUM(N60:O60) -> 0.39 | Q60: =N60*$AA$3+$O60*$AB$3 -> 0.0504 | R60: =P60+Q60 -> 0.4404 | S60: 0.138 | U60: =F60*$AA$2 -> 814.4029 | V60: =F60*$AB$2 -> 114.97453 | W60: =U60+V60 -> 929.37742 | X60: =G60 -> 132.22071 | Y60: =H60 -> 1090.3418
A61: D | B61: Balance of System (BoS)
A62: D1 | B62: DC Cables & Connectors
A63: 1 | B63: 1.8 kV DC, 1Cx 6 Sq.mm. string cables in line with EN50618 | C63: m | D63: 58 | E63: 1302246.4 | F63: =D63*E63/10^5 -> 755.30291 | G63: =$F63*$S63 -> 104.2318 | H63: =F63+G63 -> 859.53471 | N63: =ROUND($F63*$AA$2/Input!$E$4/10,2) -> 0.26 | O63: =ROUND($F63*(100%-$AA$2)/Input!$E$4/10,2) -> 0.05 | P63: =SUM(N63:O63) -> 0.31 | Q63: =N63*$AA$3+$O63*$AB$3 -> 0.0402 | R63: =P63+Q63 -> 0.3502 | S63: 0.138 | U63: =F63*$AA$2 -> 642.00748 | V63: =F63*$AB$2 -> 90.636349 | W63: =U63+V63 -> 732.64382 | X63: =G63 -> 104.2318 | Y63: =H63 -> 859.53471
A64: 2 | B64: String cable dressing | C64: # | D64: =5 -> 5 | F64: =D64*E64/10^5 -> 0 | G64: =$F64*$S64 -> 0 | H64: =F64+G64 -> 0 | N64: =ROUND($F64*$AA$2/Input!$E$4/10,2) -> 0 | O64: =ROUND($F64*(100%-$AA$2)/Input!$E$4/10,2) -> 0 | P64: =SUM(N64:O64) -> 0 | Q64: =N64*$AA$3+$O64*$AB$3 -> 0 | R64: =P64+Q64 -> 0 | S64: =$AA$4 -> 0.1236 | U64: =F64*$AA$2 -> 0 | V64: =F64*$AB$2 -> 0 | W64: =U64+V64 -> 0 | X64: =G64 -> 0 | Y64: =H64 -> 0
A65: D2 | B65: DC Connectors
A66: 1 | B66: Male - MC4 Connector for 1.8 kV DC, 6 Sq.mm. string cables with spare | C66: # | D66: =93 -> 93 | E66: 17338 | F66: =D66*E66/10^5 -> 16.12434 | G66: =$F66*$S66 -> 2.2251589 | H66: =F66+G66 -> 18.349499 | N66: =ROUND($F66*$AA$2/Input!$E$4/10,2) -> 0.01 | O66: =ROUND($F66*(100%-$AA$2)/Input!$E$4/10,2) -> 0 | P66: =SUM(N66:O66) -> 0.01 | Q66: =N66*$AA$3+$O66*$AB$3 -> 0.0012 | R66: =P66+Q66 -> 0.0112 | S66: 0.138 | U66: =F66*$AA$2 -> 13.705689 | V66: =F66*$AB$2 -> 1.9349208 | W66: =U66+V66 -> 15.64061 | X66: =G66 -> 2.2251589 | Y66: =H66 -> 18.349499
A67: 2 | B67: FeMale - MC4 Connector for 1.8 kV DC, 6 Sq.mm. string cables with spare | C67: # | D67: =93 -> 93 | E67: 17338 | F67: =D67*E67/10^5 -> 16.12434 | G67: =$F67*$S67 -> 2.2251589 | H67: =F67+G67 -> 18.349499 | N67: =ROUND($F67*$AA$2/Input!$E$4/10,2) -> 0.01 | O67: =ROUND($F67*(100%-$AA$2)/Input!$E$4/10,2) -> 0 | P67: =SUM(N67:O67) -> 0.01 | Q67: =N67*$AA$3+$O67*$AB$3 -> 0.0012 | R67: =P67+Q67 -> 0.0112 | S67: 0.138 | U67: =F67*$AA$2 -> 13.705689 | V67: =F67*$AB$2 -> 1.9349208 | W67: =U67+V67 -> 15.64061 | X67: =G67 -> 2.2251589 | Y67: =H67 -> 18.349499
A68: 3 | B68: Cable Ties-300 mm | C68: # | D68: 141 | E68: 1000 | F68: =D68*E68/10^5 -> 1.41 | G68: =$F68*$S68 -> 0.19458 | H68: =F68+G68 -> 1.60458 | N68: =ROUND($F68*$AA$2/Input!$E$4/10,2) -> 0 | O68: =ROUND($F68*(100%-$AA$2)/Input!$E$4/10,2) -> 0 | P68: =SUM(N68:O68) -> 0 | Q68: =N68*$AA$3+$O68*$AB$3 -> 0 | R68: =P68+Q68 -> 0 | S68: 0.138 | U68: =F68*$AA$2 -> 1.1985 | V68: =F68*$AB$2 -> 0.1692 | W68: =U68+V68 -> 1.3677 | X68: =G68 -> 0.19458 | Y68: =H68 -> 1.60458
A69: 4 | B69: Cable Ties-550 mm | C69: # | D69: 370 | E69: 1000 | F69: =D69*E69/10^5 -> 3.7 | G69: =$F69*$S69 -> 0.5106 | H69: =F69+G69 -> 4.2106 | N69: =ROUND($F69*$AA$2/Input!$E$4/10,2) -> 0 | O69: =ROUND($F69*(100%-$AA$2)/Input!$E$4/10,2) -> 0 | P69: =SUM(N69:O69) -> 0 | Q69: =N69*$AA$3+$O69*$AB$3 -> 0 | R69: =P69+Q69 -> 0 | S69: 0.138 | U69: =F69*$AA$2 -> 3.145 | V69: =F69*$AB$2 -> 0.444 | W69: =U69+V69 -> 3.589 | X69: =G69 -> 0.5106 | Y69: =H69 -> 4.2106
A70: 5 | B70: 32 ID / 40mm OD DWC Pipe (UV Protection & Helogen Free) | C70: m | D70: =150 -> 150 | E70: 145800 | F70: =D70*E70/10^5 -> 218.7 | G70: =$F70*$S70 -> 30.1806 | H70: =F70+G70 -> 248.8806 | N70: =ROUND($F70*$AA$2/Input!$E$4/10,2) -> 0.08 | O70: =ROUND($F70*(100%-$AA$2)/Input!$E$4/10,2) -> 0.01 | P70: =SUM(N70:O70) -> 0.09 | Q70: =N70*$AA$3+$O70*$AB$3 -> 0.0114 | R70: =P70+Q70 -> 0.1014 | S70: 0.138 | U70: =F70*$AA$2 -> 185.895 | V70: =F70*$AB$2 -> 26.244 | W70: =U70+V70 -> 212.139 | X70: =G70 -> 30.1806 | Y70: =H70 -> 248.8806
A71: 6 | B71: Fuse Connectors-30 A | C71: # | D71: 275 | E71: 17338 | F71: =D71*E71/10^5 -> 47.6795 | G71: =$F71*$S71 -> 6.579771 | H71: =F71+G71 -> 54.259271 | N71: =ROUND($F71*$AA$2/Input!$E$4/10,2) -> 0.02 | O71: =ROUND($F71*(100%-$AA$2)/Input!$E$4/10,2) -> 0 | P71: =SUM(N71:O71) -> 0.02 | Q71: =N71*$AA$3+$O71*$AB$3 -> 0.0024 | R71: =P71+Q71 -> 0.0224 | S71: 0.138 | U71: =F71*$AA$2 -> 40.527575 | V71: =F71*$AB$2 -> 5.72154 | W71: =U71+V71 -> 46.249115 | X71: =G71 -> 6.579771 | Y71: =H71 -> 54.259271
A72: 7 | B72: Precast Chambers | C72: # | D72: 10000 | E72: 100 | F72: =D72*E72/10^5 -> 10 | G72: =$F72*$S72 -> 1.38 | H72: =F72+G72 -> 11.38 | N72: =ROUND($F72*$AA$2/Input!$E$4/10,2) -> 0 | O72: =ROUND($F72*(100%-$AA$2)/Input!$E$4/10,2) -> 0 | P72: =SUM(N72:O72) -> 0 | Q72: =N72*$AA$3+$O72*$AB$3 -> 0 | R72: =P72+Q72 -> 0 | S72: 0.138 | U72: =F72*$AA$2 -> 8.5 | V72: =F72*$AB$2 -> 1.2 | W72: =U72+V72 -> 9.7 | X72: =G72 -> 1.38 | Y72: =H72 -> 11.38
A73: D3 | B73: DC Accessories
A74: 1 | B74: 1.8 kV, 1Cx300 Sq.mm. Aluminium Conductor, XLPE insulated, (1.5% loss) | C74: # | D74: =487*0.95 -> 462.65 | E74: =440000*1.2 -> 528000 | F74: =D74*E74/10^5 -> 2442.792 | G74: =$F74*$S74 -> 337.1053 | H74: =F74+G74 -> 2779.8973 | N74: =ROUND($F74*$AA$2/Input!$E$4/10,2) -> 0.85 | O74: =ROUND($F74*(100%-$AA$2)/Input!$E$4/10,2) -> 0.15 | P74: =SUM(N74:O74) -> 1 | Q74: =N74*$AA$3+$O74*$AB$3 -> 0.129 | R74: =P74+Q74 -> 1.129 | S74: 0.138 | U74: =F74*$AA$2 -> 2076.3732 | V74: =F74*$AB$2 -> 293.13504 | W74: =U74+V74 -> 2369.5082 | X74: =G74 -> 337.1053 | Y74: =H74 -> 2779.8973
A75: 2 | B75: Termination Kits for above-3.3 kV at inverter end - Gland for 300 sqmm Cable | C75: # | D75: 921 | E75: 1354.5 | F75: =D75*E75/10^5 -> 12.474945 | G75: =$F75*$S75 -> 1.7215424 | H75: =F75+G75 -> 14.196487 | N75: =ROUND($F75*$AA$2/Input!$E$4/10,2) -> 0 | O75: =ROUND($F75*(100%-$AA$2)/Input!$E$4/10,2) -> 0 | P75: =SUM(N75:O75) -> 0 | Q75: =N75*$AA$3+$O75*$AB$3 -> 0 | R75: =P75+Q75 -> 0 | S75: 0.138 | U75: =F75*$AA$2 -> 10.603703 | V75: =F75*$AB$2 -> 1.4969934 | W75: =U75+V75 -> 12.100697 | X75: =G75 -> 1.7215424 | Y75: =H75 -> 14.196487
A76: 3 | B76: Lugs for above cable including inverter end - Lugs for 300 sqmm Cable | C76: # | D76: 300 | E76: 2709 | F76: =D76*E76/10^5 -> 8.127 | G76: =$F76*$S76 -> 1.121526 | H76: =F76+G76 -> 9.248526 | N76: =ROUND($F76*$AA$2/Input!$E$4/10,2) -> 0 | O76: =ROUND($F76*(100%-$AA$2)/Input!$E$4/10,2) -> 0 | P76: =SUM(N76:O76) -> 0 | Q76: =N76*$AA$3+$O76*$AB$3 -> 0 | R76: =P76+Q76 -> 0 | S76: 0.138 | U76: =F76*$AA$2 -> 6.90795 | V76: =F76*$AB$2 -> 0.97524 | W76: =U76+V76 -> 7.88319 | X76: =G76 -> 1.121526 | Y76: =H76 -> 9.248526
A77: D4 | B77: String Monitoring Box (SMB)
A78: 1 | B78: DC disconnector - 400A, 2P; Fuse - 30A on positive side without Y connector; SPD Class 2, Metal gland | C78: # | D78: =75000 -> 75000 | E78: 688 | F78: =D78*E78/10^5 -> 516 | G78: =$F78*$S78 -> 71.208 | H78: =F78+G78 -> 587.208 | N78: =ROUND($F78*$AA$2/Input!$E$4/10,2) -> 0.18 | O78: =ROUND($F78*(100%-$AA$2)/Input!$E$4/10,2) -> 0.03 | P78: =SUM(N78:O78) -> 0.21 | Q78: =N78*$AA$3+$O78*$AB$3 -> 0.027 | R78: =P78+Q78 -> 0.237 | S78: 0.138 | U78: =F78*$AA$2 -> 438.6 | V78: =F78*$AB$2 -> 61.92 | W78: =U78+V78 -> 500.52 | X78: =G78 -> 71.208 | Y78: =H78 -> 587.208
A79: 2 | B79: Painting & Naming over SCB | C79: # | D79: =100 -> 100 | E79: 645 | F79: =D79*E79/10^5 -> 0.645 | G79: =$F79*$S79 -> 0.08901 | H79: =F79+G79 -> 0.73401 | N79: =ROUND($F79*$AA$2/Input!$E$4/10,2) -> 0 | O79: =ROUND($F79*(100%-$AA$2)/Input!$E$4/10,2) -> 0 | P79: =SUM(N79:O79) -> 0 | Q79: =N79*$AA$3+$O79*$AB$3 -> 0 | R79: =P79+Q79 -> 0 | S79: 0.138 | U79: =F79*$AA$2 -> 0.54825 | V79: =F79*$AB$2 -> 0.0774 | W79: =U79+V79 -> 0.62565 | X79: =G79 -> 0.08901 | Y79: =H79 -> 0.73401
A80: 3 | B80: Structure for mounting SCB with canopy | C80: # | D80: =4400 -> 4400 | E80: 645 | F80: =D80*E80/10^5 -> 28.38 | G80: =$F80*$S80 -> 3.91644 | H80: =F80+G80 -> 32.29644 | N80: =ROUND($F80*$AA$2/Input!$E$4/10,2) -> 0.01 | O80: =ROUND($F80*(100%-$AA$2)/Input!$E$4/10,2) -> 0 | P80: =SUM(N80:O80) -> 0.01 | Q80: =N80*$AA$3+$O80*$AB$3 -> 0.0012 | R80: =P80+Q80 -> 0.0112 | S80: 0.138 | U80: =F80*$AA$2 -> 24.123 | V80: =F80*$AB$2 -> 3.4056 | W80: =U80+V80 -> 27.5286 | X80: =G80 -> 3.91644 | Y80: =H80 -> 32.29644
A81: D5 | B81: AC Cables
A82: D5.1 | B82: AC Cables (1.9/3.3kV) - From Inverter - Inverter Transformer
A83: 1 | B83: Al 1Cx400Sq.mm, 1.9/3.3kV, Al, Ar, XLPE, FRLS Inner Sheath & Outer Sheath On Cable Tray | C83: Mtr | D83: 564 | E83: 22325 | F83: =D83*E83/10^5 -> 125.913 | G83: =$F83*$S83 -> 17.375994 | H83: =F83+G83 -> 143.28899 | N83: =ROUND($F83*$AA$2/Input!$E$4/10,2) -> 0.04 | O83: =ROUND($F83*(100%-$AA$2)/Input!$E$4/10,2) -> 0.01 | P83: =SUM(N83:O83) -> 0.05 | Q83: =N83*$AA$3+$O83*$AB$3 -> 0.0066 | R83: =P83+Q83 -> 0.0566 | S83: 0.138 | U83: =F83*$AA$2 -> 107.02605 | V83: =F83*$AB$2 -> 15.10956 | W83: =U83+V83 -> 122.13561 | X83: =G83 -> 17.375994 | Y83: =H83 -> 143.28899
A84: 2 | B84: 450x125mmx2mm thk Ladder Type HDG Cable Tray with GI Cover | C84: Mtr | D84: 480 | E84: 3500 | F84: =D84*E84/10^5 -> 16.8 | G84: =$F84*$S84 -> 2.3184 | H84: =F84+G84 -> 19.1184 | N84: =ROUND($F84*$AA$2/Input!$E$4/10,2) -> 0.01 | O84: =ROUND($F84*(100%-$AA$2)/Input!$E$4/10,2) -> 0 | P84: =SUM(N84:O84) -> 0.01 | Q84: =N84*$AA$3+$O84*$AB$3 -> 0.0012 | R84: =P84+Q84 -> 0.0112 | S84: 0.138 | U84: =F84*$AA$2 -> 14.28 | V84: =F84*$AB$2 -> 2.016 | W84: =U84+V84 -> 16.296 | X84: =G84 -> 2.3184 | Y84: =H84 -> 19.1184
A85: 3 | B85: 50x6 MM GI Earth Strip for cable tray earthing with galvanization of min 80 microns | C85: Mtr | D85: 56 | E85: 2500 | F85: =D85*E85/10^5 -> 1.4 | G85: =$F85*$S85 -> 0.1932 | H85: =F85+G85 -> 1.5932 | N85: =ROUND($F85*$AA$2/Input!$E$4/10,2) -> 0 | O85: =ROUND($F85*(100%-$AA$2)/Input!$E$4/10,2) -> 0 | P85: =SUM(N85:O85) -> 0 | Q85: =N85*$AA$3+$O85*$AB$3 -> 0 | R85: =P85+Q85 -> 0 | S85: 0.138 | U85: =F85*$AA$2 -> 1.19 | V85: =F85*$AB$2 -> 0.168 | W85: =U85+V85 -> 1.358 | X85: =G85 -> 0.1932 | Y85: =H85 -> 1.5932
A86: 4 | B86: Trefoil clamp-Nylon6 glass filled fibre clamp for 1Cx400 Sq.mm cable | C86: NOS | D86: 95 | E86: 5330 | F86: =D86*E86/10^5 -> 5.0635 | G86: =$F86*$S86 -> 0.698763 | H86: =F86+G86 -> 5.762263 | N86: =ROUND($F86*$AA$2/Input!$E$4/10,2) -> 0 | O86: =ROUND($F86*(100%-$AA$2)/Input!$E$4/10,2) -> 0 | P86: =SUM(N86:O86) -> 0 | Q86: =N86*$AA$3+$O86*$AB$3 -> 0 | R86: =P86+Q86 -> 0 | S86: 0.138 | U86: =F86*$AA$2 -> 4.303975 | V86: =F86*$AB$2 -> 0.60762 | W86: =U86+V86 -> 4.911595 | X86: =G86 -> 0.698763 | Y86: =H86 -> 5.762263
A87: 5 | B87: 4Cx 16Sqmm Al,Ar, XLPE with Cable for Peripherial lighting, FRLSH | C87: Meters | D87: 108 | E87: 20700 | F87: =D87*E87/10^5 -> 22.356 | G87: =$F87*$S87 -> 3.085128 | H87: =F87+G87 -> 25.441128 | N87: =ROUND($F87*$AA$2/Input!$E$4/10,2) -> 0.01 | O87: =ROUND($F87*(100%-$AA$2)/Input!$E$4/10,2) -> 0 | P87: =SUM(N87:O87) -> 0.01 | Q87: =N87*$AA$3+$O87*$AB$3 -> 0.0012 | R87: =P87+Q87 -> 0.0112 | S87: 0.138 | U87: =F87*$AA$2 -> 19.0026 | V87: =F87*$AB$2 -> 2.68272 | W87: =U87+V87 -> 21.68532 | X87: =G87 -> 3.085128 | Y87: =H87 -> 25.441128
A88: 6 | B88: 4Cx 16 Sqmm, Al, cable with Cable from light DB to fisrt light pole, FRLSH | C88: Meters | D88: 108 | E88: 3900 | F88: =D88*E88/10^5 -> 4.212 | G88: =$F88*$S88 -> 0.581256 | H88: =F88+G88 -> 4.793256 | N88: =ROUND($F88*$AA$2/Input!$E$4/10,2) -> 0 | O88: =ROUND($F88*(100%-$AA$2)/Input!$E$4/10,2) -> 0 | P88: =SUM(N88:O88) -> 0 | Q88: =N88*$AA$3+$O88*$AB$3 -> 0 | R88: =P88+Q88 -> 0 | S88: 0.138 | U88: =F88*$AA$2 -> 3.5802 | V88: =F88*$AB$2 -> 0.50544 | W88: =U88+V88 -> 4.08564 | X88: =G88 -> 0.581256 | Y88: =H88 -> 4.793256
A89: 7 | B89: Al 4c, 16sqmm, Al, Ar, XLPE FRLSH outer & Inner sheath | C89: Meters | D89: 108 | E89: 2350 | F89: =D89*E89/10^5 -> 2.538 | G89: =$F89*$S89 -> 0.350244 | H89: =F89+G89 -> 2.888244 | N89: =ROUND($F89*$AA$2/Input!$E$4/10,2) -> 0 | O89: =ROUND($F89*(100%-$AA$2)/Input!$E$4/10,2) -> 0 | P89: =SUM(N89:O89) -> 0 | Q89: =N89*$AA$3+$O89*$AB$3 -> 0 | R89: =P89+Q89 -> 0 | S89: 0.138 | U89: =F89*$AA$2 -> 2.1573 | V89: =F89*$AB$2 -> 0.30456 | W89: =U89+V89 -> 2.46186 | X89: =G89 -> 0.350244 | Y89: =H89 -> 2.888244
A90: 8 | B90: Al 1Cx400Sq.mm, 1.9/3.3kV, Al, Ar, XLPE, FRLS outersheath On Cable Tray | C90: Mters | D90: 564 | E90: 750 | F90: =D90*E90/10^5 -> 4.23 | G90: =$F90*$S90 -> 0.58374 | H90: =F90+G90 -> 4.81374 | N90: =ROUND($F90*$AA$2/Input!$E$4/10,2) -> 0 | O90: =ROUND($F90*(100%-$AA$2)/Input!$E$4/10,2) -> 0 | P90: =SUM(N90:O90) -> 0 | Q90: =N90*$AA$3+$O90*$AB$3 -> 0 | R90: =P90+Q90 -> 0 | S90: 0.138 | U90: =F90*$AA$2 -> 3.5955 | V90: =F90*$AB$2 -> 0.5076 | W90: =U90+V90 -> 4.1031 | X90: =G90 -> 0.58374 | Y90: =H90 -> 4.81374
A91: 9 | B91: Trefoil clamp-Nylon6 glass filled fibre clamp for 1Cx400 Sq.mm cable | C91: NOS | D91: 95 | E91: 280 | F91: =D91*E91/10^5 -> 0.266 | G91: =$F91*$S91 -> 0.036708 | H91: =F91+G91 -> 0.302708 | N91: =ROUND($F91*$AA$2/Input!$E$4/10,2) -> 0 | O91: =ROUND($F91*(100%-$AA$2)/Input!$E$4/10,2) -> 0 | P91: =SUM(N91:O91) -> 0 | Q91: =N91*$AA$3+$O91*$AB$3 -> 0 | R91: =P91+Q91 -> 0 | S91: 0.138 | U91: =F91*$AA$2 -> 0.2261 | V91: =F91*$AB$2 -> 0.03192 | W91: =U91+V91 -> 0.25802 | X91: =G91 -> 0.036708 | Y91: =H91 -> 0.302708
A92: 10 | B92: 3Cx2.5 Sq.mm Cu. Flexible cable from JB to Light fixture | C92: Meters | D92: 75 | E92: 1679 | F92: =D92*E92/10^5 -> 1.25925 | G92: =$F92*$S92 -> 0.1737765 | H92: =F92+G92 -> 1.4330265 | N92: =ROUND($F92*$AA$2/Input!$E$4/10,2) -> 0 | O92: =ROUND($F92*(100%-$AA$2)/Input!$E$4/10,2) -> 0 | P92: =SUM(N92:O92) -> 0 | Q92: =N92*$AA$3+$O92*$AB$3 -> 0 | R92: =P92+Q92 -> 0 | S92: 0.138 | U92: =F92*$AA$2 -> 1.0703625 | V92: =F92*$AB$2 -> 0.15111 | W92: =U92+V92 -> 1.2214725 | X92: =G92 -> 0.1737765 | Y92: =H92 -> 1.4330265
A93: D5.2 | B93: Control Cable
A94: 1 | B94: 3CX2.5, Cu, Ar, XLPE with FRLSH outer & Inner sheath | C94: Meters | D94: 107 | E94: 600 | F94: =D94*E94/10^5 -> 0.642 | G94: =$F94*$S94 -> 0.088596 | H94: =F94+G94 -> 0.730596 | N94: =ROUND($F94*$AA$2/Input!$E$4/10,2) -> 0 | O94: =ROUND($F94*(100%-$AA$2)/Input!$E$4/10,2) -> 0 | P94: =SUM(N94:O94) -> 0 | Q94: =N94*$AA$3+$O94*$AB$3 -> 0 | R94: =P94+Q94 -> 0 | S94: 0.138 | U94: =F94*$AA$2 -> 0.5457 | V94: =F94*$AB$2 -> 0.07704 | W94: =U94+V94 -> 0.62274 | X94: =G94 -> 0.088596 | Y94: =H94 -> 0.730596
A95: 2 | B95: 5CX2.5, Cu, Ar, XLPE with FRLSH outer & Inner sheath | C95: Meters | D95: 125 | E95: 5560 | F95: =D95*E95/10^5 -> 6.95 | G95: =$F95*$S95 -> 0.9591 | H95: =F95+G95 -> 7.9091 | N95: =ROUND($F95*$AA$2/Input!$E$4/10,2) -> 0 | O95: =ROUND($F95*(100%-$AA$2)/Input!$E$4/10,2) -> 0 | P95: =SUM(N95:O95) -> 0 | Q95: =N95*$AA$3+$O95*$AB$3 -> 0 | R95: =P95+Q95 -> 0 | S95: 0.138 | U95: =F95*$AA$2 -> 5.9075 | V95: =F95*$AB$2 -> 0.834 | W95: =U95+V95 -> 6.7415 | X95: =G95 -> 0.9591 | Y95: =H95 -> 7.9091
A96: 3 | B96: 7CX2.5, Cu, Ar, XLPE with FRLSH outer & Inner sheath | C96: Meters | D96: 140 | E96: 1060 | F96: =D96*E96/10^5 -> 1.484 | G96: =$F96*$S96 -> 0.204792 | H96: =F96+G96 -> 1.688792 | N96: =ROUND($F96*$AA$2/Input!$E$4/10,2) -> 0 | O96: =ROUND($F96*(100%-$AA$2)/Input!$E$4/10,2) -> 0 | P96: =SUM(N96:O96) -> 0 | Q96: =N96*$AA$3+$O96*$AB$3 -> 0 | R96: =P96+Q96 -> 0 | S96: 0.138 | U96: =F96*$AA$2 -> 1.2614 | V96: =F96*$AB$2 -> 0.17808 | W96: =U96+V96 -> 1.43948 | X96: =G96 -> 0.204792 | Y96: =H96 -> 1.688792
A97: 4 | B97: 10CX2.5, Cu, Ar, XLPE with FRLSH outer & Inner sheath | C97: Meters | D97: 100 | E97: 0 | F97: =D97*E97/10^5 -> 0 | G97: =$F97*$S97 -> 0 | H97: =F97+G97 -> 0 | N97: =ROUND($F97*$AA$2/Input!$E$4/10,2) -> 0 | O97: =ROUND($F97*(100%-$AA$2)/Input!$E$4/10,2) -> 0 | P97: =SUM(N97:O97) -> 0 | Q97: =N97*$AA$3+$O97*$AB$3 -> 0 | R97: =P97+Q97 -> 0 | S97: 0.138 | U97: =F97*$AA$2 -> 0 | V97: =F97*$AB$2 -> 0 | W97: =U97+V97 -> 0 | X97: =G97 -> 0 | Y97: =H97 -> 0
A98: 5 | B98: 1.1 KV, YWY, 14C X 2.5 Sq.mm Electrolytic Grade annealed plain copper, EXTRUDED HR PVC TYPE -C INSULATION AS PER IS : 5831 -1984, Extruded PVC TYPE ST-2 AS PER IS : 5831 1-984 innersheath, GS round wire, EXTRUDED FR-LSH PVC TYPE ST-2 outersheath cable | C98: Meters | D98: 220 | E98: 600 | F98: =D98*E98/10^5 -> 1.32 | G98: =$F98*$S98 -> 0.18216 | H98: =F98+G98 -> 1.50216 | N98: =ROUND($F98*$AA$2/Input!$E$4/10,2) -> 0 | O98: =ROUND($F98*(100%-$AA$2)/Input!$E$4/10,2) -> 0 | P98: =SUM(N98:O98) -> 0 | Q98: =N98*$AA$3+$O98*$AB$3 -> 0 | R98: =P98+Q98 -> 0 | S98: 0.138 | U98: =F98*$AA$2 -> 1.122 | V98: =F98*$AB$2 -> 0.1584 | W98: =U98+V98 -> 1.2804 | X98: =G98 -> 0.18216 | Y98: =H98 -> 1.50216
A99: 6 | B99: 16X2.5, Cu, Ar, XLPE with FRLSH outer & Inner sheath | C99: Meters | D99: 150 | E99: 4700 | F99: =D99*E99/10^5 -> 7.05 | G99: =$F99*$S99 -> 0.9729 | H99: =F99+G99 -> 8.0229 | N99: =ROUND($F99*$AA$2/Input!$E$4/10,2) -> 0 | O99: =ROUND($F99*(100%-$AA$2)/Input!$E$4/10,2) -> 0 | P99: =SUM(N99:O99) -> 0 | Q99: =N99*$AA$3+$O99*$AB$3 -> 0 | R99: =P99+Q99 -> 0 | S99: 0.138 | U99: =F99*$AA$2 -> 5.9925 | V99: =F99*$AB$2 -> 0.846 | W99: =U99+V99 -> 6.8385 | X99: =G99 -> 0.9729 | Y99: =H99 -> 8.0229
A100: 7 | B100: 1.1 KV, YWY, 19C X 2.5 Sq.mm Electrolytic Grade annealed plain copper, EXTRUDED HR PVC TYPE -C INSULATION AS PER IS : 5831 -1984, Extruded PVC TYPE ST-2 AS PER IS : 5831 1-984 innersheath, GS round wire, EXTRUDED FR-LSH PVC TYPE ST-2 outersheath cable | C100: Meters | D100: 190 | E100: 600 | F100: =D100*E100/10^5 -> 1.14 | G100: =$F100*$S100 -> 0.15732 | H100: =F100+G100 -> 1.29732 | N100: =ROUND($F100*$AA$2/Input!$E$4/10,2) -> 0 | O100: =ROUND($F100*(100%-$AA$2)/Input!$E$4/10,2) -> 0 | P100: =SUM(N100:O100) -> 0 | Q100: =N100*$AA$3+$O100*$AB$3 -> 0 | R100: =P100+Q100 -> 0 | S100: 0.138 | U100: =F100*$AA$2 -> 0.969 | V100: =F100*$AB$2 -> 0.1368 | W100: =U100+V100 -> 1.1058 | X100: =G100 -> 0.15732 | Y100: =H100 -> 1.29732
A101: D5.3 | B101: Cable tray
...

Sheet BOQ_T
A1: Transmission Line and Sub-station
A2: Summary | B2: Particulars | C2: Unit Price | D2: Quantity | E2: Unit Rate (Rs Lakhs) | F2: Base Cost | G2: Tax | H2: Lumpsum Cost
B3: Pooling Sub-Station - 300 MW, 33/220 KV | F3: INR Lakhs | G3: INR Lakhs | H3: INR Lakhs | J3: Equipment Cost | K3: Installation Cost | L3: Base Cost
A4: 1 | B4: 33/220 kV, 80 MVA Power Transformer | C4: Lakhs/# | D4: =Input!D151 -> 4 | E4: =$F114/$D4 -> 1321.984 | F4: =D4*E4 -> 5287.936 | G4: =F4*Input!$D$167 -> 951.82848 | H4: =F4+G4 -> 6239.7645 | J4: =F4*BOQ_G!$AA$2 -> 4494.7456 | K4: =F4*BOQ_G!$AB$2 -> 634.55232 | L4: =SUM(J4:K4) -> 5129.2979
A5: 2 | B5: 33kV Incomer Feeder Bays (25MW) to 33 kV Bus | C5: Lakhs/# | D5: =Input!D152 -> 12 | E5: =SUM($F116:$F127)/$D5 -> 20.534 | F5: =D5*E5 -> 246.408 | G5: =F5*Input!$D$167 -> 44.35344 | H5: =F5+G5 -> 290.76144 | J5: =F5*BOQ_G!$AA$2 -> 209.4468 | K5: =F5*BOQ_G!$AB$2 -> 29.56896 | L5: =SUM(J5:K5) -> 239.01576
A6: 3 | B6: 33 kV Bus Section & Bus Coupler Bays | C6: Lakhs/# | D6: =Input!D153 -> 8 | E6: =SUM($F130:$F136)/$D6 -> 13.023125 | F6: =D6*E6 -> 104.185 | G6: =F6*Input!$D$167 -> 18.7533 | H6: =F6+G6 -> 122.9383 | J6: =F6*BOQ_G!$AA$2 -> 88.55725 | K6: =F6*BOQ_G!$AB$2 -> 12.5022 | L6: =SUM(J6:K6) -> 101.05945
A7: 4 | B7: 33kV incoming feeders for Power transformer | C7: Lakhs/# | D7: =Input!D154 -> 4 | E7: =SUM(F139,F141,F143,F145)/$D7 -> 19.83 | F7: =D7*E7 -> 79.32 | G7: =F7*Input!$D$167 -> 14.2776 | H7: =F7+G7 -> 93.5976 | J7: =F7*BOQ_G!$AA$2 -> 67.422 | K7: =F7*BOQ_G!$AB$2 -> 9.5184 | L7: =SUM(J7:K7) -> 76.9404
A8: 5 | B8: Reactive Power Compensation as per CEA connectivity standard, | C8: Lakhs/MVAr | D8: =Input!D155 -> 60 | E8: =SUM(F149,F151,F153,F155,F157)/$D8 -> 20.5915 | F8: =D8*E8 -> 1235.49 | G8: =F8*Input!$D$167 -> 222.3882 | H8: =F8+G8 -> 1457.8782 | J8: =F8*BOQ_G!$AA$2 -> 1050.1665 | K8: =F8*BOQ_G!$AB$2 -> 148.2588 | L8: =SUM(J8:K8) -> 1198.4253
A9: 6 | B9: 220kV Power Transformer Bay | C9: Lakhs/# | D9: =Input!D156 -> 4 | E9: =SUM(F160,F162,F164,F166,F168)/SUM($D$9:$D$11) -> 41.548 | F9: =D9*E9 -> 166.192 | G9: =F9*Input!$D$167 -> 29.91456 | H9: =F9+G9 -> 196.10656 | J9: =F9*BOQ_G!$AA$2 -> 141.2632 | K9: =F9*BOQ_G!$AB$2 -> 19.94304 | L9: =SUM(J9:K9) -> 161.20624
A10: 7 | B10: 220 kV Line Bay+ Bus Coupler Bay | C10: Lakhs/# | D10: =Input!D157 -> 3 | E10: =SUM(F160,F162,F164,F166,F168)/SUM($D$9:$D$11) -> 41.548 | F10: =D10*E10 -> 124.644 | G10: =F10*Input!$D$167 -> 22.43592 | H10: =F10+G10 -> 147.07992 | J10: =F10*BOQ_G!$AA$2 -> 105.9474 | K10: =F10*BOQ_G!$AB$2 -> 14.95728 | L10: =SUM(J10:K10) -> 120.90468
A11: 8 | B11: 220 kV Bus Transfer Bay | C11: Lakhs/# | D11: =Input!D158 -> 1 | E11: =SUM(F160,F162,F164,F166,F168)/SUM($D$9:$D$11) -> 41.548 | F11: =D11*E11 -> 41.548 | G11: =F11*Input!$D$167 -> 7.47864 | H11: =F11+G11 -> 49.02664 | J11: =F11*BOQ_G!$AA$2 -> 35.3158 | K11: =F11*BOQ_G!$AB$2 -> 4.98576 | L11: =SUM(J11:K11) -> 40.30156
A12: 9 | B12: Control & Communication | C12: Lakhs/# | D12: =Input!D159 -> 1 | E12: =SUM(F171,F173,F175,F177:F181,F183:F184)/$D12 -> 408.01 | F12: =D12*E12 -> 408.01 | G12: =F12*Input!$D$167 -> 73.4418 | H12: =F12+G12 -> 481.4518 | J12: =F12*BOQ_G!$AA$2 -> 346.8085 | K12: =F12*BOQ_G!$AB$2 -> 48.9612 | L12: =SUM(J12:K12) -> 395.7697
A13: A | B13: Pooling Sub-station | C13: MVA | D13: 320 | E13: =IF(Input!$E$8="Yes",F13/D13,0) -> 24.042916 | F13: =IF(Input!$E$8="Yes",SUM(F4:F12),"") -> 7693.733 | G13: =IF(Input!$E$8="Yes",SUM(G4:G12),"") -> 1384.8719 | H13: =IF(Input!$E$8="Yes",SUM(H4:H12),"") -> 9078.6049 | J13: =SUM(J4:J12) -> 6539.673 | K13: =SUM(K4:K12) -> 923.24796 | L13: =SUM(J13:K13) -> 7462.921
B14: Transmission Line
B15: Transmission Line Supply of Material as per specifications
A16: 1 | B16: Supply of 220kV Towers including fasteners | C16: Lakhs/Lot | D16: =Input!$D$118 -> 4 | F16: =SUM(F45:F48) -> 165.32793 | G16: =F16*Input!$E$167 -> 29.759027 | H16: =F16+G16 -> 195.08695 | J16: =F16*BOQ_G!$AA$2 -> 140.52874 | K16: =F16*BOQ_G!$AB$2 -> 19.839351 | L16: =SUM(J16:K16) -> 160.36809
A17: 2 | B17: ACCC Conductor, Earthwire Conductor & Accessories | C17: Lakhs/Lot | D17: =Input!$D$118 -> 4 | F17: =SUM(F51,F53,F56:F65) -> 481.4585 | G17: =F17*Input!$E$167 -> 86.66253 | H17: =F17+G17 -> 568.12103 | J17: =F17*BOQ_G!$AA$2 -> 409.23973 | K17: =F17*BOQ_G!$AB$2 -> 57.77502 | L17: =SUM(J17:K17) -> 467.01475
A18: 3 | B18: 220 KV Insulator with Stringing Accessories | C18: Lakhs/Lot | D18: =Input!$D$118 -> 4 | F18: =SUM(F68) -> 15.8712 | G18: =F18*Input!$E$167 -> 2.856816 | H18: =F18+G18 -> 18.728016 | J18: =F18*BOQ_G!$AA$2 -> 13.49052 | K18: =F18*BOQ_G!$AB$2 -> 1.904544 | L18: =SUM(J18:K18) -> 15.395064
A19: 4 | B19: 220kV Tower Earthing | C19: Lakhs/Lot | D19: =Input!$D$118 -> 4 | F19: =F70 -> 1.6128 | G19: =F19*Input!$E$167 -> 0.290304 | H19: =F19+G19 -> 1.903104 | J19: =F19*BOQ_G!$AA$2 -> 1.37088 | K19: =F19*BOQ_G!$AB$2 -> 0.193536 | L19: =SUM(J19:K19) -> 1.564416
A20: 5 | B20: 220kV Tower Accessories | C20: Lakhs/Lot | D20: =Input!$D$118 -> 4 | F20: =SUM(F72:F81) -> 1.5394285 | G20: =F20*Input!$E$167 -> 0.27709713 | H20: =F20+G20 -> 1.8165256 | J20: =F20*BOQ_G!$AA$2 -> 1.3085142 | K20: =F20*BOQ_G!$AB$2 -> 0.18473142 | L20: =SUM(J20:K20) -> 1.4932456
B21: Transmission Line Services & Erection Activities
A22: 1 | B22: Survey and Field Assessment | C22: Lakhs/Lot | F22: =SUM(F84:F86) -> 2.232 | G22: =F22*Input!$E$167 -> 0.40176 | H22: =F22+G22 -> 2.63376 | J22: =F22*BOQ_G!$AA$2 -> 1.8972 | K22: =F22*BOQ_G!$AB$2 -> 0.26784 | L22: =SUM(J22:K22) -> 2.16504
A23: 2 | B23: Tower Foundation and Errection | C23: Lakhs/Lot | F23: =SUM(F88:F94) -> 160.01381 | G23: =F23*Input!$E$167 -> 28.802485 | H23: =F23+G23 -> 188.81629 | J23: =F23*BOQ_G!$AA$2 -> 136.01174 | K23: =F23*BOQ_G!$AB$2 -> 19.201657 | L23: =SUM(J23:K23) -> 155.21339
A24: 3 | B24: Mounting of Insulators and Stringing | C24: Lakhs/Lot | F24: =F96+F97 -> 31.76 | G24: =F24*Input!$E$167 -> 5.7168 | H24: =F24+G24 -> 37.4768 | J24: =F24*BOQ_G!$AA$2 -> 26.996 | K24: =F24*BOQ_G!$AB$2 -> 3.8112 | L24: =SUM(J24:K24) -> 30.8072
A25: 4 | B25: Earthing of transmission towers: | C25: Lakhs/Lot | F25: =SUM(F99) -> 0.84 | G25: =F25*Input!$E$167 -> 0.1512 | H25: =F25+G25 -> 0.9912 | J25: =F25*BOQ_G!$AA$2 -> 0.714 | K25: =F25*BOQ_G!$AB$2 -> 0.1008 | L25: =SUM(J25:K25) -> 0.8148
A26: 5 | B26: ROW / Crop & Land Compensation | C26: Lakhs/Lot | F26: =SUM(F101:F104) -> 106.8 | G26: =F26*Input!$E$167 -> 19.224 | H26: =F26+G26 -> 126.024 | J26: =F26*BOQ_G!$AA$2 -> 90.78 | K26: =F26*BOQ_G!$AB$2 -> 12.816 | L26: =SUM(J26:K26) -> 103.596
A27: 6 | B27: Centage charges | C27: Lakhs/Lot | F27: =F106 -> 33.290493 | G27: =F27*Input!$E$167 -> 5.9922887 | H27: =F27+G27 -> 39.282781 | J27: =F27*BOQ_G!$AA$2 -> 28.296919 | K27: =F27*BOQ_G!$AB$2 -> 3.9948591 | L27: =SUM(J27:K27) -> 32.291778
A28: 7 | B28: Erection Charges | C28: Lakhs/Lot | F28: =F107+F108 -> 130.097 | G28: =F28*Input!$E$167 -> 23.41746 | H28: =F28+G28 -> 153.51446 | J28: =F28*BOQ_G!$AA$2 -> 110.58245 | K28: =F28*BOQ_G!$AB$2 -> 15.61164 | L28: =SUM(J28:K28) -> 126.19409
A29: B | B29: Transmission Line System | D29: 1 | E29: =IF(Input!$E$8="Yes",F29/D29,"") -> 1130.8432 | F29: =IF(Input!$E$8="Yes",SUM(F16:F28),"") -> 1130.8432 | G29: =IF(Input!$E$8="Yes",SUM(G16:G28),"") -> 203.55177 | H29: =IF(Input!$E$8="Yes",SUM(H16:H28),"") -> 1334.3949 | J29: =SUM(J16:J28) -> 961.21668 | K29: =SUM(K16:K28) -> 135.70118 | L29: =SUM(J29:K29) -> 1096.9179
B30: Augmentation Work @ BkTPS Substation
A31: 1 | B31: 220 kV Line Bay+ Bus Section Bay | C31: Lakhs/Lot | D31: =Input!D161 -> 2 | E31: =SUM(F190,F192,F194,F196,F198)/$D31 -> 42.778 | F31: =D31*E31 -> 85.556 | G31: =F31*Input!$F$167 -> 15.40008 | H31: =F31+G31 -> 100.95608 | J31: =F31*BOQ_G!$AA$2 -> 72.7226 | K31: =F31*BOQ_G!$AB$2 -> 10.26672 | L31: =SUM(J31:K31) -> 82.98932 | P31: =D31*E31 -> 85.556
A32: 2 | B32: EHV Cabling | C32: Lakhs/Mtr | D32: =Input!D162 -> 300 | E32: =(F200+F201+F202+F203)/D32 -> 0.64764 | F32: =D32*E32 -> 194.292 | G32: =F32*Input!$F$167 -> 34.97256 | H32: =F32+G32 -> 229.26456 | J32: =F32*BOQ_G!$AA$2 -> 165.1482 | K32: =F32*BOQ_G!$AB$2 -> 23.31504 | L32: =SUM(J32:K32) -> 188.46324 | P32: =D32*E32 -> 194.292
A33: 3 | B33: Miscellaneous (Control and Protection) | C33: Lakhs/No. | D33: =Input!D163 -> 1 | E33: =F12/SUM(D9:D11)*D31+F205 -> 142.2195 | F33: =D33*E33 -> 142.2195 | G33: =F33*Input!$F$167 -> 25.59951 | H33: =F33+G33 -> 167.81901 | J33: =F33*BOQ_G!$AA$2 -> 120.88657 | K33: =F33*BOQ_G!$AB$2 -> 17.06634 | L33: =SUM(J33:K33) -> 137.95291 | P33: =D33*E33 -> 142.2195
A34: C | B34: Augmentation Works | C34: Lot | D34: 1 | E34: =IF(Input!$E$8="Yes",F34/D34,"") -> 422.0675 | F34: =IF(Input!$E$8="Yes",SUM(F31:F33),"") -> 422.0675 | G34: =IF(Input!$E$8="Yes",SUM(G31:G33),"") -> 75.97215 | H34: =IF(Input!$E$8="Yes",SUM(H31:H33),"") -> 498.03965 | J34: =SUM(J31:J33) -> 358.75737 | K34: =SUM(K31:K33) -> 50.6481 | L34: =SUM(J34:K34) -> 409.40547
B35: Other Costs
B36: Contingency
A37: 1 | B37: =B3 -> Pooling Sub-Station - 300 MW, 33/220 KV | D37: =H13 -> 9078.6049 | E37: =BOQ_G!$D$220 -> 0.03 | F37: =IF(Input!$E$8="Yes",E37*D37,"") -> 272.35815 | G37: =IF(Input!$E$8="Yes",F37*Input!$F$167,"") -> 49.024467 | H37: =IF(Input!$E$8="Yes",F37+G37,"") -> 321.38261 | J37: =F37*0.85 -> 231.50443 | K37: =F37*0.15 -> 40.853722 | L37: =SUM(J37:K37) -> 272.35815
A38: 2 | B38: =B14 -> Transmission Line | D38: =H29 -> 1334.3949 | E38: =BOQ_G!$D$220 -> 0.03 | F38: =IF(Input!$E$8="Yes",E38*D38,"") -> 40.031848 | G38: =IF(Input!$E$8="Yes",F38*Input!$F$167,"") -> 7.2057326 | H38: =IF(Input!$E$8="Yes",F38+G38,"") -> 47.23758 | J38: =F38*0.85 -> 34.027071 | K38: =F38*0.15 -> 6.0047772 | L38: =SUM(J38:K38) -> 40.031848
A39: 3 | B39: =B30 -> Augmentation Work @ BkTPS Substation | D39: =H34 -> 498.03965 | E39: =BOQ_G!$D$220 -> 0.03 | F39: =IF(Input!$E$8="Yes",E39*D39,"") -> 14.941189 | G39: =IF(Input!$E$8="Yes",F39*Input!$F$167,"") -> 2.6894141 | H39: =IF(Input!$E$8="Yes",F39+G39,"") -> 17.630604 | J39: =F39*0.85 -> 12.700011 | K39: =F39*0.15 -> 2.2411784 | L39: =SUM(J39:K39) -> 14.941189
A40: D | B40: Contingency | D40: 1 | E40: =F40/D40 -> 327.33119 | F40: =SUM(F37:F39) -> 327.33119 | G40: =SUM(G37:G39) -> 58.919613 | H40: =SUM(H37:H39) -> 386.2508 | J40: =SUM(J37:J39) -> 278.23151 | K40: =SUM(K37:K39) -> 49.099678 | L40: =SUM(J40:K40) -> 327.33119
B41: Grand Total | F41: =SUM(F13,F29,F34,F40) -> 9573.9748 | G41: =SUM(G13,G29,G34,G40) -> 1723.3155 | H41: =SUM(H13,H29,H34,H40) -> 11297.29 | J41: =J40+J34+J29+J13 -> 8137.8786 | K41: =K40+K34+K29+K13 -> 1158.6969 | L41: =L40+L34+L29+L13 -> 9296.5755
B42: Transmission Line (220 kV) - BOQ | D42: No of Units | E42: Unit Rate | F42: Rs Lakhs
B43: Transmission Line - Hardware | H43: =H40+BOQ_G!H220 -> 3163.6261
A44: 1 | B44: Supply of 220kV Towers including fasteners | C44: Unit
B45: Type A - Suspension Tower - 00 to 20 | C45: MT | D45: =Input!E130*Input!E124 -> 54.6 | E45: 119400 | F45: =D45*(E45)/10^5 -> 65.1924
B46: Type B - Double Suspension Tower- 20 to 150 | C46: MT | D46: =Input!E131*Input!E125 -> 18.72 | E46: 119400 | F46: =D46*(E46)/10^5 -> 22.35168
B47: Type C - Tension Tower - 150 to 300 | C47: MT | D47: =Input!E132*Input!E126 -> 11.232 | E47: 119400 | F47: =D47*(E47)/10^5 -> 13.411008
B48: Type D - Dead End Tower - 300 to 600 | C48: MT | D48: =Input!E133*Input!E127 -> 53.9136 | E48: 119400 | F48: =D48*(E48)/10^5 -> 64.372838
A49: 2 | B49: ACCC Conductor, Earthwire Conductor & Accessories | C49: Unit
A50: A | B50: ACCC Zebra Conductor Equivalent
B51: ACCC Zebra Conductor Equivalent | C51: km | D51: =Input!D$118*(1+Input!$D$147)*6 -> 25.2 | E51: 1368200 | F51: =D51*(E51)/10^5 -> 344.7864
A52: B | B52: Earthwire Conductor
B53: OPGW Earth Wire (24 Fibers) | C53: km | D53: =Input!D$118*(1+Input!$D$147)*2 -> 8.4 | E53: =127200*(1+10%) -> 139920 | F53: =D53*(E53)/10^5 -> 11.75328
A54: C | B54: ACCC Conductor Hardwares & Accessories
B55: Hardware
B56: Single Suspension Hardware with AGS Assembly for Zebra Eq. ACCC Conductor | C56: # | D56: =Input!E124*Input!$D141 -> 42 | E56: 15630 | F56: =D56*(E56)/10^5 -> 6.5646
B57: Double Suspension Hardware with AGS Assembly for Zebra Eq. ACCC Conductor | C57: # | D57: =Input!E125*Input!$D142 -> 24 | E57: 15630 | F57: =D57*(E57)/10^5 -> 3.7512
B58: Single Tention Hardware for Zebra Eq. ACCC Conductor | C58: # | D58: =Input!E126*Input!$D143 -> 18 | E58: 56580 | F58: =D58*(E58)/10^5 -> 10.1844
B59: Double Tention Hardware for Zebra Eq. ACCC Conductor | C59: # | D59: =Input!E127*Input!$D144 -> 120 | E59: 67940 | F59: =D59*(E59)/10^5 -> 81.528
B60: Accessories
B61: Mid span compression Joints suitable for ACCC Zebra Conductor Eq. | C61: # | D61: =D51*1000/Input!$D$148 -> 28 | E61: 58100 | F61: =D61*(E61)/10^5 -> 16.268
B62: Repairing Sleeve suitable for ACCC Zebra Conductor Eq. | C62: # | D62: =D51/Input!$D$149 -> 12.6 | E62: 4170 | F62: =D62*(E62)/10^5 -> 0.52542
B63: Vibration Damper suitable for ACCC Zebra Conductor Eq. | C63: # | D63: =(SUM(Input!E124:E127)-1)*3*2 -> 78 | E63: 5740 | F63: =D63*(E63)/10^5 -> 4.4772
B64: PI Clamp for for ACCC Zebra Conductor Eq. | C64: # | D64: =(SUM(Input!E124:E125)*3*2) -> 54 | E64: 1800 | F64: =D64*(E64)/10^5 -> 0.972
B65: Jumper cone - for each jumper in case of tention tower | C65: # | D65: =(SUM(Input!E126:E127)*3*2) -> 30 | E65: 2160 | F65: =D65*(E65)/10^5 -> 0.648
A66: 3 | B66: 220 KV Insulator with Stringing Accessories
A67: A | B67: 220 KV, 120 KN polymer Insulators
B68: 120/160 KN Polymer Insulators | C68: Set | D68: =Input!E124*Input!D141+Input!D142*Input!E125+Input!E126*Input!D143+Input!E127*Input!D144 -> 204 | E68: 7780 | F68: =D68*(E68)/10^5 -> 15.8712
A69: 4 | B69: 220kV Tower Earthing
A70: A | B70: Earthing of of 220kV Double Ckt Tower comprising of 3 meter long ISI marked B class 40 MM Dia GI Pipe along with GI Flat 50 X 6 mm | C70: Set | D70: =SUM(Input!E124:E127)*4 -> 56 | E70: 2880 | F70: =D70*(E70)/10^5 -> 1.6128
A71: 5 | B71: 220kV Tower Accessories
A72: A | B72: Number Plate | C72: # | D72: =SUM(Input!E124:E127)*4 -> 56 | E72: 300 | F72: =D72*(E72)/10^5 -> 0.168
A73: B | B73: Danger Plate | C73: # | D73: =SUM(Input!E124:E127)*4 -> 56 | E73: 300 | F73: =D73*(E73)/10^5 -> 0.168
A74: C | B74: Circuit Plate | C74: Set | D74: =SUM(Input!E124:E127)*1 -> 14 | E74: 300 | F74: =D74*(E74)/10^5 -> 0.042
A75: D | B75: Phase Plate | C75: Set | D75: =SUM(Input!E124:E127)*1 -> 14 | E75: 300 | F75: =D75*(E75)/10^5 -> 0.042
A76: E | B76: Bird Guard | C76: Set | D76: =SUM(Input!E124:E127)*1 -> 14 | E76: 2200 | F76: =D76*(E76)/10^5 -> 0.308
A77: F | B77: Anti Climbing Devices | C77: Set | E77: 0 | F77: =D77*(E77)/10^5 -> 0
A78: G | B78: Tangent Towers incl. contingencies | C78: Set | D78: =Input!E124 -> 7 | E78: 4508 | F78: =D78*(E78)/10^5 -> 0.31556
A79: H | B79: Small Angle Towers incl. contingencies | C79: Set | D79: =Input!E125 -> 2 | E79: 6011.05 | F79: =D79*(E79)/10^5 -> 0.120221
A80: I | B80: Medium Angle Towers incl. contingencies | C80: Set | D80: =Input!E126 -> 1 | E80: 7512.95 | F80: =D80*(E80)/10^5 -> 0.0751295
A81: J | B81: Large Angle and Dead End Towers incl. contingencies | C81: Set | D81: =Input!E127 -> 4 | E81: 7512.95 | F81: =D81*(E81)/10^5 -> 0.300518
B82: Transmission Line - Services & Erection
A83: 1 | B83: Survey and Field Assessment
A84: A | B84: Preliminary Survey with GPS survey, theodilite & total station, marking route on topo sheets represents actual field conditions | C84: km | D84: =Input!D118 -> 4 | E84: 13700 | F84: =D84*(E84)/10^5 -> 0.548
A85: B | B85: Detailed Survey with GPS, total stations, Digital theodolite etc., along the approved alignments preparation of profiles, tower spotting, tower schedules and soil resistivity | C85: km | D85: =D84 -> 4 | E85: 26600 | F85: =D85*(E85)/10^5 -> 1.064
A86: C | B86: Check Survey, peg marking the tower positions on ground, conforming to the approved Profile and tower schedules using GPS, Total stations, Digital theodolites etc. | C86: km | D86: =D84 -> 4 | E86: 15500 | F86: =D86*(E86)/10^5 -> 0.62
A87: 2 | B87: Tower Foundation and Errection
A88: A | B88: Setting with stub for all types of towers with stub setting template which includes erection of stubs, fixing of jacks for supporting template, alignment and leveling excluding cost of excavation and concrete (excluding transportation charges) | C88: Set | D88: =SUM(Input!E124:E127) -> 14 | E88: 10300 | F88: =D88*(E88)/10^5 -> 1.442
A89: B | B89: Foundation Cost for 220kV Double Ckt Tower including excavation, cement, reinforcement etc
B90: Type A - Suspension Tower - 00 to 20 | C90: # | D90: =Input!E124 -> 7 | E90: =Input!E136 -> 800000 | F90: =D90*(E90)/10^5 -> 56
B91: Type B - Double Suspension Tower - 20 to 150 | C91: # | D91: =Input!E125 -> 2 | E91: =E90*(1+Input!$D$135) -> 920000 | F91: =D91*(E91)/10^5 -> 18.4
B92: Type C - Tension Tower - 150 to 300 | C92: # | D92: =Input!E126 -> 1 | E92: =E91*(1+Input!$D$135) -> 1058000 | F92: =D92*(E92)/10^5 -> 10.58
B93: Type D - Dead End Tower - 300 to 600 | C93: # | D93: =Input!E127 -> 4 | E93: =E92*(1+Input!$D$135) -> 1216700 | F93: =D93*(E93)/10^5 -> 48.668
A94: C | B94: Super structure erection of all type of towers including extensions except RC towers including fitting of step bolts, danger plates, number plates, phase plates, circuit plates, bird guards, anti-climbing devices etc. | C94: MT | D94: =SUM(D45:D48) -> 138.4656 | E94: 18000 | F94: =D94*(E94)/10^5 -> 24.923808
B95: Mounting of Insulators and Stringing
A96: A | B96: Mounting of Insulators and stringing of single circuit with ACCC Zebra Conductor including laying, jointing, tensioning, sagging clamping and fixing spacers (excluding transportation charges). | C96: km | D96: =D84 -> 4 | E96: 729000 | F96: =D96*(E96)/10^5 -> 29.16
A97: B | B97: Stringing of one (1) no. OPGW earthwire, including laying jointing, tensioning etc., with necessary accessories (excluding transportation charges). | C97: km | D97: =D84 -> 4 | E97: 65000 | F97: =D97*(E97)/10^5 -> 2.6
B98: Earthing of transmission towers:
A99: A | B99: Pipe type earthing including cost of BH coke & salt but excluding cost of earthing set | C99: set | D99: =SUM(Input!E124:E127) -> 14 | E99: 6000 | F99: =D99*(E99)/10^5 -> 0.84
B100: ROW / Crop & Land Compensation
...

Sheet BOQ_I
A1: Transmission Line and Sub-station
A2: Summary | B2: Particulars | D2: Unit Rate | E2: Quantity | F2: Base Cost | G2: Tax | H2: Lumpsum Cost | J2: Equipment Cost | K2: Installation Cost
A3: A | B3: Land & Site Development | F3: =F15+F19 -> 1502.05 | G3: =G15+G19 -> 270.369 | H3: =F3+G3 -> 1772.419 | J3: =F3*BOQ_G!$AA$2 -> 1276.7425 | K3: =F3*BOQ_G!$AB$2 -> 180.246
A4: B | B4: Road Infrastructure | F4: =F22 -> 73.5 | G4: =G22 -> 13.23 | H4: =F4+G4 -> 86.73 | J4: =F4*BOQ_G!$AA$2 -> 62.475 | K4: =F4*BOQ_G!$AB$2 -> 8.82
B5: Infrastructure Cost Total | F5: =SUM(F3:F4) -> 1575.55 | G5: =SUM(G3:G4) -> 283.599 | H5: =SUM(H3:H4) -> 1859.149 | J5: =F5*BOQ_G!$AA$2 -> 1339.2175 | K5: =F5*BOQ_G!$AB$2 -> 189.066
A6: C | B6: Other Charges | F6: =F29 -> 208.24 | G6: =G29 -> 37.4832 | H6: =H29 -> 245.7232 | J6: =F6*BOQ_G!$AA$2 -> 177.004 | K6: =F6*BOQ_G!$AB$2 -> 24.9888
B7: Grand Total | F7: =F5+F6 -> 1783.79 | G7: =G5+G6 -> 321.0822 | H7: =H5+H6 -> 2104.8722 | J7: =F7*BOQ_G!$AA$2 -> 1516.2215 | K7: =F7*BOQ_G!$AB$2 -> 214.0548
B9: Infrastructure Development | C9: Unit Price | D9: Rate | E9: Quantity | F9: Base Cost | G9: Tax | H9: Total Cost
A10: A | B10: Land
A11: 1 | B11: Pooling S/S + Control Room | C11: Rs Lakh/ acre | D11: =(Input!D77*Input!E77+Input!D78*Input!E78)/SUM(Input!E77:E78) -> 0 | E11: =SUM(Input!E77:E78) -> 11.125 | F11: =D11*E11 -> 0 | G11: =F11*$J11 -> 0 | H11: =F11+G11 -> 0 | J11: 0.18
A12: 2 | B12: Approach Roads | C12: Rs Lakh/ acre | D12: =Input!D79 -> 0 | E12: =Input!E79 -> 0.6125 | F12: =D12*E12 -> 0 | G12: =F12*$J12 -> 0 | H12: =F12+G12 -> 0 | J12: 0.18
A13: 3 | B13: FSPV Master Control Room | C13: Rs Lakh/ acre | D13: =Input!D80 -> 0 | E13: =Input!E80 -> 3.8955 | F13: =D13*E13 -> 0 | G13: =F13*$J13 -> 0 | H13: =F13+G13 -> 0
A14: 4 | B14: Storage | C14: Rs Lakh/ acre | D14: =Input!D81 -> 0 | E14: =Input!E81 -> 4.125 | F14: =D14*E14 -> 0 | G14: =F14*$J14 -> 0 | H14: =F14+G14 -> 0 | J14: 0.18
B15: Land Total | C15: Rs Lakh | E15: =SUM(E11:E14) -> 19.758 | F15: =SUM(F11:F14) -> 0 | G15: =SUM(G11:G14) -> 0 | H15: =SUM(H11:H14) -> 0
A16: B | B16: Site Development
A17: 1 | B17: Site Development | C17: Rs Lakh | D17: =Input!D84 -> 100 | E17: =Input!E84 -> 15.0205 | F17: =D17*E17 -> 1502.05 | G17: =F17*$J17 -> 270.369 | H17: =F17+G17 -> 1772.419 | J17: =Input!$E$225 -> 0.18
A18: 2 | B18: Green Belt | C18: Rs Lakh | D18: =Input!D101 -> 0 | E18: =Input!E101 -> 0 | F18: =D18*E18 -> 0 | G18: =F18*$J18 -> 0 | H18: =F18+G18 -> 0 | J18: =Input!$E$225 -> 0.18
B19: Site Development Total | F19: =SUM(F17:F18) -> 1502.05 | G19: =SUM(G17:G18) -> 270.369 | H19: =SUM(H17:H18) -> 1772.419
A20: C | B20: Road Infrastructure
A21: 1 | B21: Access Road to Site | C21: Rs Lakh | D21: =Input!D86 -> 120 | E21: =Input!E86 -> 0.6125 | F21: =D21*E21 -> 73.5 | G21: =F21*$J21 -> 13.23 | H21: =F21+G21 -> 86.73 | J21: =Input!$E$225 -> 0.18
B22: Road Infrastructure Total | E22: =SUM(E21:E21) -> 0.6125 | F22: =SUM(F21:F21) -> 73.5 | G22: =SUM(G21:G21) -> 13.23 | H22: =SUM(H21:H21) -> 86.73
B24: Other Charges/Statutory Charges
A25: 1 | B25: Local Area Development Charges | C25: Rs Lakh | D25: =Input!D107 -> 100000 | E25: =Input!E107 -> 203.24 | F25: =D25*E25/10^5 -> 203.24 | G25: =F25*$J25 -> 36.5832 | H25: =F25+G25 -> 239.8232 | J25: =Input!$E$225 -> 0.18
A26: 2 | B26: Registration Cost | C26: Rs Lakh | D26: =Input!D108 -> 0 | E26: =Input!E108 -> 203.24 | F26: =D26*E26/10^5 -> 0 | G26: =F26*$J26 -> 0 | H26: =F26+G26 -> 0 | J26: =Input!$E$225 -> 0.18
A27: 3 | B27: Legal Charges | C27: Rs Lakh | D27: =Input!D109 -> 0 | E27: =Input!E109 -> 203.24 | F27: =D27*E27/10^5 -> 0 | G27: =F27*$J27 -> 0 | H27: =F27+G27 -> 0 | J27: =Input!$E$225 -> 0.18
A28: 4 | B28: Regulatory Charges | C28: Rs Lakh | D28: =Input!D110 -> 500000 | E28: =Input!E110 -> 1 | F28: =D28*E28/10^5 -> 5 | G28: =F28*$J28 -> 0.9 | H28: =F28+G28 -> 5.9 | J28: =Input!$E$225 -> 0.18
B29: Other Charges - Total | C29: Rs Lakh | F29: =SUM(F25:F28) -> 208.24 | G29: =SUM(G25:G28) -> 37.4832 | H29: =SUM(H25:H28) -> 245.7232

Sheet Working
B1: Particulars | C1: Units | D1: Inputs | E1: =YEAR(E2) -> 2026 | F1: =E1+1 -> 2027 | G1: =F1+1 -> 2028 | H1: =G1+1 -> 2029 | I1: =H1+1 -> 2030 | J1: =I1+1 -> 2031 | K1: =J1+1 -> 2032 | L1: =K1+1 -> 2033 | M1: =L1+1 -> 2034 | ... AJ1: =AI1+1 -> 2057
D2: =Input!D238 -> 45747 | E2: =EOMONTH(D2,12) -> 46112 | F2: =EOMONTH(E2,12) -> 46477 | G2: =EOMONTH(F2,12) -> 46843 | H2: =EOMONTH(G2,12) -> 47208 | I2: =EOMONTH(H2,12) -> 47573 | J2: =EOMONTH(I2,12) -> 47938 | K2: =EOMONTH(J2,12) -> 48304 | L2: =EOMONTH(K2,12) -> 48669 | ... AJ2: =EOMONTH(AI2,12) -> 57435
B3: Total Year Counter | D3: 0 | E3: =D3+1 -> 1 | F3: =E3+1 -> 2 | G3: =F3+1 -> 3 | H3: =G3+1 -> 4 | I3: =H3+1 -> 5 | J3: =I3+1 -> 6 | K3: =J3+1 -> 7 | L3: =K3+1 -> 8 | ... AJ3: =AI3+1 -> 32
B4: Is Operational ? | C4: =SUM(E4:AI4) -> 26 | E4: =IF(AND(E2>=Input!$E$180,E2<=Input!$E$182),1,0) -> 0 | F4: =IF(AND(F2>=Input!$E$180,F2<=Input!$E$182),1,0) -> 1 | G4: =IF(AND(G2>=Input!$E$180,G2<=Input!$E$182),1,0) -> 1 | H4: =IF(AND(H2>=Input!$E$180,H2<=Input!$E$182),1,0) -> 1 | I4: =IF(AND(I2>=Input!$E$180,I2<=Input!$E$182),1,0) -> 1 | J4: =IF(AND(J2>=Input!$E$180,J2<=Input!$E$182),1,0) -> 1 | K4: =IF(AND(K2>=Input!$E$180,K2<=Input!$E$182),1,0) -> 1 | L4: =IF(AND(L2>=Input!$E$180,L2<=Input!$E$182),1,0) -> 1 | ... AJ4: =IF(AND(AJ2>=Input!$E$180,AJ2<=Input!$E$182),1,0) -> 0
B5: Operational Year Number | E5: =SUM($E4:E$4) -> 0 | F5: =SUM($E4:F$4) -> 1 | G5: =SUM($E4:G$4) -> 2 | H5: =SUM($E4:H$4) -> 3 | I5: =SUM($E4:I$4) -> 4 | J5: =SUM($E4:J$4) -> 5 | K5: =SUM($E4:K$4) -> 6 | L5: =SUM($E4:L$4) -> 7 | ... AJ5: =SUM($E4:AJ$4) -> 26
B6: Days in year | E6: =E2-D2 -> 365 | F6: =F2-E2 -> 365 | G6: =G2-F2 -> 366 | H6: =H2-G2 -> 365 | I6: =I2-H2 -> 365 | J6: =J2-I2 -> 365 | K6: =K2-J2 -> 366 | L6: =L2-K2 -> 365 | ... AJ6: =AJ2-AI2 -> 365
B7: Days of Construction | E7: =E6-E8 -> 365 | F7: =F6-F8 -> 183 | G7: =G6-G8 -> 0 | H7: =H6-H8 -> 0 | I7: =I6-I8 -> 0 | J7: =J6-J8 -> 0 | K7: =K6-K8 -> 0 | L7: =L6-L8 -> 0
B8: Days in Operations | E8: =IF(E2=Input!$E$182,Input!$E$181-D2,IF(E2-Input!$E$178+1>=365,E2-D2,E2-Input!$E$178+1))*E4 -> 0 | F8: =IF(F2=Input!$E$182,Input!$E$181-E2,IF(F2-Input!$E$178+1>=365,F2-E2,F2-Input!$E$178+1))*F4 -> 182 | G8: =IF(G2=Input!$E$182,Input!$E$181-F2,IF(G2-Input!$E$178+1>=365,G2-F2,G2-Input!$E$178+1))*G4 -> 366 | H8: =IF(H2=Input!$E$182,Input!$E$181-G2,IF(H2-Input!$E$178+1>=365,H2-G2,H2-Input!$E$178+1))*H4 -> 365 | I8: =IF(I2=Input!$E$182,Input!$E$181-H2,IF(I2-Input!$E$178+1>=365,I2-H2,I2-Input!$E$178+1))*I4 -> 365 | J8: =IF(J2=Input!$E$182,Input!$E$181-I2,IF(J2-Input!$E$178+1>=365,J2-I2,J2-Input!$E$178+1))*J4 -> 365 | K8: =IF(K2=Input!$E$182,Input!$E$181-J2,IF(K2-Input!$E$178+1>=365,K2-J2,K2-Input!$E$178+1))*K4 -> 366 | L8: =IF(L2=Input!$E$182,Input!$E$181-K2,IF(L2-Input!$E$178+1>=365,L2-K2,L2-Input!$E$178+1))*L4 -> 365 | ... AJ8: =IF(AJ2=Input!$E$182,Input!$E$181-AI2,IF(AJ2-Input!$E$178+1>=365,AJ2-AI2,AJ2-Input!$E$178+1))*AJ4 -> 0
B9: Proportion of year in operation | E9: =IF(E6,E8/E6,0) -> 0 | F9: =IF(F6,F8/F6,0) -> 0.49863014 | G9: =IF(G6,G8/G6,0) -> 1 | H9: =IF(H6,H8/H6,0) -> 1 | I9: =IF(I6,I8/I6,0) -> 1 | J9: =IF(J6,J8/J6,0) -> 1 | K9: =IF(K6,K8/K6,0) -> 1 | L9: =IF(L6,L8/L6,0) -> 1 | ... AJ9: =IF(AJ6,AJ8/AJ6,0) -> 0
B10: Cumulative number of year in operation | E10: =D10+E9 -> 0 | F10: =E10+F9 -> 0.49863014 | G10: =F10+G9 -> 1.4986301 | H10: =G10+H9 -> 2.4986301 | I10: =H10+I9 -> 3.4986301 | J10: =I10+J9 -> 4.4986301 | K10: =J10+K9 -> 5.4986301 | L10: =K10+L9 -> 6.4986301 | ... AJ10: =AI10+AJ9 -> 24.99863
A12: CapEX
B13: Capacity of the Project | C13: MW | D13: =Input!E6 -> 203.24 | F13: MWp | G13: =Input!$E$4 -> 243.888
B14: Generation Project | C14: Unit | D14: Unit Cost | E14: Quantity | F14: Cost (Rs Lakh) | G14: Tax | H14: Total Cost
A15: II | B15: Capital Expenditure - Generation
A16: A | B16: SPV Modules | C16: Lot | D16: =BOQ_G!D2 -> 159 | E16: =BOQ_G!E2 -> 243.888 | F16: =BOQ_G!F2 -> 38728.483 | G16: =BOQ_G!G2 -> 5344.5306 | H16: =BOQ_G!H2 -> 44073.013
A17: B | B17: Inverters | C17: Lot | D17: =BOQ_G!D3 -> 13 | E17: =BOQ_G!E3 -> 203.24 | F17: =BOQ_G!F3 -> 2650.5 | G17: =BOQ_G!G3 -> 365.769 | H17: =BOQ_G!H3 -> 3016.269
A18: C | B18: Floating Structure for Module and inverters | C18: Lot | D18: =BOQ_G!D4 -> 135 | E18: =BOQ_G!E4 -> 243.888 | F18: =BOQ_G!F4 -> 32929.861 | G18: =BOQ_G!G4 -> 4544.3208 | H18: =BOQ_G!H4 -> 37474.182
A19: D | B19: Balance of Plant (Cables, SCB, Accessories) | C19: Lot | D19: =BOQ_G!D8 -> 40 | E19: =BOQ_G!E8 -> 243.888 | F19: =BOQ_G!F8 -> 9694.1833 | G19: =BOQ_G!G8 -> 1337.7973 | H19: =BOQ_G!H8 -> 11031.981
A20: E | B20: Civil Structure | C20: Lot | D20: =BOQ_G!D14 -> 7 | E20: =BOQ_G!E14 -> 243.888 | F20: =BOQ_G!F14 -> 1663.1343 | G20: =BOQ_G!G14 -> 229.51254 | H20: =BOQ_G!H14 -> 1892.6469
B21: Capital Expenditure - Generation | C21: Lot | F21: =SUM(F16:F20) -> 85666.161 | G21: =SUM(G16:G20) -> 11821.93 | H21: =SUM(H16:H20) -> 97488.091
A22: III | B22: Capital Expenditure - Transmission Evacuation
A23: A | B23: Pooling Sub-station | C23: MVA | D23: =F23/E23 -> 24.042916 | E23: =BOQ_T!D13 -> 320 | F23: =BOQ_T!F13 -> 7693.733 | G23: =BOQ_T!G13 -> 1384.8719 | H23: =BOQ_T!H13 -> 9078.6049
A24: B | B24: Transmission Line System | C24: kM | D24: =F24/E24 -> 282.71079 | E24: =Input!D118 -> 4 | F24: =BOQ_T!F29 -> 1130.8432 | G24: =BOQ_T!G29 -> 203.55177 | H24: =BOQ_T!H29 -> 1334.3949
A25: C | B25: Augmentation Works | C25: Lot | D25: =F25/E25 -> 422.0675 | E25: 1 | F25: =BOQ_T!F34 -> 422.0675 | G25: =BOQ_T!G34 -> 75.97215 | H25: =BOQ_T!H34 -> 498.03965
B26: Capital Expenditure - Transmission Evacuation | C26: Lot | F26: =SUM(F23:F25) -> 9246.6437 | G26: =SUM(G23:G25) -> 1664.3959 | H26: =SUM(H23:H25) -> 10911.04
A27: I | B27: Capital Expenditure - Infrastructure
A28: A | B28: Land & Site Development | C28: Lot | D28: =BOQ_I!D3 -> 0 | E28: =BOQ_I!E3 -> 0 | F28: =BOQ_I!F3 -> 1502.05 | G28: =BOQ_I!G3 -> 270.369 | H28: =SUM(F28:G28) -> 1772.419
A29: B | B29: Road Infrastructure | C29: Lot | D29: =BOQ_I!D4 -> 0 | E29: =BOQ_I!E4 -> 0 | F29: =BOQ_I!F4 -> 73.5 | G29: =BOQ_I!G4 -> 13.23 | H29: =SUM(F29:G29) -> 86.73
B30: Capital Expenditure - Infrastructure | C30: Lot | F30: =SUM(F28:F29) -> 1575.55 | G30: =SUM(G28:G29) -> 283.599 | H30: =SUM(H28:H29) -> 1859.149
A31: IV | B31: Capital Expenditure - Other Costs
A32: A | B32: Generation (Contingency, Insurance, Warranty, etc) | C32: Lot | F32: =BOQ_G!F19+BOQ_G!F21 -> 9449.5874 | G32: =BOQ_G!G19+BOQ_G!G21 -> 1304.0431 | H32: =BOQ_G!H19+BOQ_G!H21 -> 10753.63
A33: B | B33: Transmission (Contingency, Insurance, Warranty, etc) | C33: Lot | F33: =BOQ_T!F40 -> 327.33119 | G33: =BOQ_T!G40 -> 58.919613 | H33: =BOQ_T!H40 -> 386.2508
A34: C | B34: Other Charges/Statutory Charges | C34: Lot | F34: =BOQ_I!F6 -> 208.24 | G34: =BOQ_I!G6 -> 37.4832 | H34: =BOQ_I!H6 -> 245.7232
B35: Capital Expenditure - Other Costs | C35: Lot | F35: =SUM(F32:F34) -> 9985.1586 | G35: =SUM(G32:G34) -> 1400.4459 | H35: =SUM(H32:H34) -> 11385.604
B36: Total Project Cost w/o IDC | F36: =F21+F26+F30+F35 -> 106473.51 | G36: =G21+G26+G30+G35 -> 15170.371 | H36: =H21+H26+H30+H35 -> 121643.88
B37: Interest During Construction | C37: Lot | H37: =D52*100 -> 2612.319
B38: Grand Total | C38: Lot | F38: =F36+F37 -> 106473.51 | G38: =G36+G37 -> 15170.371 | H38: =H36+H37 -> 124256.2
B39: Capital Cost without IDC
A40: 1 | B40: Capital Expenditure - Generation & Transmission | C40: Rs Cr | F40: =(F26+F21)/100 -> 949.12805 | G40: =(G26+G21)/100 -> 134.86326 | H40: =(H26+H21)/100 -> 1083.9913
A41: 2 | B41: Capital Expenditure - Infrastructure | C41: Rs Cr | F41: =F30/100 -> 15.7555 | G41: =G30/100 -> 2.83599 | H41: =H30/100 -> 18.59149
A42: 3 | B42: Capital Expenditure - Other Costs | C42: Rs Cr | F42: =F35/100 -> 99.851586 | G42: =G35/100 -> 14.004459 | H42: =H35/100 -> 113.85604
B43: Capital Cost - Total | C43: Rs Cr | F43: =SUM(F40:F42) -> 1064.7351 | G43: =SUM(G40:G42) -> 151.70371 | H43: =SUM(H40:H42) -> 1216.4388
B44: Interest During Construction | C44: Rs Cr | H44: =D52 -> 26.12319
B45: Gross Capital Cost | C45: Rs Cr | H45: =SUM(H43:H44) -> 1242.562
A47: Phasing
A48: 1 | B48: Capital Expenditure - Generation & Transmission | C48: Rs Cr | D48: =SUM(E48:AI48) -> 1083.9913 | E48: =$H$40*Input!E$241 -> 559.93326 | F48: =$H$40*Input!F$241 -> 524.05805 | G48: =$H$40*Input!H$241 -> 0 | H48: =$H$40*Input!I$241 -> 0 | I48: =$H$40*Input!J$241 -> 0 | J48: =$H$40*Input!K$241 -> 0 | K48: =$H$40*Input!L$241 -> 0 | L48: =$H$40*Input!M$241 -> 0 | M48: =$H$40*Input!N$241 -> 0 | N48: =$H$40*Input!O$241 -> 0 | ... AI48: =$H$40*Input!AJ$241 -> 0
A49: 2 | B49: Capital Expenditure - Infrastructure | C49: Rs Cr | D49: =SUM(E49:AI49) -> 18.59149 | E49: =$H$41*Input!E$242 -> 5.577447 | F49: =$H$41*Input!F$242 -> 13.014043 | G49: =$H$41*Input!H$242 -> 0 | H49: =$H$41*Input!I$242 -> 0 | I49: =$H$41*Input!J$242 -> 0 | J49: =$H$41*Input!K$242 -> 0 | K49: =$H$41*Input!L$242 -> 0 | L49: =$H$41*Input!M$242 -> 0 | M49: =$H$41*Input!N$242 -> 0 | N49: =$H$41*Input!O$242 -> 0 | ... AI49: =$H$41*Input!AJ$242 -> 0
A50: 3 | B50: Capital Expenditure - Other Costs | C50: Rs Cr | D50: =SUM(E50:AI50) -> 113.85604 | E50: =$H$42*Input!E$243 -> 11.385604 | F50: =$H$42*Input!F$243 -> 102.47044 | G50: =$H$42*Input!H$243 -> 0 | H50: =$H$42*Input!I$243 -> 0 | I50: =$H$42*Input!J$243 -> 0 | J50: =$H$42*Input!K$243 -> 0 | K50: =$H$42*Input!L$243 -> 0 | L50: =$H$42*Input!M$243 -> 0 | M50: =$H$42*Input!N$243 -> 0 | N50: =$H$42*Input!O$243 -> 0 | ... AI50: =$H$42*Input!AJ$243 -> 0
B51: Phasing - Capex | C51: Rs Cr | D51: =SUM(E51:AI51) -> 1216.4388 | E51: =SUM(E48:E50) -> 576.89631 | F51: =SUM(F48:F50) -> 639.54253 | G51: =SUM(G48:G50) -> 0 | H51: =SUM(H48:H50) -> 0 | I51: =SUM(I48:I50) -> 0 | J51: =SUM(J48:J50) -> 0 | K51: =SUM(K48:K50) -> 0 | L51: =SUM(L48:L50) -> 0 | ... AI51: =SUM(AI48:AI50) -> 0
B52: IDC | C52: Rs Cr | D52: =SUM(E52:AI52) -> 26.12319 | E52: =IF(Input!$L$2,E90+E80,0) -> 5.1522659 | F52: =IF(Input!$L$2,F90+F80,0) -> 20.970924 | G52: =IF(Input!$L$2,G90+G80,0) -> 0 | H52: =IF(Input!$L$2,H90+H80,0) -> 0 | I52: =IF(Input!$L$2,I90+I80,0) -> 0 | J52: =IF(Input!$L$2,J90+J80,0) -> 0 | K52: =IF(Input!$L$2,K90+K80,0) -> 0 | L52: =IF(Input!$L$2,L90+L80,0) -> 0 | ... AI52: =IF(Input!$L$2,AI90+AI80,0) -> 0
B53: Capex incl. IDC | C53: Rs Cr | D53: =SUM(E53:AI53) -> 1242.562 | E53: =(E51+E52)*(1+Input!$I$10) -> 582.04858 | F53: =(F51+F52)*(1+Input!$I$10) -> 660.51346 | G53: =G51+G52 -> 0 | H53: =H51+H52 -> 0 | I53: =I51+I52 -> 0 | J53: =J51+J52 -> 0 | K53: =K51+K52 -> 0 | L53: =L51+L52 -> 0 | M53: =M51+M52 -> 0 | N53: =N51+N52 -> 0 | ... AI53: =AI51+AI52 -> 0
B55: Commerical Loan 1 | C55: % | E55: =Input!E245 -> 0.7 | F55: =Input!F245 -> 0.7 | G55: =Input!H245 -> 0.7 | H55: =Input!J245 -> 0.7 | I55: =Input!K245 -> 0.7 | J55: =Input!L245 -> 0.7 | K55: =Input!M245 -> 0.7 | L55: =Input!N245 -> 0.7 | M55: =Input!O245 -> 0.7 | N55: =Input!P245 -> 0.7 | O55: =Input!Q245 -> 0.7 | ... AI55: =Input!AK245 -> 0.7
B56: Commercial Loan 2 | C56: % | E56: =Input!E246 -> 0 | F56: =Input!F246 -> 0 | G56: =Input!H246 -> 0 | H56: =Input!J246 -> 0 | I56: =Input!K246 -> 0 | J56: =Input!L246 -> 0 | K56: =Input!M246 -> 0 | L56: =Input!N246 -> 0 | M56: =Input!O246 -> 0 | N56: =Input!P246 -> 0 | O56: =Input!Q246 -> 0 | ... AI56: =Input!AK246 -> 0
B57: Grant | C57: % | E57: =Input!E247 -> 0 | F57: =Input!F247 -> 0 | G57: =Input!H247 -> 0 | H57: =Input!J247 -> 0 | I57: =Input!K247 -> 0 | J57: =Input!L247 -> 0 | K57: =Input!M247 -> 0 | L57: =Input!N247 -> 0 | M57: =Input!O247 -> 0 | N57: =Input!P247 -> 0 | O57: =Input!Q247 -> 0 | ... AI57: =Input!AK247 -> 0
B58: Equity | C58: % | E58: =Input!E248 -> 0.3 | F58: =Input!F248 -> 0.3 | G58: =Input!H248 -> 0.3 | H58: =Input!J248 -> 0.3 | I58: =Input!K248 -> 0.3 | J58: =Input!L248 -> 0.3 | K58: =Input!M248 -> 0.3 | L58: =Input!N248 -> 0.3 | M58: =Input!O248 -> 0.3 | N58: =Input!P248 -> 0.3 | O58: =Input!Q248 -> 0.3 | ... AI58: =Input!AK248 -> 0.3
B60: Commerical Loan 1 | C60: Rs Cr | D60: =SUM(E60:AI60) -> 869.79342 | E60: =E$53*E55 -> 407.434 | F60: =F$53*F55 -> 462.35942 | G60: =G$53*G55 -> 0 | H60: =H$53*H55 -> 0 | I60: =I$53*I55 -> 0 | J60: =J$53*J55 -> 0 | K60: =K$53*K55 -> 0 | L60: =L$53*L55 -> 0 | ... AI60: =AI$53*AI55 -> 0
B61: Commerical Loan 2 | C61: Rs Cr | D61: =SUM(E61:AI61) -> 0 | E61: =E$53*E56 -> 0 | F61: =F$53*F56 -> 0 | G61: =G$53*G56 -> 0 | H61: =H$53*H56 -> 0 | I61: =I$53*I56 -> 0 | J61: =J$53*J56 -> 0 | K61: =K$53*K56 -> 0 | L61: =L$53*L56 -> 0 | ... AI61: =AI$53*AI56 -> 0
B62: Grant | C62: Rs Cr | D62: =SUM(E62:AI62) -> 0 | E62: =E$53*E57 -> 0 | F62: =F$53*F57 -> 0 | G62: =G$53*G57 -> 0 | H62: =H$53*H57 -> 0 | I62: =I$53*I57 -> 0 | J62: =J$53*J57 -> 0 | K62: =K$53*K57 -> 0 | L62: =L$53*L57 -> 0 | ... AI62: =AI$53*AI57 -> 0
B63: Equity | C63: Rs Cr | D63: =SUM(E63:AI63) -> 372.76861 | E63: =E$53*E58 -> 174.61457 | F63: =F$53*F58 -> 198.15404 | G63: =G$53*G58 -> 0 | H63: =H$53*H58 -> 0 | I63: =I$53*I58 -> 0 | J63: =J$53*J58 -> 0 | K63: =K$53*K58 -> 0 | L63: =L$53*L58 -> 0 | ... AI63: =AI$53*AI58 -> 0
D64: =SUM(D60:D63)-D53 -> 0
A65: Grant Schedule
B66: Grant | C66: Rs Cr | E66: =E62 -> 0 | F66: =F62 -> 0 | G66: =G62 -> 0 | H66: =H62 -> 0 | I66: =I62 -> 0 | J66: =J62 -> 0 | K66: =K62 -> 0 | L66: =L62 -> 0 | ... AI66: =AI62 -> 0
B67: Cumulative Grant | C67: Rs Cr | E67: =D67+E66 -> 0 | F67: =E67+F66 -> 0 | G67: =F67+G66 -> 0 | H67: =G67+H66 -> 0 | I67: =H67+I66 -> 0 | J67: =I67+J66 -> 0 | K67: =J67+K66 -> 0 | L67: =K67+L66 -> 0 | ... AI67: =AH67+AI66 -> 0
A69: Equity Schedule
B70: Equity | C70: Rs Cr | E70: =E63 -> 174.61457 | F70: =F63 -> 198.15404 | G70: =G63 -> 0 | H70: =H63 -> 0 | I70: =I63 -> 0 | J70: =J63 -> 0 | K70: =K63 -> 0 | L70: =L63 -> 0 | ... AI70: =AI63 -> 0
B71: Cumulative Equity | C71: Rs Cr | E71: =D71+E70 -> 174.61457 | F71: =E71+F70 -> 372.76861 | G71: =F71+G70 -> 372.76861 | H71: =G71+H70 -> 372.76861 | I71: =H71+I70 -> 372.76861 | J71: =I71+J70 -> 372.76861 | K71: =J71+K70 -> 372.76861 | L71: =K71+L70 -> 372.76861 | ... AI71: =AH71+AI70 -> 372.76861
A73: Commerical Loan 1 Schedule
B74: Opening | C74: Rs Cr | E74: =D77 -> 0 | F74: =E77 -> 407.434 | G74: =F77 -> 840.80031 | H74: =G77 -> 782.81408 | I74: =H77 -> 724.82785 | J74: =I77 -> 666.84162 | K74: =J77 -> 608.8554 | L74: =K77 -> 550.86917 | ... AI74: =AH77 -> 0
B75: Addition | C75: Rs Cr | D75: =SUM(E75:V75) -> 869.79342 | E75: =SUMIF(IDC_Q!$E$6:$AJ$6,E$3,IDC_Q!$E$75:$AI$75) -> 407.434 | F75: =SUMIF(IDC_Q!$E$6:$AJ$6,F$3,IDC_Q!$E$75:$AI$75) -> 462.35942 | G75: =SUMIF(IDC_Q!$E$6:$AJ$6,G$3,IDC_Q!$E$75:$AI$75) -> 0 | H75: =SUMIF(IDC_Q!$E$6:$AJ$6,H$3,IDC_Q!$E$75:$AI$75) -> 0 | I75: =SUMIF(IDC_Q!$E$6:$AJ$6,I$3,IDC_Q!$E$75:$AI$75) -> 0 | J75: =SUMIF(IDC_Q!$E$6:$AJ$6,J$3,IDC_Q!$E$75:$AI$75) -> 0 | K75: =SUMIF(IDC_Q!$E$6:$AJ$6,K$3,IDC_Q!$E$75:$AI$75) -> 0 | L75: =SUMIF(IDC_Q!$E$6:$AJ$6,L$3,IDC_Q!$E$75:$AI$75) -> 0 | ... AI75: =SUMIF(IDC_Q!$E$6:$AJ$6,AI$3,IDC_Q!$E$75:$AI$75) -> 0
B76: Repayments | C76: Rs Cr | E76: =IF(E$10>Input!$E$184,MIN(E74+E75,$D$75/(Input!$E$185)),0) -> 0 | F76: =IF(F$10>Input!$E$184,MIN(F74+F75,$D$75/(Input!$E$185*2)),0) -> 28.993114 | G76: =IF(G$10>Input!$E$184,MIN(G74+G75,$D$75/(Input!$E$185)),0) -> 57.986228 | H76: =IF(H$10>Input!$E$184,MIN(H74+H75,$D$75/(Input!$E$185)),0) -> 57.986228 | I76: =IF(I$10>Input!$E$184,MIN(I74+I75,$D$75/(Input!$E$185)),0) -> 57.986228 | J76: =IF(J$10>Input!$E$184,MIN(J74+J75,$D$75/(Input!$E$185)),0) -> 57.986228 | K76: =IF(K$10>Input!$E$184,MIN(K74+K75,$D$75/(Input!$E$185)),0) -> 57.986228 | L76: =IF(L$10>Input!$E$184,MIN(L74+L75,$D$75/(Input!$E$185)),0) -> 57.986228 | M76: =IF(M$10>Input!$E$184,MIN(M74+M75,$D$75/(Input!$E$185)),0) -> 57.986228 | N76: =IF(N$10>Input!$E$184,MIN(N74+N75,$D$75/(Input!$E$185)),0) -> 57.986228 | ... AI76: =IF(AI$10>Input!$E$184,MIN(AI74+AI75,$D$75/(Input!$E$185)),0) -> 0
B77: Closing | C77: Rs Cr | E77: =E74+E75-E76 -> 407.434 | F77: =F74+F75-F76 -> 840.80031 | G77: =G74+G75-G76 -> 782.81408 | H77: =H74+H75-H76 -> 724.82785 | I77: =I74+I75-I76 -> 666.84162 | J77: =J74+J75-J76 -> 608.8554 | K77: =K74+K75-K76 -> 550.86917 | L77: =L74+L75-L76 -> 492.88294 | ... AI77: =AI74+AI75-AI76 -> 0
B79: Interest Rate | C79: % | E79: =Input!$E$186 -> 0.06 | F79: =Input!$E$186 -> 0.06 | G79: =Input!$E$186 -> 0.06 | H79: =Input!$E$186 -> 0.06 | I79: =Input!$E$186 -> 0.06 | J79: =Input!$E$186 -> 0.06 | K79: =Input!$E$186 -> 0.06 | L79: =Input!$E$186 -> 0.06 | ... AI79: =Input!$E$186 -> 0.06
B80: IDC | C80: Rs Cr | E80: =SUMIF(IDC_Q!$E$6:$AJ$6,E$3,IDC_Q!$E$80:$AI$80) -> 5.1522659 | F80: =SUMIF(IDC_Q!$E$6:$AJ$6,F$3,IDC_Q!$E$80:$AI$80) -> 20.970924 | G80: =SUMIF(IDC_Q!$E$6:$AJ$6,G$3,IDC_Q!$E$80:$AI$80) -> 0 | H80: =SUMIF(IDC_Q!$E$6:$AJ$6,H$3,IDC_Q!$E$80:$AI$80) -> 0 | I80: =SUMIF(IDC_Q!$E$6:$AJ$6,I$3,IDC_Q!$E$80:$AI$80) -> 0 | J80: =SUMIF(IDC_Q!$E$6:$AJ$6,J$3,IDC_Q!$E$80:$AI$80) -> 0 | K80: =SUMIF(IDC_Q!$E$6:$AJ$6,K$3,IDC_Q!$E$80:$AI$80) -> 0 | L80: =SUMIF(IDC_Q!$E$6:$AJ$6,L$3,IDC_Q!$E$80:$AI$80) -> 0 | ... AI80: =SUMIF(IDC_Q!$E$6:$AJ$6,AI$3,IDC_Q!$E$80:$AI$80) -> 0
B81: Interest Charge | C81: Rs Cr | D81: =SUM(E81:AF81) -> 384.85525 | E81: =AVERAGE(E74,E77)*E79*E9 -> 0 | F81: =AVERAGE(F74,F77)*F79*F9 -> 18.672217 | G81: =AVERAGE(G74,G77)*G79*G9 -> 48.708432 | H81: =AVERAGE(H74,H77)*H79*H9 -> 45.229258 | I81: =AVERAGE(I74,I77)*I79*I9 -> 41.750084 | J81: =AVERAGE(J74,J77)*J79*J9 -> 38.270911 | K81: =AVERAGE(K74,K77)*K79*K9 -> 34.791737 | L81: =AVERAGE(L74,L77)*L79*L9 -> 31.312563 | ... AI81: =AVERAGE(AI74,AI77)*AI79*AI9 -> 0
A83: Commercial Loan 2 Schedule
B84: Opening | C84: Rs Cr | E84: =D87 -> 0 | F84: =E87 -> 0 | G84: =F87 -> 0 | H84: =G87 -> 0 | I84: =H87 -> 0 | J84: =I87 -> 0 | K84: =J87 -> 0 | L84: =K87 -> 0 | ... AI84: =AH87 -> 0
B85: Addition | C85: Rs Cr | D85: =SUM(E85:V85) -> 0 | E85: =SUMIF(IDC_Q!$E$6:$AJ$6,E$3,IDC_Q!$E85:$AI85) -> 0 | F85: =SUMIF(IDC_Q!$E$6:$AJ$6,F$3,IDC_Q!$E85:$AI85) -> 0 | G85: =SUMIF(IDC_Q!$E$6:$AJ$6,G$3,IDC_Q!$E85:$AI85) -> 0 | H85: =SUMIF(IDC_Q!$E$6:$AJ$6,H$3,IDC_Q!$E85:$AI85) -> 0 | I85: =SUMIF(IDC_Q!$E$6:$AJ$6,I$3,IDC_Q!$E85:$AI85) -> 0 | J85: =SUMIF(IDC_Q!$E$6:$AJ$6,J$3,IDC_Q!$E85:$AI85) -> 0 | K85: =SUMIF(IDC_Q!$E$6:$AJ$6,K$3,IDC_Q!$E85:$AI85) -> 0 | L85: =SUMIF(IDC_Q!$E$6:$AJ$6,L$3,IDC_Q!$E85:$AI85) -> 0 | ... AI85: =SUMIF(IDC_Q!$E$6:$AJ$6,AI$3,IDC_Q!$E85:$AI85) -> 0
B86: Repayments | C86: Rs Cr | E86: =IF(E$10>Input!$E$188,MIN(E84+E85,$D$85/(Input!$E$189)),0) -> 0 | F86: =IF(F$10>Input!$E$188,MIN(F84+F85,$D$85/(Input!$E$189)),0) -> 0 | G86: =IF(G$10>Input!$E$188,MIN(G84+G85,$D$85/(Input!$E$189)),0) -> 0 | H86: =IF(H$10>Input!$E$188,MIN(H84+H85,$D$85/(Input!$E$189)),0) -> 0 | I86: =IF(I$10>Input!$E$188,MIN(I84+I85,$D$85/(Input!$E$189)),0) -> 0 | J86: =IF(J$10>Input!$E$188,MIN(J84+J85,$D$85/(Input!$E$189)),0) -> 0 | K86: =IF(K$10>Input!$E$188,MIN(K84+K85,$D$85/(Input!$E$189)),0) -> 0 | L86: =IF(L$10>Input!$E$188,MIN(L84+L85,$D$85/(Input!$E$189)),0) -> 0 | ... AI86: =IF(AI$10>Input!$E$188,MIN(AI84+AI85,$D$85/(Input!$E$189)),0) -> 0
B87: Closing | C87: Rs Cr | E87: =E84+E85-E86 -> 0 | F87: =F84+F85-F86 -> 0 | G87: =G84+G85-G86 -> 0 | H87: =H84+H85-H86 -> 0 | I87: =I84+I85-I86 -> 0 | J87: =J84+J85-J86 -> 0 | K87: =K84+K85-K86 -> 0 | L87: =L84+L85-L86 -> 0 | ... AI87: =AI84+AI85-AI86 -> 0
B89: Interest Rate | C89: % | E89: =Input!$E$190 -> 0.085 | F89: =Input!$E$190 -> 0.085 | G89: =Input!$E$190 -> 0.085 | H89: =Input!$E$190 -> 0.085 | I89: =Input!$E$190 -> 0.085 | J89: =Input!$E$190 -> 0.085 | K89: =Input!$E$190 -> 0.085 | L89: =Input!$E$190 -> 0.085 | ... AI89: =Input!$E$190 -> 0.085
B90: IDC | C90: Rs Cr | E90: =SUMIF(IDC_Q!$E$6:$AJ$6,E$3,IDC_Q!$E90:$AI90) -> 0 | F90: =SUMIF(IDC_Q!$E$6:$AJ$6,F$3,IDC_Q!$E90:$AI90) -> 0 | G90: =SUMIF(IDC_Q!$E$6:$AJ$6,G$3,IDC_Q!$E90:$AI90) -> 0 | H90: =SUMIF(IDC_Q!$E$6:$AJ$6,H$3,IDC_Q!$E90:$AI90) -> 0 | I90: =SUMIF(IDC_Q!$E$6:$AJ$6,I$3,IDC_Q!$E90:$AI90) -> 0 | J90: =SUMIF(IDC_Q!$E$6:$AJ$6,J$3,IDC_Q!$E90:$AI90) -> 0 | K90: =SUMIF(IDC_Q!$E$6:$AJ$6,K$3,IDC_Q!$E90:$AI90) -> 0 | L90: =SUMIF(IDC_Q!$E$6:$AJ$6,L$3,IDC_Q!$E90:$AI90) -> 0 | ... AI90: =SUMIF(IDC_Q!$E$6:$AJ$6,AI$3,IDC_Q!$E90:$AI90) -> 0
B91: Interest Charge | C91: Rs Cr | E91: =AVERAGE(E84,E87)*E89*E9 -> 0 | F91: =AVERAGE(F84,F87)*F89*F9 -> 0 | G91: =AVERAGE(G84,G87)*G89*G9 -> 0 | H91: =AVERAGE(H84,H87)*H89*H9 -> 0 | I91: =AVERAGE(I84,I87)*I89*I9 -> 0 | J91: =AVERAGE(J84,J87)*J89*J9 -> 0 | K91: =AVERAGE(K84,K87)*K89*K9 -> 0 | L91: =AVERAGE(L84,L87)*L89*L9 -> 0 | ... AI91: =AVERAGE(AI84,AI87)*AI89*AI9 -> 0
A93: GFA & Depreciation Schedule
A94: CWIP Schedule
B95: Opening | C95: Rs Cr | E95: =D98 -> 0 | F95: =E98 -> 582.04858 | G95: =F98 -> 0 | H95: =G98 -> 0 | I95: =H98 -> 0 | J95: =I98 -> 0 | K95: =J98 -> 0 | L95: =K98 -> 0 | ... AI95: =AH98 -> 0
B96: Addition | C96: Rs Cr | E96: =E53 -> 582.04858 | F96: =F53 -> 660.51346 | G96: =G53 -> 0 | H96: =H53 -> 0 | I96: =I53 -> 0 | J96: =J53 -> 0 | K96: =K53 -> 0 | L96: =L53 -> 0 | ... AI96: =AI53 -> 0
B97: Capitalised | C97: Rs Cr | E97: =IF(E5=1,E95+E96,0) -> 0 | F97: =IF(F5=1,F95+F96,0) -> 1242.562 | G97: =IF(G5=1,G95+G96,0) -> 0 | H97: =IF(H5=1,H95+H96,0) -> 0 | I97: =IF(I5=1,I95+I96,0) -> 0 | J97: =IF(J5=1,J95+J96,0) -> 0 | K97: =IF(K5=1,K95+K96,0) -> 0 | L97: =IF(L5=1,L95+L96,0) -> 0 | ... AI97: =IF(AI5=1,AI95+AI96,0) -> 0
B98: Closing | C98: Rs Cr | E98: =E95+E96-E97 -> 582.04858 | F98: =F95+F96-F97 -> 0 | G98: =G95+G96-G97 -> 0 | H98: =H95+H96-H97 -> 0 | I98: =I95+I96-I97 -> 0 | J98: =J95+J96-J97 -> 0 | K98: =K95+K96-K97 -> 0 | L98: =L95+L96-L97 -> 0 | ... AI98: =AI95+AI96-AI97 -> 0
A100: Book Depreciation | S100: =(S102+S103)*15% -> 186.3843
B101: GFA Schedule | S101: =S107-R105 -> 393.03973 | T101: =T107-S105 -> 335.01209 | U101: =U107-T105 -> 276.98444 | V101: =V107-U105 -> 252.1332 | W101: =W107-V105 -> 227.28196 | X101: =X107-W105 -> 202.43072 | Y101: =Y107-X105 -> 177.57948 | Z101: =Z107-Y105 -> 152.72824
B102: Opening GFA | C102: Rs Cr | E102: =D106 -> 0 | F102: =E106 -> 0 | G102: =F106 -> 1242.562 | H102: =G106 -> 1242.562 | I102: =H106 -> 1242.562 | J102: =I106 -> 1242.562 | K102: =J106 -> 1242.562 | L102: =K106 -> 1242.562 | ... AI102: =AH106 -> 1242.562
B103: Additions | C103: Rs Cr | D103: =SUM(E103:AI103) -> 1242.562 | E103: =E97 -> 0 | F103: =F97 -> 1242.562 | G103: =G97 -> 0 | H103: =H97 -> 0 | I103: =I97 -> 0 | J103: =J97 -> 0 | K103: =K97 -> 0 | L103: =L97 -> 0 | ... AI103: =AI97 -> 0
B104: Depreciation | C104: Rs Cr | D104: =SUM(E104:AI104) -> 1102.2594 | E104: =IF(E$4,MIN(E107-D105,(E102+E103)*Input!E250*E$9),0) -> 0 | F104: =IF(F$4,MIN(F107-E105,(F102+F103)*Input!F250*F$9),0) -> 28.934334 | G104: =IF(G$4,MIN(G107-F105,(G102+G103)*Input!H250*G$9),0) -> 58.027647 | H104: =IF(H$4,MIN(H107-G105,(H102+H103)*Input!I250*H$9),0) -> 58.027647 | I104: =IF(I$4,MIN(I107-H105,(I102+I103)*Input!J250*I$9),0) -> 58.027647 | J104: =IF(J$4,MIN(J107-I105,(J102+J103)*Input!K250*J$9),0) -> 58.027647 | K104: =IF(K$4,MIN(K107-J105,(K102+K103)*Input!L250*K$9),0) -> 58.027647 | L104: =IF(L$4,MIN(L107-K105,(L102+L103)*Input!M250*L$9),0) -> 58.027647 | M104: =IF(M$4,MIN(M107-L105,(M102+M103)*Input!N250*M$9),0) -> 58.027647 | N104: =IF(N$4,MIN(N107-M105,(N102+N103)*Input!O250*N$9),0) -> 58.027647 | ... AI104: =IF(AI$4,MIN(AI107-AH105,(AI102+AI103)*Input!AJ250*AI$9),0) -> 0
B105: Accumulated depreciation | C105: Rs Cr | E105: =D105+E104 -> 0 | F105: =E105+F104 -> 28.934334 | G105: =F105+G104 -> 86.96198 | H105: =G105+H104 -> 144.98963 | I105: =H105+I104 -> 203.01727 | J105: =I105+J104 -> 261.04492 | K105: =J105+K104 -> 319.07257 | L105: =K105+L104 -> 377.10022 | ... AI105: =AH105+AI104 -> 1102.2594
B106: Closing GFA | C106: Rs Cr | E106: =E102+E103 -> 0 | F106: =F102+F103 -> 1242.562 | G106: =G102+G103 -> 1242.562 | H106: =H102+H103 -> 1242.562 | I106: =I102+I103 -> 1242.562 | J106: =J102+J103 -> 1242.562 | K106: =K102+K103 -> 1242.562 | L106: =L102+L103 -> 1242.562 | ... AI106: =AI102+AI103 -> 1242.562
B107: Max depreciation | C107: Rs Cr | D107: =D104/D103 -> 0.88708603 | E107: =E106*Input!$D$251 -> 0 | F107: =F106*Input!$D$251 -> 1118.3058 | G107: =G106*Input!$D$251 -> 1118.3058 | H107: =H106*Input!$D$251 -> 1118.3058 | I107: =I106*Input!$D$251 -> 1118.3058 | J107: =J106*Input!$D$251 -> 1118.3058 | K107: =K106*Input!$D$251 -> 1118.3058 | L107: =L106*Input!$D$251 -> 1118.3058 | ... AI107: =AI106*Input!$D$251 -> 1118.3058
S108: =S106-S107 -> 124.2562 | T108: =T106-T107 -> 124.2562 | U108: =U106-U107 -> 124.2562 | V108: =V106-V107 -> 124.2562 | W108: =W106-W107 -> 124.2562 | X108: =X106-X107 -> 124.2562
B109: Opening NFA | C109: Rs Cr | E109: =D112 -> 0 | F109: =E112 -> 0 | G109: =F112 -> 1213.6277 | H109: =G112 -> 1155.6001 | I109: =H112 -> 1097.5724 | J109: =I112 -> 1039.5448 | K109: =J112 -> 981.51711 | L109: =K112 -> 923.48946 | ... AI109: =AH112 -> 140.30262
B110: Addition - NFA | C110: Rs Cr | D110: =SUM(E110:AI110) -> 1242.562 | E110: =E103 -> 0 | F110: =F103 -> 1242.562 | G110: =G103 -> 0 | H110: =H103 -> 0 | I110: =I103 -> 0 | J110: =J103 -> 0 | K110: =K103 -> 0 | L110: =L103 -> 0 | ... AI110: =AI103 -> 0
B111: Depreciation | C111: Rs Cr | D111: =SUM(E111:AI111) -> 1102.2594 | E111: =E104 -> 0 | F111: =F104 -> 28.934334 | G111: =G104 -> 58.027647 | H111: =H104 -> 58.027647 | I111: =I104 -> 58.027647 | J111: =J104 -> 58.027647 | K111: =K104 -> 58.027647 | L111: =L104 -> 58.027647 | ... AI111: =AI104 -> 0
...

Sheet Output
B2: Project Assumptions | C2: Units | D2: FSP | G2: Units | H2: FSP | K2: Capex Breakup | L2: Rs per Wp | M2: Rs Lakh /MW | N2: Rs Crore
B3: Project Assumptions | F3: Capital Expenditure | K3: Float Devices
B4: Capacity | C4: MWp | D4: =Input!$E$4 -> 243.888 | F4: Capex | G4: Rs Lakh | H4: =Working!D51*100 -> 121643.88 | I4: =H4/$D$4/100 -> 4.9876945 | J4: =H4/$D$5/100 -> 5.9852334 | K4: Floats and Platforms | L4: =ROUND(BOQ_G!H5/$D$4/10,3) -> 7.685 | M4: =ROUND(BOQ_G!H5/$D$5/1,2) -> 92.22 | N4: =M4*$D$5/100 -> 187.42793
B5: Capacity | C5: =Input!C6 -> MW | D5: =Input!E6 -> 203.24 | F5: IDC | G5: Rs Lakh | H5: =Working!D52*100 -> 2612.319 | I5: =H5/$D$4/100 -> 0.10711142 | J5: =H5/$D$5/100 -> 0.1285337 | K5: IT Platform | L5: =ROUND(BOQ_G!H6/$D$4/10,3) -> 2.802 | M5: =ROUND(BOQ_G!H6/$D$5/1,2) -> 33.63 | N5: =M5*$D$5/100 -> 68.349612
B6: CUF | C6: =Input!C7 -> % | D6: =Input!E7 -> 0.19317816 | F6: Capex including IDC | G6: Rs Lakh | H6: =SUM(H4:H5) -> 124256.2 | I6: =H6/$D$4/100 -> 5.0948059 | J6: =H6/$D$5/100 -> 6.1137671 | K6: Anchor and Mooring | L6: =ROUND(BOQ_G!H7/$D$4/10,3) -> 4.878 | M6: =ROUND(BOQ_G!H7/$D$5/1,2) -> 58.53 | N6: =M6*$D$5/100 -> 118.95637
B7: COD | C7: =Input!C178 -> Date | D7: =Input!E178 -> 46296 | K7: Float Devices | L7: =SUM(L4:L6) -> 15.365 | M7: =SUM(M4:M6) -> 184.38 | N7: =SUM(N4:N6) -> 374.73391
B8: Life of Project | C8: =Input!C179 -> Years | D8: =Input!E179 -> 25 | F8: Funding | K8: Solar PV System
B9: Funding Assumptions | F9: Commerical Loan 1 | G9: Rs Lakh | H9: =Working!D60*100 -> 86979.342 | K9: PV Module | L9: =ROUND(Working!$H$16/$D$4/10,2) -> 18.07 | M9: =ROUND(Working!$H$16/$D$5/1,2) -> 216.85 | N9: =M9*$D$5/100 -> 440.72594
B10: Commerical Loan 1 | C10: % | D10: =Input!E245 -> 0.7 | F10: Commerical Loan 2 | G10: Rs Lakh | H10: =Working!D61*100 -> 0 | K10: Inverter (including switchgear) | L10: =ROUND(Working!$H$17/$D$4/10,2) -> 1.24 | M10: =ROUND(Working!$H$17/$D$5/1,2) -> 14.84 | N10: =M10*$D$5/100 -> 30.160816
B11: Commerical Loan 2 | C11: % | D11: =Input!E246 -> 0 | F11: Grant/ Capital Subsidy | G11: Rs Lakh | H11: =Working!D62*100 -> 0 | K11: Balance of System (BoS) | L11: =ROUND((Working!$H$19)/$D$4/10,2) -> 4.52 | M11: =ROUND((Working!$H$19)/$D$5/1,2) -> 54.28 | N11: =M11*$D$5/100 -> 110.31867
B12: Grant/ Capital Subsidy | C12: % | D12: =Input!E247 -> 0 | F12: Equity | G12: Rs Lakh | H12: =Working!D63*100 -> 37276.861 | K12: Civil Structure | L12: =ROUND((Working!$H$20)/$D$4/10,2) -> 0.78 | M12: =ROUND((Working!$H$20)/$D$5/1,2) -> 9.31 | N12: =M12*$D$5/100 -> 18.921644
B13: Equity | C13: % | D13: =Input!E248 -> 0.3 | F13: Total Financing | G13: Rs Lakh | H13: =SUM(H9:H12) -> 124256.2 | K13: PV System | L13: =SUM(L9:L12) -> 24.61 | M13: =SUM(M9:M12) -> 295.28 | N13: =SUM(N9:N12) -> 600.12707
B14: Debt Assumptions | F14: Levelized Tariff | K14: Infrastructure
B15: =Input!B184 -> Moratorium Period (from start of operations) | C15: Years | D15: =Input!E184 -> 0 | F15: Generation O&M | G15: Rs/kWh | H15: =Working!D267 -> 0.62716264 | K15: Land and Site Development | L15: =ROUND(Working!$H$28/$D$4/10,2) -> 0.73 | M15: =ROUND(Working!$H$28/$D$5/1,2) -> 8.72 | N15: =M15*$D$5/100 -> 17.722528
B16: =Input!B185 -> Repayment Period | C16: Years | D16: =Input!E185 -> 15 | F16: Infrastructure O&M | G16: Rs/kWh | H16: =Working!D268 -> 0.11342013 | K16: Road Infrastructure | L16: =ROUND(Working!$H$29/$D$4/10,2) -> 0.04 | M16: =ROUND(Working!$H$29/$D$5/1,2) -> 0.43 | N16: =M16*$D$5/100 -> 0.873932
B17: =Input!B186 -> Interest Rate | C17: % | D17: =Input!E186 -> 0.06 | F17: Depreciation | G17: Rs/kWh | H17: =Working!D269 -> 1.6265289 | K17: Infrastructure | L17: =SUM(L15:L16) -> 0.77 | M17: =SUM(M15:M16) -> 9.15 | N17: =SUM(N15:N16) -> 18.59646
F18: Interest on Term Loan | G18: Rs/kWh | H18: =Working!D270 -> 0.74265307 | K18: Evacuation System
B19: Return Assumption | F19: Interest on WC | G19: Rs/kWh | H19: =Working!D271 -> 0.071544083 | K19: Sub-station | L19: =ROUND(Working!$H$23/$D$4/10,2) -> 3.72 | M19: =ROUND(Working!$H$23/$D$5/1,2) -> 44.67 | N19: =M19*$D$5/100 -> 90.787308
B20: =Input!B192 -> Return on Equity (RoE) - Post Tax | C20: % | D20: =Input!E192 -> 0.14 | F20: ROE | G20: Rs/kWh | H20: =Working!D274 -> 2.0722429 | K20: Transmission Line | L20: =ROUND(Working!$H$24/$D$4/10,2) -> 0.55 | M20: =ROUND(Working!$H$24/$D$5/1,2) -> 6.57 | N20: =M20*$D$5/100 -> 13.352868
F21: Project Tariff | G21: Rs/kWh | H21: =SUM(H15:H20) -> 5.2535517 | K21: Augmentation | L21: =ROUND(Working!$H$25/$D$4/10,2) -> 0.2 | M21: =ROUND(Working!$H$25/$D$5/1,2) -> 2.45 | N21: =M21*$D$5/100 -> 4.97938
B22: Working Capital Assumptions | K22: Evacuation System | L22: =SUM(L19:L21) -> 4.47 | M22: =SUM(M19:M21) -> 53.69 | N22: =SUM(N19:N21) -> 109.11956
B23: =Input!B216 -> Receivables | C23: Months | D23: =Input!E216 -> 1.5 | F23: Project Cost | G23: Rs Cr/MW | H23: =ROUND(H6/D5,2)*10^-2 -> 6.1138 | K23: Other Costs
B24: =Input!B217 -> O&M | C24: Months | D24: =Input!E217 -> 1 | F24: Project IRR | H24: =Working!D421 -> 0.087955957 | K24: Contingency, Insurance | L24: =ROUND(Working!$H$35/$D$4/10,2) -> 4.67 | M24: =ROUND(Working!$H$35/$D$5/1,2) -> 56.02 | N24: =M24*$D$5/100 -> 113.85505
B25: =Input!B218 -> Maintenance spares | C25: % | D25: =Input!E218 -> 0.15 | F25: Equity IRR | H25: =Working!D438 -> 0.134209 | K25: IDC | L25: =ROUND(Working!$D$52*100/$D$4/10,2) -> 1.07 | M25: =ROUND(Working!$D$52*100/$D$5/1,2) -> 12.85 | N25: =M25*$D$5/100 -> 26.11634
B26: =Input!B220 -> Interest on WC | C26: % | D26: =Input!E220 -> 0.115 | F26: EIRR | H26: =Working!D482 -> 0.19492022 | K26: Other Cost | L26: =SUM(L24:L25) -> 5.74 | M26: =SUM(M24:M25) -> 68.87 | N26: =SUM(N24:N25) -> 139.97139
F27: Discount Factor | H27: =Input!$E$228 -> 0.07476 | K27: Floating Solar Project Cost | L27: =L7+L13+L17+L22+L26 -> 50.955 | M27: =M7+M13+M17+M22+M26 -> 611.37 | N27: =N7+N13+N17+N22+N26 -> 1242.5484
F28: Average DSCR | H28: =Working!D405 -> 2.240914

Sheet Tables
G1: =BOQ_G!AA2 -> 0.85 | H1: =BOQ_G!AB2 -> 0.12 | I1: =BOQ_G!S37 -> 0.138
C2: Generation and Infrastructure BOQ | E2: =Input!J2 -> 5.2535517
B4: BOQ SPV
B5: S.N | C5: FPV plant | D5: Unit | E5: Quantity | F5: Unit Cost (Rs./Unit) | G5: Equipment Cost (Rs. Lakhs) | H5: Erection Cost (Rs. Lakhs) | I5: Base Cost (Rs. Lakhs) | J5: Tax (Rs. Lakhs) | K5: Total Cost (Rs. Lakhs) | AB5: Description | AC5: Total Cost (Rs Lakhs)
B6: A | C6: PV Modules | D6: Lot | E6: =BOQ_G!E36+BOQ_G!E37 -> 421385 | F6: =BOQ_G!D36 -> 9187.2 | G6: =I6*$G$1 -> 32906.46 | H6: =I6*$H$1 -> 4645.6179 | I6: =BOQ_G!F36+BOQ_G!F37 -> 38713.483 | J6: =I6*$I$1 -> 5342.4606 | K6: =I6+J6 -> 44055.943 | AB6: Land Cost | AC6: -
B7: B | C7: EL Testing | D7: Lot | E7: =BOQ_G!E38 -> 1 | F7: =BOQ_G!D38 -> 1000000 | G7: =I7*$G$1 -> 8.5 | H7: =I7*$H$1 -> 1.2 | I7: =BOQ_G!F38 -> 10 | J7: =I7*$I$1 -> 1.38 | K7: =I7+J7 -> 11.38 | AB7: PV Module Cost | AC7: =K9 -> 44073.013
B8: C | C8: Thermography | D8: Lot | E8: =BOQ_G!E39 -> 1 | F8: =BOQ_G!D39 -> 500000 | G8: =I8*$G$1 -> 4.25 | H8: =I8*$H$1 -> 0.6 | I8: =BOQ_G!F39 -> 5 | J8: =I8*$I$1 -> 0.69 | K8: =I8+J8 -> 5.69 | AB8: Inverter Cost | AC8: =K17 -> 3016.269
C9: Grand Total | G9: =I9*$G$1 -> 32919.21 | H9: =I9*$H$1 -> 4647.4179 | I9: =SUM(I6:I8) -> 38728.483 | J9: =SUM(J6:J8) -> 5344.5306 | K9: =SUM(K6:K8) -> 44073.013 | AB9: Floating Structure Cost | AC9: =K45 -> 37474.182
AB10: Electrical Infrastructure | AC10: =K82 -> 11031.383
AB11: Civil Infrastructure | AC11: =K92 -> 350.65686
AB12: Road & Drainage Infrastructure | AC12: =K124 -> 1859.149
B13: BOQ Inverter | AB13: Water Infrastructure | AC13: =K102 -> 318.64
B14: S.N | C14: FPV plant | D14: Unit | E14: Quantity | F14: Unit Cost (Rs./Unit) | G14: Equipment Cost (Rs. Lakhs) | H14: Erection Cost (Rs. Lakhs) | I14: Base Cost (Rs. Lakhs) | J14: Tax (Rs. Lakhs) | K14: Total Cost (Rs. Lakhs) | AB14: Street-Light
B15: A | C15: Inverter 4.4 MW | D15: Lot | E15: =BOQ_G!E41 -> 44 | F15: =BOQ_G!D41 -> 5700000 | G15: =I15*$G$1 -> 2131.8 | H15: =I15*$H$1 -> 300.96 | I15: =BOQ_G!F41 -> 2508 | J15: =I15*$I$1 -> 346.104 | K15: =I15+J15 -> 2854.104 | AB15: Cost of Power Evacuation
B16: B | C16: Inverter 1.1 MW | D16: Lot | E16: =BOQ_G!E42 -> 12 | F16: =BOQ_G!D42 -> 1187500 | G16: =I16*$G$1 -> 121.125 | H16: =I16*$H$1 -> 17.1 | I16: =BOQ_G!F42 -> 142.5 | J16: =I16*$I$1 -> 19.665 | K16: =I16+J16 -> 162.165 | AB16: Statutory and Other Fees
C17: Grand Total | G17: =I17*$G$1 -> 2252.925 | H17: =I17*$H$1 -> 318.06 | I17: =SUM(I15:I16) -> 2650.5 | J17: =SUM(J15:J16) -> 365.769 | K17: =SUM(K15:K16) -> 3016.269 | AB17: Project Cost
AB18: Interest During Construction (IDC)
AB19: Total project cost
B20: BOQ Floats
B21: S.N | C21: FPV plant | D21: Unit | E21: Quantity | F21: Unit Cost (Rs./Unit) | G21: Equipment Cost (Rs. Lakhs) | H21: Erection Cost (Rs. Lakhs) | I21: Base Cost (Rs. Lakhs) | J21: Tax (Rs. Lakhs) | K21: Total Cost (Rs. Lakhs)
B22: A | C22: Floating Structure
B23: 1 | C23: =BOQ_G!B45 -> OMF (Module Float) | D23: Rs. Per Float | E23: =BOQ_G!E45 -> 420544 | F23: =G23/E23*10^5 -> 888.25 | G23: =I23*$G$1 -> 3735.4821 | H23: =I23*$H$1 -> 527.36218 | I23: =BOQ_G!F45 -> 4394.6848 | J23: =I23*$I$1 -> 606.4665 | K23: =I23+J23 -> 5001.1513
B24: 2 | C24: =BOQ_G!B46 -> OMWF (Main Walkway Float) | D24: Rs. Per Float | E24: =BOQ_G!E46 -> 48032 | F24: =G24/E24*10^5 -> 3415.725 | G24: =I24*$G$1 -> 1640.641 | H24: =I24*$H$1 -> 231.61991 | I24: =BOQ_G!F46 -> 1930.1659 | J24: =I24*$I$1 -> 266.3629 | K24: =I24+J24 -> 2196.5288
B25: 3 | C25: =BOQ_G!B47 -> OLSF (Long Secondary Float) | D25: Rs. Per Float | E25: =BOQ_G!E47 -> 163308 | F25: =G25/E25*10^5 -> 2049.435 | G25: =I25*$G$1 -> 3346.8913 | H25: =I25*$H$1 -> 472.5023 | I25: =BOQ_G!F47 -> 3937.5192 | J25: =I25*$I$1 -> 543.37765 | K25: =I25+J25 -> 4480.8968
B26: 4 | C26: =BOQ_G!B48 -> OSSF (Small Secondary Float) | D26: Rs. Per Float | E26: =BOQ_G!E48 -> 148016 | F26: =G26/E26*10^5 -> 1366.29 | G26: =I26*$G$1 -> 2022.3278 | H26: =I26*$H$1 -> 285.5051 | I26: =BOQ_G!F48 -> 2379.2092 | J26: =I26*$I$1 -> 328.33087 | K26: =I26+J26 -> 2707.5401
B27: 5 | C27: =BOQ_G!B49 -> OSSFx (Small Secondary Walkway Float) | D27: Rs. Per Float | E27: =BOQ_G!E49 -> 24096 | F27: =G27/E27*10^5 -> 6772.9062 | G27: =I27*$G$1 -> 1631.9995 | H27: =I27*$H$1 -> 230.39993 | I27: =BOQ_G!F49 -> 1919.9994 | J27: =I27*$I$1 -> 264.95992 | K27: =I27+J27 -> 2184.9593
B28: 6 | C28: =BOQ_G!B50 -> OCF (Cable Float)-DC | D28: Rs. Per Float | E28: =BOQ_G!E50 -> 755372 | F28: =G28/E28*10^5 -> 107.3975 | G28: =I28*$G$1 -> 811.25064 | H28: =I28*$H$1 -> 114.5295 | I28: =BOQ_G!F50 -> 954.41252 | J28: =I28*$I$1 -> 131.70893 | K28: =I28+J28 -> 1086.1215
B29: 7 | C29: =BOQ_G!B51 -> OCF (Cable Float)-AC | D29: Rs. Per Float | E29: =BOQ_G!E51 -> 905308 | F29: =G29/E29*10^5 -> 89.6325 | G29: =I29*$G$1 -> 811.45019 | H29: =I29*$H$1 -> 114.55767 | I29: =BOQ_G!F51 -> 954.64729 | J29: =I29*$I$1 -> 131.74133 | K29: =I29+J29 -> 1086.3886
C30: sub total | G30: =I30*$G$1 -> 14000.043 | H30: =I30*$H$1 -> 1976.4766 | I30: =SUM(I23:I29) -> 16470.638 | J30: =SUM(J23:J29) -> 2272.9481 | K30: =SUM(K23:K29) -> 18743.586
B32: B | C32: Inverter Transformer Platform
B33: 1 | C33: =BOQ_G!B53 -> Transformer of Size 5.5 MVA | D33: Rs. Per I.T. Platform | E33: =BOQ_G!E53 -> 12 | F33: =G33/E33*10^5 -> 4921712.5 | G33: =I33*$G$1 -> 590.6055 | H33: =I33*$H$1 -> 83.3796 | I33: =BOQ_G!F53 -> 694.83 | J33: =I33*$I$1 -> 95.88654 | K33: =I33+J33 -> 790.71654
B34: 2 | C34: =BOQ_G!B54 -> Transformer of Size 6.5 MVA | D34: Rs. Per I.T. Platform | E34: =BOQ_G!E54 -> 32 | F34: =G34/E34*10^5 -> 5943200 | G34: =I34*$G$1 -> 1901.824 | H34: =I34*$H$1 -> 268.4928 | I34: =BOQ_G!F54 -> 2237.44 | J34: =I34*$I$1 -> 308.76672 | K34: =I34+J34 -> 2546.2067
B35: 3 | C35: =BOQ_G!B55 -> Platform-Ferro Cement | D35: Lum Sum Cost | E35: =BOQ_G!E55 -> 52 | F35: =G35/E35*10^5 -> 4675000 | G35: =I35*$G$1 -> 2431 | H35: =I35*$H$1 -> 343.2 | I35: =BOQ_G!F55 -> 2860 | J35: =I35*$I$1 -> 394.68 | K35: =I35+J35 -> 3254.68
B36: 4 | C36: =BOQ_G!B56 -> Inverter Barge- Mooring Line length | D36: Rs per KM | E36: =BOQ_G!E56 -> 11.88 | F36: =G36/E36*10^5 -> 1525510 | G36: =I36*$G$1 -> 181.23059 | H36: =I36*$H$1 -> 25.585495 | I36: =BOQ_G!F56 -> 213.21246 | J36: =I36*$I$1 -> 29.42332 | K36: =I36+J36 -> 242.63578
C37: sub total | G37: =SUM(G33:G36) -> 5104.6601 | H37: =SUM(H33:H36) -> 720.6579 | I37: =SUM(I33:I36) -> 6005.4825 | J37: =SUM(J33:J36) -> 828.75658 | K37: =SUM(K33:K36) -> 6834.239
B39: C | C39: Anchoring & Mooring
B40: 1 | C40: =BOQ_G!B58 -> Mooring System | D40: KM | E40: =BOQ_G!E58 -> 158.48 | F40: =G40/E40*10^5 -> 4996323.9 | G40: =I40*$G$1 -> 7918.1741 | H40: =I40*$H$1 -> 1117.8599 | I40: =BOQ_G!F58 -> 9315.4989 | J40: =I40*$I$1 -> 1285.5389 | K40: =I40+J40 -> 10601.038
B41: 2 | C41: =BOQ_G!B59 -> Mooring Line Accessories | D41: Lot | E41: =BOQ_G!E59 -> 2400 | F41: =G41/E41*10^5 -> 6379.25 | G41: =I41*$G$1 -> 153.102 | H41: =I41*$H$1 -> 21.6144 | I41: =BOQ_G!F59 -> 180.12 | J41: =I41*$I$1 -> 24.85656 | K41: =I41+J41 -> 204.97656
B42: 3 | C42: =BOQ_G!B60 -> Anchor System | D42: Rs. Per Anchor | E42: =BOQ_G!E60 -> 5536 | F42: =G42/E42*10^5 -> 14711.035 | G42: =I42*$G$1 -> 814.4029 | H42: =I42*$H$1 -> 114.97453 | I42: =BOQ_G!F60 -> 958.12106 | J42: =I42*$I$1 -> 132.22071 | K42: =I42+J42 -> 1090.3418
C43: sub total | G43: =I43*$G$1 -> 8885.679 | H43: =I43*$H$1 -> 1254.4488 | I43: =SUM(I40:I42) -> 10453.74 | J43: =SUM(J40:J42) -> 1442.6161 | K43: =SUM(K40:K42) -> 11896.356
C45: Grand Total | G45: =I45*$G$1 -> 27990.382 | H45: =I45*$H$1 -> 3951.5833 | I45: =I43+I37+I30 -> 32929.861 | J45: =J43+J37+J30 -> 4544.3208 | K45: =K43+K37+K30 -> 37474.182
B47: BOQ Electrical
B48: S.N | C48: FPV plant | D48: Unit | E48: Quantity | F48: Unit Cost (Rs./Unit) | G48: Equipment Cost (Rs. Lakhs) | H48: Erection Cost (Rs. Lakhs) | I48: Base Cost (Rs. Lakhs) | J48: Tax (Rs. Lakhs) | K48: Total Cost (Rs. Lakhs)
B49: A | C49: DC BoS
B50: 1 | C50: DC Cable | D50: m | E50: =BOQ_G!E63 -> 1302246.4 | F50: =BOQ_G!D63 -> 58 | G50: =I50*$G$1 -> 642.00748 | H50: =I50*$H$1 -> 90.636349 | I50: =BOQ_G!F63 -> 755.30291 | J50: =I50*$I$1 -> 104.2318 | K50: =I50+J50 -> 859.53471
B51: 2 | C51: DC Connectors | D51: Lot | E51: 1 | F51: =G51/E51*10^5 -> 26667745 | G51: =I51*$G$1 -> 266.67745 | H51: =I51*$H$1 -> 37.648582 | I51: =SUM(BOQ_G!F66:F72) -> 313.73818 | J51: =I51*$I$1 -> 43.295869 | K51: =I51+J51 -> 357.03405
B52: 3 | C52: DC Accessories | D52: Lot | E52: 1 | F52: =G52/E52*10^5 -> 2.0938849e+08 | G52: =I52*$G$1 -> 2093.8849 | H52: =I52*$H$1 -> 295.60727 | I52: =SUM(BOQ_G!F74:F76) -> 2463.3939 | J52: =I52*$I$1 -> 339.94836 | K52: =I52+J52 -> 2803.3423
B53: 4 | C53: String Monitoring Box | D53: Lot | E53: 1 | F53: =G53/E53*10^5 -> 46327125 | G53: =I53*$G$1 -> 463.27125 | H53: =I53*$H$1 -> 65.403 | I53: =SUM(BOQ_G!F78:F80) -> 545.025 | J53: =I53*$I$1 -> 75.21345 | K53: =I53+J53 -> 620.23845
C54: sub total | G54: =I54*$G$1 -> 3465.841 | H54: =I54*$H$1 -> 489.2952 | I54: =SUM(I50:I53) -> 4077.46 | J54: =SUM(J50:J53) -> 562.68949 | K54: =SUM(K50:K53) -> 4640.1495
B56: B | C56: AC BoS
B57: 1 | C57: AC Cables (1.9/3.3kV) - From Inverter - Inverter Transformer | D57: Lot | E57: 1 | F57: =G57/E57*10^5 -> 15643209 | G57: =I57*$G$1 -> 156.43209 | H57: =I57*$H$1 -> 22.08453 | I57: =SUM(BOQ_G!F83:F92) -> 184.03775 | J57: =I57*$I$1 -> 25.397209 | K57: =I57+J57 -> 209.43496
B58: 2 | C58: Control Cable | D58: m | E58: =SUM(BOQ_G!E94:E100) -> 13120 | F58: =G58/E58*10^5 -> 120.41235 | G58: =I58*$G$1 -> 15.7981 | H58: =I58*$H$1 -> 2.23032 | I58: =SUM(BOQ_G!F94:F100) -> 18.586 | J58: =I58*$I$1 -> 2.564868 | K58: =I58+J58 -> 21.150868
B59: 3 | C59: Cable Tray | D59: m | E59: =SUM(BOQ_G!E102:E103) -> 340 | F59: =G59/E59*10^5 -> 329.5 | G59: =I59*$G$1 -> 1.1203 | H59: =I59*$H$1 -> 0.15816 | I59: =SUM(BOQ_G!F102:F103) -> 1.318 | J59: =I59*$I$1 -> 0.181884 | K59: =I59+J59 -> 1.499884
B60: 4 | C60: Perforated cable tray | D60: Lot | E60: 1 | F60: =G60/E60*10^5 -> 1189320 | G60: =I60*$G$1 -> 11.8932 | H60: =I60*$H$1 -> 1.67904 | I60: =SUM(BOQ_G!F105:F107) -> 13.992 | J60: =I60*$I$1 -> 1.930896 | K60: =I60+J60 -> 15.922896
B61: 5 | C61: Hume Pipe | D61: m | E61: =SUM(BOQ_G!E109:E112) -> 6227.2 | F61: =G61/E61*10^5 -> 18.90633 | G61: =I61*$G$1 -> 1.177335 | H61: =I61*$H$1 -> 0.166212 | I61: =SUM(BOQ_G!F109:F112) -> 1.3851 | J61: =I61*$I$1 -> 0.1911438 | K61: =I61+J61 -> 1.5762438
C62: sub total | G62: =I62*$G$1 -> 186.42102 | H62: =I62*$H$1 -> 26.318262 | I62: =SUM(I57:I61) -> 219.31885 | J62: =SUM(J57:J61) -> 30.266001 | K62: =SUM(K57:K61) -> 249.58485
B64: D | C64: Inverter Transformers, Switchgear and Panels
B65: 1 | C65: Inverter Transformer | D65: # | E65: =SUM(BOQ_G!E114:E116) -> 46 | F65: =G65/E65*10^5 -> 4697391 | G65: =I65*$G$1 -> 2160.7999 | H65: =I65*$H$1 -> 305.0541 | I65: =SUM(BOQ_G!F114:F116) -> 2542.1175 | J65: =I65*$I$1 -> 350.81221 | K65: =I65+J65 -> 2892.9297
B66: 2 | C66: HT Panels & RMU | D66: # | E66: =SUM(BOQ_G!E118:E121) -> 30 | F66: =G66/E66*10^5 -> 1452656.8 | G66: =I66*$G$1 -> 435.79704 | H66: =I66*$H$1 -> 61.524288 | I66: =SUM(BOQ_G!F118:F121) -> 512.7024 | J66: =I66*$I$1 -> 70.752931 | K66: =I66+J66 -> 583.45533
B67: 3 | C67: HT Cables & Terminations | D67: Lot | E67: 1 | F67: =G67/E67*10^5 -> 62263180 | G67: =I67*$G$1 -> 622.6318 | H67: =I67*$H$1 -> 87.90096 | I67: =SUM(BOQ_G!F123:F131) -> 732.508 | J67: =I67*$I$1 -> 101.0861 | K67: =I67+J67 -> 833.5941
B68: 4 | C68: LT System & Auxiliary System | D68: # | E68: =SUM(BOQ_G!E135:E154) -> 149 | F68: =G68/E68*10^5 -> 77070.47 | G68: =I68*$G$1 -> 114.835 | H68: =I68*$H$1 -> 16.212 | I68: =SUM(BOQ_G!F135:F154) -> 135.1 | J68: =I68*$I$1 -> 18.6438 | K68: =I68+J68 -> 153.7438
C69: sub total | G69: =I69*$G$1 -> 3334.0637 | H69: =I69*$H$1 -> 470.69135 | I69: =SUM(I65:I68) -> 3922.4279 | J69: =SUM(J65:J68) -> 541.29505 | K69: =SUM(K65:K68) -> 4463.723
B71: E | C71: Illumination System, Earthing
B72: 5 | C72: Earthing System | D72: Lot | E72: 1 | F72: =G72/E72*10^5 -> 37267019 | G72: =I72*$G$1 -> 372.67019 | H72: =I72*$H$1 -> 52.612261 | I72: =SUM(BOQ_G!F156:F164) -> 438.43551 | J72: =I72*$I$1 -> 60.504101 | K72: =I72+J72 -> 498.93961
B73: 6 | C73: Lightning Protection with Earthing | D73: Lot | E73: 1 | F73: =G73/E73*10^5 -> 43861360 | G73: =I73*$G$1 -> 438.6136 | H73: =I73*$H$1 -> 61.92192 | I73: =SUM(BOQ_G!F166:F174) -> 516.016 | J73: =I73*$I$1 -> 71.210208 | K73: =I73+J73 -> 587.22621
B74: 7 | C74: Illumination System & Security System | D74: Set | E74: =SUM(BOQ_G!E176:E177) -> 2400 | F74: =G74/E74*10^5 -> 2833.3333 | G74: =I74*$G$1 -> 68 | H74: =I74*$H$1 -> 9.6 | I74: =SUM(BOQ_G!F176:F177) -> 80 | J74: =I74*$I$1 -> 11.04 | K74: =I74+J74 -> 91.04
C75: sub total | G75: =I75*$G$1 -> 879.28379 | H75: =I75*$H$1 -> 124.13418 | I75: =SUM(I72:I74) -> 1034.4515 | J75: =SUM(J72:J74) -> 142.75431 | K75: =SUM(K72:K74) -> 1177.2058
B77: F | C77: SCADA & Master Control Room
B78: 1 | C78: SCADA | D78: Lot | E78: 1 | F78: =G78/E78*10^5 -> 37400000 | G78: =I78*$G$1 -> 374 | H78: =I78*$H$1 -> 52.8 | I78: =SUM(BOQ_G!F179:F188) -> 440 | J78: =I78*$I$1 -> 60.72 | K78: =I78+J78 -> 500.72
B79: 2 | C79: Master Control Room | D79: Lot | E79: 1 | F79: =G79/E79*10^5 -> 0 | G79: =I79*$G$1 -> 0 | H79: =I79*$H$1 -> 0 | I79: =SUM(BOQ_G!F190:F193) -> 0 | J79: =I79*$I$1 -> 0 | K79: =I79+J79 -> 0
C80: sub total | G80: =I80*$G$1 -> 374 | H80: =I80*$H$1 -> 52.8 | I80: =SUM(I78:I79) -> 440 | J80: =SUM(J78:J79) -> 60.72 | K80: =SUM(K78:K79) -> 500.72
C82: Grand Total | G82: =I82*$G$1 -> 8239.6096 | H82: =I82*$H$1 -> 1163.239 | I82: =I80+I75+I69+I62+I54 -> 9693.6583 | J82: =J80+J75+J69+J62+J54 -> 1337.7248 | K82: =K80+K75+K69+K62+K54 -> 11031.383
I84: =I82+I45+I17+I9 -> 84002.502 | J84: =J82+J45+J17+J9 -> 11592.345 | K84: =K82+K45+K17+K9 -> 95594.847
B85: BOQ Civil Infrastructure
B86: S.N | C86: FPV plant | D86: Unit | E86: Quantity | F86: Unit Cost (Rs./Unit) | G86: Equipment Cost (Rs. Lakhs) | H86: Erection Cost (Rs. Lakhs) | I86: Base Cost (Rs. Lakhs) | J86: Tax (Rs. Lakhs) | K86: Total Cost (Rs. Lakhs)
B87: A | C87: Building and Civil Infrastructure
B88: 1 | C88: Master Control Room | D88: sq ft | E88: =BOQ_G!E196 -> 15582 | F88: =G88/E88*10^5 -> 574.6 | G88: =I88*$G$1 -> 89.534172 | H88: =I88*$H$1 -> 12.640118 | I88: =BOQ_G!F196 -> 105.33432 | J88: =I88*$I$1 -> 14.536136 | K88: =I88+J88 -> 119.87046
B89: 2 | C89: Offices | D89: sq ft | E89: =BOQ_G!E197 -> 20000 | F89: =G89/E89*10^5 -> 574.6 | G89: =I89*$G$1 -> 114.92 | H89: =I89*$H$1 -> 16.224 | I89: =BOQ_G!F197 -> 135.2 | J89: =I89*$I$1 -> 18.6576 | K89: =I89+J89 -> 153.8576
B90: 3 | C90: Common Infrastructure | D90: sq ft | E90: =BOQ_G!E199 -> 10000 | F90: =G90/E90*10^5 -> 574.6 | G90: =I90*$G$1 -> 57.46 | H90: =I90*$H$1 -> 8.112 | I90: =BOQ_G!F199 -> 67.6 | J90: =I90*$I$1 -> 9.3288 | K90: =I90+J90 -> 76.9288
C92: Grand Total | G92: =I92*$G$1 -> 261.91417 | H92: =I92*$H$1 -> 36.976118 | I92: =SUM(I88:I90) -> 308.13432 | J92: =SUM(J88:J90) -> 42.522536 | K92: =SUM(K88:K90) -> 350.65686
B95: BOQ Water Infrastructure
B96: S.N | C96: FPV plant | D96: Unit | E96: Quantity | F96: Unit Cost (Rs./Unit) | G96: Equipment Cost (Rs. Lakhs) | H96: Erection Cost (Rs. Lakhs) | I96: Base Cost (Rs. Lakhs) | J96: Tax (Rs. Lakhs) | K96: Total Cost (Rs. Lakhs)
B97: A | C97: Water Infrastructure
B98: 1 | C98: Pier | D98: # | E98: =BOQ_G!E202 -> 1 | F98: =G98/E98*10^5 -> 1700000 | G98: =I98*$G$1 -> 17 | H98: =I98*$H$1 -> 2.4 | I98: =BOQ_G!F202 -> 20 | J98: =I98*$I$1 -> 2.76 | K98: =I98+J98 -> 22.76
B99: 2 | C99: Ferro Cement Launching Pads | D99: # | E99: =BOQ_G!E203 -> 4 | F99: =G99/E99*10^5 -> 4250000 | G99: =I99*$G$1 -> 170 | H99: =I99*$H$1 -> 24 | I99: =BOQ_G!F203 -> 200 | J99: =I99*$I$1 -> 27.6 | K99: =I99+J99 -> 227.6
B100: 3 | C100: Launch Pads | D100: # | E100: =BOQ_G!E204 -> 6 | F100: =G100/E100*10^5 -> 850000 | G100: =I100*$G$1 -> 51 | H100: =I100*$H$1 -> 7.2 | I100: =BOQ_G!F204 -> 60 | J100: =I100*$I$1 -> 8.28 | K100: =I100+J100 -> 68.28
C102: Grand Total | G102: =I102*$G$1 -> 238 | H102: =I102*$H$1 -> 33.6 | I102: =SUM(I97:I100) -> 280 | J102: =SUM(J97:J100) -> 38.64 | K102: =SUM(K97:K100) -> 318.64
B105: BOQ Others
B106: S.N | C106: FPV plant | D106: Unit | E106: Quantity | F106: Unit Cost (Rs./Unit) | G106: Equipment Cost (Rs. Lakhs) | H106: Erection Cost (Rs. Lakhs) | I106: Base Cost (Rs. Lakhs) | J106: Tax (Rs. Lakhs) | K106: Total Cost (Rs. Lakhs)
B107: A | C107: Other Infrastructure
B108: 1 | C108: Lighting | D108: # | E108: =BOQ_G!E206 -> 2000 | F108: =G108/E108*10^5 -> 2550 | G108: =I108*$G$1 -> 51 | H108: =I108*$H$1 -> 7.2 | I108: =BOQ_G!F206 -> 60 | J108: =I108*$I$1 -> 8.28 | K108: =I108+J108 -> 68.28
B109: 2 | C109: Gates | D109: # | E109: =BOQ_G!E209 -> 1 | F109: =G109/E109*10^5 -> 425000 | G109: =I109*$G$1 -> 4.25 | H109: =I109*$H$1 -> 0.6 | I109: =BOQ_G!F209 -> 5 | J109: =I109*$I$1 -> 0.69 | K109: =I109+J109 -> 5.69
B110: 3 | C110: Green Belt | D110: # | E110: =BOQ_G!E212 -> 1 | F110: =G110/E110*10^5 -> 850000 | G110: =I110*$G$1 -> 8.5 | H110: =I110*$H$1 -> 1.2 | I110: =BOQ_G!F212 -> 10 | J110: =I110*$I$1 -> 1.38 | K110: =I110+J110 -> 11.38
B111: 4 | C111: Environment Mitigation Charges | D111: # | E111: 1 | I111: =BOQ_G!F214 -> 1000 | J111: =BOQ_G!G214 -> 138 | K111: =BOQ_G!H214 -> 1138
C112: Grand Total | G112: =I112*$G$1 -> 913.75 | H112: =I112*$H$1 -> 129 | I112: =SUM(I108:I111) -> 1075 | J112: =SUM(J108:J111) -> 148.35 | K112: =SUM(K108:K111) -> 1223.35
C115: Total Generation Cost | G115: =G112+G102+G92+G82+G45+G17+G9 -> 72815.791 | H115: =H112+H102+H92+H82+H45+H17+H9 -> 10279.876 | I115: =I112+I102+I92+I82+I45+I17+I9 -> 85665.636 | J115: =J112+J102+J92+J82+J45+J17+J9 -> 11821.858 | K115: =K112+K102+K92+K82+K45+K17+K9 -> 97487.494
B118: BOQ Road Development and Drainage Infrastructure
B119: S.N | C119: FPV plant | D119: Unit | E119: Quantity | F119: Unit Cost (Rs./Unit) | G119: Equipment Cost (Rs. Lakhs) | H119: Erection Cost (Rs. Lakhs) | I119: Base Cost (Rs. Lakhs) | J119: Tax (Rs. Lakhs) | K119: Total Cost (Rs. Lakhs)
B120: A | C120: Road Development and Drainage Infrastructure
B121: 1 | C121: Land and Site Development | D121: # | E121: =BOQ_I!E17 -> 15.0205 | F121: =G121/E121*10^5 -> 8500000 | G121: =I121*$G$1 -> 1276.7425 | H121: =I121*$H$1 -> 180.246 | I121: =BOQ_I!F3 -> 1502.05 | J121: =BOQ_I!G19 -> 270.369 | K121: =I121+J121 -> 1772.419
...

Sheet Assumptions
B2: ASSUMPTION TABLE
B4: Project Particulars | F4: Operational Details of the Project
B5: Installed Capacity of the plant | C5: MWp | D5: =Input!E4 -> 243.888 | F5: Capacity Utilization Factor | G5: % | H5: =Input!E7 -> 0.19317816
B6: Start of the Project | C6: Date | D6: =Input!E176 -> 45748 | F6: Annual Degradation (3rd Year Onwards) | G6: % | H6: =Input!I239 -> 0.005
B7: Construction Period | C7: Months | D7: =Input!E177 -> 18 | F7: Aux Consumption | G7: % | H7: =Input!I240 -> 0.0075
B8: Start of Operations | C8: Date | D8: =Input!E178 -> 46296
B9: First Operational Financial Year | C9: Date | D9: =Input!E180 -> 46477 | F9: Depreciation Assumption
B10: Project Life | C10: Months | D10: =Input!E179 -> 25 | F10: Normative Life of Project | G10: Years | H10: =D10 -> 25
B11: Project End Date | C11: Date | D11: =Input!E182 -> 55609 | F11: Depreciation Rate (1st 13 years) | G11: % | H11: =Input!H250 -> 0.0467
F12: Depreciation Rate (After 13 Years) | G12: % | H12: =Input!X250 -> 0.02
B13: Financing Details
B14: Project Cost | C14: INR Cr | D14: =Output!H6/100 -> 1242.562 | F14: Tax Assumption
B15: Loan | C15: % | D15: =Input!E245 -> 0.7 | F15: Income Tax Rate | G15: % | H15: =Input!E223 -> 0.22
B16: Equity | C16: % | D16: =Input!E248 -> 0.3
B17: Grant | C17: % | D17: =1-D15-D16 -> 0 | F17: Working Capital Assumption
B18: Moratorium Period | C18: Years | D18: =Input!E188 -> 0 | F18: O&M Expenses (including GST) | G18: Lakhs/MW/year | H18: =Input!E205 -> 5.4988
B19: Repayment Period | C19: Years | D19: =Input!E189 -> 15 | F19: O&M Expenses Escalation | G19: % | H19: =Input!E206 -> 0.0525
B20: Interest Rate | C20: % | D20: =Input!E186 -> 0.06 | F20: Maintenance Spares | G20: % | H20: =Input!E218 -> 0.15
B21: Return on Equity | C21: % | D21: =Input!E192 -> 0.14 | F21: Receivables | G21: Months | H21: =Input!E216 -> 1.5
F22: Interest on Working Capital | G22: % | H22: =Input!E220 -> 0.115
F23: Working Capital Margin | G23: % | H23: =Input!E221 -> 0.25
F25: Levelized Tariff Calculation
F26: Discounting Factor | G26: % | H26: =Input!E228 -> 0.07476
F27: Levelized Tariff | G27: INR/KWh | H27: =Input!J2 -> 5.2535517

Sheet Tariff
B1: Particulars | C1: Units | D1: Inputs | E1: =YEAR(E2) -> 2026 | F1: =E1+1 -> 2027 | G1: =F1+1 -> 2028 | H1: =G1+1 -> 2029 | I1: =H1+1 -> 2030 | J1: =I1+1 -> 2031 | K1: =J1+1 -> 2032 | L1: =K1+1 -> 2033 | M1: =L1+1 -> 2034 | ... AE1: =AD1+1 -> 2052
D2: =Input!D238 -> 45747 | E2: =EOMONTH(D2,12) -> 46112 | F2: =EOMONTH(E2,12) -> 46477 | G2: =EOMONTH(F2,12) -> 46843 | H2: =EOMONTH(G2,12) -> 47208 | I2: =EOMONTH(H2,12) -> 47573 | J2: =EOMONTH(I2,12) -> 47938 | K2: =EOMONTH(J2,12) -> 48304 | L2: =EOMONTH(K2,12) -> 48669 | ... AE2: =EOMONTH(AD2,12) -> 55609
B3: Total Year Counter | D3: 0 | E3: =D3+1 -> 1 | F3: =E3+1 -> 2 | G3: =F3+1 -> 3 | H3: =G3+1 -> 4 | I3: =H3+1 -> 5 | J3: =I3+1 -> 6 | K3: =J3+1 -> 7 | L3: =K3+1 -> 8 | ... AE3: =AD3+1 -> 27
B4: Is Operational ? | C4: =SUM(E4:AE4) -> 26 | E4: =IF(AND(E2>=Input!$E$180,E2<=Input!$E$182),1,0) -> 0 | F4: =IF(AND(F2>=Input!$E$180,F2<=Input!$E$182),1,0) -> 1 | G4: =IF(AND(G2>=Input!$E$180,G2<=Input!$E$182),1,0) -> 1 | H4: =IF(AND(H2>=Input!$E$180,H2<=Input!$E$182),1,0) -> 1 | I4: =IF(AND(I2>=Input!$E$180,I2<=Input!$E$182),1,0) -> 1 | J4: =IF(AND(J2>=Input!$E$180,J2<=Input!$E$182),1,0) -> 1 | K4: =IF(AND(K2>=Input!$E$180,K2<=Input!$E$182),1,0) -> 1 | L4: =IF(AND(L2>=Input!$E$180,L2<=Input!$E$182),1,0) -> 1 | ... AE4: =IF(AND(AE2>=Input!$E$180,AE2<=Input!$E$182),1,0) -> 1
B5: Operational Year Number | E5: =SUM($E4:E$4) -> 0 | F5: =SUM($E4:F$4) -> 1 | G5: =SUM($E4:G$4) -> 2 | H5: =SUM($E4:H$4) -> 3 | I5: =SUM($E4:I$4) -> 4 | J5: =SUM($E4:J$4) -> 5 | K5: =SUM($E4:K$4) -> 6 | L5: =SUM($E4:L$4) -> 7 | ... AE5: =SUM($E4:AE$4) -> 26
B6: Days in year | E6: =E2-D2 -> 365 | F6: =F2-E2 -> 365 | G6: =G2-F2 -> 366 | H6: =H2-G2 -> 365 | I6: =I2-H2 -> 365 | J6: =J2-I2 -> 365 | K6: =K2-J2 -> 366 | L6: =L2-K2 -> 365 | ... AE6: =AE2-AD2 -> 366
B7: Days of Construction | E7: =E6-E8 -> 365 | F7: =F6-F8 -> 183 | G7: =G6-G8 -> 0 | H7: =H6-H8 -> 0 | I7: =I6-I8 -> 0 | J7: =J6-J8 -> 0 | K7: =K6-K8 -> 0 | L7: =L6-L8 -> 0
B8: Days in Operations | E8: =IF(E2=Input!$E$182,Input!$E$181-D2,IF(E2-Input!$E$178+1>=365,E2-D2,E2-Input!$E$178+1))*E4 -> 0 | F8: =IF(F2=Input!$E$182,Input!$E$181-E2,IF(F2-Input!$E$178+1>=365,F2-E2,F2-Input!$E$178+1))*F4 -> 182 | G8: =IF(G2=Input!$E$182,Input!$E$181-F2,IF(G2-Input!$E$178+1>=365,G2-F2,G2-Input!$E$178+1))*G4 -> 366 | H8: =IF(H2=Input!$E$182,Input!$E$181-G2,IF(H2-Input!$E$178+1>=365,H2-G2,H2-Input!$E$178+1))*H4 -> 365 | I8: =IF(I2=Input!$E$182,Input!$E$181-H2,IF(I2-Input!$E$178+1>=365,I2-H2,I2-Input!$E$178+1))*I4 -> 365 | J8: =IF(J2=Input!$E$182,Input!$E$181-I2,IF(J2-Input!$E$178+1>=365,J2-I2,J2-Input!$E$178+1))*J4 -> 365 | K8: =IF(K2=Input!$E$182,Input!$E$181-J2,IF(K2-Input!$E$178+1>=365,K2-J2,K2-Input!$E$178+1))*K4 -> 366 | L8: =IF(L2=Input!$E$182,Input!$E$181-K2,IF(L2-Input!$E$178+1>=365,L2-K2,L2-Input!$E$178+1))*L4 -> 365 | ... AE8: =IF(AE2=Input!$E$182,Input!$E$181-AD2,IF(AE2-Input!$E$178+1>=365,AE2-AD2,AE2-Input!$E$178+1))*AE4 -> 183
B9: Proportion of year in operation | E9: =IF(E6,E8/E6,0) -> 0 | F9: =IF(F6,F8/F6,0) -> 0.49863014 | G9: =IF(G6,G8/G6,0) -> 1 | H9: =IF(H6,H8/H6,0) -> 1 | I9: =IF(I6,I8/I6,0) -> 1 | J9: =IF(J6,J8/J6,0) -> 1 | K9: =IF(K6,K8/K6,0) -> 1 | L9: =IF(L6,L8/L6,0) -> 1 | ... AE9: =IF(AE6,AE8/AE6,0) -> 0.5
B10: Cumulative number of year in operation | E10: =D10+E9 -> 0 | F10: =E10+F9 -> 0.49863014 | G10: =F10+G9 -> 1.4986301 | H10: =G10+H9 -> 2.4986301 | I10: =H10+I9 -> 3.4986301 | J10: =I10+J9 -> 4.4986301 | K10: =J10+K9 -> 5.4986301 | L10: =K10+L9 -> 6.4986301 | ... AE10: =AD10+AE9 -> 24.99863
B12: Energy Generation Computation
B13: Capacity | C13: MW | D13: =Working!D153 -> 203.24 | E13: =Working!E153 -> 203.24 | F13: =Working!F153 -> 203.24 | G13: =Working!G153 -> 203.24 | H13: =Working!H153 -> 203.24 | I13: =Working!I153 -> 203.24 | J13: =Working!J153 -> 203.24 | K13: =Working!K153 -> 203.24 | ... AE13: =Working!AE153 -> 203.24
B14: Degradation | C14: % | D14: =Working!D154 -> 0 | E14: =Working!E154 -> 0 | F14: =Working!F154 -> 0.0024931507 | G14: =Working!G154 -> 0.005 | H14: =Working!H154 -> 0.005 | I14: =Working!I154 -> 0.005 | J14: =Working!J154 -> 0.005 | K14: =Working!K154 -> 0.005 | ... AE14: =Working!AE154 -> 0.0025
B15: Effective capacity | C15: MW | D15: =Working!D155 -> 203.24 | E15: =Working!E155 -> 203.24 | F15: =Working!F155 -> 203.24 | G15: =Working!G155 -> 203.24 | H15: =Working!H155 -> 203.24 | I15: =Working!I155 -> 203.24 | J15: =Working!J155 -> 203.24 | K15: =Working!K155 -> 203.24 | ... AE15: =Working!AE155 -> 203.24
B16: CUF | C16: % | D16: =Working!D156 -> 0.19317816 | E16: =Working!E156 -> 0 | F16: =Working!F156 -> 0.19257684 | G16: =Working!G156 -> 0.18905273 | H16: =Working!H156 -> 0.18720105 | I16: =Working!I156 -> 0.18486103 | J16: =Working!J156 -> 0.18255027 | K16: =Working!K156 -> 0.17977586 | ... AE16: =Working!AE156 -> 0.16470322
B17: Net Saleable Energy | C17: MU | D17: =Working!D158 -> 343.931 | E17: =Working!E158 -> 0 | F17: =Working!F158 -> 170.96054 | G17: =Working!G158 -> 337.5083 | H17: =Working!H158 -> 333.28945 | I17: =Working!I158 -> 329.12333 | J17: =Working!J158 -> 325.00929 | K17: =Working!K158 -> 320.94667 | ... AE17: =Working!AE158 -> 147.01905
B19: Fixed Charge Computation
B20: =Working!B256 -> Generation O&M | C20: =Working!C256 -> Rs Cr | E20: =Working!E256 -> 0 | F20: =Working!F256 -> 5.5725713 | G20: =Working!G256 -> 11.762489 | H20: =Working!H256 -> 12.380019 | I20: =Working!I256 -> 13.02997 | J20: =Working!J256 -> 13.714044 | K20: =Working!K256 -> 14.434031 | L20: =Working!L256 -> 15.191818 | ... AE20: =Working!AE256 -> 20.081665
B21: =Working!B257 -> Infrastructure O&M | C21: =Working!C257 -> Rs Cr | E21: =Working!E257 -> 0 | F21: =Working!F257 -> 1.1877748 | G21: =Working!G257 -> 2.4718801 | H21: =Working!H257 -> 2.56507 | I21: =Working!I257 -> 2.6617731 | J21: =Working!J257 -> 2.762122 | K21: =Working!K257 -> 2.866254 | L21: =Working!L257 -> 2.9743118 | ... AE21: =Working!AE257 -> 2.9490701
B22: =Working!B258 -> Depreciation | C22: =Working!C258 -> Rs Cr | E22: =Working!E258 -> 0 | F22: =Working!F258 -> 28.934334 | G22: =Working!G258 -> 58.027647 | H22: =Working!H258 -> 58.027647 | I22: =Working!I258 -> 58.027647 | J22: =Working!J258 -> 58.027647 | K22: =Working!K258 -> 58.027647 | L22: =Working!L258 -> 58.027647 | ... AE22: =Working!AE258 -> 12.42562
B23: =Working!B259 -> Interest on Term Loan | C23: =Working!C259 -> Rs Cr | E23: =Working!E259 -> 0 | F23: =Working!F259 -> 18.672217 | G23: =Working!G259 -> 48.708432 | H23: =Working!H259 -> 45.229258 | I23: =Working!I259 -> 41.750084 | J23: =Working!J259 -> 38.270911 | K23: =Working!K259 -> 34.791737 | L23: =Working!L259 -> 31.312563 | ... AE23: =Working!AE259 -> 0
B24: =Working!B260 -> Interest on WC | C24: =Working!C260 -> Rs Cr | E24: =Working!E260 -> 0 | F24: =Working!F260 -> 1.10437 | G24: =Working!G260 -> 2.1981088 | H24: =Working!H260 -> 2.1885165 | I24: =Working!I260 -> 2.1799461 | J24: =Working!J260 -> 2.1724307 | K24: =Working!K260 -> 2.1660055 | L24: =Working!L260 -> 2.1607077 | ... AE24: =Working!AE260 -> 1.2962073
B25: Total Cost | C25: =Working!C261 -> Rs Cr | F25: =SUM(F20:F24) -> 55.471267 | G25: =SUM(G20:G24) -> 123.16856 | H25: =SUM(H20:H24) -> 120.39051 | I25: =SUM(I20:I24) -> 117.64942 | J25: =SUM(J20:J24) -> 114.94715 | K25: =SUM(K20:K24) -> 112.28567 | L25: =SUM(L20:L24) -> 109.66705 | M25: =SUM(M20:M24) -> 107.09344 | ... AE25: =SUM(AE20:AE24) -> 36.752563
B26: =Working!B263 -> ROE | C26: =Working!C263 -> Rs Cr | E26: =Working!E263 -> 0 | F26: =Working!F263 -> 31.412739 | G26: =Working!G263 -> 62.998075 | H26: =Working!H263 -> 62.998075 | I26: =Working!I263 -> 62.998075 | J26: =Working!J263 -> 62.998075 | K26: =Working!K263 -> 62.998075 | L26: =Working!L263 -> 62.998075 | ... AE26: =Working!AE263 -> 33.453593
B27: Total ARR | C27: =Working!C265 -> Rs Cr | E27: =Working!E265 -> 0 | F27: =F25+F26 -> 86.884006 | G27: =G25+G26 -> 186.16663 | H27: =H25+H26 -> 183.38859 | I27: =I25+I26 -> 180.6475 | J27: =J25+J26 -> 177.94523 | K27: =K25+K26 -> 175.28375 | L27: =L25+L26 -> 172.66512 | M27: =M25+M26 -> 170.09152 | ... AE27: =AE25+AE26 -> 70.206156
B29: Per Unit Cost
B30: =Working!B267 -> Generation O&M | C30: =Working!C267 -> Rs/kWh | F30: =Working!F267 -> 0.32595658 | G30: =Working!G267 -> 0.34850961 | H30: =Working!H267 -> 0.37144948 | I30: =Working!I267 -> 0.39589932 | J30: =Working!J267 -> 0.42195851 | K30: =Working!K267 -> 0.449733 | L30: =Working!L267 -> 0.47933568 | M30: =Working!M267 -> 0.51088688 | ... AE30: =Working!AE267 -> 1.3659227
B31: =Working!B268 -> Infrastructure O&M | C31: =Working!C268 -> Rs/kWh | F31: =Working!F268 -> 0.069476548 | G31: =Working!G268 -> 0.073239091 | H31: =Working!H268 -> 0.076962232 | I31: =Working!I268 -> 0.080874641 | J31: =Working!J268 -> 0.08498594 | K31: =Working!K268 -> 0.089306237 | L31: =Working!L268 -> 0.09384616 | M31: =Working!M268 -> 0.098616871 | ... AE31: =Working!AE268 -> 0.20059103
B32: =Working!B269 -> Depreciation | C32: =Working!C269 -> Rs/kWh | F32: =Working!F269 -> 1.6924569 | G32: =Working!G269 -> 1.7192954 | H32: =Working!H269 -> 1.7410586 | I32: =Working!I269 -> 1.7630973 | J32: =Working!J269 -> 1.785415 | K32: =Working!K269 -> 1.8080152 | L32: =Working!L269 -> 1.8309015 | M32: =Working!M269 -> 1.8540774 | ... AE32: =Working!AE269 -> 0.84517079
B33: =Working!B270 -> Interest on Term Loan | C33: =Working!C270 -> Rs/kWh | F33: =Working!F270 -> 1.0921946 | G33: =Working!G270 -> 1.4431773 | H33: =Working!H270 -> 1.3570564 | I33: =Working!I270 -> 1.268524 | J33: =Working!J270 -> 1.1775328 | K33: =Working!K270 -> 1.0840348 | L33: =Working!L270 -> 0.9879811 | M33: =Working!M270 -> 0.88932195 | ... AE33: =Working!AE270 -> 0
B34: =Working!B271 -> Interest on WC | C34: =Working!C271 -> Rs/kWh | F34: =Working!F271 -> 0.064597946 | G34: =Working!G271 -> 0.065127547 | H34: =Working!H271 -> 0.06566414 | I34: =Working!I271 -> 0.066234931 | J34: =Working!J271 -> 0.066842112 | K34: =Working!K271 -> 0.067488019 | L34: =Working!L271 -> 0.068175139 | M34: =Working!M271 -> 0.068906118 | ... AE34: =Working!AE271 -> 0.088165944
B35: =Working!B274 -> ROE | C35: =Working!C274 -> Rs/kWh | F35: =Working!F274 -> 1.8374263 | G35: =Working!G274 -> 1.8665637 | H35: =Working!H274 -> 1.8901911 | I35: =Working!I274 -> 1.9141176 | J35: =Working!J274 -> 1.9383469 | K35: =Working!K274 -> 1.9628829 | L35: =Working!L274 -> 1.9877296 | M35: =Working!M274 -> 2.0128907 | ... AE35: =Working!AE274 -> 2.2754598
B36: Year on Year Tariff | C36: =Working!C276 -> Rs/kWh | F36: =Working!F276 -> 5.0821088 | G36: =Working!G276 -> 5.5159126 | H36: =Working!H276 -> 5.502382 | I36: =Working!I276 -> 5.4887478 | J36: =Working!J276 -> 5.4750813 | K36: =Working!K276 -> 5.4614602 | L36: =Working!L276 -> 5.4479691 | M36: =Working!M276 -> 5.4347 | ... AE36: =Working!AE276 -> 4.7753103
B37: Discounting Factor | F37: =Working!F254 -> 1 | G37: =Working!G254 -> 0.93044028 | H37: =Working!H254 -> 0.86571912 | I37: =Working!I254 -> 0.80549995 | J37: =Working!J254 -> 0.7494696 | K37: =Working!K254 -> 0.69733671 | L37: =Working!L254 -> 0.64883016 | M37: =Working!M254 -> 0.60369772 | ... AE37: =Working!AE254 -> 0.16489695
B39: =Working!B277 -> Levelized Tariff | C39: =Working!C277 -> Rs/kWh | D39: =Working!D277 -> 5.2535517

Sheet IDC_Q
B1: Particulars | C1: Units | D1: Inputs | E1: =D2+DAY(1) -> 45748 | F1: =E2+DAY(1) -> 45839 | G1: =F2+DAY(1) -> 45931 | H1: =G2+DAY(1) -> 46023 | I1: =H2+DAY(1) -> 46113 | J1: =I2+DAY(1) -> 46204 | K1: =J2+DAY(1) -> 46296 | L1: =K2+DAY(1) -> 46388 | ... AK1: =AJ2+DAY(1) -> 48670
D2: =Input!D238 -> 45747 | E2: =EOMONTH(D2,3) -> 45838 | F2: =EOMONTH(E2,3) -> 45930 | G2: =EOMONTH(F2,3) -> 46022 | H2: =EOMONTH(G2,3) -> 46112 | I2: =EOMONTH(H2,3) -> 46203 | J2: =EOMONTH(I2,3) -> 46295 | K2: =EOMONTH(J2,3) -> 46387 | L2: =EOMONTH(K2,3) -> 46477 | ... AJ2: =EOMONTH(AI2,3) -> 48669
B3: Is Operational ? | C3: =SUM(E3:AI3) -> 25 | E3: =IF(AND((E2)>=Input!$E$178,E2<=Input!$E$182),1,0) -> 0 | F3: =IF(AND((F2)>=Input!$E$178,F2<=Input!$E$182),1,0) -> 0 | G3: =IF(AND((G2)>=Input!$E$178,G2<=Input!$E$182),1,0) -> 0 | H3: =IF(AND((H2)>=Input!$E$178,H2<=Input!$E$182),1,0) -> 0 | I3: =IF(AND((I2)>=Input!$E$178,I2<=Input!$E$182),1,0) -> 0 | J3: =IF(AND((J2)>=Input!$E$178,J2<=Input!$E$182),1,0) -> 0 | K3: =IF(AND((K2)>=Input!$E$178,K2<=Input!$E$182),1,0) -> 1 | L3: =IF(AND((L2)>=Input!$E$178,L2<=Input!$E$182),1,0) -> 1 | ... AJ3: =IF(AND((AJ2)>=Input!$E$178,AJ2<=Input!$E$182),1,0) -> 1
B4: Operational Quarter Number | E4: =SUM($E3:E$3) -> 0 | F4: =SUM($E3:F$3) -> 0 | G4: =SUM($E3:G$3) -> 0 | H4: =SUM($E3:H$3) -> 0 | I4: =SUM($E3:I$3) -> 0 | J4: =SUM($E3:J$3) -> 0 | K4: =SUM($E3:K$3) -> 1 | L4: =SUM($E3:L$3) -> 2 | ... AJ4: =SUM($E3:AJ$3) -> 26
B5: Days in Quarter | E5: =E2-D2 -> 91 | F5: =F2-E2 -> 92 | G5: =G2-F2 -> 92 | H5: =H2-G2 -> 90 | I5: =I2-H2 -> 91 | J5: =J2-I2 -> 92 | K5: =K2-J2 -> 92 | L5: =L2-K2 -> 90 | ... AJ5: =AJ2-AI2 -> 90
B6: Year No. | D6: 0 | E6: =IF(MONTH(E1)=4,D6+1,D6) -> 1 | F6: =IF(MONTH(F1)=4,E6+1,E6) -> 1 | G6: =IF(MONTH(G1)=4,F6+1,F6) -> 1 | H6: =IF(MONTH(H1)=4,G6+1,G6) -> 1 | I6: =IF(MONTH(I1)=4,H6+1,H6) -> 2 | J6: =IF(MONTH(J1)=4,I6+1,I6) -> 2 | K6: =IF(MONTH(K1)=4,J6+1,J6) -> 2 | L6: =IF(MONTH(L1)=4,K6+1,K6) -> 2 | ... AJ6: =IF(MONTH(AJ1)=4,AI6+1,AI6) -> 8
B7: Days in Operations | E7: =IF(E2=Input!$E$182,Input!$E$181-D2,IF(E2-Input!$E$178+1>=(365/4),E2-D2,E2-Input!$E$178+1))*E3 -> 0 | F7: =IF(F2=Input!$E$182,Input!$E$181-E2,IF(F2-Input!$E$178+1>=(365/4),F2-E2,F2-Input!$E$178+1))*F3 -> 0 | G7: =IF(G2=Input!$E$182,Input!$E$181-F2,IF(G2-Input!$E$178+1>=(365/4),G2-F2,G2-Input!$E$178+1))*G3 -> 0 | H7: =IF(H2=Input!$E$182,Input!$E$181-G2,IF(H2-Input!$E$178+1>=(365/4),H2-G2,H2-Input!$E$178+1))*H3 -> 0 | I7: =IF(I2=Input!$E$182,Input!$E$181-H2,IF(I2-Input!$E$178+1>=(365/4),I2-H2,I2-Input!$E$178+1))*I3 -> 0 | J7: =IF(J2=Input!$E$182,Input!$E$181-I2,IF(J2-Input!$E$178+1>=(365/4),J2-I2,J2-Input!$E$178+1))*J3 -> 0 | K7: =IF(K2=Input!$E$182,Input!$E$181-J2,IF(K2-Input!$E$178+1>=(365/4),K2-J2,K2-Input!$E$178+1))*K3 -> 92 | L7: =IF(L2=Input!$E$182,Input!$E$181-K2,IF(L2-Input!$E$178+1>=(365/4),L2-K2,L2-Input!$E$178+1))*L3 -> 90 | ... AJ7: =IF(AJ2=Input!$E$182,Input!$E$181-AI2,IF(AJ2-Input!$E$178+1>=(365/4),AJ2-AI2,AJ2-Input!$E$178+1))*AJ3 -> 90
B8: Days in Construction | E8: =E5-E7 -> 91 | F8: =F5-F7 -> 92 | G8: =G5-G7 -> 92 | H8: =H5-H7 -> 90 | I8: =I5-I7 -> 91 | J8: =J5-J7 -> 92 | K8: =K5-K7 -> 0 | L8: =L5-L7 -> 0 | ... AJ8: =AJ5-AJ7 -> 0
B9: Proportion of year in operation | E9: =IF(E5,E7/E5,0) -> 0 | F9: =IF(F5,F7/F5,0) -> 0 | G9: =IF(G5,G7/G5,0) -> 0 | H9: =IF(H5,H7/H5,0) -> 0 | I9: =IF(I5,I7/I5,0) -> 0 | J9: =IF(J5,J7/J5,0) -> 0 | K9: =IF(K5,K7/K5,0) -> 1 | L9: =IF(L5,L7/L5,0) -> 1 | ... AJ9: =IF(AJ5,AJ7/AJ5,0) -> 1
B10: Cumulative number of year in operation | E10: =D10+E9 -> 0 | F10: =E10+F9 -> 0 | G10: =F10+G9 -> 0 | H10: =G10+H9 -> 0 | I10: =H10+I9 -> 0 | J10: =I10+J9 -> 0 | K10: =J10+K9 -> 1 | L10: =K10+L9 -> 2 | ... AJ10: =AI10+AJ9 -> 26
A12: CapEX
B13: Capacity of the Project | C13: MW | D13: =Input!E6 -> 203.24 | F13: MWp | G13: =Input!$E$4 -> 243.888
B14: Generation Project | C14: Unit | D14: Unit Cost | E14: Quantity | F14: Cost (Rs Lakh) | G14: Tax | H14: Total Cost
A15: II | B15: Capital Expenditure - Generation
A16: A | B16: SPV Modules | C16: Lot | D16: =Working!D16 -> 159 | E16: =Working!E16 -> 243.888 | F16: =Working!F16 -> 38728.483 | G16: =Working!G16 -> 5344.5306 | H16: =Working!H16 -> 44073.013
A17: B | B17: Inverters | C17: Lot | D17: =Working!D17 -> 13 | E17: =Working!E17 -> 203.24 | F17: =Working!F17 -> 2650.5 | G17: =Working!G17 -> 365.769 | H17: =Working!H17 -> 3016.269
A18: C | B18: Floating Structure for Module and inverters | C18: Lot | D18: =Working!D18 -> 135 | E18: =Working!E18 -> 243.888 | F18: =Working!F18 -> 32929.861 | G18: =Working!G18 -> 4544.3208 | H18: =Working!H18 -> 37474.182
A19: D | B19: Balance of Plant (Cables, SCB, Accessories) | C19: Lot | D19: =Working!D19 -> 40 | E19: =Working!E19 -> 243.888 | F19: =Working!F19 -> 9694.1833 | G19: =Working!G19 -> 1337.7973 | H19: =Working!H19 -> 11031.981
A20: E | B20: Civil Structure | C20: Lot | D20: =Working!D20 -> 7 | E20: =Working!E20 -> 243.888 | F20: =Working!F20 -> 1663.1343 | G20: =Working!G20 -> 229.51254 | H20: =Working!H20 -> 1892.6469
B21: Capital Expenditure - Generation | C21: Lot | F21: =SUM(F16:F20) -> 85666.161 | G21: =SUM(G16:G20) -> 11821.93 | H21: =SUM(H16:H20) -> 97488.091
A22: III | B22: Capital Expenditure - Transmission Evacuation
A23: A | B23: Pooling Sub-station | C23: MVA | D23: =Working!D23 -> 24.042916 | E23: =Working!E23 -> 320 | F23: =Working!F23 -> 7693.733 | G23: =Working!G23 -> 1384.8719 | H23: =Working!H23 -> 9078.6049
A24: B | B24: Transmission Line System | C24: kM | D24: =Working!D24 -> 282.71079 | E24: =Working!E24 -> 4 | F24: =Working!F24 -> 1130.8432 | G24: =Working!G24 -> 203.55177 | H24: =Working!H24 -> 1334.3949
A25: C | B25: Augmentation Works | C25: Lot | D25: =Working!D25 -> 422.0675 | E25: =Working!E25 -> 1 | F25: =Working!F25 -> 422.0675 | G25: =Working!G25 -> 75.97215 | H25: =Working!H25 -> 498.03965
B26: Capital Expenditure - Transmission Evacuation | C26: Lot | F26: =SUM(F23:F25) -> 9246.6437 | G26: =SUM(G23:G25) -> 1664.3959 | H26: =SUM(H23:H25) -> 10911.04
A27: I | B27: Capital Expenditure - Infrastructure
A28: A | B28: Land & Site Development | C28: Lot | D28: =Working!D28 -> 0 | E28: =Working!E28 -> 0 | F28: =Working!F28 -> 1502.05 | G28: =Working!G28 -> 270.369 | H28: =Working!H28 -> 1772.419
A29: C | B29: Road Infrastructure | C29: Lot | D29: =Working!D29 -> 0 | E29: =Working!E29 -> 0 | F29: =Working!F29 -> 73.5 | G29: =Working!G29 -> 13.23 | H29: =Working!H29 -> 86.73
B30: Capital Expenditure - Infrastructure | C30: Lot | F30: =SUM(F28:F29) -> 1575.55 | G30: =SUM(G28:G29) -> 283.599 | H30: =SUM(H28:H29) -> 1859.149
A31: IV | B31: Capital Expenditure - Other Costs
A32: A | B32: Generation (Contingency, Insurance, Warranty, etc) | C32: Lot | D32: =Working!D32 -> 0 | E32: =Working!E32 -> 0 | F32: =Working!F32 -> 9449.5874 | G32: =Working!G32 -> 1304.0431 | H32: =Working!H32 -> 10753.63
A33: B | B33: Transmission (Contingency, Insurance, Warranty, etc) | C33: Lot | D33: =Working!D33 -> 0 | E33: =Working!E33 -> 0 | F33: =Working!F33 -> 327.33119 | G33: =Working!G33 -> 58.919613 | H33: =Working!H33 -> 386.2508
A34: C | B34: Other Charges/Statutory Charges | C34: Lot | D34: =Working!D34 -> 0 | E34: =Working!E34 -> 0 | F34: =Working!F34 -> 208.24 | G34: =Working!G34 -> 37.4832 | H34: =Working!H34 -> 245.7232
B35: Capital Expenditure - Other Costs | C35: Lot | F35: =SUM(F32:F34) -> 9985.1586 | G35: =SUM(G32:G34) -> 1400.4459 | H35: =SUM(H32:H34) -> 11385.604
G36: =G21+G26+G30+G35 -> 15170.371 | H36: =H21+H26+H30+H35 -> 121643.88
B37: Interest During Construction | C37: Lot | H37: =Working!H37 -> 2612.319
B38: Grand Total | C38: Lot | F38: =F36+F37 -> 0 | G38: =G36+G37 -> 15170.371 | H38: =H36+H37 -> 124256.2
B39: Capital Cost without IDC
A40: 1 | B40: Capital Expenditure - Generation & Transmission | C40: Rs Cr | F40: =Working!F40 -> 949.12805 | G40: =Working!G40 -> 134.86326 | H40: =Working!H40 -> 1083.9913
A41: 2 | B41: Capital Expenditure - Infrastructure | C41: Rs Cr | F41: =Working!F41 -> 15.7555 | G41: =Working!G41 -> 2.83599 | H41: =Working!H41 -> 18.59149
A42: 3 | B42: Capital Expenditure - Other Costs | C42: Rs Cr | F42: =Working!F42 -> 99.851586 | G42: =Working!G42 -> 14.004459 | H42: =Working!H42 -> 113.85604
B43: Capital Cost - Total | C43: Rs Cr | F43: =F42+F41+F40 -> 1064.7351 | G43: =G42+G41+G40 -> 151.70371 | H43: =H42+H41+H40 -> 1216.4388
B44: Interest During Construction | C44: Rs Cr | H44: =Working!H44 -> 26.12319
B45: Gross Capital Cost | C45: Rs Cr | H45: =SUM(H43:H44) -> 1242.562
A47: Phasing | C47: Rs Cr
A48: 1 | B48: Capital Expenditure - Generation & Transmission | C48: Rs Cr | D48: =SUM(E48:AI48) -> 1083.9913 | E48: =$H$40*Input!E266 -> 0 | F48: =$H$40*Input!F266 -> 38.075281 | G48: =$H$40*Input!H266 -> 113.58546 | H48: =$H$40*Input!I266 -> 408.27252 | I48: =$H$40*Input!J266 -> 436.3831 | J48: =$H$40*Input!K266 -> 87.674951 | K48: =$H$40*Input!L266 -> 0 | L48: =$H$40*Input!M266 -> 0 | M48: =$H$40*Input!N266 -> 0 | N48: =$H$40*Input!O266 -> 0 | ... AI48: =$H$40*Input!AJ266 -> 0
A49: 2 | B49: Capital Expenditure - Infrastructure | D49: =SUM(E49:AI49) -> 18.59149 | E49: =$H$41*Input!E267 -> 0 | F49: =$H$41*Input!F267 -> 0 | G49: =$H$41*Input!H267 -> 2.7887235 | H49: =$H$41*Input!I267 -> 2.7887235 | I49: =$H$41*Input!J267 -> 6.5070215 | J49: =$H$41*Input!K267 -> 6.5070215 | K49: =$H$41*Input!L267 -> 0 | L49: =$H$41*Input!M267 -> 0 | M49: =$H$41*Input!N267 -> 0 | N49: =$H$41*Input!O267 -> 0 | ... AI49: =$H$41*Input!AJ267 -> 0
A50: 3 | B50: Capital Expenditure - Other Costs | C50: Rs Cr | D50: =SUM(E50:AI50) -> 113.85604 | E50: =$H$42*Input!E268 -> 0 | F50: =$H$42*Input!F268 -> 0 | G50: =$H$42*Input!H268 -> 5.6928022 | H50: =$H$42*Input!I268 -> 5.6928022 | I50: =$H$42*Input!J268 -> 51.23522 | J50: =$H$42*Input!K268 -> 51.23522 | K50: =$H$42*Input!L268 -> 0 | L50: =$H$42*Input!M268 -> 0 | M50: =$H$42*Input!N268 -> 0 | N50: =$H$42*Input!O268 -> 0 | ... AI50: =$H$42*Input!AJ268 -> 0
B51: Phasing - Capex | C51: Rs Cr | D51: =SUM(E51:AI51) -> 1216.4388 | E51: =SUM(E48:E50) -> 0 | F51: =SUM(F48:F50) -> 38.075281 | G51: =SUM(G48:G50) -> 122.06699 | H51: =SUM(H48:H50) -> 416.75404 | I51: =SUM(I48:I50) -> 494.12534 | J51: =SUM(J48:J50) -> 145.41719 | K51: =SUM(K48:K50) -> 0 | L51: =SUM(L48:L50) -> 0 | ... AI51: =SUM(AI48:AI50) -> 0
B52: IDC | C52: Rs Cr | D52: =SUM(E52:AI52) -> 26.12319 | E52: =IF(Input!$L$2,E90+E80,0) -> 0 | F52: =IF(Input!$L$2,F90+F80,0) -> 0.20095022 | G52: =IF(Input!$L$2,G90+G80,0) -> 1.0482555 | H52: =IF(Input!$L$2,H90+H80,0) -> 3.9030603 | I52: =IF(Input!$L$2,I90+I80,0) -> 8.7516141 | J52: =IF(Input!$L$2,J90+J80,0) -> 12.21931 | K52: =IF(Input!$L$2,K90+K80,0) -> 0 | L52: =IF(Input!$L$2,L90+L80,0) -> 0 | ... AI52: =IF(Input!$L$2,AI90+AI80,0) -> 0
B53: Capex incl. IDC | C53: Rs Cr | D53: =SUM(E53:AI53) -> 1242.562 | E53: =(E51+E52)*(1+Input!$I$10) -> 0 | F53: =(F51+F52)*(1+Input!$I$10) -> 38.276231 | G53: =G51+G52 -> 123.11524 | H53: =H51+H52 -> 420.6571 | I53: =I51+I52 -> 502.87695 | J53: =J51+J52 -> 157.6365 | K53: =K51+K52 -> 0 | L53: =L51+L52 -> 0 | M53: =M51+M52 -> 0 | N53: =N51+N52 -> 0 | ... AI53: =AI51+AI52 -> 0
B55: Commerical Loan 1 | C55: % | E55: =Input!E245 -> 0.7 | F55: =Input!F245 -> 0.7 | G55: =Input!H245 -> 0.7 | H55: =Input!J245 -> 0.7 | I55: =Input!K245 -> 0.7 | J55: =Input!L245 -> 0.7 | K55: =Input!M245 -> 0.7 | L55: =Input!N245 -> 0.7 | M55: =Input!O245 -> 0.7 | N55: =Input!P245 -> 0.7 | O55: =Input!Q245 -> 0.7 | ... AI55: =Input!AK245 -> 0.7
B56: Commercial Loan 2 | C56: % | E56: =Input!E246 -> 0 | F56: =Input!F246 -> 0 | G56: =Input!H246 -> 0 | H56: =Input!J246 -> 0 | I56: =Input!K246 -> 0 | J56: =Input!L246 -> 0 | K56: =Input!M246 -> 0 | L56: =Input!N246 -> 0 | M56: =Input!O246 -> 0 | N56: =Input!P246 -> 0 | O56: =Input!Q246 -> 0 | ... AI56: =Input!AK246 -> 0
B57: Grant | C57: % | E57: =Input!E247 -> 0 | F57: =Input!F247 -> 0 | G57: =Input!H247 -> 0 | H57: =Input!J247 -> 0 | I57: =Input!K247 -> 0 | J57: =Input!L247 -> 0 | K57: =Input!M247 -> 0 | L57: =Input!N247 -> 0 | M57: =Input!O247 -> 0 | N57: =Input!P247 -> 0 | O57: =Input!Q247 -> 0 | ... AI57: =Input!AK247 -> 0
B58: Equity | C58: % | E58: =Input!E248 -> 0.3 | F58: =Input!F248 -> 0.3 | G58: =Input!H248 -> 0.3 | H58: =Input!J248 -> 0.3 | I58: =Input!K248 -> 0.3 | J58: =Input!L248 -> 0.3 | K58: =Input!M248 -> 0.3 | L58: =Input!N248 -> 0.3 | M58: =Input!O248 -> 0.3 | N58: =Input!P248 -> 0.3 | O58: =Input!Q248 -> 0.3 | ... AI58: =Input!AK248 -> 0.3
B60: Commerical Loan 1 | C60: Rs Cr | D60: =SUM(E60:AI60) -> 869.79342 | E60: =E$53*E55 -> 0 | F60: =F$53*F55 -> 26.793362 | G60: =G$53*G55 -> 86.180669 | H60: =H$53*H55 -> 294.45997 | I60: =I$53*I55 -> 352.01387 | J60: =J$53*J55 -> 110.34555 | K60: =K$53*K55 -> 0 | L60: =L$53*L55 -> 0 | ... AI60: =AI$53*AI55 -> 0
B61: Commerical Loan 2 | C61: Rs Cr | D61: =SUM(E61:AI61) -> 0 | E61: =E$53*E56 -> 0 | F61: =F$53*F56 -> 0 | G61: =G$53*G56 -> 0 | H61: =H$53*H56 -> 0 | I61: =I$53*I56 -> 0 | J61: =J$53*J56 -> 0 | K61: =K$53*K56 -> 0 | L61: =L$53*L56 -> 0 | ... AI61: =AI$53*AI56 -> 0
B62: Grant | C62: Rs Cr | D62: =SUM(E62:AI62) -> 0 | E62: =E$53*E57 -> 0 | F62: =F$53*F57 -> 0 | G62: =G$53*G57 -> 0 | H62: =H$53*H57 -> 0 | I62: =I$53*I57 -> 0 | J62: =J$53*J57 -> 0 | K62: =K$53*K57 -> 0 | L62: =L$53*L57 -> 0 | ... AI62: =AI$53*AI57 -> 0
B63: Equity | C63: Rs Cr | D63: =SUM(E63:AI63) -> 372.76861 | E63: =E$53*E58 -> 0 | F63: =F$53*F58 -> 11.482869 | G63: =G$53*G58 -> 36.934573 | H63: =H$53*H58 -> 126.19713 | I63: =I$53*I58 -> 150.86309 | J63: =J$53*J58 -> 47.290951 | K63: =K$53*K58 -> 0 | L63: =L$53*L58 -> 0 | ... AI63: =AI$53*AI58 -> 0
D64: =SUM(D60:D63)-D53 -> 0
A65: Grant Schedule
B66: Grant | C66: Rs Cr | E66: =E62 -> 0 | F66: =F62 -> 0 | G66: =G62 -> 0 | H66: =H62 -> 0 | I66: =I62 -> 0 | J66: =J62 -> 0 | K66: =K62 -> 0 | L66: =L62 -> 0 | ... AI66: =AI62 -> 0
B67: Cumulative Grant | C67: Rs Cr | E67: =D67+E66 -> 0 | F67: =E67+F66 -> 0 | G67: =F67+G66 -> 0 | H67: =G67+H66 -> 0 | I67: =H67+I66 -> 0 | J67: =I67+J66 -> 0 | K67: =J67+K66 -> 0 | L67: =K67+L66 -> 0 | ... AI67: =AH67+AI66 -> 0
A69: Equity Schedule
B70: Equity | C70: Rs Cr | E70: =E63 -> 0 | F70: =F63 -> 11.482869 | G70: =G63 -> 36.934573 | H70: =H63 -> 126.19713 | I70: =I63 -> 150.86309 | J70: =J63 -> 47.290951 | K70: =K63 -> 0 | L70: =L63 -> 0 | ... AI70: =AI63 -> 0
B71: Cumulative Equity | C71: Rs Cr | E71: =D71+E70 -> 0 | F71: =E71+F70 -> 11.482869 | G71: =F71+G70 -> 48.417442 | H71: =G71+H70 -> 174.61457 | I71: =H71+I70 -> 325.47766 | J71: =I71+J70 -> 372.76861 | K71: =J71+K70 -> 372.76861 | L71: =K71+L70 -> 372.76861 | ... AI71: =AH71+AI70 -> 372.76861
A73: Commerical Loan 1 Schedule
B74: Opening | C74: Rs Cr | E74: =D77 -> 0 | F74: =E77 -> 0 | G74: =F77 -> 26.793362 | H74: =G77 -> 112.97403 | I74: =H77 -> 407.434 | J74: =I77 -> 759.44787 | K74: =J77 -> 869.79342 | L74: =K77 -> 855.29687 | ... AI74: =AH77 -> 521.87605
B75: Drawdown | C75: Rs Cr | D75: =SUM(E75:V75) -> 869.79342 | E75: =E60 -> 0 | F75: =F60 -> 26.793362 | G75: =G60 -> 86.180669 | H75: =H60 -> 294.45997 | I75: =I60 -> 352.01387 | J75: =J60 -> 110.34555 | K75: =K60 -> 0 | L75: =L60 -> 0 | ... AI75: =AI60 -> 0
B76: Repayments | C76: Rs Cr | E76: =IF(E$10>Input!$E$184,MIN(E74+E75,$D$75/(Input!$E$185*4)),0) -> 0 | F76: =IF(F$10>Input!$E$184,MIN(F74+F75,$D$75/(Input!$E$185*4)),0) -> 0 | G76: =IF(G$10>Input!$E$184,MIN(G74+G75,$D$75/(Input!$E$185*4)),0) -> 0 | H76: =IF(H$10>Input!$E$184,MIN(H74+H75,$D$75/(Input!$E$185*4)),0) -> 0 | I76: =IF(I$10>Input!$E$184,MIN(I74+I75,$D$75/(Input!$E$185*4)),0) -> 0 | J76: =IF(J$10>Input!$E$184,MIN(J74+J75,$D$75/(Input!$E$185*4)),0) -> 0 | K76: =IF(K$10>Input!$E$184,MIN(K74+K75,$D$75/(Input!$E$185*4)),0) -> 14.496557 | L76: =IF(L$10>Input!$E$184,MIN(L74+L75,$D$75/(Input!$E$185*4)),0) -> 14.496557 | ... AI76: =IF(AI$10>Input!$E$184,MIN(AI74+AI75,$D$75/(Input!$E$185*4)),0) -> 14.496557
B77: Closing | C77: Rs Cr | E77: =E74+E75-E76 -> 0 | F77: =F74+F75-F76 -> 26.793362 | G77: =G74+G75-G76 -> 112.97403 | H77: =H74+H75-H76 -> 407.434 | I77: =I74+I75-I76 -> 759.44787 | J77: =J74+J75-J76 -> 869.79342 | K77: =K74+K75-K76 -> 855.29687 | L77: =L74+L75-L76 -> 840.80031 | ... AI77: =AI74+AI75-AI76 -> 507.3795
B79: Interest Rate | C79: % | E79: =Input!$E$186 -> 0.06 | F79: =Input!$E$186 -> 0.06 | G79: =Input!$E$186 -> 0.06 | H79: =Input!$E$186 -> 0.06 | I79: =Input!$E$186 -> 0.06 | J79: =Input!$E$186 -> 0.06 | K79: =Input!$E$186 -> 0.06 | L79: =Input!$E$186 -> 0.06 | ... AI79: =Input!$E$186 -> 0.06
B80: IDC | C80: Rs Cr | D80: =SUM(E80:AI80) -> 26.12319 | E80: =AVERAGE(E74,E77)*E79/4*(E8/E5) -> 0 | F80: =AVERAGE(F74,F77)*F79/4*(F8/F5) -> 0.20095022 | G80: =AVERAGE(G74,G77)*G79/4*(G8/G5) -> 1.0482555 | H80: =AVERAGE(H74,H77)*H79/4*(H8/H5) -> 3.9030603 | I80: =AVERAGE(I74,I77)*I79/4*(I8/I5) -> 8.7516141 | J80: =AVERAGE(J74,J77)*J79/4*(J8/J5) -> 12.21931 | K80: =AVERAGE(K74,K77)*K79/4*(K8/K5) -> 0 | L80: =AVERAGE(L74,L77)*L79/4*(L8/L5) -> 0 | ... AI80: =AVERAGE(AI74,AI77)*AI79/4*(AI8/AI5) -> 0
B81: Interest Charge | C81: Rs Cr | D81: =SUM(E81:AF81) -> 937.63731 | E81: =AVERAGE(E74,E77)*E79*E9 -> 0 | F81: =AVERAGE(F74,F77)*F79*F9 -> 0 | G81: =AVERAGE(G74,G77)*G79*G9 -> 0 | H81: =AVERAGE(H74,H77)*H79*H9 -> 0 | I81: =AVERAGE(I74,I77)*I79*I9 -> 0 | J81: =AVERAGE(J74,J77)*J79*J9 -> 0 | K81: =AVERAGE(K74,K77)*K79*K9 -> 51.752709 | L81: =AVERAGE(L74,L77)*L79*L9 -> 50.882915 | ... AI81: =AVERAGE(AI74,AI77)*AI79*AI9 -> 30.877667
A83: Commercial Loan 2 Schedule
B84: Opening | C84: Rs Cr | E84: =D87 -> 0 | F84: =E87 -> 0 | G84: =F87 -> 0 | H84: =G87 -> 0 | I84: =H87 -> 0 | J84: =I87 -> 0 | K84: =J87 -> 0 | L84: =K87 -> 0 | ... AI84: =AH87 -> 0
B85: Addition | C85: Rs Cr | D85: =SUM(E85:V85) -> 0 | E85: =E61 -> 0 | F85: =F61 -> 0 | G85: =G61 -> 0 | H85: =H61 -> 0 | I85: =I61 -> 0 | J85: =J61 -> 0 | K85: =K61 -> 0 | L85: =L61 -> 0 | ... AI85: =AI61 -> 0
B86: Repayments | C86: Rs Cr | E86: =IF(E$10>Input!$E$188,MIN(E84+E85,$D$85/(Input!$E$189*4)),0) -> 0 | F86: =IF(F$10>Input!$E$188,MIN(F84+F85,$D$85/(Input!$E$189*4)),0) -> 0 | G86: =IF(G$10>Input!$E$188,MIN(G84+G85,$D$85/(Input!$E$189*4)),0) -> 0 | H86: =IF(H$10>Input!$E$188,MIN(H84+H85,$D$85/(Input!$E$189*4)),0) -> 0 | I86: =IF(I$10>Input!$E$188,MIN(I84+I85,$D$85/(Input!$E$189*4)),0) -> 0 | J86: =IF(J$10>Input!$E$188,MIN(J84+J85,$D$85/(Input!$E$189*4)),0) -> 0 | K86: =IF(K$10>Input!$E$188,MIN(K84+K85,$D$85/(Input!$E$189*4)),0) -> 0 | L86: =IF(L$10>Input!$E$188,MIN(L84+L85,$D$85/(Input!$E$189*4)),0) -> 0 | ... AI86: =IF(AI$10>Input!$E$188,MIN(AI84+AI85,$D$85/(Input!$E$189*4)),0) -> 0
B87: Closing | C87: Rs Cr | E87: =E84+E85-E86 -> 0 | F87: =F84+F85-F86 -> 0 | G87: =G84+G85-G86 -> 0 | H87: =H84+H85-H86 -> 0 | I87: =I84+I85-I86 -> 0 | J87: =J84+J85-J86 -> 0 | K87: =K84+K85-K86 -> 0 | L87: =L84+L85-L86 -> 0 | ... AI87: =AI84+AI85-AI86 -> 0
B89: Interest Rate | C89: % | E89: =Input!$E$190 -> 0.085 | F89: =Input!$E$190 -> 0.085 | G89: =Input!$E$190 -> 0.085 | H89: =Input!$E$190 -> 0.085 | I89: =Input!$E$190 -> 0.085 | J89: =Input!$E$190 -> 0.085 | K89: =Input!$E$190 -> 0.085 | L89: =Input!$E$190 -> 0.085 | ... AI89: =Input!$E$190 -> 0.085
B90: IDC | C90: Rs Cr | E90: =AVERAGE(E84,E87)*E89*(1-E9) -> 0 | F90: =AVERAGE(F84,F87)*F89*(1-F9) -> 0 | G90: =AVERAGE(G84,G87)*G89*(1-G9) -> 0 | H90: =AVERAGE(H84,H87)*H89*(1-H9) -> 0 | I90: =AVERAGE(I84,I87)*I89*(1-I9) -> 0 | J90: =AVERAGE(J84,J87)*J89*(1-J9) -> 0 | K90: =AVERAGE(K84,K87)*K89*(1-K9) -> 0 | L90: =AVERAGE(L84,L87)*L89*(1-L9) -> 0 | ... AI90: =AVERAGE(AI84,AI87)*AI89*(1-AI9) -> 0
B91: Interest Charge | C91: Rs Cr | E91: =AVERAGE(E84,E87)*E89/4*(E8/E5) -> 0 | F91: =AVERAGE(F84,F87)*F89/4*(F8/F5) -> 0 | G91: =AVERAGE(G84,G87)*G89/4*(G8/G5) -> 0 | H91: =AVERAGE(H84,H87)*H89/4*(H8/H5) -> 0 | I91: =AVERAGE(I84,I87)*I89/4*(I8/I5) -> 0 | J91: =AVERAGE(J84,J87)*J89/4*(J8/J5) -> 0 | K91: =AVERAGE(K84,K87)*K89/4*(K8/K5) -> 0 | L91: =AVERAGE(L84,L87)*L89/4*(L8/L5) -> 0 | ... AI91: =AVERAGE(AI84,AI87)*AI89/4*(AI8/AI5) -> 0

Sheet FS
B1: Particulars | C1: Units | D1: Inputs | E1: =YEAR(E2) -> 2026 | F1: =E1+1 -> 2027 | G1: =F1+1 -> 2028 | H1: =G1+1 -> 2029 | I1: =H1+1 -> 2030 | J1: =I1+1 -> 2031 | K1: =J1+1 -> 2032 | L1: =K1+1 -> 2033 | M1: =L1+1 -> 2034 | ... AE1: =AD1+1 -> 2052
D2: =Input!D238 -> 45747 | E2: =EOMONTH(D2,12) -> 46112 | F2: =EOMONTH(E2,12) -> 46477 | G2: =EOMONTH(F2,12) -> 46843 | H2: =EOMONTH(G2,12) -> 47208 | I2: =EOMONTH(H2,12) -> 47573 | J2: =EOMONTH(I2,12) -> 47938 | K2: =EOMONTH(J2,12) -> 48304 | L2: =EOMONTH(K2,12) -> 48669 | ... AE2: =EOMONTH(AD2,12) -> 55609
B3: Total Year Counter | D3: 0 | E3: =D3+1 -> 1 | F3: =E3+1 -> 2 | G3: =F3+1 -> 3 | H3: =G3+1 -> 4 | I3: =H3+1 -> 5 | J3: =I3+1 -> 6 | K3: =J3+1 -> 7 | L3: =K3+1 -> 8 | ... AE3: =AD3+1 -> 27
B4: Is Operational ? | C4: =SUM(E4:AE4) -> 26 | E4: =IF(AND(E2>=Input!$E$180,E2<=Input!$E$182),1,0) -> 0 | F4: =IF(AND(F2>=Input!$E$180,F2<=Input!$E$182),1,0) -> 1 | G4: =IF(AND(G2>=Input!$E$180,G2<=Input!$E$182),1,0) -> 1 | H4: =IF(AND(H2>=Input!$E$180,H2<=Input!$E$182),1,0) -> 1 | I4: =IF(AND(I2>=Input!$E$180,I2<=Input!$E$182),1,0) -> 1 | J4: =IF(AND(J2>=Input!$E$180,J2<=Input!$E$182),1,0) -> 1 | K4: =IF(AND(K2>=Input!$E$180,K2<=Input!$E$182),1,0) -> 1 | L4: =IF(AND(L2>=Input!$E$180,L2<=Input!$E$182),1,0) -> 1 | ... AE4: =IF(AND(AE2>=Input!$E$180,AE2<=Input!$E$182),1,0) -> 1
B5: Operational Year Number | E5: =SUM($E4:E$4) -> 0 | F5: =SUM($E4:F$4) -> 1 | G5: =SUM($E4:G$4) -> 2 | H5: =SUM($E4:H$4) -> 3 | I5: =SUM($E4:I$4) -> 4 | J5: =SUM($E4:J$4) -> 5 | K5: =SUM($E4:K$4) -> 6 | L5: =SUM($E4:L$4) -> 7 | ... AE5: =SUM($E4:AE$4) -> 26
B6: Days in year | E6: =E2-D2 -> 365 | F6: =F2-E2 -> 365 | G6: =G2-F2 -> 366 | H6: =H2-G2 -> 365 | I6: =I2-H2 -> 365 | J6: =J2-I2 -> 365 | K6: =K2-J2 -> 366 | L6: =L2-K2 -> 365 | ... AE6: =AE2-AD2 -> 366
B7: Days of Construction | E7: =E6-E8 -> 365 | F7: =F6-F8 -> 183 | G7: =G6-G8 -> 0 | H7: =H6-H8 -> 0 | I7: =I6-I8 -> 0 | J7: =J6-J8 -> 0 | K7: =K6-K8 -> 0 | L7: =L6-L8 -> 0
B8: Days in Operations | E8: =IF(E2=Input!$E$182,Input!$E$181-D2,IF(E2-Input!$E$178+1>=365,E2-D2,E2-Input!$E$178+1))*E4 -> 0 | F8: =IF(F2=Input!$E$182,Input!$E$181-E2,IF(F2-Input!$E$178+1>=365,F2-E2,F2-Input!$E$178+1))*F4 -> 182 | G8: =IF(G2=Input!$E$182,Input!$E$181-F2,IF(G2-Input!$E$178+1>=365,G2-F2,G2-Input!$E$178+1))*G4 -> 366 | H8: =IF(H2=Input!$E$182,Input!$E$181-G2,IF(H2-Input!$E$178+1>=365,H2-G2,H2-Input!$E$178+1))*H4 -> 365 | I8: =IF(I2=Input!$E$182,Input!$E$181-H2,IF(I2-Input!$E$178+1>=365,I2-H2,I2-Input!$E$178+1))*I4 -> 365 | J8: =IF(J2=Input!$E$182,Input!$E$181-I2,IF(J2-Input!$E$178+1>=365,J2-I2,J2-Input!$E$178+1))*J4 -> 365 | K8: =IF(K2=Input!$E$182,Input!$E$181-J2,IF(K2-Input!$E$178+1>=365,K2-J2,K2-Input!$E$178+1))*K4 -> 366 | L8: =IF(L2=Input!$E$182,Input!$E$181-K2,IF(L2-Input!$E$178+1>=365,L2-K2,L2-Input!$E$178+1))*L4 -> 365 | ... AE8: =IF(AE2=Input!$E$182,Input!$E$181-AD2,IF(AE2-Input!$E$178+1>=365,AE2-AD2,AE2-Input!$E$178+1))*AE4 -> 183
A9: Financial Statements & IRR
A10: P&L Account
B12: Revenue | C12: =Working!C317 -> Rs Cr | D12: =Working!D317 -> 0 | E12: =Working!E317 -> 0 | F12: =Working!F317 -> 89.815004 | G12: =Working!G317 -> 177.31173 | H12: =Working!H317 -> 175.09534 | I12: =Working!I317 -> 172.90665 | J12: =Working!J317 -> 170.74531 | ... AE12: =Working!AE317 -> 77.237216
B13: Expenditure | C13: =Working!C318 -> 0 | D13: =Working!D318 -> 0 | E13: =Working!E318 -> 0 | F13: =Working!F318 -> 0 | G13: =Working!G318 -> 0 | H13: =Working!H318 -> 0 | I13: =Working!I318 -> 0 | J13: =Working!J318 -> 0 | ... AE13: =Working!AE318 -> 0
B14: Generation O&M | C14: =Working!C319 -> Rs Cr | D14: =Working!D319 -> 0 | E14: =Working!E319 -> 0 | F14: =Working!F319 -> 5.5725713 | G14: =Working!G319 -> 11.762489 | H14: =Working!H319 -> 12.380019 | I14: =Working!I319 -> 13.02997 | J14: =Working!J319 -> 13.714044 | ... AE14: =Working!AE319 -> 20.081665
B15: Infrastructure O&M | C15: =Working!C320 -> Rs Cr | D15: =Working!D320 -> 0 | E15: =Working!E320 -> 0 | F15: =Working!F320 -> 1.1877748 | G15: =Working!G320 -> 2.4718801 | H15: =Working!H320 -> 2.56507 | I15: =Working!I320 -> 2.6617731 | J15: =Working!J320 -> 2.762122 | ... AE15: =Working!AE320 -> 2.9490701
B16: PBITDA | C16: =Working!C321 -> Rs Cr | D16: =Working!D321 -> 0 | E16: =Working!E321 -> 0 | F16: =Working!F321 -> 83.054657 | G16: =Working!G321 -> 163.07736 | H16: =Working!H321 -> 160.15025 | I16: =Working!I321 -> 157.2149 | J16: =Working!J321 -> 154.26915 | ... AE16: =Working!AE321 -> 54.20648
B17: Depreciation | C17: =Working!C322 -> Rs Cr | D17: =Working!D322 -> 0 | E17: =Working!E322 -> 0 | F17: =Working!F322 -> 28.934334 | G17: =Working!G322 -> 58.027647 | H17: =Working!H322 -> 58.027647 | I17: =Working!I322 -> 58.027647 | J17: =Working!J322 -> 58.027647 | ... AE17: =Working!AE322 -> 12.42562
B18: PBIT | C18: =Working!C323 -> Rs Cr | D18: =Working!D323 -> 0 | E18: =Working!E323 -> 0 | F18: =Working!F323 -> 54.120324 | G18: =Working!G323 -> 105.04972 | H18: =Working!H323 -> 102.1226 | I18: =Working!I323 -> 99.187255 | J18: =Working!J323 -> 96.241499 | ... AE18: =Working!AE323 -> 41.78086
B19: Interest on Loan | C19: =Working!C324 -> Rs Cr | D19: =Working!D324 -> 0 | E19: =Working!E324 -> 0 | F19: =Working!F324 -> 18.672217 | G19: =Working!G324 -> 48.708432 | H19: =Working!H324 -> 45.229258 | I19: =Working!I324 -> 41.750084 | J19: =Working!J324 -> 38.270911 | ... AE19: =Working!AE324 -> 0
B20: Interest on WC Loan | C20: =Working!C325 -> Rs Cr | D20: =Working!D325 -> 0 | E20: =Working!E325 -> 0 | F20: =Working!F325 -> 1.10437 | G20: =Working!G325 -> 2.1981088 | H20: =Working!H325 -> 2.1885165 | I20: =Working!I325 -> 2.1799461 | J20: =Working!J325 -> 2.1724307 | ... AE20: =Working!AE325 -> 1.2962073
B21: Profits Before Tax (PBT) | C21: =Working!C329 -> Rs Cr | D21: =Working!D329 -> 0 | E21: =Working!E329 -> 0 | F21: =Working!F329 -> 34.343737 | G21: =Working!G329 -> 54.143177 | H21: =Working!H329 -> 54.704826 | I21: =Working!I329 -> 55.257224 | J21: =Working!J329 -> 55.798158 | ... AE21: =Working!AE329 -> 40.484653
B22: Tax | C22: =Working!C330 -> Rs Cr | D22: =Working!D330 -> 0 | E22: =Working!E330 -> 0 | F22: =Working!F330 -> 5.8933852 | G22: =Working!G330 -> 9.2909692 | H22: =Working!H330 -> 9.3873482 | I22: =Working!I330 -> 9.4821397 | J22: =Working!J330 -> 9.5749639 | ... AE22: =Working!AE330 -> 11.64026
B23: Profits After Tax (PAT) | C23: =Working!C331 -> Rs Cr | D23: =Working!D331 -> 0 | E23: =Working!E331 -> 0 | F23: =Working!F331 -> 28.450351 | G23: =Working!G331 -> 44.852208 | H23: =Working!H331 -> 45.317478 | I23: =Working!I331 -> 45.775085 | J23: =Working!J331 -> 46.223194 | ... AE23: =Working!AE331 -> 28.844393
A25: Cash flow statement
B26: Revenue | C26: Rs Cr | D26: =Working!D334 -> 0 | E26: =Working!E334 -> 0 | F26: =Working!F334 -> 89.815004 | G26: =Working!G334 -> 177.31173 | H26: =Working!H334 -> 175.09534 | I26: =Working!I334 -> 172.90665 | J26: =Working!J334 -> 170.74531 | K26: =Working!K334 -> 168.611 | ... AE26: =Working!AE334 -> 77.237216
B27: Generation O&M | C27: Rs Cr | D27: =Working!D335 -> 0 | E27: =Working!E335 -> 0 | F27: =Working!F335 -> -5.5725713 | G27: =Working!G335 -> -11.762489 | H27: =Working!H335 -> -12.380019 | I27: =Working!I335 -> -13.02997 | J27: =Working!J335 -> -13.714044 | K27: =Working!K335 -> -14.434031 | ... AE27: =Working!AE335 -> -20.081665
B28: Infrastructure O&M | C28: Rs Cr | D28: =Working!D336 -> 0 | E28: =Working!E336 -> 0 | F28: =Working!F336 -> -1.1877748 | G28: =Working!G336 -> -2.4718801 | H28: =Working!H336 -> -2.56507 | I28: =Working!I336 -> -2.6617731 | J28: =Working!J336 -> -2.762122 | K28: =Working!K336 -> -2.866254 | ... AE28: =Working!AE336 -> -2.9490701
B29: Taxes | C29: Rs Cr | D29: =Working!D337 -> 0 | E29: =Working!E337 -> 0 | F29: =Working!F337 -> -5.8933852 | G29: =Working!G337 -> -9.2909692 | H29: =Working!H337 -> -9.3873482 | I29: =Working!I337 -> -9.4821397 | J29: =Working!J337 -> -9.5749639 | K29: =Working!K337 -> -9.6654251 | ... AE29: =Working!AE337 -> -11.64026
B30: Change in DSRA | C30: Rs Cr | D30: =Working!D338 -> 0 | E30: =Working!E338 -> 0 | F30: =Working!F338 -> 0 | G30: =Working!G338 -> 0 | H30: =Working!H338 -> 0 | I30: =Working!I338 -> 0 | J30: =Working!J338 -> 0 | K30: =Working!K338 -> 0 | ... AE30: =Working!AE338 -> 0
B31: Interest Income on DSRA | C31: Rs Cr | D31: =Working!D339 -> 0 | E31: =Working!E339 -> 0 | F31: =Working!F339 -> 0 | G31: =Working!G339 -> 0 | H31: =Working!H339 -> 0 | I31: =Working!I339 -> 0 | J31: =Working!J339 -> 0 | K31: =Working!K339 -> 0 | ... AE31: =Working!AE339 -> 0
B32: BG Cost on DSRA | C32: Rs Cr | D32: =Working!D340 -> 0 | E32: =Working!E340 -> 0 | F32: =Working!F340 -> 0 | G32: =Working!G340 -> 0 | H32: =Working!H340 -> 0 | I32: =Working!I340 -> 0 | J32: =Working!J340 -> 0 | K32: =Working!K340 -> 0 | ... AE32: =Working!AE340 -> 0
B33: Change in WC | C33: Rs Cr | D33: =Working!D341 -> 0 | E33: =Working!E341 -> 0 | F33: =Working!F341 -> -25.678932 | G33: =Working!G341 -> 0.19361294 | H33: =Working!H341 -> 0.11121479 | I33: =Working!I341 -> 0.099367162 | J33: =Working!J341 -> 0.087134766 | K33: =Working!K341 -> 0.074495048 | ... AE33: =Working!AE341 -> -3.206091
B34: Cash Flow from Operating Activities | C34: Rs Cr | D34: =Working!D342 -> 0 | E34: =Working!E342 -> 0 | F34: =Working!F342 -> 51.48234 | G34: =Working!G342 -> 153.98001 | H34: =Working!H342 -> 150.87411 | I34: =Working!I342 -> 147.83213 | J34: =Working!J342 -> 144.78132 | K34: =Working!K342 -> 141.71978 | ... AE34: =Working!AE342 -> 39.360129
B36: Capital Expenditure | C36: Rs Cr | D36: =Working!D344 -> 0 | E36: =Working!E344 -> -582.04858 | F36: =Working!F344 -> -660.51346 | G36: =Working!G344 -> 0 | H36: =Working!H344 -> 0 | I36: =Working!I344 -> 0 | J36: =Working!J344 -> 0 | K36: =Working!K344 -> 0 | ... AE36: =Working!AE344 -> 0
B37: Cash Flow from Investing Activities | C37: Rs Cr | D37: =Working!D345 -> 0 | E37: =Working!E345 -> -582.04858 | F37: =Working!F345 -> -660.51346 | G37: =Working!G345 -> 0 | H37: =Working!H345 -> 0 | I37: =Working!I345 -> 0 | J37: =Working!J345 -> 0 | K37: =Working!K345 -> 0 | ... AE37: =Working!AE345 -> 0
D38: =Working!D346 -> 0
B39: Commerical Loan - Additions | C39: Rs Cr | D39: =Working!D347 -> 0 | E39: =Working!E347 -> 407.434 | F39: =Working!F347 -> 462.35942 | G39: =Working!G347 -> 0 | H39: =Working!H347 -> 0 | I39: =Working!I347 -> 0 | J39: =Working!J347 -> 0 | K39: =Working!K347 -> 0 | ... AE39: =Working!AE347 -> 0
B40: Grant | C40: Rs Cr | D40: =Working!D349 -> 0 | E40: =Working!E349 -> 0 | F40: =Working!F349 -> 0 | G40: =Working!G349 -> 0 | H40: =Working!H349 -> 0 | I40: =Working!I349 -> 0 | J40: =Working!J349 -> 0 | K40: =Working!K349 -> 0 | ... AE40: =Working!AE349 -> 0
B41: Equity | C41: Rs Cr | D41: =Working!D350 -> 0 | E41: =Working!E350 -> 174.61457 | F41: =Working!F350 -> 198.15404 | G41: =Working!G350 -> 0 | H41: =Working!H350 -> 0 | I41: =Working!I350 -> 0 | J41: =Working!J350 -> 0 | K41: =Working!K350 -> 0 | ... AE41: =Working!AE350 -> 0
B42: Commerical Loan - Repayment | C42: Rs Cr | D42: =Working!D352 -> 0 | E42: =Working!E352 -> 0 | F42: =Working!F352 -> -28.993114 | G42: =Working!G352 -> -57.986228 | H42: =Working!H352 -> -57.986228 | I42: =Working!I352 -> -57.986228 | J42: =Working!J352 -> -57.986228 | K42: =Working!K352 -> -57.986228 | ... AE42: =Working!AE352 -> 0
B43: Change in WC Loan | C43: Rs Cr | D43: =Working!D355 -> 0 | E43: =Working!E355 -> 0 | F43: =Working!F355 -> 19.259199 | G43: =Working!G355 -> -0.1452097 | H43: =Working!H355 -> -0.083411095 | I43: =Working!I355 -> -0.074525372 | J43: =Working!J355 -> -0.065351075 | K43: =Working!K355 -> -0.055871286 | ... AE43: =Working!AE355 -> 2.4045683
B44: Interest on Debt | C44: Rs Cr | D44: =Working!D356 -> 0 | E44: =Working!E356 -> 0 | F44: =Working!F356 -> -18.672217 | G44: =Working!G356 -> -48.708432 | H44: =Working!H356 -> -45.229258 | I44: =Working!I356 -> -41.750084 | J44: =Working!J356 -> -38.270911 | K44: =Working!K356 -> -34.791737 | ... AE44: =Working!AE356 -> 0
B45: Interest on WC Loan | C45: Rs Cr | D45: =Working!D357 -> 0 | E45: =Working!E357 -> 0 | F45: =Working!F357 -> -1.10437 | G45: =Working!G357 -> -2.1981088 | H45: =Working!H357 -> -2.1885165 | I45: =Working!I357 -> -2.1799461 | J45: =Working!J357 -> -2.1724307 | K45: =Working!K357 -> -2.1660055 | ... AE45: =Working!AE357 -> -1.2962073
B46: Cash Flow from Financing Activities | C46: Rs Cr | D46: =Working!D359 -> 0 | E46: =Working!E359 -> 582.04858 | F46: =Working!F359 -> 631.00295 | G46: =Working!G359 -> -109.03798 | H46: =Working!H359 -> -105.48741 | I46: =Working!I359 -> -101.99078 | J46: =Working!J359 -> -98.494921 | K46: =Working!K359 -> -94.999842 | ... AE46: =Working!AE359 -> 1.108361
A48: Cash Schedule
B49: Opening cash balance | C49: Rs Cr | D49: =Working!D362 -> 0 | E49: =Working!E362 -> 0 | F49: =Working!F362 -> 0 | G49: =Working!G362 -> 21.971838 | H49: =Working!H362 -> 66.913868 | I49: =Working!I362 -> 112.30057 | J49: =Working!J362 -> 158.14191 | K49: =Working!K362 -> 204.42831 | ... AE49: =Working!AE362 -> 1507.4748
B50: Cash generated during the year | C50: Rs Cr | D50: =Working!D363 -> 0 | E50: =Working!E363 -> 0 | F50: =Working!F363 -> 21.971838 | G50: =Working!G363 -> 44.94203 | H50: =Working!H363 -> 45.3867 | I50: =Working!I363 -> 45.841345 | J50: =Working!J363 -> 46.286397 | K50: =Working!K363 -> 46.719939 | ... AE50: =Working!AE363 -> 40.46849
B51: Closing Cash Balance | C51: Rs Cr | D51: =Working!D364 -> 0 | E51: =Working!E364 -> 0 | F51: =Working!F364 -> 21.971838 | G51: =Working!G364 -> 66.913868 | H51: =Working!H364 -> 112.30057 | I51: =Working!I364 -> 158.14191 | J51: =Working!J364 -> 204.42831 | K51: =Working!K364 -> 251.14825 | ... AE51: =Working!AE364 -> 1547.9433
A53: Balance Sheet Statement
A54: Assets
B55: GFA | C55: Rs Cr | D55: =Working!D368 -> 0 | E55: =Working!E368 -> 0 | F55: =Working!F368 -> 1242.562 | G55: =Working!G368 -> 1242.562 | H55: =Working!H368 -> 1242.562 | I55: =Working!I368 -> 1242.562 | J55: =Working!J368 -> 1242.562 | K55: =Working!K368 -> 1242.562 | ... AE55: =Working!AE368 -> 1242.562
B56: Accumulated Depreciation | C56: Rs Cr | D56: =Working!D369 -> 0 | E56: =Working!E369 -> 0 | F56: =Working!F369 -> 28.934334 | G56: =Working!G369 -> 86.96198 | H56: =Working!H369 -> 144.98963 | I56: =Working!I369 -> 203.01727 | J56: =Working!J369 -> 261.04492 | K56: =Working!K369 -> 319.07257 | ... AE56: =Working!AE369 -> 1102.2594
B57: Net Fixed Assets | C57: Rs Cr | D57: =Working!D370 -> 0 | E57: =Working!E370 -> 0 | F57: =Working!F370 -> 1213.6277 | G57: =Working!G370 -> 1155.6001 | H57: =Working!H370 -> 1097.5724 | I57: =Working!I370 -> 1039.5448 | J57: =Working!J370 -> 981.51711 | K57: =Working!K370 -> 923.48946 | ... AE57: =Working!AE370 -> 140.30262
B58: CWIP | C58: Rs Cr | D58: =Working!D371 -> 0 | E58: =Working!E371 -> 582.04858 | F58: =Working!F371 -> 0 | G58: =Working!G371 -> 0 | H58: =Working!H371 -> 0 | I58: =Working!I371 -> 0 | J58: =Working!J371 -> 0 | K58: =Working!K371 -> 0 | ... AE58: =Working!AE371 -> 0
B60: Current Assets | C60: Rs Cr | D60: =Working!D373 -> 0 | E60: =Working!E373 -> 0 | F60: =Working!F373 -> 25.678932 | G60: =Working!G373 -> 25.485319 | H60: =Working!H373 -> 25.374105 | I60: =Working!I373 -> 25.274737 | J60: =Working!J373 -> 25.187603 | K60: =Working!K373 -> 25.113108 | ... AE60: =Working!AE373 -> 30.056981
B61: DSRA | C61: Rs Cr | D61: =Working!D374 -> 0 | E61: =Working!E374 -> 0 | F61: =Working!F374 -> 0 | G61: =Working!G374 -> 0 | H61: =Working!H374 -> 0 | I61: =Working!I374 -> 0 | J61: =Working!J374 -> 0 | K61: =Working!K374 -> 0 | ... AE61: =Working!AE374 -> 0
B62: Cash & Bank Balance | C62: Rs Cr | D62: =Working!D375 -> 0 | E62: =Working!E375 -> 0 | F62: =Working!F375 -> 21.971838 | G62: =Working!G375 -> 66.913868 | H62: =Working!H375 -> 112.30057 | I62: =Working!I375 -> 158.14191 | J62: =Working!J375 -> 204.42831 | K62: =Working!K375 -> 251.14825 | ... AE62: =Working!AE375 -> 1547.9433
B64: TOTAL ASSETS | C64: Rs Cr | D64: =Working!D377 -> 0 | E64: =Working!E377 -> 582.04858 | F64: =Working!F377 -> 1261.2785 | G64: =Working!G377 -> 1247.9992 | H64: =Working!H377 -> 1235.2471 | I64: =Working!I377 -> 1222.9614 | J64: =Working!J377 -> 1211.133 | K64: =Working!K377 -> 1199.7508 | ... AE64: =Working!AE377 -> 1718.3029
A66: Equity and Liabilities
B67: Equity | C67: Rs Cr | D67: =Working!D380 -> 0 | E67: =Working!E380 -> 174.61457 | F67: =Working!F380 -> 372.76861 | G67: =Working!G380 -> 372.76861 | H67: =Working!H380 -> 372.76861 | I67: =Working!I380 -> 372.76861 | J67: =Working!J380 -> 372.76861 | K67: =Working!K380 -> 372.76861 | ... AE67: =Working!AE380 -> 372.76861
B68: Reserve and Surplus | C68: Rs Cr | D68: =Working!D381 -> 0 | E68: =Working!E381 -> 0 | F68: =Working!F381 -> 28.450351 | G68: =Working!G381 -> 73.302559 | H68: =Working!H381 -> 118.62004 | I68: =Working!I381 -> 164.39512 | J68: =Working!J381 -> 210.61832 | K68: =Working!K381 -> 257.27821 | ... AE68: =Working!AE381 -> 1322.9915
B69: Grants | C69: Rs Cr | D69: =Working!D383 -> 0 | E69: =Working!E383 -> 0 | F69: =Working!F383 -> 0 | G69: =Working!G383 -> 0 | H69: =Working!H383 -> 0 | I69: =Working!I383 -> 0 | J69: =Working!J383 -> 0 | K69: =Working!K383 -> 0 | ... AE69: =Working!AE383 -> 0
B70: Commercial Loan | C70: Rs Cr | D70: =Working!D384 -> 0 | E70: =Working!E384 -> 407.434 | F70: =Working!F384 -> 840.80031 | G70: =Working!G384 -> 782.81408 | H70: =Working!H384 -> 724.82785 | I70: =Working!I384 -> 666.84162 | J70: =Working!J384 -> 608.8554 | K70: =Working!K384 -> 550.86917 | ... AE70: =Working!AE384 -> 0
B71: Working Capital Loan | C71: Rs Cr | D71: =Working!D387 -> 0 | E71: =Working!E387 -> 0 | F71: =Working!F387 -> 19.259199 | G71: =Working!G387 -> 19.11399 | H71: =Working!H387 -> 19.030578 | I71: =Working!I387 -> 18.956053 | J71: =Working!J387 -> 18.890702 | K71: =Working!K387 -> 18.834831 | ... AE71: =Working!AE387 -> 22.542735
B72: TOTAL LIABILITIES | C72: Rs Cr | D72: =Working!D390 -> 0 | E72: =Working!E390 -> 582.04858 | F72: =Working!F390 -> 1261.2785 | G72: =Working!G390 -> 1247.9992 | H72: =Working!H390 -> 1235.2471 | I72: =Working!I390 -> 1222.9614 | J72: =Working!J390 -> 1211.133 | K72: =Working!K390 -> 1199.7508 | ... AE72: =Working!AE390 -> 1718.3029

Sheet IDC Schedule
B1: Particulars | C1: Units | D1: From | E1: =C2+DAY(1) -> 45748 | F1: =E2+DAY(1) -> 45839 | G1: =F2+DAY(1) -> 45931 | H1: =G2+DAY(1) -> 46023 | I1: =H2+DAY(1) -> 46113 | J1: =I2+DAY(1) -> 46204 | K1: =J2+DAY(1) -> 46296 | L1: =K2+DAY(1) -> 46388
C2: =Input!D238 -> 45747 | D2: To | E2: =EOMONTH(C2,3) -> 45838 | F2: =EOMONTH(E2,3) -> 45930 | G2: =EOMONTH(F2,3) -> 46022 | H2: =EOMONTH(G2,3) -> 46112 | I2: =EOMONTH(H2,3) -> 46203 | J2: =EOMONTH(I2,3) -> 46295 | K2: =EOMONTH(J2,3) -> 46387 | L2: =EOMONTH(K2,3) -> 46477
B3: Is Operational ? | C3: =SUM(E3:L3) -> 2 | E3: =IF(AND((E2)>=Input!$E$178,E2<=Input!$E$182),1,0) -> 0 | F3: =IF(AND((F2)>=Input!$E$178,F2<=Input!$E$182),1,0) -> 0 | G3: =IF(AND((G2)>=Input!$E$178,G2<=Input!$E$182),1,0) -> 0 | H3: =IF(AND((H2)>=Input!$E$178,H2<=Input!$E$182),1,0) -> 0 | I3: =IF(AND((I2)>=Input!$E$178,I2<=Input!$E$182),1,0) -> 0 | J3: =IF(AND((J2)>=Input!$E$178,J2<=Input!$E$182),1,0) -> 0 | K3: =IF(AND((K2)>=Input!$E$178,K2<=Input!$E$182),1,0) -> 1 | L3: =IF(AND((L2)>=Input!$E$178,L2<=Input!$E$182),1,0) -> 1
B4: Operational Quarter Number | E4: =SUM($E3:E$3) -> 0 | F4: =SUM($E3:F$3) -> 0 | G4: =SUM($E3:G$3) -> 0 | H4: =SUM($E3:H$3) -> 0 | I4: =SUM($E3:I$3) -> 0 | J4: =SUM($E3:J$3) -> 0 | K4: =SUM($E3:K$3) -> 1 | L4: =SUM($E3:L$3) -> 2
B5: Days in Quarter | E5: =E2-C2 -> 91 | F5: =F2-E2 -> 92 | G5: =G2-F2 -> 92 | H5: =H2-G2 -> 90 | I5: =I2-H2 -> 91 | J5: =J2-I2 -> 92 | K5: =K2-J2 -> 92 | L5: =L2-K2 -> 90
B6: Year No. | D6: 0 | E6: =IF(MONTH(E1)=4,D6+1,D6) -> 1 | F6: =IF(MONTH(F1)=4,E6+1,E6) -> 1 | G6: =IF(MONTH(G1)=4,F6+1,F6) -> 1 | H6: =IF(MONTH(H1)=4,G6+1,G6) -> 1 | I6: =IF(MONTH(I1)=4,H6+1,H6) -> 2 | J6: =IF(MONTH(J1)=4,I6+1,I6) -> 2 | K6: =IF(MONTH(K1)=4,J6+1,J6) -> 2 | L6: =IF(MONTH(L1)=4,K6+1,K6) -> 2
B7: Days in Operations | E7: =IF(E2=Input!$E$182,Input!$E$181-C2,IF(E2-Input!$E$178+1>=(365/4),E2-C2,E2-Input!$E$178+1))*E3 -> 0 | F7: =IF(F2=Input!$E$182,Input!$E$181-E2,IF(F2-Input!$E$178+1>=(365/4),F2-E2,F2-Input!$E$178+1))*F3 -> 0 | G7: =IF(G2=Input!$E$182,Input!$E$181-F2,IF(G2-Input!$E$178+1>=(365/4),G2-F2,G2-Input!$E$178+1))*G3 -> 0 | H7: =IF(H2=Input!$E$182,Input!$E$181-G2,IF(H2-Input!$E$178+1>=(365/4),H2-G2,H2-Input!$E$178+1))*H3 -> 0 | I7: =IF(I2=Input!$E$182,Input!$E$181-H2,IF(I2-Input!$E$178+1>=(365/4),I2-H2,I2-Input!$E$178+1))*I3 -> 0 | J7: =IF(J2=Input!$E$182,Input!$E$181-I2,IF(J2-Input!$E$178+1>=(365/4),J2-I2,J2-Input!$E$178+1))*J3 -> 0 | K7: =IF(K2=Input!$E$182,Input!$E$181-J2,IF(K2-Input!$E$178+1>=(365/4),K2-J2,K2-Input!$E$178+1))*K3 -> 92 | L7: =IF(L2=Input!$E$182,Input!$E$181-K2,IF(L2-Input!$E$178+1>=(365/4),L2-K2,L2-Input!$E$178+1))*L3 -> 90
B8: Days in Construction | E8: =E5-E7 -> 91 | F8: =F5-F7 -> 92 | G8: =G5-G7 -> 92 | H8: =H5-H7 -> 90 | I8: =I5-I7 -> 91 | J8: =J5-J7 -> 92 | K8: =K5-K7 -> 0 | L8: =L5-L7 -> 0
B9: Proportion of year in operation | E9: =IF(E5,E7/E5,0) -> 0 | F9: =IF(F5,F7/F5,0) -> 0 | G9: =IF(G5,G7/G5,0) -> 0 | H9: =IF(H5,H7/H5,0) -> 0 | I9: =IF(I5,I7/I5,0) -> 0 | J9: =IF(J5,J7/J5,0) -> 0 | K9: =IF(K5,K7/K5,0) -> 1 | L9: =IF(L5,L7/L5,0) -> 1
B10: Cumulative number of year in operation | E10: =D10+E9 -> 0 | F10: =E10+F9 -> 0 | G10: =F10+G9 -> 0 | H10: =G10+H9 -> 0 | I10: =H10+I9 -> 0 | J10: =I10+J9 -> 0 | K10: =J10+K9 -> 1 | L10: =K10+L9 -> 2
B12: Project Phasing as per Erection Schedule
B13: Solar Generation and Transmission
A14: A | B14: Material Phasing Schedule
B15: Module | C15: % | E15: =Input!E273 -> 0 | F15: =Input!F273 -> 0 | G15: =Input!H273 -> 0 | H15: =Input!I273 -> 0.5 | I15: =Input!J273 -> 0.5 | J15: =Input!K273 -> 0
B16: Floating System | C16: % | E16: =Input!E274 -> 0 | F16: =Input!F274 -> 0.1 | G16: =Input!H274 -> 0.2 | H16: =Input!I274 -> 0.2 | I16: =Input!J274 -> 0.3 | J16: =Input!K274 -> 0.2
B17: Anchoring Mooring System | C17: % | E17: =Input!E275 -> 0 | F17: =Input!F275 -> 0.2 | G17: =Input!H275 -> 0.6 | H17: =Input!I275 -> 0.2 | I17: =Input!J275 -> 0 | J17: =Input!K275 -> 0
B18: UV/DC/AC/HT Cables | C18: % | E18: =Input!E276 -> 0 | F18: =Input!F276 -> 0 | G18: =Input!H276 -> 0.3 | H18: =Input!I276 -> 0.3 | I18: =Input!J276 -> 0.3 | J18: =Input!K276 -> 0.1
B19: Inverter & Inverter Duty Transformer | C19: % | E19: =Input!E277 -> 0 | F19: =Input!F277 -> 0 | G19: =Input!H277 -> 0 | H19: =Input!I277 -> 0.5 | I19: =Input!J277 -> 0.5 | J19: =Input!K277 -> 0
B20: HT Panels & MCR Equipments | C20: % | E20: =Input!E278 -> 0 | F20: =Input!F278 -> 0 | G20: =Input!H278 -> 0 | H20: =Input!I278 -> 0.5 | I20: =Input!J278 -> 0.5 | J20: =Input!K278 -> 0
B21: 220 KV PSS Equipments & Structures | C21: % | E21: =Input!E279 -> 0 | F21: =Input!F279 -> 0 | G21: =Input!H279 -> 0 | H21: =Input!I279 -> 0.5 | I21: =Input!J279 -> 0.5 | J21: =Input!K279 -> 0
B22: Transmission Line | C22: % | E22: =Input!E280 -> 0 | F22: =Input!F280 -> 0 | G22: =Input!H280 -> 0 | H22: =Input!I280 -> 0.5 | I22: =Input!J280 -> 0.5 | J22: =Input!K280 -> 0
B23: 220 KV Bay Activities | C23: % | E23: =Input!E281 -> 0 | F23: =Input!F281 -> 0 | G23: =Input!H281 -> 0 | H23: =Input!I281 -> 0.5 | I23: =Input!J281 -> 0.5 | J23: =Input!K281 -> 0
A25: B | B25: Erection & Commissioning Schedule
B26: Module | C26: % | E26: =Input!E284 -> 0 | F26: =Input!F284 -> 0 | G26: =Input!H284 -> 0 | H26: =Input!I284 -> 0 | I26: =Input!J284 -> 0 | J26: =Input!K284 -> 0
B27: Floating System | C27: % | E27: =Input!E285 -> 0 | F27: =Input!F285 -> 0 | G27: =Input!H285 -> 0 | H27: =Input!I285 -> 0.2 | I27: =Input!J285 -> 0.4 | J27: =Input!K285 -> 0.4
B28: Anchoring Mooring System | C28: % | E28: =Input!E286 -> 0 | F28: =Input!F286 -> 0 | G28: =Input!H286 -> 0 | H28: =Input!I286 -> 0.2 | I28: =Input!J286 -> 0.4 | J28: =Input!K286 -> 0.4
B29: UV/DC/AC/HT Cables | C29: % | E29: =Input!E287 -> 0 | F29: =Input!F287 -> 0 | G29: =Input!H287 -> 0.2 | H29: =Input!I287 -> 0.4 | I29: =Input!J287 -> 0.4 | J29: =Input!K287 -> 0
B30: Inverter & Inverter Duty Transformer | C30: % | E30: =Input!E288 -> 0 | F30: =Input!F288 -> 0 | G30: =Input!H288 -> 0 | H30: =Input!I288 -> 0.4 | I30: =Input!J288 -> 0.4 | J30: =Input!K288 -> 0.2
B31: HT Panels & MCR Equipments | C31: % | E31: =Input!E289 -> 0 | F31: =Input!F289 -> 0 | G31: =Input!H289 -> 0 | H31: =Input!I289 -> 0 | I31: =Input!J289 -> 0.5 | J31: =Input!K289 -> 0.5
B32: 220 KV PSS Equipments & Structures | C32: % | E32: =Input!E290 -> 0 | F32: =Input!F290 -> 0 | G32: =Input!H290 -> 0 | H32: =Input!I290 -> 0 | I32: =Input!J290 -> 0.5 | J32: =Input!K290 -> 0.5
B33: Transmission Line | C33: % | E33: =Input!E291 -> 0 | F33: =Input!F291 -> 0 | G33: =Input!H291 -> 0 | H33: =Input!I291 -> 0 | I33: =Input!J291 -> 0.5 | J33: =Input!K291 -> 0.5
B34: 220 KV Bay Activities | C34: % | E34: =Input!E292 -> 0 | F34: =Input!F292 -> 0 | G34: =Input!H292 -> 0 | H34: =Input!I292 -> 0 | I34: =Input!J292 -> 0.5 | J34: =Input!K292 -> 0.5
B36: Infrastructure Cost Phasing
A37: C | B37: Civil and Other Construction Cost Schedule | C37: % | E37: =Input!E267 -> 0 | F37: =Input!F267 -> 0 | G37: =Input!H267 -> 0.15 | H37: =Input!I267 -> 0.15 | I37: =Input!J267 -> 0.35 | J37: =Input!K267 -> 0.35
B40: Project Phasing as per Erection Schedule
B41: Solar Generation and Transmission
A42: A | B42: Material Phasing Cost
B43: Module | C43: Rs Crore | D43: =SUM(E43:J43) -> 329.1921 | E43: =Input!E298/100 -> 0 | F43: =Input!F298/100 -> 0 | G43: =Input!H298/100 -> 0 | H43: =Input!I298/100 -> 164.59605 | I43: =Input!J298/100 -> 164.59605 | J43: =Input!K298/100 -> 0
B44: Floating System | C44: Rs Crore | D44: =SUM(E44:J44) -> 140.00043 | E44: =Input!E299/100 -> 0 | F44: =Input!F299/100 -> 14.000043 | G44: =Input!H299/100 -> 28.000085 | H44: =Input!I299/100 -> 28.000085 | I44: =Input!J299/100 -> 42.000128 | J44: =Input!K299/100 -> 28.000085
B45: Anchoring Mooring System | C45: Rs Crore | D45: =SUM(E45:J45) -> 88.85679 | E45: =Input!E300/100 -> 0 | F45: =Input!F300/100 -> 17.771358 | G45: =Input!H300/100 -> 53.314074 | H45: =Input!I300/100 -> 17.771358 | I45: =Input!J300/100 -> 0 | J45: =Input!K300/100 -> 0
B46: UV/DC/AC/HT Cables | C46: Rs Crore | D46: =SUM(E46:J46) -> 36.522621 | E46: =Input!E301/100 -> 0 | F46: =Input!F301/100 -> 0 | G46: =Input!H301/100 -> 10.956786 | H46: =Input!I301/100 -> 10.956786 | I46: =Input!J301/100 -> 10.956786 | J46: =Input!K301/100 -> 3.6522621
B47: Inverter & Inverter Duty Transformer | C47: Rs Crore | D47: =SUM(E47:J47) -> 106.92095 | E47: =Input!E302/100 -> 0 | F47: =Input!F302/100 -> 0 | G47: =Input!H302/100 -> 0 | H47: =Input!I302/100 -> 53.460475 | I47: =Input!J302/100 -> 53.460475 | J47: =Input!K302/100 -> 0
B48: HT Panels & MCR Equipments | C48: Rs Crore | D48: =SUM(E48:J48) -> 12.532838 | E48: =Input!E303/100 -> 0 | F48: =Input!F303/100 -> 0 | G48: =Input!H303/100 -> 0 | H48: =Input!I303/100 -> 6.2664189 | I48: =Input!J303/100 -> 6.2664189 | J48: =Input!K303/100 -> 0
B49: 220 KV PSS Equipments & Structures | C49: Rs Crore | D49: =SUM(E49:J49) -> 65.39673 | E49: =Input!E304/100 -> 0 | F49: =Input!F304/100 -> 0 | G49: =Input!H304/100 -> 0 | H49: =Input!I304/100 -> 32.698365 | I49: =Input!J304/100 -> 32.698365 | J49: =Input!K304/100 -> 0
B50: Transmission Line | C50: Rs Crore | D50: =SUM(E50:J50) -> 9.6121668 | E50: =Input!E305/100 -> 0 | F50: =Input!F305/100 -> 0 | G50: =Input!H305/100 -> 0 | H50: =Input!I305/100 -> 4.8060834 | I50: =Input!J305/100 -> 4.8060834 | J50: =Input!K305/100 -> 0
B51: 220 KV Bay Activities | C51: Rs Crore | D51: =SUM(E51:J51) -> 3.5875737 | E51: =Input!E306/100 -> 0 | F51: =Input!F306/100 -> 0 | G51: =Input!H306/100 -> 0 | H51: =Input!I306/100 -> 1.7937869 | I51: =Input!J306/100 -> 1.7937869 | J51: =Input!K306/100 -> 0
B52: sub total | C52: Rs Crore | D52: =SUM(E52:J52) -> 792.6222 | E52: =SUM(E43:E51) -> 0 | F52: =SUM(F43:F51) -> 31.771401 | G52: =SUM(G43:G51) -> 92.270945 | H52: =SUM(H43:H51) -> 320.34941 | I52: =SUM(I43:I51) -> 316.5781 | J52: =SUM(J43:J51) -> 31.652347
A54: B | B54: Erection & Commissioning Cost
B55: Module | C55: Rs Crore | D55: =SUM(E55:J55) -> 46.474179 | E55: =Input!E310/100 -> 0 | F55: =Input!F310/100 -> 0 | G55: =Input!H310/100 -> 0 | H55: =Input!I310/100 -> 9.2948359 | I55: =Input!J310/100 -> 18.589672 | J55: =Input!K310/100 -> 18.589672
B56: Floating System | C56: Rs Crore | D56: =SUM(E56:J56) -> 19.764766 | E56: =Input!E311/100 -> 0 | F56: =Input!F311/100 -> 0 | G56: =Input!H311/100 -> 0 | H56: =Input!I311/100 -> 3.9529532 | I56: =Input!J311/100 -> 7.9059064 | J56: =Input!K311/100 -> 7.9059064
B57: Anchoring Mooring System | C57: Rs Crore | D57: =SUM(E57:J57) -> 12.544488 | E57: =Input!E312/100 -> 0 | F57: =Input!F312/100 -> 0 | G57: =Input!H312/100 -> 2.5088976 | H57: =Input!I312/100 -> 5.0177952 | I57: =Input!J312/100 -> 5.0177952 | J57: =Input!K312/100 -> 0
B58: UV/DC/AC/HT Cables | C58: Rs Crore | D58: =SUM(E58:J58) -> 5.1561347 | E58: =Input!E313/100 -> 0 | F58: =Input!F313/100 -> 0 | G58: =Input!H313/100 -> 0 | H58: =Input!I313/100 -> 2.0624539 | I58: =Input!J313/100 -> 2.0624539 | J58: =Input!K313/100 -> 1.0312269
B59: Inverter & Inverter Duty Transformer | C59: Rs Crore | D59: =SUM(E59:J59) -> 15.094722 | E59: =Input!E314/100 -> 0 | F59: =Input!F314/100 -> 0 | G59: =Input!H314/100 -> 0 | H59: =Input!I314/100 -> 0 | I59: =Input!J314/100 -> 7.5473612 | J59: =Input!K314/100 -> 7.5473612
B60: HT Panels & MCR Equipments | C60: Rs Crore | D60: =SUM(E60:J60) -> 1.7693418 | E60: =Input!E315/100 -> 0 | F60: =Input!F315/100 -> 0 | G60: =Input!H315/100 -> 0 | H60: =Input!I315/100 -> 0 | I60: =Input!J315/100 -> 0.88467091 | J60: =Input!K315/100 -> 0.88467091
B61: 220 KV PSS Equipments & Structures | C61: Rs Crore | D61: =SUM(E61:J61) -> 9.2324796 | E61: =Input!E316/100 -> 0 | F61: =Input!F316/100 -> 0 | G61: =Input!H316/100 -> 0 | H61: =Input!I316/100 -> 0 | I61: =Input!J316/100 -> 4.6162398 | J61: =Input!K316/100 -> 4.6162398
B62: Transmission Line | C62: Rs Crore | D62: =SUM(E62:J62) -> 1.3570118 | E62: =Input!E317/100 -> 0 | F62: =Input!F317/100 -> 0 | G62: =Input!H317/100 -> 0 | H62: =Input!I317/100 -> 0 | I62: =Input!J317/100 -> 0.67850589 | J62: =Input!K317/100 -> 0.67850589
B63: 220 KV Bay Activities | C63: Rs Crore | D63: =SUM(E63:J63) -> 0.506481 | E63: =Input!E318/100 -> 0 | F63: =Input!F318/100 -> 0 | G63: =Input!H318/100 -> 0 | H63: =Input!I318/100 -> 0 | I63: =Input!J318/100 -> 0.2532405 | J63: =Input!K318/100 -> 0.2532405
B64: sub total | C64: Rs Crore | D64: =SUM(E64:J64) -> 111.8996 | E64: =SUM(E55:E63) -> 0 | F64: =SUM(F55:F63) -> 0 | G64: =SUM(G55:G63) -> 2.5088976 | H64: =SUM(H55:H63) -> 20.328038 | I64: =SUM(I55:I63) -> 47.555845 | J64: =SUM(J55:J63) -> 41.506823
A66: A+B | B66: Total | C66: Rs Crore | D66: =SUM(E66:J66) -> 904.5218 | E66: =E64+E52 -> 0 | F66: =F64+F52 -> 31.771401 | G66: =G64+G52 -> 94.779843 | H66: =H64+H52 -> 340.67745 | I66: =I64+I52 -> 364.13394 | J66: =J64+J52 -> 73.159171
A68: C | B68: Infrastructure Cost Phasing
B69: Civil and Other Construction Cost Schedule | C69: Rs Crore | D69: =SUM(E69:J69) -> 32.386843 | E69: =Input!E267*Input!$D$267/100 -> 0 | F69: =Input!F267*Input!$D$267/100 -> 0 | G69: =Input!H267*Input!$D$267/100 -> 4.8580265 | H69: =Input!I267*Input!$D$267/100 -> 4.8580265 | I69: =Input!J267*Input!$D$267/100 -> 11.335395 | J69: =Input!K267*Input!$D$267/100 -> 11.335395
B71: Total Solar Generation and Transmission Cost | C71: Rs Crore | D71: =SUM(E71:J71) -> 936.90865 | E71: =E66+E69 -> 0 | F71: =F66+F69 -> 31.771401 | G71: =G66+G69 -> 99.637869 | H71: =H66+H69 -> 345.53548 | I71: =I66+I69 -> 375.46934 | J71: =J66+J69 -> 84.494566
B73: Summary of Phasing as per Erection Schedule
B74: Solar Generation and Transmission Phasing | C74: % | E74: =E66/(SUM($E$66:$J$66)) -> 0 | F74: =F66/(SUM($E$66:$J$66)) -> 0.03512508 | G74: =G66/(SUM($E$66:$J$66)) -> 0.10478448 | H74: =H66/(SUM($E$66:$J$66)) -> 0.37663818 | I74: =I66/(SUM($E$66:$J$66)) -> 0.40257066 | J74: =J66/(SUM($E$66:$J$66)) -> 0.0808816 | L74: as a % of Total Generation & Transmission Cost
B75: Infrastructure Cost | C75: % | E75: =E69/SUM($E$69:$J$69) -> 0 | F75: =F69/SUM($E$69:$J$69) -> 0 | G75: =G69/SUM($E$69:$J$69) -> 0.15 | H75: =H69/SUM($E$69:$J$69) -> 0.15 | I75: =I69/SUM($E$69:$J$69) -> 0.35 | J75: =J69/SUM($E$69:$J$69) -> 0.35 | L75: as % of Total Infrastructure Cost
B76: Other Cost Phasing | C76: % | E76: =Input!E268 -> 0 | F76: =Input!F268 -> 0 | G76: =Input!H268 -> 0.05 | H76: =Input!I268 -> 0.05 | I76: =Input!J268 -> 0.45 | J76: =Input!K268 -> 0.45
B78: Phasing of All cost inclusive of Tacx
A79: =IDC_Q!A48 -> 1 | B79: =IDC_Q!B48 -> Capital Expenditure - Generation & Transmission | C79: =IDC_Q!C48 -> Rs Cr | E79: =IDC_Q!E48 -> 0 | F79: =IDC_Q!F48 -> 38.075281 | G79: =IDC_Q!G48 -> 113.58546 | H79: =IDC_Q!H48 -> 408.27252 | I79: =IDC_Q!I48 -> 436.3831 | J79: =IDC_Q!J48 -> 87.674951 | K79: =IDC_Q!K48 -> 0 | L79: =IDC_Q!L48 -> 0
A80: =IDC_Q!A49 -> 2 | B80: =IDC_Q!B49 -> Capital Expenditure - Infrastructure | C80: =IDC_Q!C49 -> 0 | E80: =IDC_Q!E49 -> 0 | F80: =IDC_Q!F49 -> 0 | G80: =IDC_Q!G49 -> 2.7887235 | H80: =IDC_Q!H49 -> 2.7887235 | I80: =IDC_Q!I49 -> 6.5070215 | J80: =IDC_Q!J49 -> 6.5070215 | K80: =IDC_Q!K49 -> 0 | L80: =IDC_Q!L49 -> 0
A81: =IDC_Q!A50 -> 3 | B81: =IDC_Q!B50 -> Capital Expenditure - Other Costs | C81: =IDC_Q!C50 -> Rs Cr | E81: =IDC_Q!E50 -> 0 | F81: =IDC_Q!F50 -> 0 | G81: =IDC_Q!G50 -> 5.6928022 | H81: =IDC_Q!H50 -> 5.6928022 | I81: =IDC_Q!I50 -> 51.23522 | J81: =IDC_Q!J50 -> 51.23522 | K81: =IDC_Q!K50 -> 0 | L81: =IDC_Q!L50 -> 0
B82: =IDC_Q!B51 -> Phasing - Capex | C82: =IDC_Q!C51 -> Rs Cr | E82: =IDC_Q!E51 -> 0 | F82: =IDC_Q!F51 -> 38.075281 | G82: =IDC_Q!G51 -> 122.06699 | H82: =IDC_Q!H51 -> 416.75404 | I82: =IDC_Q!I51 -> 494.12534 | J82: =IDC_Q!J51 -> 145.41719 | K82: =IDC_Q!K51 -> 0 | L82: =IDC_Q!L51 -> 0
