Workbook
Name _cp_table_9_566: Charges_Schedule!$A$3
Name Building_rate: '[1]A (1)'!$D$58
Name Building_rate_C: '[1]A (C)'!$D$58
Name Building_rate2: '[1]A (2)'!$D$58
Name Building_rate3: '[1]A (3)'!$D$58
Name Building_rate4: '[1]A (4)'!$D$58
Name Building_rate5: '[1]A (5)'!$D$58
Name contract_per_year2: '[1]A (2)'!$D$107
Name contract_per_year3: '[1]A (3)'!$D$107
Name contract_per_year4: '[1]A (4)'!$D$107
Name contract_per_year5: '[1]A (5)'!$D$107
Name contract_price: '[1]A (1)'!$D$108
Name contract_price_C: '[1]A (C)'!$D$108
Name contract_price2: '[1]A (2)'!$D$108
Name contract_price3: '[1]A (3)'!$D$108
Name contract_price4: '[1]A (4)'!$D$108
Name contract_price5: '[1]A (5)'!$D$108
Name contracts_per_year: '[1]A (1)'!$D$107
Name contracts_per_year_C: '[1]A (C)'!$D$107
Name converions_ratio5: '[1]A (5)'!$D$14
Name conversion_ratio: '[1]A (1)'!$D$14
Name conversion_ratio_C: '[1]A (C)'!$D$14
Name conversion_ratio2: '[1]A (2)'!$D$14
Name conversion_ratio3: '[1]A (3)'!$D$14
Name conversion_ratio4: '[1]A (4)'!$D$14
Name Cost_of_debt: '[1]A (1)'!$D$120
Name Cost_of_debt_C: '[1]A (C)'!$D$120
Name Cost_of_debt2: '[1]A (2)'!$D$120
Name Cost_of_debt3: '[1]A (3)'!$D$120
Name Cost_of_debt4: '[1]A (4)'!$D$120
Name Cost_of_debt5: '[1]A (5)'!$D$120
Name CPI: '[1]A (1)'!$D$83
Name CPI_2: '[1]A (2)'!$D$83
Name CPI_3: '[1]A (3)'!$D$83
Name CPI_4: '[1]A (4)'!$D$83
Name CPI_5: '[1]A (5)'!$D$83
Name CPI_C: '[1]A (C)'!$D$83
Name Creditor_days: '[1]A (1)'!$D$136
Name Creditor_days_C: '[1]A (C)'!$D$136
Name Creditor_days2: '[1]A (2)'!$D$136
Name Creditor_days3: '[1]A (3)'!$D$136
Name Creditor_days4: '[1]A (4)'!$D$136
Name Creditor_days5: '[1]A (5)'!$D$136
Name Debt_ratio: '[1]A (1)'!$D$117
Name Debt_ratio_C: '[1]A (C)'!$D$117
Name Debt_ratio2: '[1]A (2)'!$D$117
Name Debt_ratio3: '[1]A (3)'!$D$117
Name Debt_ratio4: '[1]A (4)'!$D$117
Name Debt_ratio5: '[1]A (5)'!$D$117
Name Debtor_days: '[1]A (1)'!$D$135
Name Debtor_days_C: '[1]A (C)'!$D$135
Name Debtor_days2: '[1]A (2)'!$D$135
Name Debtor_days3: '[1]A (3)'!$D$135
Name Debtor_days4: '[1]A (4)'!$D$135
Name Debtor_days5: '[1]A (5)'!$D$135
Name Electricity_tariff_eff: '[1]A (1)'!$D$95
Name Electricity_tariff_eff_C: '[1]A (C)'!$D$95
Name Electricity_tariff_eff2: '[1]A (2)'!$D$95
Name Electricity_tariff_eff3: '[1]A (3)'!$D$95
Name Electricity_tariff_eff4: '[1]A (4)'!$D$95

Sheet Compare
B1: Copy Paste | E1: Original-> | N1: Revised -> | O1: Developer | Y1: Revised -> | Z1: Loan
B2: =Inputs!H2 -> 3 | C2: =IF(Inputs!E66,"Developer","Loan") -> Developer | E2: Phase 1 | F2: 1 | H2: Phase 2 | I2: 2 | K2: Combined | L2: 3 | N2: Phase 1 | O2: 1 | Q2: Phase 2 | R2: 2 | T2: Combined | U2: 3 | W2: Check | Y2: Phase 1 | Z2: 1 | AB2: Phase 2 | AC2: 2 | AE2: Combined | AF2: 3 | AH2: Check
A3: Park Infrastructure Cost Breakup | E3: Rs Crore | F3: Rs Lakh per MW | H3: Rs Crore | I3: Rs Lakh per MW | K3: Rs Crore | L3: Rs Lakh per MW | N3: Rs Crore | O3: Rs Lakh per MW | Q3: Rs Crore | R3: Rs Lakh per MW | T3: Rs Crore | U3: Rs Lakh per MW | Y3: Rs Crore | Z3: Rs Lakh per MW | AB3: Rs Crore | AC3: Rs Lakh per MW | AE3: Rs Crore | AF3: Rs Lakh per MW
A4: Capital Expenditure
A5: Land | B5: =Dashboard!G5 -> 1.705258 | C5: =Dashboard!H5 -> 0.284 | E5: 0.817012 | F5: 0.272 | H5: 0.888246 | I5: 0.296 | K5: 1.705258 | L5: 0.284 | N5: 0.817012 | O5: 0.272 | Q5: 0.888246 | R5: 0.296 | T5: 1.705258 | U5: 0.284 | W5: =T5-Q5-N5 -> 0 | Y5: 0.817012 | Z5: 0.272 | AB5: 0.888246 | AC5: 0.296 | AE5: 1.705258 | AF5: 0.284 | AH5: =AE5-AB5-Y5 -> 0
A6: Road, Building & other civil | B6: =Dashboard!G6 -> 25.425 | C6: =Dashboard!H6 -> 4.238 | E6: 15.35 | F6: 5.117 | H6: 10.075 | I6: 3.358 | K6: 25.425 | L6: 4.238 | N6: 15.35 | O6: 5.117 | Q6: 10.075 | R6: 3.358 | T6: 25.425 | U6: 4.238 | W6: =T6-Q6-N6 -> 0 | Y6: 15.35 | Z6: 5.117 | AB6: 10.075 | AC6: 3.358 | AE6: 25.425 | AF6: 4.238 | AH6: =AE6-AB6-Y6 -> 0
A7: Evacuation - Sub-station | B7: =Dashboard!G7 -> 116.8 | C7: =Dashboard!H7 -> 19.467 | E7: 58.4 | F7: 19.467 | H7: 58.4 | I7: 19.467 | K7: 116.8 | L7: 19.467 | N7: 58.4 | O7: 19.467 | Q7: 58.4 | R7: 19.467 | T7: 116.8 | U7: 19.467 | W7: =T7-Q7-N7 -> 0 | Y7: 58.4 | Z7: 19.467 | AB7: 58.4 | AC7: 19.467 | AE7: 116.8 | AF7: 19.467 | AH7: =AE7-AB7-Y7 -> 0
A8: Evacuation - Transmission Line | B8: =Dashboard!G8 -> 104.31453 | C8: =Dashboard!H8 -> 17.386 | E8: 56.432711 | F8: 18.811 | H8: 47.881823 | I8: 15.961 | K8: 104.31453 | L8: 17.386 | N8: 56.432711 | O8: 18.811 | Q8: 47.881823 | R8: 15.961 | T8: 104.31453 | U8: 17.386 | W8: =T8-Q8-N8 -> 0 | Y8: 56.432711 | Z8: 18.811 | AB8: 47.881823 | AC8: 15.961 | AE8: 104.31453 | AF8: 17.386 | AH8: =AE8-AB8-Y8 -> 0
A9: Other Costs | B9: =Dashboard!G9 -> 63.066421 | C9: =Dashboard!H9 -> 10.511 | E9: 52.827545 | F9: 17.609 | H9: 51.624355 | I9: 17.208 | K9: 104.4519 | L9: 17.409 | N9: 31.50242 | O9: 10.501 | Q9: 31.565162 | R9: 10.522 | T9: 63.067582 | U9: 10.511 | W9: =T9-Q9-N9 -> -1.1209828e-08 | Y9: 31.50242 | Z9: 10.501 | AB9: 31.565162 | AC9: 10.522 | AE9: 63.067582 | AF9: 10.511 | AH9: =AE9-AB9-Y9 -> -1.1209828e-08
A10: Base Cost Total | B10: =Dashboard!G10 -> 311.31121 | C10: =Dashboard!H10 -> 51.89 | E10: 183.82727 | F10: 61.28 | H10: 168.86942 | I10: 56.29 | K10: 352.69669 | L10: 58.78 | N10: 162.50214 | O10: 54.17 | Q10: 148.81023 | R10: 49.6 | T10: 311.31237 | U10: 51.89 | W10: =T10-Q10-N10 -> -1.1209835e-08 | Y10: 162.50214 | Z10: 54.17 | AB10: 148.81023 | AC10: 49.6 | AE10: 311.31237 | AF10: 51.89 | AH10: =AE10-AB10-Y10 -> -1.1209835e-08
A11: Contingency & Insurance Charges | B11: =Dashboard!G11 -> 9.1237087 | C11: =Dashboard!H11 -> 1.521 | E11: 4.9307893 | F11: 1.644 | H11: 4.5395223 | I11: 1.513 | K11: 9.4703025 | L11: 1.578 | N11: 4.7574854 | O11: 1.586 | Q11: 4.3662671 | R11: 1.455 | T11: 9.1237435 | U11: 1.521 | W11: =T11-Q11-N11 -> -9.0403363e-06 | Y11: 4.7574854 | Z11: 1.586 | AB11: 4.3662671 | AC11: 1.455 | AE11: 9.1237435 | AF11: 1.521 | AH11: =AE11-AB11-Y11 -> -9.0403363e-06
A12: Capital Expenditure | B12: =Dashboard!G12 -> 320.43492 | C12: =Dashboard!H12 -> 53.411 | E12: 188.75806 | F12: 62.924 | H12: 173.40895 | I12: 57.803 | K12: 362.16699 | L12: 60.358 | N12: 167.25963 | O12: 55.756 | Q12: 153.1765 | R12: 51.055 | T12: 320.43612 | U12: 53.411 | W12: =T12-Q12-N12 -> -9.0515461e-06 | Y12: 167.25963 | Z12: 55.756 | AB12: 153.1765 | AC12: 51.055 | AE12: 320.43612 | AF12: 53.411 | AH12: =AE12-AB12-Y12 -> -9.0515461e-06
A13: IDC | B13: =Dashboard!G13 -> 9.2617535 | C13: =Dashboard!H13 -> 0.154 | E13: 5.596097 | F13: 0.187 | H13: 5.1413022 | I13: 0.171 | K13: 10.737399 | L13: 0.179 | N13: 5.3020063 | O13: 0.177 | Q13: 4.9063376 | R13: 0.164 | T13: 10.208344 | U13: 0.17 | W13: =T13-Q13-N13 -> -9.9326625e-08 | Y13: 5.3020063 | Z13: 0.177 | AB13: 4.9063376 | AC13: 0.164 | AE13: 10.208344 | AF13: 0.17 | AH13: =AE13-AB13-Y13 -> -9.9326625e-08
A14: Capex including IDC | B14: =Dashboard!G14 -> 329.69667 | C14: =Dashboard!H14 -> 53.565 | E14: 194.35415 | F14: 63.111 | H14: 178.55025 | I14: 57.974 | K14: 372.90439 | L14: 60.537 | N14: 172.56163 | O14: 55.933 | Q14: 158.08284 | R14: 51.219 | T14: 330.64446 | U14: 53.581 | W14: =T14-Q14-N14 -> -9.1508728e-06 | Y14: 172.56163 | Z14: 55.933 | AB14: 158.08284 | AC14: 51.219 | AE14: 330.64446 | AF14: 53.581 | AH14: =AE14-AB14-Y14 -> -9.1508728e-06
W15: =T15-Q15-N15 -> 0
A16: Financing | B16: =Dashboard!G16 -> Rs Crore | C16: =Dashboard!H16 -> 0 | E16: Rs Crore | H16: Rs Crore | K16: Rs Crore | N16: Rs Crore | O16: 0 | Q16: Rs Crore | R16: 0 | T16: Rs Crore | U16: 0 | Y16: Rs Crore | Z16: 0 | AB16: Rs Crore | AC16: 0 | AE16: Rs Crore | AF16: 0
A17: Commerical Loan 1 | B17: =Dashboard!G17 -> 161.55137 | C17: =Dashboard!H17 -> 0.49 | E17: 95.233536 | F17: 0.49 | H17: 87.489622 | I17: 0.49 | K17: 182.72315 | L17: 0.49 | N17: 84.555201 | O17: 0.49 | Q17: 77.46059 | R17: 0.49 | T17: 162.01579 | U17: 0.49 | W17: =T17-Q17-N17 -> -4.4839276e-06 | Y17: 84.555201 | Z17: 0.49 | AB17: 77.46059 | AC17: 0.49 | AE17: 162.01579 | AF17: 0.49 | AH17: =AE17-AB17-Y17 -> -4.4839276e-06
A18: Commerical Loan 2 | B18: =Dashboard!G18 -> 0 | C18: =Dashboard!H18 -> 0 | E18: 0 | F18: 0 | H18: 0 | I18: 0 | K18: 0 | L18: 0 | N18: 0 | O18: 0 | Q18: 0 | R18: 0 | T18: 0 | U18: 0 | W18: =T18-Q18-N18 -> 0 | Y18: 0 | Z18: 0 | AB18: 0 | AC18: 0 | AE18: 0 | AF18: 0 | AH18: =AE18-AB18-Y18 -> 0
A19: Grant/ Capital Subsidy | B19: =Dashboard!G19 -> 98.909002 | C19: =Dashboard!H19 -> 0.3 | E19: 58.306246 | F19: 0.3 | H19: 53.565074 | I19: 0.3 | K19: 111.87132 | L19: 0.3 | N19: 51.76849 | O19: 0.3 | Q19: 47.424851 | R19: 0.3 | T19: 99.193338 | U19: 0.3 | W19: =T19-Q19-N19 -> -2.7452618e-06 | Y19: 51.76849 | Z19: 0.3 | AB19: 47.424851 | AC19: 0.3 | AE19: 99.193338 | AF19: 0.3 | AH19: =AE19-AB19-Y19 -> -2.7452618e-06
A20: Deferred Capital Subisdy | B20: =Dashboard!G20 -> -15.807321 | C20: =Dashboard!H20 -> -0.047945041 | N20: -8.3673811 | O20: -0.048489232 | Q20: -7.5235497 | R20: -0.047592452 | T20: -15.890929 | U20: -0.048060474 | Y20: -8.3673811 | Z20: -0.048489232 | AB20: -7.5235497 | AC20: -0.047592452 | AE20: -15.890929 | AF20: -0.048060474
A21: Equity | B21: =Dashboard!G21 -> 0 | C21: =Dashboard!H21 -> 0 | E21: 0 | F21: 0 | H21: 0 | I21: 0 | K21: 0 | L21: 0 | N21: 0 | O21: 0 | Q21: 0 | R21: 0 | T21: 0 | U21: 0 | W21: =T21-Q21-N21 -> 0 | Y21: 0 | Z21: 0 | AB21: 0 | AC21: 0 | AE21: 0 | AF21: 0 | AH21: =AE21-AB21-Y21 -> 0
A22: Upfront Contribution from Developer | B22: =Dashboard!G22 -> 85.043622 | C22: =Dashboard!H22 -> 0.25794504 | E22: 40.814372 | F22: 0.21 | H22: 37.495552 | I22: 0.21 | K22: 78.309923 | L22: 0.21 | N22: 44.605324 | O22: 0.25848923 | Q22: 40.720945 | R22: 0.25759245 | T22: 85.326266 | U22: 0.25806047 | W22: =T22-Q22-N22 -> -3.2895817e-06 | Y22: 36.237943 | Z22: 0.21 | AB22: 33.197396 | AC22: 0.21 | AE22: 69.435337 | AF22: 0.21 | AH22: =AE22-AB22-Y22 -> -1.9216833e-06
A23: Total | B23: =Dashboard!G24 -> 329.69667 | C23: =Dashboard!H24 -> 1 | E23: 194.35415 | F23: 1 | H23: 178.55025 | I23: 1 | K23: 372.90439 | L23: 1 | N23: 172.56163 | O23: 1 | Q23: 158.08284 | R23: 1 | T23: 330.64446 | U23: 1 | W23: =T23-Q23-N23 -> -9.1508727e-06 | Y23: 172.56163 | Z23: 1 | AB23: 158.08284 | AC23: 1 | AE23: 330.64446 | AF23: 1 | AH23: =AE23-AB23-Y23 -> -9.1508727e-06
W24: =T24-Q24-N24 -> 0 | AH24: =AE24-AB24-Y24 -> 0
A25: Check Contribution | E25: =SUM(E27:E29)-E22 -> 0 | H25: =SUM(H27:H29)-H22 -> 0 | K25: =SUM(K27:K29)-K22 -> 0
A26: Upfront Charges (Rs Cr) | E26: Rs Cr | H26: Rs Cr | K26: Rs Cr
A27: Execution Date for ISA + 0.5 month | B27: =Dashboard!K5 -> 20.770891 | C27: =Dashboard!L5 -> 3.4618151 | E27: 10.623833 | F27: 3.5412775 | H27: 9.8500763 | I27: 3.2833588 | K27: 20.473908 | L27: 3.412318 | N27: 10.871383 | O27: 3.6237943 | Q27: 9.9592187 | R27: 3.3197396 | T27: 20.830601 | U27: 3.4717668 | W27: =T27-Q27-N27 -> -5.7650498e-07 | Y27: 10.871383 | Z27: 3.6237943 | AB27: 9.9592187 | AC27: 3.3197396 | AE27: 20.830601 | AF27: 3.4717668 | AH27: =AE27-AB27-Y27 -> -5.7650498e-07
A28: Execution Date for ISA + 6 month | B28: =Dashboard!K6 -> 24.232706 | C28: =Dashboard!L6 -> 4.0387843 | E28: 12.852587 | F28: 4.2841955 | H28: 11.62969 | I28: 3.8765633 | K28: 24.482276 | L28: 4.0803793 | N28: 12.68328 | O28: 4.22776 | Q28: 11.619088 | R28: 3.8730295 | T28: 24.302368 | U28: 4.0503946 | W28: =T28-Q28-N28 -> -6.7258915e-07 | Y28: 12.68328 | Z28: 4.22776 | AB28: 11.619088 | AC28: 3.8730295 | AE28: 24.302368 | AF28: 4.0503946 | AH28: =AE28-AB28-Y28 -> -6.7258915e-07
A29: Execution Date for ISA + 12 months | B29: =Dashboard!K7 -> 40.040026 | C29: =Dashboard!L7 -> 6.6733377 | E29: 17.337953 | F29: 5.7793178 | H29: 16.015786 | I29: 5.3385953 | K29: 33.353739 | L29: 5.5589564 | N29: 21.050661 | O29: 7.0168871 | Q29: 19.142638 | R29: 6.3808794 | T29: 40.193297 | U29: 6.6988829 | W29: =T29-Q29-N29 -> -2.0404876e-06 | Y29: 12.68328 | Z29: 4.22776 | AB29: 11.619088 | AC29: 3.8730295 | AE29: 24.302368 | AF29: 4.0503946 | AH29: =AE29-AB29-Y29 -> -6.7258915e-07
A30: Project CoD + 1 day | B30: =Dashboard!K10 -> 5.4491489 | C30: =Dashboard!L10 -> 0.90819149 | E30: 14.582124 | H30: 14.013315 | K30: 24.672852 | N30: 5.2515479 | O30: 1.750516 | Q30: 5.5785505 | R30: 1.8595168 | T30: 6.9058268 | U30: 1.1509711 | W30: =T30-Q30-N30 -> -3.9242717 | Y30: 14.053505 | Z30: 4.6845017 | AB30: 13.49285 | AC30: 4.4976167 | AE30: 23.622082 | AF30: 3.9370137 | AH30: =AE30-AB30-Y30 -> -3.9242731
A31: Project CoD + 0.5 years + 1 day | B31: =Dashboard!K11 -> 9.8409561 | C31: =Dashboard!L11 -> 1.6401593 | E31: 5.7492638 | H31: 5.5506342 | K31: 11.532482 | N31: 5.200448 | O31: 1.7334827 | Q31: 5.0287913 | R31: 1.6762638 | T31: 10.460274 | U31: 1.743379 | W31: =T31-Q31-N31 -> 0.23103458 | Y31: 5.1814293 | Z31: 1.7271431 | AB31: 5.0116907 | AC31: 1.6705636 | AE31: 10.424155 | AF31: 1.7373591 | AH31: =AE31-AB31-Y31 -> 0.23103459
A32: Project CoD + 1 years + 1 day | B32: =Dashboard!K12 -> 21.846455 | C32: =Dashboard!L12 -> 3.6410759 | N32: 11.582949 | O32: 3.860983 | Q32: 10.885335 | R32: 3.628445 | T32: 22.514267 | U32: 3.7523779 | W32: =T32-Q32-N32 -> 0.045983303 | Y32: 11.583963 | Z32: 3.861321 | AB32: 10.886247 | AC32: 3.6287489 | AE32: 22.516193 | AF32: 3.7526988 | AH32: =AE32-AB32-Y32 -> 0.045983303
A33: Total | B33: =Dashboard!K2 -> 663.87665 | N33: 342.7365 | Q33: 337.12871 | T33: 675.80194 | W33: =T33-Q33-N33 -> -4.0632675 | Y33: 343.15303 | AB33: 337.50323 | AE33: 676.59299 | AH33: =AE33-AB33-Y33 -> -4.0632675
A34: Revenue | B34: =Working!$D$413 -> 594.64035 | N34: 306.49856 | Q34: 303.93131 | T34: 606.3666 | W34: =T34-Q34-N34 -> -4.0632656 | Y34: 306.91509 | AB34: 304.30583 | AE34: 607.15765 | AH34: =AE34-AB34-Y34 -> -4.0632656
A35: Levelized Cost | B35: =Working!$D$451 -> 2.4589586 | N35: 2.6298805 | Q35: 2.5280595 | T35: 2.5449831 | Y35: 2.6388215 | AB35: 2.5360992 | AE35: 2.5534733
A36: Check - Contribution | B36: =SUM(B27:B29)-B22 -> 0 | N36: =SUM(N27:N29)-N22 -> 0 | Q36: =SUM(Q27:Q29)-Q22 -> 0 | T36: =SUM(T27:T29)-T22 -> 0 | W36: =SUM(W27:W29)-W22 -> 7.1054274e-15 | Y36: =SUM(Y27:Y29)-Y22 -> 0 | AB36: =SUM(AB27:AB29)-AB22 -> 0 | AE36: =SUM(AE27:AE29)-AE22 -> 0 | AH36: =SUM(AH27:AH29)-AH22 -> 1.7763568e-15
A37: First Installment | N37: =N30-Y30 -> -8.8019571 | Q37: =Q30-AB30 -> -7.9142997 | T37: =T30-AE30 -> -16.716255
N38: =N37-N20 -> -0.43457597 | Q38: =Q37-Q20 -> -0.39074997 | T38: =T37-T20 -> -0.82532587

Sheet Norms
B1: Norms for Capex | C1: MNRE Revised Norms | D1: Omkareshwar Model | F1: Actual Rs Cr | G1: Ceiling
A2: 1 | B2: Internal Evacuation incl bays, S/S, Transformers, T/L | C2: Schedule of STU/ CTU | D2: As per CTU; | F2: to be revised to STU cost schedule
A3: 2 | B3: Road, water infra, building fencing, street lighting | C3: As per Schedule of rates of PWD of GoMP | D3: As per PWD rates - RUMSL to confirm | F3: =Capex!I14+Capex!I19 -> 2542.5 | G3: =F3 -> 2542.5
A4: 3 | B4: Incidental Expenses during construction - Pre-operative costs, IDC, Finance Cost, Project Management Costs | C4: upto 10.75% of Capex | D4: =F4/(Capex!I61/100) -> 0.095194694 | F4: =Capex!I129+Capex!I60/100 -> 31.385374 | G4: =10.75%*Capex!I61/100 -> 35.442393
A5: 4 | B5: Contingency | C5: Upto 3% of Capex | D5: =ROUND(Capex!I56/Capex!I54,3) -> 0.028 | F5: =Capex!I56/100 -> 8.6385598 | G5: =3%*Capex!I54/100 -> 9.3393364
A6: 5 | B6: Grid Connectivity, LTOA charges, ESIA Charges | C6: As per rates notified by concerned agencies/ STU/ CTU | D6: As per CERC guidelines
A7: 6 | B7: Land Charges, Registration, Land conversion, Land Crop compensation, ROW | C7: As per rates notified by State Govt or its agencies | D7: State regulations
B9: Norms for O&M | C9: MNRE Revised Norms | D9: Omkareshwar Model | F9: Actual Rs Cr | G9: Ceiling
A10: 1 | B10: Internal Evacuation incl bays, S/S, Transformers, T/L | C10: As per Norms of CERC/ SERC | D10: =Inputs!E90 -> 1.047 | F10: =Working!J304 -> 3.0844558 | G10: =F10 -> 3.0844558
A11: 2 | B11: Road, water infra, building fencing, street lighting | C11: As per schedule of rates of PWD subject to ceiling of 5% of capex | D11: =F11/G11 -> 0.0064244393 | F11: =Inputs!E87 -> 0.1 | G11: =5%*Capex!I54/100 -> 15.565561
A12: 3 | B12: Establishment, admin, manpower | C12: As per schedule of rates of PWD sub to ceiling of 10% of O&M charges above (1&2) | D12: =F12/G12 -> 0.31396221 | F12: =Working!J303 -> 0.58554004 | G12: =10%*(G10+G11) -> 1.8650016
A13: 4 | B13: Power consumption charges, water consumption charges, land lease rentals | C13: As per rates finalized by state govt or its agencies | D13: Nil
A14: 5 | B14: Annual Escalation | C14: As per CERC/ SERC regulations | D14: =Inputs!F90 -> 0.037 | F14: =D14 -> 0.037 | G14: 0.037

Sheet Inputs
A1: RUMSL | C1: Units | E1: Input | G1: Bridge Financing | H1: =IF(E66,"Developer","Loan") -> Developer | I1: Circularity | J1: TRUE | Q1: Module size(Wp) | U1: 1 | V1: Yes
A2: Project | G2: Phase | H2: 3 | I2: 1=Phase 1; 2=Phase 2; 3=Combined | U2: 2 | V2: No
B3: Capacity of the Project | C3: MW | E3: =IF($H$2=1,300,IF($H$2=2,300,600)) -> 600 | G3: ESIA, IE, Legal,DPR, Consultancy | H3: 0.5 | I3: =IF(H3=0.5,"Shared","Independent") -> Shared | P3: Option 1 | Q3: 350 | T3: TRUE | U3: 3
B4: Conversion Factor | C4: AC:DC | E4: 1.4 | G4: Connectivity | H4: 0.5 | I4: =IF(H4=0.5,"Shared","Independent") -> Shared | P4: 2.5 | Q4: 44 | T4: FALSE
B5: CUF of the project | C5: % | E5: 0.2494 | G5: Regulatory | H5: 0.5 | I5: =IF(H5=0.5,"Shared","Independent") -> Shared | P5: Option 2 | Q5: 445
B6: Annual Generation | C6: MU | E6: =E5*E3*8.76 -> 1310.8464 | G6: Common Corridor | H6: Yes | I6: =IF(H6="Yes","Combined cost","Bifurcated Cost") -> Combined cost | P6: Plot Capacity (MW) | Q6: Mooring Lines (No)
B7: Derating | C7: % | E7: 0.0025
B8: Capital Cost of Solar Project | C8: Rs Cr/ MW | E8: 5.06 | G8: (Estimates)
B9: Levelized Generation Tariff | C9: Rs per Unit | E9: 2.95 | G9: (Estimates)
A10: Solar Park
B11: Stamp Duty | C11: Land | E11: =12.5%*0 -> 0 | F11: NA | G11: As per RUMSL inputs dated 26-Oct-2021
B12: Registration Charges - Land | C12: Land | E12: 0 | F12: NA | G12: As per RUMSL inputs dated 26-Oct-2021
B13: Admin charges - Land | C13: Land | E13: =1.5%*0+0 -> 0 | F13: NA | G13: As per RUMSL inputs dated 26-Oct-2021
A14: MPTransco | B14: PMC Cost - Transmission | C14: % | E14: 0.08 | F14: Yes | G14: As per RUMSL inputs dated 26-Oct-2021
B15: PMC charges to MPUVNL | E15: 0 | F15: Yes | G15: As per RUMSL inputs dated 26-Oct-2021 (Changed from 10% to 8%), 15-Mar-2022 (8% to 0%) - To be specified in ISA
B16: Upfront PMC charges to MPUVNL | E16: 1 | F16: Yes | G16: As per RUMSL inputs dated 08-Dec-2021
B17: Period for payment of remainder PMC charges (years) | E17: 1 | F17: Yes
B18: Local Area Development Charges | C18: Rs Lakh/ MW | E18: 1 | F18: Yes
B19: LAD - Years for Payment | C19: # | E19: 2 | F19: Yes | G19: =74.37+63.92+74.37+35.77 -> 248.43 | H19: =58.45+52.4+58.45+29.29 -> 198.59
B20: Registration Cost | C20: Rs Lakh/ MW | E20: 1 | F20: Yes
A21: Not Used | B21: PSF Fees | C21: Upfront | E21: 0.001 | G21: As per RUMSL inputs dated 26-Oct-2021
A22: Not Used | B22: PSF Fees - Applicable | E22: FALSE | F22: No | G22: As per RUMSL inputs dated 26-Oct-2021 - Annual Charges
B23: Financing Cost (first 100 Cr) | C23: % | E23: 0.0025 | F23: Yes | G23: As per RUMSL inputs dated 15-Mar-2022
B24: Financing Cost (beyond 100 Cr) | C24: % | E24: 0.0025 | F24: Yes | G24: As per RUMSL inputs dated 26-Oct-2021, 15-Mar-2022
B25: ESIA Cost | C25: Rs Lakh | E25: =69.3 -> 69.3 | F25: Yes | G25: As per RUMSL inputs dated 26-Oct-2021
B26: RAP/ LRP Cost | C26: Rs Lakh/ MW | E26: =1500/600 -> 2.5 | F26: Yes | G26: As per RUMSL inputs dated 08-Dec-2021/ 01-Mar-2022/ updated RUMSL mail 25-Mar-22 | L26: =E26*600/100 -> 15
B27: ESMP Cost | C27: Rs Lakh/ MW | E27: =ROUND(650/600,4) -> 1.0833 | F27: Yes | G27: As per RUMSL inputs dated 08-Dec-2021/ updated RUMSL mail 25-Mar-2022 | L27: =E27*600/100 -> 6.4998
B28: Independent Engineer Fee | C28: Rs Lakh/ visit | E28: 2 | F28: Yes | G28: As per RUMSL inputs dated 26-Oct-2021
B29: Legal Charges | C29: Rs Lakh | E29: 15 | F29: Yes | G29: As per RUMSL inputs dated 26-Oct-2021
B30: LTA Application Cost | C30: Rs Lakh | E30: 25 | F30: Yes | G30: Grant of connectivity, LTA application (As per the CERC's Grant of Connectivity regulations); As per RUMSL inputs dated 01-Mar-2022
B31: Regulatory Charges | C31: Rs Lakh | E31: =IF($H$2=1,5,IF($H$2=2,30,35)) -> 35 | F31: Yes | G31: As per RUMSL inputs dated 26-Oct-2021 (Tariff Adoption: 25 L; Deviation Petition:5 L)/ 01-Mar-2022
B32: DPR Preparation | C32: Rs Lakh | E32: =IF($H$2=1,0.5,IF($H$2=2,0.5,1))*111*1.18*600/(600+950) -> 50.701935 | F32: Yes | G32: As per RUMSL inputs dated 08-Dec-2021/ 01-Mar-2022
B33: TA Consultancy Charges | C33: Rs Lakh | E33: =IF($H$2=1,0.5,IF($H$2=2,0.5,1))*1.74*1.18*100 -> 205.32 | F33: Yes | G33: Actuals with taxes; As per RUMSL inputs dated 01-Mar-2022
A34: Financial Parameters
B35: Taxes | C35: % | E35: 0.18
B36: Contingency | C36: % | E36: 0.03 | G36: Max as per revised guidelines
A37: Solar Park Infrastructure Project Details | K37: As per SBG
F38: Site | G38: Sub-station | H38: Tr Lines | I38: Other | K38: Sub-station | L38: 21 | M38: Months
B39: Project Start Date | C39: Date | E39: 44713 | F39: =E39 -> 44713 | G39: =E39 -> 44713 | H39: =E39 -> 44713 | I39: =E39 -> 44713 | K39: Transmission Lines | L39: 21 | M39: Months
B40: Park Construction Period | C40: Month | E40: =MAX(F40:I40) -> 16 | F40: 6 | G40: 16 | H40: 16 | I40: 12 | K40: Other Infrastructure | L40: 21 | M40: Months
B41: Start of Operation | C41: Date | E41: =MAX(F41:I41) -> 45200 | F41: =EDATE(F39,F40) -> 44896 | G41: =EDATE(G39,G40) -> 45200 | H41: =EDATE(H39,H40) -> 45200 | I41: =EDATE(I39,I40) -> 45078 | J41: As per RUMSL inputs dated 08-Dec-2021
B42: Number of year in operation | C42: Years | E42: 25
B43: First operational Financial year | C43: Date | E43: =IF(MONTH(E41)<=3,DATE(YEAR(E41),3,31),DATE(YEAR(E41)+1,3,31)) -> 45382
B44: Last day of operation | C44: Date | E44: =DATE(YEAR(E41)+E42,MONTH(E41),DAY(E41)-1) -> 54331
B45: Last financial year of operation | C45: Date | E45: =IF(MONTH(E44)<=3,DATE(YEAR(E44),3,31),DATE(YEAR(E44)+1,3,31)) -> 54513
B46: First operational Half year | C46: Date | E46: =IF(AND(MONTH(E41)>3,MONTH(E41)<=9),DATE(YEAR(E41),9,30),IF(MONTH(E41)<=3,DATE(YEAR(E41),3,31),DATE(YEAR(E41)+1,3,31))) -> 45382
B47: Last Half year of operation | C47: Date | E47: =IF(AND(MONTH(E44)>3,MONTH(E44)<=9),DATE(YEAR(E44),9,30),IF(MONTH(E44)<=3,DATE(YEAR(E44),3,31),DATE(YEAR(E44)+1,3,31))) -> 54331
F48: (Combined = 0.5,Individual = 1)
A49: Commercial Loan 1
B50: Commerical Loan 1 | C50: % | E50: =70%*70% -> 0.49
B51: Moratorium Period (from start of operations) | C51: Years | E51: 1
B52: Repayment Period | C52: Years | E52: 15 | G52: As per RUMSL inputs dated 01-Mar-2022
B53: Interest Rate | C53: % | E53: 0.08 | G53: As per RUMSL inputs dated 01-Mar-2022
A54: Commercial Loan 2
B55: Commerical Loan 2 | C55: % | E55: 0
B56: Moratorium Period (from start of operations) | C56: Years | E56: 1
B57: Repayment Period | C57: Years | E57: =E52 -> 15
B58: Interest Rates | C58: % | E58: =E53 -> 0.08
A59: Equity
B60: Equity | C60: % | E60: 0
B61: Return on Equity (RoE) - Post Tax | C61: % | E61: 0
A63: Bridge Financing (Delayed subsidy disbursal)
B64: Subsidy Disbursement Amount | C64: % | E64: 0.15 | F64: =E64*Dashboard!$G$19 -> 14.83635 | G64: Rs Cr
B65: Interest Rate | C65: % | E65: =E58+1% -> 0.09 | G65: Added as per RUMSL inputs dated 15-Mar-2022
B66: From Developer | E66: TRUE | G66: Added as per RUMSL inputs dated 15-Mar-2022
B69: DSRA Months | C69: months | E69: 6
B70: DSRA Source | E70: Cash
B71: Bank Guarantee Fee | C71: % | E71: 0.007
B72: Interest on DSRA | C72: % | E72: 0.04
A73: Cash Deficit Loan
B74: Interest Rates on Cash Deficit Loan | C74: % | E74: 0.09
B75: Repayment of Cash Deficit Loan | E75: TRUE
B76: Minimum Cash Balance | C76: Rs Cr | E76: 3
B77: Interest on Cash balance | C77: % | E77: 0.09
A78: Working Capital
B79: Receivables | C79: Months | E79: 1
B80: O&M | C80: Months | E80: 1
B81: Maintenance spares | C81: % | E81: 0
B82: IOWC | C82: % | E82: 0.1
B83: Margin Money for WC | C83: % | E83: 0.25
A84: O&M | F84: Escalation
B85: Land Rent | C85: Rs Lakh/ Hectare | E85: 0 | F85: 0.05
B86: Water use charges | C86: Rs Lakh/ Litre | E86: 0 | F86: 0.05
B87: Road, building maintenance | C87: % of Assets | E87: 0.1 | F87: 0.01
B88: SLDC Charges | C88: Rs Lakh/ MW | E88: 0 | F88: 0.05
B89: A&G charges | C89: Rs Lakh/ MW | E89: 0.2 | F89: 0.05 | G89: As per RUMSL inputs dated 26-Oct-2021/ 01-Mar-2022/ Revised 15-Mar-2022 | K89: Omkareshwewar | L89: Nos # | M89: O&M (Rs L) | N89: Annual O&M Norms | O89: FY 23 | P89: FY 24 | Q89: Source: CERC Order FY19-24
A90: 1 | B90: O&M charges - Electrical | C90: Rs Lakh/ MW | E90: =IF(A90=1, ROUND(SUM(M90:M93)/$E$3,3), 0.85) -> 1.047 | F90: 0.037 | G90: As per RUMSL inputs dated 26-Oct-2021 - CERC norms | K90: Sub-station bays | L90: =F125+F126+(IF(Inputs!$H$2=1,0,IF(Inputs!$H$2=2,1,2))) -> 14 | M90: =P90*L90 -> 361.76 | N90: 220 kV Sub-station (Rs Lakh/ bay) | O90: 24.96 | P90: 25.84 | S90: 25.84
B91: PSF charges | C91: % of MSO | E91: 0.001 | G91: As per RUMSL inputs dated 15-Mar-2021 | K91: Transmission Line D/C | L91: =Capex!D105+Capex!D106 -> 37.174 | M91: =P91*L91 -> 16.096342 | N91: D/C bundled conductor (Rs L per kM) | O91: 0.377 | P91: 0.433 | Q91: Source: CERC Order FY19-24 | S91: 0.433
B92: Insurance Cost | C92: % of Assets | E92: 0.002 | F92: 0.01 | G92: 1 crore per 250 MW; 1 cr per 250 MW for insurance | K92: Transmission Line M/C | L92: =Capex!D107 -> 28.911 | M92: =P92*L92 -> 25.036926 | N92: M/C (Bundled - 4 or more sub-conductor) | O92: 0.754 | P92: 0.866 | S92: 0.866
A93: Tariff Option | K93: Transformer (MVA) | L93: =100*F125 -> 800 | M93: =P93*L93 -> 225.6 | N93: 220 kV Transformer (Rs L/MVA) | O93: 0.272 | P93: 0.282 | S93: 0.282
B94: Option 1: Levelized Tariff; Option2: Yearly Tariff; Option 3: User Input | E94: Option2 | K94: Net | L94: =M94/$E$3 -> 1.0474888 | M94: =SUM(M90:M93) -> 628.49327 | N94: O&M Escalation | O94: 0.037
A95: Others
B96: IRG to be considered | E96: FALSE
B97: Tax Rate | C97: % | E97: 0.2517
B98: MAT Rate | C98: % | E98: =15%*(1+10%)*(1+4%) -> 0.1716
B99: Discounting Factor | C99: % | E99: =(Working!E43*E53*(1-E97)+Working!E44*E58*(1-E97)+Working!E46*E61)*0+9.36% -> 0.0936
A101: Allocation | E101: Land | F101: Civil Works | G101: Electrical | H101: Other Assets
B102: Land | C102: % | E102: 1 | F102: 0 | G102: 0 | H102: =1-E102-F102-G102 -> 0
B103: Site Development Cost | C103: % | E103: 0 | F103: 0.8 | G103: 0 | H103: =1-E103-F103-G103 -> 0.2
B104: Evacuation Infrastructure Cost | C104: % | E104: 0 | F104: 0.2 | G104: 0.8 | H104: =1-E104-F104-G104 -> 0
...

Sheet Dashboard
B1: Assumptions | F1: Results | J1: Comprehensive Park Charges | N1: Modified Comprehensive Park Charges | R1: Reduction | S1: (Deducted A&G charges) | U1: Year | V1: Cash
F2: Phasing | G2: =Inputs!H1 -> Developer | H2: =IF(Inputs!$H$2=1,"Phase 1",IF(Inputs!$H$2=2,"Phase 2","Combined")) -> Combined | K2: =SUM(K5:K60) -> 663.87665 | O2: =SUM(O5:O60) -> 607.29426 | R2: =SUM(R5:R60) -> 56.582387
C3: Units | F3: Park Infrastructure Cost Breakup | G3: Rs Crore | H3: Rs Lakh per MW | J3: Solar park charges as per milestone | K3: Solar Park-Infra | N3: Solar park charges as per milestone | O3: Solar Park-Infra
B4: General | F4: Capital Expenditure | I4: Target | J4: Upfront Charges (Rs Cr) | K4: Rs Cr | L4: Rs Lakhs/MW | N4: Upfront Charges (Rs Cr)
B5: Capacity | C5: =Inputs!C3 -> MW | D5: =Inputs!E3 -> 600 | F5: Land | G5: =(Capex!I6)/100 -> 1.705258 | H5: =ROUND(G5*100/$D$5,3) -> 0.284 | J5: Execution Date for ISA + 0.5 month | K5: =SUMIFS(Working!$E$81:$BL$81,Working!$E$2:$BL$2,S5)+SUMIFS(Working!$E$413:$BL$413,Working!$E$2:$BL$2,S5) -> 20.770891 | L5: =K5/Inputs!$E$3*100 -> 3.4618151 | N5: Execution Date for ISA + 0.5 month | O5: =SUMIFS(Working!$E$81:$BL$81,Working!$E$2:$BL$2,S5)+SUMIFS(Working!$E$413:$BL$413,Working!$E$2:$BL$2,S5) -> 20.770891 | P5: =O5/Inputs!$E$3*100 -> 3.4618151 | R5: =K5-O5 -> 0 | S5: =EOMONTH(S6,-6) -> 44834
B6: CUF | C6: =Inputs!C5 -> % | D6: =Inputs!E5 -> 0.2494 | F6: Road, Building & other civil | G6: =(Capex!I14+Capex!I19)/100 -> 25.425 | H6: =ROUND(G6*100/$D$5,3) -> 4.238 | J6: Execution Date for ISA + 6 month | K6: =SUMIFS(Working!$E$81:$BL$81,Working!$E$2:$BL$2,S6)+SUMIFS(Working!$E$413:$BL$413,Working!$E$2:$BL$2,S6) -> 24.232706 | L6: =K6/Inputs!$E$3*100 -> 4.0387843 | N6: Execution Date for ISA + 6 month | O6: =SUMIFS(Working!$E$81:$BL$81,Working!$E$2:$BL$2,S6)+SUMIFS(Working!$E$413:$BL$413,Working!$E$2:$BL$2,S6) -> 24.232706 | P6: =O6/Inputs!$E$3*100 -> 4.0387843 | R6: =K6-O6 -> 0 | S6: =EOMONTH(S7,-6) -> 45016
B7: Energy | C7: =Inputs!C6 -> MU | D7: =Inputs!E6 -> 1310.8464 | F7: Evacuation - Sub-station | G7: =(Capex!I26)/100 -> 116.8 | H7: =ROUND(G7*100/$D$5,3) -> 19.467 | J7: Execution Date for ISA + 12 months | K7: =SUMIFS(Working!$E$81:$BL$81,Working!$E$2:$BL$2,S7)+SUMIFS(Working!$E$413:$BL$413,Working!$E$2:$BL$2,S7) -> 40.040026 | L7: =K7/Inputs!$E$3*100 -> 6.6733377 | N7: Execution Date for ISA + 12 months | O7: =SUMIFS(Working!$E$81:$BL$81,Working!$E$2:$BL$2,S7)+SUMIFS(Working!$E$413:$BL$413,Working!$E$2:$BL$2,S7) -> 40.040026 | P7: =O7/Inputs!$E$3*100 -> 6.6733377 | R7: =K7-O7 -> 0 | S7: =EOMONTH(S10,-6) -> 45199
B8: Park COD | C8: =Inputs!C41 -> Date | D8: =Inputs!E41 -> 45200 | F8: Evacuation - Transmission Line | G8: =(Capex!I32)/100 -> 104.31453 | H8: =ROUND(G8*100/$D$5,3) -> 17.386
B9: Life of Project | C9: =Inputs!C42 -> Years | D9: =Inputs!E42 -> 25 | F9: Other Costs | G9: =(Capex!$I$53)/100 -> 63.066421 | H9: =ROUND(G9*100/$D$5,3) -> 10.511 | J9: Half Yearly Charges (Rs Cr) | N9: Half Yearly Charges (Rs Cr)
F10: Base Cost Total | G10: =SUM(G5:G9) -> 311.31121 | H10: =ROUND(G10*100/$D$5,2) -> 51.89 | J10: Project CoD + 1 day | K10: =SUMIFS(Working!$E$413:$BL$413,Working!$E$2:$BL$2,S10)-SUMIFS(Working!$E$408:$BL$408,Working!$E$2:$BL$2,S10) -> 5.4491489 | L10: =K10/Inputs!$E$3*100 -> 0.90819149 | N10: Project CoD + 1 day | O10: =$K10-SUMIFS(Working!$E$303:$BL$303,Working!$E$2:$BL$2,S10) -> 4.8636089 | P10: =O10/Inputs!$E$3*100 -> 0.81060148 | R10: =K10-O10 -> 0.58554004 | S10: =Inputs!E46 -> 45382 | U10: ="FY "&RIGHT(V10,2) -> FY 24 | V10: {=TRANSPOSE(Working!I1:BG1)} -> 2024 | W10: {=TRANSPOSE(Working!I380:BG380)} -> 0
B11: Financing | F11: Contingency & Insurance Charges | G11: =(Capex!I58)/100 -> 9.1237087 | H11: =ROUND(G11*100/$D$5,3) -> 1.521 | J11: Project CoD + 0.5 years + 1 day | K11: =SUMIFS(Working!$E$413:$BL$413,Working!$E$2:$BL$2,S11)-SUMIFS(Working!$E$408:$BL$408,Working!$E$2:$BL$2,S11) -> 9.8409561 | L11: =K11/Inputs!$E$3*100 -> 1.6401593 | N11: Project CoD + 0.5 years + 1 day | O11: =$K11-SUMIFS(Working!$E$303:$BL$303,Working!$E$2:$BL$2,S11) -> 9.2409561 | P11: =O11/Inputs!$E$3*100 -> 1.5401593 | R11: =K11-O11 -> 0.6 | S11: =EOMONTH(S10,6) -> 45565 | U11: ="FY "&RIGHT(V11,2) -> FY 24 | V11: 2024 | W11: 3
B12: =Inputs!B51 -> Moratorium Period (from start of operations) | C12: =Inputs!C51 -> Years | D12: =Inputs!E51 -> 1 | F12: Capital Expenditure | G12: =G10+G11 -> 320.43492 | H12: =H10+H11 -> 53.411 | J12: Project CoD + 1 years + 1 day | K12: =SUMIFS(Working!$E$413:$BL$413,Working!$E$2:$BL$2,S12)-SUMIFS(Working!$E$408:$BL$408,Working!$E$2:$BL$2,S12) -> 21.846455 | L12: =K12/Inputs!$E$3*100 -> 3.6410759 | N12: Project CoD + 1 years + 1 day | O12: =$K12-SUMIFS(Working!$E$303:$BL$303,Working!$E$2:$BL$2,S12) -> 21.231638 | P12: =O12/Inputs!$E$3*100 -> 3.5386064 | R12: =K12-O12 -> 0.61481705 | S12: =EOMONTH(S11,6) -> 45747 | U12: ="FY "&RIGHT(V12,2) -> FY 25 | V12: 2025 | W12: 3
B13: =Inputs!B52 -> Repayment Period | C13: =Inputs!C52 -> Years | D13: =Inputs!E52 -> 15 | F13: IDC | G13: =Working!$D$62 -> 9.2617535 | H13: =ROUND(G13/D5*10,3) -> 0.154 | J13: Project CoD + 1.5 years + 1 day | K13: =SUMIFS(Working!$E$413:$BL$413,Working!$E$2:$BL$2,S13)-SUMIFS(Working!$E$408:$BL$408,Working!$E$2:$BL$2,S13) -> 14.955944 | L13: =K13/Inputs!$E$3*100 -> 2.4926573 | N13: Project CoD + 1.5 years + 1 day | O13: =$K13-SUMIFS(Working!$E$303:$BL$303,Working!$E$2:$BL$2,S13) -> 14.325944 | P13: =O13/Inputs!$E$3*100 -> 2.3876573 | R13: =K13-O13 -> 0.63 | S13: =EOMONTH(S12,6) -> 45930 | U13: ="FY "&RIGHT(V13,2) -> FY 25 | V13: 2025 | W13: 3
B14: =Inputs!B53 -> Interest Rate | C14: =Inputs!C53 -> % | D14: =Inputs!E53 -> 0.08 | F14: Capex including IDC | G14: =G12+G13 -> 329.69667 | H14: =H12+H13 -> 53.565 | J14: Project CoD + 2 years + 1 day | K14: =SUMIFS(Working!$E$413:$BL$413,Working!$E$2:$BL$2,S14)-SUMIFS(Working!$E$408:$BL$408,Working!$E$2:$BL$2,S14) -> 15.116414 | L14: =K14/Inputs!$E$3*100 -> 2.5194024 | N14: Project CoD + 2 years + 1 day | O14: =$K14-SUMIFS(Working!$E$303:$BL$303,Working!$E$2:$BL$2,S14) -> 14.470856 | P14: =O14/Inputs!$E$3*100 -> 2.4118094 | R14: =K14-O14 -> 0.6455579 | S14: =EOMONTH(S13,6) -> 46112 | U14: ="FY "&RIGHT(V14,2) -> FY 26 | V14: 2026 | W14: 3
J15: Project CoD + 2.5 years + 1 day | K15: =SUMIFS(Working!$E$413:$BL$413,Working!$E$2:$BL$2,S15)-SUMIFS(Working!$E$408:$BL$408,Working!$E$2:$BL$2,S15) -> 14.969877 | L15: =K15/Inputs!$E$3*100 -> 2.4949795 | N15: Project CoD + 2.5 years + 1 day | O15: =$K15-SUMIFS(Working!$E$303:$BL$303,Working!$E$2:$BL$2,S15) -> 14.308377 | P15: =O15/Inputs!$E$3*100 -> 2.3847295 | R15: =K15-O15 -> 0.6615 | S15: =EOMONTH(S14,6) -> 46295 | U15: ="FY "&RIGHT(V15,2) -> FY 26 | V15: 2026 | W15: 3
B16: Return | F16: Financing | G16: Rs Crore | J16: Project CoD + 3 years + 1 day | K16: =SUMIFS(Working!$E$413:$BL$413,Working!$E$2:$BL$2,S16)-SUMIFS(Working!$E$408:$BL$408,Working!$E$2:$BL$2,S16) -> 14.838376 | L16: =K16/Inputs!$E$3*100 -> 2.4730627 | N16: Project CoD + 3 years + 1 day | O16: =$K16-SUMIFS(Working!$E$303:$BL$303,Working!$E$2:$BL$2,S16) -> 14.160541 | P16: =O16/Inputs!$E$3*100 -> 2.3600901 | R16: =K16-O16 -> 0.67783579 | S16: =EOMONTH(S15,6) -> 46477 | U16: ="FY "&RIGHT(V16,2) -> FY 27 | V16: 2027 | W16: 3
B17: =Inputs!B61 -> Return on Equity (RoE) - Post Tax | C17: % | D17: =Inputs!E61 -> 0 | F17: Commerical Loan 1 | G17: =Working!D65 -> 161.55137 | H17: =G17/$G$24 -> 0.49 | I17: 162.02 | J17: Project CoD + 3.5 years + 1 day | K17: =SUMIFS(Working!$E$413:$BL$413,Working!$E$2:$BL$2,S17)-SUMIFS(Working!$E$408:$BL$408,Working!$E$2:$BL$2,S17) -> 14.70785 | L17: =K17/Inputs!$E$3*100 -> 2.4513084 | N17: Project CoD + 3.5 years + 1 day | O17: =$K17-SUMIFS(Working!$E$303:$BL$303,Working!$E$2:$BL$2,S17) -> 14.013275 | P17: =O17/Inputs!$E$3*100 -> 2.3355459 | R17: =K17-O17 -> 0.694575 | S17: =EOMONTH(S16,6) -> 46660 | U17: ="FY "&RIGHT(V17,2) -> FY 27 | V17: 2027 | W17: 3
F18: Commerical Loan 2 | G18: =Working!D66 -> 0 | H18: =G18/$G$24 -> 0 | J18: Project CoD + 4 years + 1 day | K18: =SUMIFS(Working!$E$413:$BL$413,Working!$E$2:$BL$2,S18)-SUMIFS(Working!$E$408:$BL$408,Working!$E$2:$BL$2,S18) -> 14.578947 | L18: =K18/Inputs!$E$3*100 -> 2.4298244 | N18: Project CoD + 4 years + 1 day | O18: =$K18-SUMIFS(Working!$E$303:$BL$303,Working!$E$2:$BL$2,S18) -> 13.867219 | P18: =O18/Inputs!$E$3*100 -> 2.3112032 | R18: =K18-O18 -> 0.71172758 | S18: =EOMONTH(S17,6) -> 46843 | U18: ="FY "&RIGHT(V18,2) -> FY 28 | V18: 2028 | W18: 3
B19: Working Capital | F19: Grant/ Capital Subsidy | G19: =Working!D67+Working!D70 -> 98.909002 | H19: =G19/$G$24 -> 0.3 | I19: =G19-G20 -> 114.71632 | J19: Project CoD + 4.5 years + 1 day | K19: =SUMIFS(Working!$E$413:$BL$413,Working!$E$2:$BL$2,S19)-SUMIFS(Working!$E$408:$BL$408,Working!$E$2:$BL$2,S19) -> 14.45167 | L19: =K19/Inputs!$E$3*100 -> 2.4086117 | N19: Project CoD + 4.5 years + 1 day | O19: =$K19-SUMIFS(Working!$E$303:$BL$303,Working!$E$2:$BL$2,S19) -> 13.722366 | P19: =O19/Inputs!$E$3*100 -> 2.2870611 | R19: =K19-O19 -> 0.72930375 | S19: =EOMONTH(S18,6) -> 47026 | U19: ="FY "&RIGHT(V19,2) -> FY 28 | V19: 2028 | W19: 3
B20: =Inputs!B79 -> Receivables | C20: =Inputs!C79 -> Months | D20: =Inputs!E79 -> 1 | F20: Deferred Capital Subisdy | G20: =-Working!D70 -> -15.807321 | H20: =G20/$G$24 -> -0.047945041 | J20: Project CoD + 5 years + 1 day | K20: =SUMIFS(Working!$E$413:$BL$413,Working!$E$2:$BL$2,S20)-SUMIFS(Working!$E$408:$BL$408,Working!$E$2:$BL$2,S20) -> 14.326055 | L20: =K20/Inputs!$E$3*100 -> 2.3876758 | N20: Project CoD + 5 years + 1 day | O20: =$K20-SUMIFS(Working!$E$303:$BL$303,Working!$E$2:$BL$2,S20) -> 13.578741 | P20: =O20/Inputs!$E$3*100 -> 2.2631235 | R20: =K20-O20 -> 0.74731396 | S20: =EOMONTH(S19,6) -> 47208 | U20: ="FY "&RIGHT(V20,2) -> FY 29 | V20: 2029 | W20: 3
B21: =Inputs!B80 -> O&M | C21: =Inputs!C80 -> Months | D21: =Inputs!E80 -> 1 | F21: Equity | G21: =Working!D68 -> 0 | H21: =G21/$G$24 -> 0 | I21: =G24-I17-I19 -> 52.960352 | J21: Project CoD + 5.5 years + 1 day | K21: =SUMIFS(Working!$E$413:$BL$413,Working!$E$2:$BL$2,S21)-SUMIFS(Working!$E$408:$BL$408,Working!$E$2:$BL$2,S21) -> 14.212371 | L21: =K21/Inputs!$E$3*100 -> 2.3687286 | N21: Project CoD + 5.5 years + 1 day | O21: =$K21-SUMIFS(Working!$E$303:$BL$303,Working!$E$2:$BL$2,S21) -> 13.446602 | P21: =O21/Inputs!$E$3*100 -> 2.2411004 | R21: =K21-O21 -> 0.76576894 | S21: =EOMONTH(S20,6) -> 47391 | U21: ="FY "&RIGHT(V21,2) -> FY 29 | V21: 2029 | W21: 3
B22: =Inputs!B81 -> Maintenance spares | C22: =Inputs!C81 -> % | D22: =Inputs!E81 -> 0 | F22: Developer Contribution - Upfront | G22: =Working!D69+IF(Inputs!$E$66,Working!D70,0) -> 85.043622 | H22: =G22/$G$24 -> 0.25794504 | J22: Project CoD + 6 years + 1 day | K22: =SUMIFS(Working!$E$413:$BL$413,Working!$E$2:$BL$2,S22)-SUMIFS(Working!$E$408:$BL$408,Working!$E$2:$BL$2,S22) -> 14.089664 | L22: =K22/Inputs!$E$3*100 -> 2.3482773 | N22: Project CoD + 6 years + 1 day | O22: =$K22-SUMIFS(Working!$E$303:$BL$303,Working!$E$2:$BL$2,S22) -> 13.304984 | P22: =O22/Inputs!$E$3*100 -> 2.2174974 | R22: =K22-O22 -> 0.78467966 | S22: =EOMONTH(S21,6) -> 47573 | U22: ="FY "&RIGHT(V22,2) -> FY 30 | V22: 2030 | W22: 3
B23: =Inputs!B82 -> IOWC | C23: =Inputs!C82 -> % | D23: =Inputs!E82 -> 0.1 | F23: Additional Loan | G23: =IF(Inputs!$E$66,0,Working!D70) -> 0 | H23: =G23/$G$24 -> 0 | J23: Project CoD + 6.5 years + 1 day | K23: =SUMIFS(Working!$E$413:$BL$413,Working!$E$2:$BL$2,S23)-SUMIFS(Working!$E$408:$BL$408,Working!$E$2:$BL$2,S23) -> 13.969293 | L23: =K23/Inputs!$E$3*100 -> 2.3282155 | N23: Project CoD + 6.5 years + 1 day | O23: =$K23-SUMIFS(Working!$E$303:$BL$303,Working!$E$2:$BL$2,S23) -> 13.165235 | P23: =O23/Inputs!$E$3*100 -> 2.1942059 | R23: =K23-O23 -> 0.80405738 | S23: =EOMONTH(S22,6) -> 47756 | U23: ="FY "&RIGHT(V23,2) -> FY 30 | V23: 2030 | W23: 3
B24: =Inputs!B83 -> Margin Money for WC | C24: =Inputs!C83 -> % | D24: =Inputs!E83 -> 0.25 | F24: Total | G24: =SUM(G17:G23) -> 329.69667 | H24: =SUM(H17:H23) -> 1 | J24: Project CoD + 7 years + 1 day | K24: =SUMIFS(Working!$E$413:$BL$413,Working!$E$2:$BL$2,S24)-SUMIFS(Working!$E$408:$BL$408,Working!$E$2:$BL$2,S24) -> 13.85069 | L24: =K24/Inputs!$E$3*100 -> 2.3084483 | N24: Project CoD + 7 years + 1 day | O24: =$K24-SUMIFS(Working!$E$303:$BL$303,Working!$E$2:$BL$2,S24) -> 13.026776 | P24: =O24/Inputs!$E$3*100 -> 2.1711293 | R24: =K24-O24 -> 0.82391364 | S24: =EOMONTH(S23,6) -> 47938 | U24: ="FY "&RIGHT(V24,2) -> FY 31 | V24: 2031 | W24: 3
H25: =G22-SUM(K5:K7) -> 0 | J25: Project CoD + 7.5 years + 1 day | K25: =SUMIFS(Working!$E$413:$BL$413,Working!$E$2:$BL$2,S25)-SUMIFS(Working!$E$408:$BL$408,Working!$E$2:$BL$2,S25) -> 13.733922 | L25: =K25/Inputs!$E$3*100 -> 2.2889871 | N25: Project CoD + 7.5 years + 1 day | O25: =$K25-SUMIFS(Working!$E$303:$BL$303,Working!$E$2:$BL$2,S25) -> 12.889662 | P25: =O25/Inputs!$E$3*100 -> 2.148277 | R25: =K25-O25 -> 0.84426025 | S25: =EOMONTH(S24,6) -> 48121 | U25: ="FY "&RIGHT(V25,2) -> FY 31 | V25: 2031 | W25: 3
J26: Project CoD + 8 years + 1 day | K26: =SUMIFS(Working!$E$413:$BL$413,Working!$E$2:$BL$2,S26)-SUMIFS(Working!$E$408:$BL$408,Working!$E$2:$BL$2,S26) -> 13.619026 | L26: =K26/Inputs!$E$3*100 -> 2.2698377 | N26: Project CoD + 8 years + 1 day | O26: =$K26-SUMIFS(Working!$E$303:$BL$303,Working!$E$2:$BL$2,S26) -> 12.753917 | P26: =O26/Inputs!$E$3*100 -> 2.1256528 | R26: =K26-O26 -> 0.86510933 | S26: =EOMONTH(S25,6) -> 48304 | U26: ="FY "&RIGHT(V26,2) -> FY 32 | V26: 2032 | W26: 3
B27: Tariff Assumptions | F27: Park Infrastructure Cost Breakup | G27: Share | J27: Project CoD + 8.5 years + 1 day | K27: =SUMIFS(Working!$E$413:$BL$413,Working!$E$2:$BL$2,S27)-SUMIFS(Working!$E$408:$BL$408,Working!$E$2:$BL$2,S27) -> 13.506039 | L27: =K27/Inputs!$E$3*100 -> 2.2510065 | N27: Project CoD + 8.5 years + 1 day | O27: =$K27-SUMIFS(Working!$E$303:$BL$303,Working!$E$2:$BL$2,S27) -> 12.619566 | P27: =O27/Inputs!$E$3*100 -> 2.1032609 | R27: =K27-O27 -> 0.88647327 | S27: =EOMONTH(S26,6) -> 48487 | U27: ="FY "&RIGHT(V27,2) -> FY 32 | V27: 2032 | W27: 3
B28: =Inputs!E94 -> Option2 | D28: Yearly Tariff | F28: Land | G28: =H5/$H$14 -> 0.0053019696 | J28: Project CoD + 9 years + 1 day | K28: =SUMIFS(Working!$E$413:$BL$413,Working!$E$2:$BL$2,S28)-SUMIFS(Working!$E$408:$BL$408,Working!$E$2:$BL$2,S28) -> 13.394998 | L28: =K28/Inputs!$E$3*100 -> 2.2324997 | N28: Project CoD + 9 years + 1 day | O28: =$K28-SUMIFS(Working!$E$303:$BL$303,Working!$E$2:$BL$2,S28) -> 12.486634 | P28: =O28/Inputs!$E$3*100 -> 2.0811056 | R28: =K28-O28 -> 0.90836479 | S28: =EOMONTH(S27,6) -> 48669 | U28: ="FY "&RIGHT(V28,2) -> FY 33 | V28: 2033 | W28: 3
F29: Road, Building & other civil | G29: =H6/$H$14 -> 0.079118828 | J29: Project CoD + 9.5 years + 1 day | K29: =SUMIFS(Working!$E$413:$BL$413,Working!$E$2:$BL$2,S29)-SUMIFS(Working!$E$408:$BL$408,Working!$E$2:$BL$2,S29) -> 13.285944 | L29: =K29/Inputs!$E$3*100 -> 2.214324 | N29: Project CoD + 9.5 years + 1 day | O29: =$K29-SUMIFS(Working!$E$303:$BL$303,Working!$E$2:$BL$2,S29) -> 12.355147 | P29: =O29/Inputs!$E$3*100 -> 2.0591912 | R29: =K29-O29 -> 0.93079693 | S29: =EOMONTH(S28,6) -> 48852 | U29: ="FY "&RIGHT(V29,2) -> FY 33 | V29: 2033 | W29: 3
B30: COD Date | D30: 45139 | F30: Sub-station | G30: =H7/$H$14 -> 0.36342761 | J30: Project CoD + 10 years + 1 day | K30: =SUMIFS(Working!$E$413:$BL$413,Working!$E$2:$BL$2,S30)-SUMIFS(Working!$E$408:$BL$408,Working!$E$2:$BL$2,S30) -> 13.178915 | L30: =K30/Inputs!$E$3*100 -> 2.1964858 | N30: Project CoD + 10 years + 1 day | O30: =$K30-SUMIFS(Working!$E$303:$BL$303,Working!$E$2:$BL$2,S30) -> 12.225132 | P30: =O30/Inputs!$E$3*100 -> 2.037522 | R30: =K30-O30 -> 0.95378303 | S30: =EOMONTH(S29,6) -> 49034 | U30: ="FY "&RIGHT(V30,2) -> FY 34 | V30: 2034 | W30: 3
F31: Transmission | G31: =H8/$H$14 -> 0.32457762 | J31: Project CoD + 10.5 years + 1 day | K31: =SUMIFS(Working!$E$413:$BL$413,Working!$E$2:$BL$2,S31)-SUMIFS(Working!$E$408:$BL$408,Working!$E$2:$BL$2,S31) -> 13.073953 | L31: =K31/Inputs!$E$3*100 -> 2.1789921 | N31: Project CoD + 10.5 years + 1 day | O31: =$K31-SUMIFS(Working!$E$303:$BL$303,Working!$E$2:$BL$2,S31) -> 12.096616 | P31: =O31/Inputs!$E$3*100 -> 2.0161026 | R31: =K31-O31 -> 0.97733678 | S31: =EOMONTH(S30,6) -> 49217 | U31: ="FY "&RIGHT(V31,2) -> FY 34 | V31: 2034 | W31: 3
F32: Other Costs | G32: =H9/$H$14 -> 0.19622888 | J32: Project CoD + 11 years + 1 day | K32: =SUMIFS(Working!$E$413:$BL$413,Working!$E$2:$BL$2,S32)-SUMIFS(Working!$E$408:$BL$408,Working!$E$2:$BL$2,S32) -> 12.971098 | L32: =K32/Inputs!$E$3*100 -> 2.1618497 | N32: Project CoD + 11 years + 1 day | O32: =$K32-SUMIFS(Working!$E$303:$BL$303,Working!$E$2:$BL$2,S32) -> 11.969626 | P32: =O32/Inputs!$E$3*100 -> 1.9949376 | R32: =K32-O32 -> 1.0014722 | S32: =EOMONTH(S31,6) -> 49399 | U32: ="FY "&RIGHT(V32,2) -> FY 35 | V32: 2035 | W32: 3
F33: Contingency & Insurance Charges | G33: =H11/$H$14 -> 0.028395407 | J33: Project CoD + 11.5 years + 1 day | K33: =SUMIFS(Working!$E$413:$BL$413,Working!$E$2:$BL$2,S33)-SUMIFS(Working!$E$408:$BL$408,Working!$E$2:$BL$2,S33) -> 12.870394 | L33: =K33/Inputs!$E$3*100 -> 2.1450656 | N33: Project CoD + 11.5 years + 1 day | O33: =$K33-SUMIFS(Working!$E$303:$BL$303,Working!$E$2:$BL$2,S33) -> 11.84419 | P33: =O33/Inputs!$E$3*100 -> 1.9740317 | R33: =K33-O33 -> 1.0262036 | S33: =EOMONTH(S32,6) -> 49582 | U33: ="FY "&RIGHT(V33,2) -> FY 35 | V33: 2035 | W33: 3
F34: Total | G34: =SUM(G28:G33) -> 0.99705031 | J34: Project CoD + 12 years + 1 day | K34: =SUMIFS(Working!$E$413:$BL$413,Working!$E$2:$BL$2,S34)-SUMIFS(Working!$E$408:$BL$408,Working!$E$2:$BL$2,S34) -> 12.771883 | L34: =K34/Inputs!$E$3*100 -> 2.1286471 | N34: Project CoD + 12 years + 1 day | O34: =$K34-SUMIFS(Working!$E$303:$BL$303,Working!$E$2:$BL$2,S34) -> 11.720337 | P34: =O34/Inputs!$E$3*100 -> 1.9533895 | R34: =K34-O34 -> 1.0515458 | S34: =EOMONTH(S33,6) -> 49765 | U34: ="FY "&RIGHT(V34,2) -> FY 36 | V34: 2036 | W34: 3
F35: IDC | G35: =H13/$H$14 -> 0.0028750117 | J35: Project CoD + 12.5 years + 1 day | K35: =SUMIFS(Working!$E$413:$BL$413,Working!$E$2:$BL$2,S35)-SUMIFS(Working!$E$408:$BL$408,Working!$E$2:$BL$2,S35) -> 12.675609 | L35: =K35/Inputs!$E$3*100 -> 2.1126016 | N35: Project CoD + 12.5 years + 1 day | O35: =$K35-SUMIFS(Working!$E$303:$BL$303,Working!$E$2:$BL$2,S35) -> 11.598096 | P35: =O35/Inputs!$E$3*100 -> 1.9330159 | R35: =K35-O35 -> 1.0775138 | S35: =EOMONTH(S34,6) -> 49948 | U35: ="FY "&RIGHT(V35,2) -> FY 36 | V35: 2036 | W35: 3
F36: Grand Total | G36: =H14/$H$14 -> 1 | J36: Project CoD + 13 years + 1 day | K36: =SUMIFS(Working!$E$413:$BL$413,Working!$E$2:$BL$2,S36)-SUMIFS(Working!$E$408:$BL$408,Working!$E$2:$BL$2,S36) -> 12.581618 | L36: =K36/Inputs!$E$3*100 -> 2.0969364 | N36: Project CoD + 13 years + 1 day | O36: =$K36-SUMIFS(Working!$E$303:$BL$303,Working!$E$2:$BL$2,S36) -> 11.477495 | P36: =O36/Inputs!$E$3*100 -> 1.9129159 | R36: =K36-O36 -> 1.1041231 | S36: =EOMONTH(S35,6) -> 50130 | U36: ="FY "&RIGHT(V36,2) -> FY 37 | V36: 2037 | W36: 3
J37: Project CoD + 13.5 years + 1 day | K37: =SUMIFS(Working!$E$413:$BL$413,Working!$E$2:$BL$2,S37)-SUMIFS(Working!$E$408:$BL$408,Working!$E$2:$BL$2,S37) -> 13.405535 | L37: =K37/Inputs!$E$3*100 -> 2.2342559 | N37: Project CoD + 13.5 years + 1 day | O37: =$K37-SUMIFS(Working!$E$303:$BL$303,Working!$E$2:$BL$2,S37) -> 12.274146 | P37: =O37/Inputs!$E$3*100 -> 2.0456909 | R37: =K37-O37 -> 1.1313895 | S37: =EOMONTH(S36,6) -> 50313 | U37: ="FY "&RIGHT(V37,2) -> FY 37 | V37: 2037 | W37: 3
F38: Other Charges - Breakup | G38: Rs Crore | H38: Rs Lakh per MW | J38: Project CoD + 14 years + 1 day | K38: =SUMIFS(Working!$E$413:$BL$413,Working!$E$2:$BL$2,S38)-SUMIFS(Working!$E$408:$BL$408,Working!$E$2:$BL$2,S38) -> 13.267436 | L38: =K38/Inputs!$E$3*100 -> 2.2112393 | N38: Project CoD + 14 years + 1 day | O38: =$K38-SUMIFS(Working!$E$303:$BL$303,Working!$E$2:$BL$2,S38) -> 12.108107 | P38: =O38/Inputs!$E$3*100 -> 2.0180178 | R38: =K38-O38 -> 1.1593292 | S38: =EOMONTH(S37,6) -> 50495 | U38: ="FY "&RIGHT(V38,2) -> FY 38 | V38: 2038 | W38: 3
F39: PMC Cost - Transmission | G39: =Capex!I35/100 -> 17.689163 | H39: =Capex!J35 -> 2.95 | J39: Project CoD + 14.5 years + 1 day | K39: =SUMIFS(Working!$E$413:$BL$413,Working!$E$2:$BL$2,S39)-SUMIFS(Working!$E$408:$BL$408,Working!$E$2:$BL$2,S39) -> 13.183174 | L39: =K39/Inputs!$E$3*100 -> 2.1971957 | N39: Project CoD + 14.5 years + 1 day | O39: =$K39-SUMIFS(Working!$E$303:$BL$303,Working!$E$2:$BL$2,S39) -> 11.995215 | P39: =O39/Inputs!$E$3*100 -> 1.9992025 | R39: =K39-O39 -> 1.187959 | S39: =EOMONTH(S38,6) -> 50678 | U39: ="FY "&RIGHT(V39,2) -> FY 38 | V39: 2038 | W39: 3
F40: PMC charges to MPUVNL - Upfront | G40: =Capex!I36/100 -> 0 | H40: =Capex!J40 -> 0.07 | J40: Project CoD + 15 years + 1 day | K40: =SUMIFS(Working!$E$413:$BL$413,Working!$E$2:$BL$2,S40)-SUMIFS(Working!$E$408:$BL$408,Working!$E$2:$BL$2,S40) -> 13.098643 | L40: =K40/Inputs!$E$3*100 -> 2.1831071 | N40: Project CoD + 15 years + 1 day | O40: =$K40-SUMIFS(Working!$E$303:$BL$303,Working!$E$2:$BL$2,S40) -> 11.881347 | P40: =O40/Inputs!$E$3*100 -> 1.9802245 | R40: =K40-O40 -> 1.2172957 | S40: =EOMONTH(S39,6) -> 50860 | U40: ="FY "&RIGHT(V40,2) -> FY 39 | V40: 2039 | W40: 3
F41: Local Area development charges | G41: =Capex!I37/100 -> 12 | H41: =Capex!J41 -> 0.12 | J41: Project CoD + 15.5 years + 1 day | K41: =SUMIFS(Working!$E$413:$BL$413,Working!$E$2:$BL$2,S41)-SUMIFS(Working!$E$408:$BL$408,Working!$E$2:$BL$2,S41) -> 6.4447953 | L41: =K41/Inputs!$E$3*100 -> 1.0741326 | N41: Project CoD + 15.5 years + 1 day | O41: =$K41-SUMIFS(Working!$E$303:$BL$303,Working!$E$2:$BL$2,S41) -> 5.1974384 | P41: =O41/Inputs!$E$3*100 -> 0.86623974 | R41: =K41-O41 -> 1.2473569 | S41: =EOMONTH(S40,6) -> 51043 | U41: ="FY "&RIGHT(V41,2) -> FY 39 | V41: 2039 | W41: 3
F42: Registration Cost | G42: =Capex!I38/100 -> 6 | H42: =Capex!J42 -> 2.5 | J42: Project CoD + 16 years + 1 day | K42: =SUMIFS(Working!$E$413:$BL$413,Working!$E$2:$BL$2,S42)-SUMIFS(Working!$E$408:$BL$408,Working!$E$2:$BL$2,S42) -> 7.101025 | L42: =K42/Inputs!$E$3*100 -> 1.1835042 | N42: Project CoD + 16 years + 1 day | O42: =$K42-SUMIFS(Working!$E$303:$BL$303,Working!$E$2:$BL$2,S42) -> 5.8228645 | P42: =O42/Inputs!$E$3*100 -> 0.97047742 | R42: =K42-O42 -> 1.2781605 | S42: =EOMONTH(S41,6) -> 51226 | U42: ="FY "&RIGHT(V42,2) -> FY 40 | V42: 2040 | W42: 3
F43: PSF Fees - IREDA | G43: =Capex!I39/100 -> 0 | H43: =Capex!J43 -> 1.08 | J43: Project CoD + 16.5 years + 1 day | K43: =SUMIFS(Working!$E$413:$BL$413,Working!$E$2:$BL$2,S43)-SUMIFS(Working!$E$408:$BL$408,Working!$E$2:$BL$2,S43) -> 7.2138322 | L43: =K43/Inputs!$E$3*100 -> 1.2023054 | N43: Project CoD + 16.5 years + 1 day | O43: =$K43-SUMIFS(Working!$E$303:$BL$303,Working!$E$2:$BL$2,S43) -> 5.9041074 | P43: =O43/Inputs!$E$3*100 -> 0.98401791 | R43: =K43-O43 -> 1.3097248 | S43: =EOMONTH(S42,6) -> 51409 | U43: ="FY "&RIGHT(V43,2) -> FY 40 | V43: 2040 | W43: 3
F44: Financing costs | G44: =Capex!I40/100 -> 0.40387843 | H44: =Capex!J44 -> 0.8 | J44: Project CoD + 17 years + 1 day | K44: =SUMIFS(Working!$E$413:$BL$413,Working!$E$2:$BL$2,S44)-SUMIFS(Working!$E$408:$BL$408,Working!$E$2:$BL$2,S44) -> 7.3532128 | L44: =K44/Inputs!$E$3*100 -> 1.2255355 | N44: Project CoD + 17 years + 1 day | O44: =$K44-SUMIFS(Working!$E$303:$BL$303,Working!$E$2:$BL$2,S44) -> 6.0111443 | P44: =O44/Inputs!$E$3*100 -> 1.0018574 | R44: =K44-O44 -> 1.3420685 | S44: =EOMONTH(S43,6) -> 51591 | U44: ="FY "&RIGHT(V44,2) -> FY 41 | V44: 2041 | W44: 3
F45: ESIA Charges | G45: =Capex!I41/100 -> 0.693 | H45: =Capex!J45 -> 0.06 | J45: Project CoD + 17.5 years + 1 day | K45: =SUMIFS(Working!$E$413:$BL$413,Working!$E$2:$BL$2,S45)-SUMIFS(Working!$E$408:$BL$408,Working!$E$2:$BL$2,S45) -> 7.494278 | L45: =K45/Inputs!$E$3*100 -> 1.2490463 | N45: Project CoD + 17.5 years + 1 day | O45: =$K45-SUMIFS(Working!$E$303:$BL$303,Working!$E$2:$BL$2,S45) -> 6.119067 | P45: =O45/Inputs!$E$3*100 -> 1.0198445 | R45: =K45-O45 -> 1.375211 | S45: =EOMONTH(S44,6) -> 51774 | U45: ="FY "&RIGHT(V45,2) -> FY 41 | V45: 2041 | W45: 3
F46: RAP Cost | G46: =Capex!I42/100 -> 15 | H46: =Capex!J42 -> 2.5 | J46: Project CoD + 18 years + 1 day | K46: =SUMIFS(Working!$E$413:$BL$413,Working!$E$2:$BL$2,S46)-SUMIFS(Working!$E$408:$BL$408,Working!$E$2:$BL$2,S46) -> 7.6381746 | L46: =K46/Inputs!$E$3*100 -> 1.2730291 | N46: Project CoD + 18 years + 1 day | O46: =$K46-SUMIFS(Working!$E$303:$BL$303,Working!$E$2:$BL$2,S46) -> 6.2290027 | P46: =O46/Inputs!$E$3*100 -> 1.0381671 | R46: =K46-O46 -> 1.4091719 | S46: =EOMONTH(S45,6) -> 51956 | U46: ="FY "&RIGHT(V46,2) -> FY 42 | V46: 2042 | W46: 3
F47: ESMP Cost | G47: =Capex!I43/100 -> 6.4998 | H47: =Capex!J43 -> 1.08 | J47: Project CoD + 18.5 years + 1 day | K47: =SUMIFS(Working!$E$413:$BL$413,Working!$E$2:$BL$2,S47)-SUMIFS(Working!$E$408:$BL$408,Working!$E$2:$BL$2,S47) -> 7.784911 | L47: =K47/Inputs!$E$3*100 -> 1.2974852 | N47: Project CoD + 18.5 years + 1 day | O47: =$K47-SUMIFS(Working!$E$303:$BL$303,Working!$E$2:$BL$2,S47) -> 6.3409394 | P47: =O47/Inputs!$E$3*100 -> 1.0568232 | R47: =K47-O47 -> 1.4439715 | S47: =EOMONTH(S46,6) -> 52139 | U47: ="FY "&RIGHT(V47,2) -> FY 42 | V47: 2042 | W47: 3
F48: Pre operative expenses | G48: =SUM(G49:G56) -> 4.7805794 | H48: =SUM(H49:H56) -> 0.79 | J48: Project CoD + 19 years + 1 day | K48: =SUMIFS(Working!$E$413:$BL$413,Working!$E$2:$BL$2,S48)-SUMIFS(Working!$E$408:$BL$408,Working!$E$2:$BL$2,S48) -> 7.9345467 | L48: =K48/Inputs!$E$3*100 -> 1.3224245 | N48: Project CoD + 19 years + 1 day | O48: =$K48-SUMIFS(Working!$E$303:$BL$303,Working!$E$2:$BL$2,S48) -> 6.4549162 | P48: =O48/Inputs!$E$3*100 -> 1.0758194 | R48: =K48-O48 -> 1.4796305 | S48: =EOMONTH(S47,6) -> 52321 | U48: ="FY "&RIGHT(V48,2) -> FY 43 | V48: 2043 | W48: 3
F49: Construction Power | G49: =Capex!I45/100 -> 0.3838 | H49: =Capex!J45 -> 0.06 | J49: Project CoD + 19.5 years + 1 day | K49: =SUMIFS(Working!$E$413:$BL$413,Working!$E$2:$BL$2,S49)-SUMIFS(Working!$E$408:$BL$408,Working!$E$2:$BL$2,S49) -> 8.0871404 | L49: =K49/Inputs!$E$3*100 -> 1.3478567 | N49: Project CoD + 19.5 years + 1 day | O49: =$K49-SUMIFS(Working!$E$303:$BL$303,Working!$E$2:$BL$2,S49) -> 6.5709703 | P49: =O49/Inputs!$E$3*100 -> 1.0951617 | R49: =K49-O49 -> 1.5161701 | S49: =EOMONTH(S48,6) -> 52504 | U49: ="FY "&RIGHT(V49,2) -> FY 43 | V49: 2043 | W49: 3
F50: Construction Power | G50: =Capex!I46/100 -> 0.84656 | H50: =Capex!J46 -> 0.14 | J50: Project CoD + 20 years + 1 day | K50: =SUMIFS(Working!$E$413:$BL$413,Working!$E$2:$BL$2,S50)-SUMIFS(Working!$E$408:$BL$408,Working!$E$2:$BL$2,S50) -> 8.2427518 | L50: =K50/Inputs!$E$3*100 -> 1.373792 | N50: Project CoD + 20 years + 1 day | O50: =$K50-SUMIFS(Working!$E$303:$BL$303,Working!$E$2:$BL$2,S50) -> 6.6891397 | P50: =O50/Inputs!$E$3*100 -> 1.1148566 | R50: =K50-O50 -> 1.5536121 | S50: =EOMONTH(S49,6) -> 52687 | U50: ="FY "&RIGHT(V50,2) -> FY 44 | V50: 2044 | W50: 3
F51: Independent Engineer Fee | G51: =Capex!I47/100 -> 0.24 | H51: =Capex!J47 -> 0.04 | J51: Project CoD + 20.5 years + 1 day | K51: =SUMIFS(Working!$E$413:$BL$413,Working!$E$2:$BL$2,S51)-SUMIFS(Working!$E$408:$BL$408,Working!$E$2:$BL$2,S51) -> 8.401442 | L51: =K51/Inputs!$E$3*100 -> 1.4002403 | N51: Project CoD + 20.5 years + 1 day | O51: =$K51-SUMIFS(Working!$E$303:$BL$303,Working!$E$2:$BL$2,S51) -> 6.8094634 | P51: =O51/Inputs!$E$3*100 -> 1.1349106 | R51: =K51-O51 -> 1.5919786 | S51: =EOMONTH(S50,6) -> 52870 | U51: ="FY "&RIGHT(V51,2) -> FY 44 | V51: 2044 | W51: 3
F52: Legal Charges | G52: =Capex!I48/100 -> 0.15 | H52: =Capex!J48 -> 0.03 | J52: Project CoD + 21 years + 1 day | K52: =SUMIFS(Working!$E$413:$BL$413,Working!$E$2:$BL$2,S52)-SUMIFS(Working!$E$408:$BL$408,Working!$E$2:$BL$2,S52) -> 8.5632733 | L52: =K52/Inputs!$E$3*100 -> 1.4272122 | N52: Project CoD + 21 years + 1 day | O52: =$K52-SUMIFS(Working!$E$303:$BL$303,Working!$E$2:$BL$2,S52) -> 6.9319806 | P52: =O52/Inputs!$E$3*100 -> 1.1553301 | R52: =K52-O52 -> 1.6312927 | S52: =EOMONTH(S51,6) -> 53052 | U52: ="FY "&RIGHT(V52,2) -> FY 45 | V52: 2045 | W52: 3
F53: Connectivity Charges | G53: =Capex!I49/100 -> 0.25 | H53: =Capex!J49 -> 0.04 | J53: Project CoD + 21.5 years + 1 day | K53: =SUMIFS(Working!$E$413:$BL$413,Working!$E$2:$BL$2,S53)-SUMIFS(Working!$E$408:$BL$408,Working!$E$2:$BL$2,S53) -> 8.7283094 | L53: =K53/Inputs!$E$3*100 -> 1.4547182 | N53: Project CoD + 21.5 years + 1 day | O53: =$K53-SUMIFS(Working!$E$303:$BL$303,Working!$E$2:$BL$2,S53) -> 7.0567318 | P53: =O53/Inputs!$E$3*100 -> 1.176122 | R53: =K53-O53 -> 1.6715776 | S53: =EOMONTH(S52,6) -> 53235 | U53: ="FY "&RIGHT(V53,2) -> FY 45 | V53: 2045 | W53: 3
F54: Regulatory Filing Charges | G54: =Capex!I50/100 -> 0.35 | H54: =Capex!J50 -> 0.06 | J54: Project CoD + 22 years + 1 day | K54: =SUMIFS(Working!$E$413:$BL$413,Working!$E$2:$BL$2,S54)-SUMIFS(Working!$E$408:$BL$408,Working!$E$2:$BL$2,S54) -> 8.8966151 | L54: =K54/Inputs!$E$3*100 -> 1.4827692 | N54: Project CoD + 22 years + 1 day | O54: =$K54-SUMIFS(Working!$E$303:$BL$303,Working!$E$2:$BL$2,S54) -> 7.1837578 | P54: =O54/Inputs!$E$3*100 -> 1.197293 | R54: =K54-O54 -> 1.7128573 | S54: =EOMONTH(S53,6) -> 53417 | U54: ="FY "&RIGHT(V54,2) -> FY 46 | V54: 2046 | W54: 3
F55: DPR Preparation | G55: =Capex!I51/100 -> 0.50701935 | H55: =Capex!J51 -> 0.08 | J55: Project CoD + 22.5 years + 1 day | K55: =SUMIFS(Working!$E$413:$BL$413,Working!$E$2:$BL$2,S55)-SUMIFS(Working!$E$408:$BL$408,Working!$E$2:$BL$2,S55) -> 9.0682569 | L55: =K55/Inputs!$E$3*100 -> 1.5113761 | N55: Project CoD + 22.5 years + 1 day | O55: =$K55-SUMIFS(Working!$E$303:$BL$303,Working!$E$2:$BL$2,S55) -> 7.3131004 | P55: =O55/Inputs!$E$3*100 -> 1.2188501 | R55: =K55-O55 -> 1.7551564 | S55: =EOMONTH(S54,6) -> 53600 | U55: ="FY "&RIGHT(V55,2) -> FY 46 | V55: 2046 | W55: 3
F56: TA Consultancy Charges | G56: =Capex!I52/100 -> 2.0532 | H56: =Capex!J52 -> 0.34 | J56: Project CoD + 23 years + 1 day | K56: =SUMIFS(Working!$E$413:$BL$413,Working!$E$2:$BL$2,S56)-SUMIFS(Working!$E$408:$BL$408,Working!$E$2:$BL$2,S56) -> 9.2433023 | L56: =K56/Inputs!$E$3*100 -> 1.5405504 | N56: Project CoD + 23 years + 1 day | O56: =$K56-SUMIFS(Working!$E$303:$BL$303,Working!$E$2:$BL$2,S56) -> 7.4448021 | P56: =O56/Inputs!$E$3*100 -> 1.2408003 | R56: =K56-O56 -> 1.7985002 | S56: =EOMONTH(S55,6) -> 53782 | U56: ="FY "&RIGHT(V56,2) -> FY 47 | V56: 2047 | W56: 3
F57: Other Charges Total | G57: =SUM(G39:G48) -> 63.066421 | H57: =Capex!J53 -> 10.52 | J57: Project CoD + 23.5 years + 1 day | K57: =SUMIFS(Working!$E$413:$BL$413,Working!$E$2:$BL$2,S57)-SUMIFS(Working!$E$408:$BL$408,Working!$E$2:$BL$2,S57) -> 9.4218203 | L57: =K57/Inputs!$E$3*100 -> 1.5703034 | N57: Project CoD + 23.5 years + 1 day | O57: =$K57-SUMIFS(Working!$E$303:$BL$303,Working!$E$2:$BL$2,S57) -> 7.5789061 | P57: =O57/Inputs!$E$3*100 -> 1.263151 | R57: =K57-O57 -> 1.8429143 | S57: =EOMONTH(S56,6) -> 53965 | U57: ="FY "&RIGHT(V57,2) -> FY 47 | V57: 2047 | W57: 3
J58: Project CoD + 24 years + 1 day | K58: =SUMIFS(Working!$E$413:$BL$413,Working!$E$2:$BL$2,S58)-SUMIFS(Working!$E$408:$BL$408,Working!$E$2:$BL$2,S58) -> 9.6038816 | L58: =K58/Inputs!$E$3*100 -> 1.6006469 | N58: Project CoD + 24 years + 1 day | O58: =$K58-SUMIFS(Working!$E$303:$BL$303,Working!$E$2:$BL$2,S58) -> 7.7154564 | P58: =O58/Inputs!$E$3*100 -> 1.2859094 | R58: =K58-O58 -> 1.8884252 | S58: =EOMONTH(S57,6) -> 54148 | U58: ="FY "&RIGHT(V58,2) -> FY 48 | V58: 2048 | W58: 3
F59: Annual Charges | G59: Rs Crore | H59: Rs Lakh per MW | J59: Project CoD + 24.5 years + 1 day | K59: =SUMIFS(Working!$E$413:$BL$413,Working!$E$2:$BL$2,S59)-SUMIFS(Working!$E$408:$BL$408,Working!$E$2:$BL$2,S59) -> 9.789558 | L59: =K59/Inputs!$E$3*100 -> 1.631593 | N59: Project CoD + 24.5 years + 1 day | O59: =$K59-SUMIFS(Working!$E$303:$BL$303,Working!$E$2:$BL$2,S59) -> 7.854498 | P59: =O59/Inputs!$E$3*100 -> 1.309083 | R59: =K59-O59 -> 1.93506 | S59: =EOMONTH(S58,6) -> 54331 | U59: ="FY "&RIGHT(V59,2) -> FY 48 | V59: 2048 | W59: 3
F60: O&M Total | G60: =SUM(Working!E307:BL307) -> 321.23716 | H60: =G60*100/$D$5 -> 53.539527 | J60: Project CoD + 25 years | K60: =SUMIFS(Working!$E$413:$BL$413,Working!$E$2:$BL$2,S60)-SUMIFS(Working!$E$408:$BL$408,Working!$E$2:$BL$2,S60) -> 0 | L60: =K60/Inputs!$E$3*100 -> 0 | N60: Project CoD + 25 years | O60: =$K60-SUMIFS(Working!$E$303:$BL$303,Working!$E$2:$BL$2,S60) -> 0 | P60: =O60/Inputs!$E$3*100 -> 0 | R60: =K60-O60 -> 0 | S60: =EOMONTH(S59,6) -> 54513 | U60: ="FY "&RIGHT(V60,2) -> FY 49 | V60: 2049 | W60: 3
F61: MPUVNL Charges - Deferred | G61: =SUM(Working!E313:BL313) -> 0 | H61: =G61*100/$D$5 -> 0
G63: Check
G64: =G12-Capex!I59/100 -> 0
G65: =G22-SUM(K5:K8) -> 0
G66: =G57-G9 -> 0
G67: =Working!D312-Working!D313 -> 0
B72: Particulars | C72: Formula | D72: Rs Crore | F72: Roads | G72: kM
B73: Project Cost eligible for subsidy | C73: a | D73: =G14 -> 329.69667 | F73: Saktapur S/S | G73: =Capex!D66+Capex!D67 -> 6.5 | H73: 1.1 | I73: =G73*H73 -> 7.15
B74: Subsidy computation | F74: Chitramod S/S | G74: =Capex!D68+Capex!D69 -> 2.25 | H74: 1.1 | I74: =G74*H74 -> 2.475
B75: 30% of Project Cost | C75: b = 30%*a | D75: =D73*30% -> 98.909002 | F75: Total | G75: =SUM(G73:G74) -> 8.75 | I75: =SUM(I73:I74) -> 9.625
B76: Subsidy @ 20 Lakhs per MW | C76: c = 0.2*600 | D76: =0.2*600 -> 120 | F76: Gunjari Assembly | G76: =Capex!D74 -> 1 | H76: 0.75 | I76: =ROUND(G76*H76,3) -> 0.75
B77: Applicable Subsidy | C77: d = Min (b, c) | D77: =MIN(D75:D76) -> 98.909002 | F77: Bilaya | G77: =Capex!D75 -> 9 | H77: 0.75 | I77: =ROUND(G77*H77,3) -> 6.75
F78: Indhawadi | G78: =Capex!D73 -> 9 | H78: 0.75 | I78: =ROUND(G78*H78,3) -> 6.75
F79: Saktapur | G79: =Capex!D72 -> 1.8 | H79: 0.75 | I79: =ROUND(G79*H79,3) -> 1.35
F80: Total | G80: =SUM(G76:G79) -> 20.8 | I80: =SUM(I76:I79) -> 15.6
F81: Grand total | G81: =G80+G75 -> 29.55 | I81: =I80+I75 -> 25.225
F83: Land - Government Parcel
F84: Saktapur | G84: =Capex!D81+Capex!D88 -> 29.179 | H84: =Inputs!E133*10^5 -> 280000 | I84: =G84*H84/10^5 -> 81.7012
F85: Chitramod | G85: =Capex!D83+Capex!D90 -> 28.449 | H85: =Inputs!E134*10^5 -> 300000 | I85: =G85*H85/10^5 -> 85.347
F86: Others (Bilaya, Indhawadi) | G86: =Capex!D92+Capex!D94 -> 1.242 | H86: =Inputs!E135*10^5 -> 280000 | I86: =G86*H86/10^5 -> 3.4776
F87: Sub-Total | G87: =SUM(G84:G86) -> 58.87 | I87: =SUM(I84:I86) -> 170.5258
F89: PMC Charges
F90: MPUVNL | G90: =Capex!I61*Inputs!E15/100 -> 0
F91: Upfront | G91: =Inputs!E16*G90 -> 0
F92: Remaining | G92: =G90-G91 -> 0
F94: Items | G94: Unit | H94: Chitramod | I94: Saktapur
F95: 220 kV Transmission Line (D/C) - Zebra | G95: kM | H95: =IF(Inputs!$H$2=2,Inputs!C139+Inputs!C141,0) -> 0 | I95: =IF(Inputs!$H$2=1,Inputs!C138+Inputs!C140,0) -> 0
F96: 33/220 kV, 100 MVA Power Transformer | G96: No. | H96: =Inputs!D122 -> 4 | I96: =Inputs!E122 -> 4
F97: 33 kV Incomer Bay (25 MW) | G97: No. | H97: =Inputs!D123 -> 14 | I97: =Inputs!E123 -> 14
F98: 33 kV Transformer bay | G98: No. | H98: =Inputs!D124 -> 4 | I98: =Inputs!E124 -> 4
F99: 220kV Power Transformer bay | G99: No | H99: =Inputs!D125 -> 4 | I99: =Inputs!E125 -> 4
F100: 220 kV Line Bay+ Bus Section Bay | G100: No. | H100: =Inputs!D126 -> 2 | I100: =Inputs!E126 -> 2
F101: Control & Communication | G101: No. | H101: =Inputs!D128 -> 1 | I101: =Inputs!E128 -> 1
F103: Line Items | G103: Units | H103: Unit Cost (Rs Lakhs) | I103: Base Cost (Rs Lakhs)
F104: Chitramod S/S | G104: 1 | H104: =Capex!$I$26/2 -> 5840 | I104: =G104*H104 -> 5840
F105: Saktapur S/S | G105: 1 | H105: =Capex!$I$26/2 -> 5840 | I105: =G105*H105 -> 5840
F106: Chitramod -Common Point – 220 kV DC-SC (Panther) line | G106: =Capex!D105*2&" Ckt kM" -> 23.266 Ckt kM | H106: =I106/(Capex!D105*2) -> 66.46535 | I106: =Capex!I105 -> 1546.3828
F107: Saktapur – Common Point – 220 kV DC-SC (Panther) line | G107: =Capex!D106*2&" Ckt kM" -> 51.082 Ckt kM | H107: =I107/(Capex!D106*2) -> 66.187405 | I107: =Capex!I106 -> 3380.985
F108: Common Point – Khandwa – 220 kV MC-SC (Panther) line | G108: =Capex!D107*4&" Ckt kM" -> 115.644 Ckt kM | H108: =I108/(Capex!D107*4) -> 33.323166 | I108: =Capex!I107 -> 3853.6243
F109: ROW Compensation | G109: =Capex!D109&" Ckt kM" -> 66.085 Ckt kM | H109: =I109/(Capex!D109) -> 7.4449573 | I109: 492
...

Sheet Interest Rate Assessment
F1: 0.095
C2: Upfront Charges Assessment | D2: Unit | E2: Total Value | F2: Net Present Value | G2: Execution Date for ISA + 0.5 month | H2: Execution Date for ISA + 6 month | I2: Execution Date for ISA + 12 months | J2: Project CoD + 1 day | K2: Project CoD + 0.5 years + 1 day | L2: Project CoD + 1 years + 1 day | M2: Project CoD + 1.5 years + 1 day | N2: Project CoD + 2 years + 1 day | O2: Project CoD + 2.5 years + 1 day | P2: Project CoD + 3 years + 1 day | Q2: Project CoD + 3.5 years + 1 day | R2: Project CoD + 4 years + 1 day | S2: Project CoD + 4.5 years + 1 day | T2: Project CoD + 5 years + 1 day | U2: Project CoD + 5.5 years + 1 day | V2: Project CoD + 6 years + 1 day | W2: Project CoD + 6.5 years + 1 day | X2: Project CoD + 7 years + 1 day | Y2: Project CoD + 7.5 years + 1 day | Z2: Project CoD + 8 years + 1 day | AA2: Project CoD + 8.5 years + 1 day | AB2: Project CoD + 9 years + 1 day | AC2: Project CoD + 9.5 years + 1 day | AD2: Project CoD + 10 years + 1 day | AE2: Project CoD + 10.5 years + 1 day | AF2: Project CoD + 11 years + 1 day | AG2: Project CoD + 11.5 years + 1 day | AH2: Project CoD + 12 years + 1 day | AI2: Project CoD + 12.5 years + 1 day | AJ2: Project CoD + 13 years + 1 day | AK2: Project CoD + 13.5 years + 1 day | AL2: Project CoD + 14 years + 1 day | AM2: Project CoD + 14.5 years + 1 day | AN2: Project CoD + 15 years + 1 day | AO2: Project CoD + 15.5 years + 1 day | AP2: Project CoD + 16 years + 1 day | AQ2: Project CoD + 16.5 years + 1 day | AR2: Project CoD + 17 years + 1 day | AS2: Project CoD + 17.5 years + 1 day | AT2: Project CoD + 18 years + 1 day | AU2: Project CoD + 18.5 years + 1 day | AV2: Project CoD + 19 years + 1 day | AW2: Project CoD + 19.5 years + 1 day | AX2: Project CoD + 20 years + 1 day | AY2: Project CoD + 20.5 years + 1 day | AZ2: Project CoD + 21 years + 1 day | BA2: Project CoD + 21.5 years + 1 day | BB2: Project CoD + 22 years + 1 day | BC2: Project CoD + 22.5 years + 1 day | BD2: Project CoD + 23 years + 1 day | BE2: Project CoD + 23.5 years + 1 day | BF2: Project CoD + 24 years + 1 day | BG2: Project CoD + 24.5 years + 1 day | BH2: Project CoD + 25 years
B3: A | C3: Base Case | D3: Rs Cr. | E3: =SUM(G3:BH3) -> 663.87665 | F3: =NPV($F$1,G3:BH3) -> 175.60222 | G3: 20.770891 | H3: 24.232706 | I3: 40.040026 | J3: 5.4491489 | K3: 9.8409561 | L3: 21.846455 | M3: 14.955944 | N3: 15.116414 | O3: 14.969877 | P3: 14.838376 | Q3: 14.70785 | R3: 14.578947 | S3: 14.45167 | T3: 14.326055 | U3: 14.212371 | V3: 14.089664 | W3: 13.969293 | X3: 13.85069 | Y3: 13.733922 | Z3: 13.619026 | AA3: 13.506039 | AB3: 13.394998 | AC3: 13.285944 | AD3: 13.178915 | AE3: 13.073953 | AF3: 12.971098 | AG3: 12.870394 | AH3: 12.771883 | AI3: 12.675609 | AJ3: 12.581618 | AK3: 13.405535 | AL3: 13.267436 | AM3: 13.183174 | AN3: 13.098643 | AO3: 6.4447953 | AP3: 7.101025 | AQ3: 7.2138322 | AR3: 7.3532128 | AS3: 7.494278 | AT3: 7.6381746 | AU3: 7.784911 | AV3: 7.9345467 | AW3: 8.0871404 | AX3: 8.2427518 | AY3: 8.401442 | AZ3: 8.5632733 | BA3: 8.7283094 | BB3: 8.8966151 | BC3: 9.0682569 | BD3: 9.2433023 | BE3: 9.4218203 | BF3: 9.6038816 | BG3: 9.789558 | BH3: 0
D4: Rs Lakhs/MW | E4: =SUM(G4:BH4) -> 110.64611 | F4: =NPV($F$1,G4:BH4) -> 29.267036 | G4: 3.4618151 | H4: 4.0387843 | I4: 6.6733377 | J4: 0.90819149 | K4: 1.6401593 | L4: 3.6410759 | M4: 2.4926573 | N4: 2.5194024 | O4: 2.4949795 | P4: 2.4730627 | Q4: 2.4513084 | R4: 2.4298244 | S4: 2.4086117 | T4: 2.3876758 | U4: 2.3687286 | V4: 2.3482773 | W4: 2.3282155 | X4: 2.3084483 | Y4: 2.2889871 | Z4: 2.2698377 | AA4: 2.2510065 | AB4: 2.2324997 | AC4: 2.214324 | AD4: 2.1964858 | AE4: 2.1789921 | AF4: 2.1618497 | AG4: 2.1450656 | AH4: 2.1286471 | AI4: 2.1126016 | AJ4: 2.0969364 | AK4: 2.2342559 | AL4: 2.2112393 | AM4: 2.1971957 | AN4: 2.1831071 | AO4: 1.0741326 | AP4: 1.1835042 | AQ4: 1.2023054 | AR4: 1.2255355 | AS4: 1.2490463 | AT4: 1.2730291 | AU4: 1.2974852 | AV4: 1.3224245 | AW4: 1.3478567 | AX4: 1.373792 | AY4: 1.4002403 | AZ4: 1.4272122 | BA4: 1.4547182 | BB4: 1.4827692 | BC4: 1.5113761 | BD4: 1.5405504 | BE4: 1.5703034 | BF4: 1.6006469 | BG4: 1.631593 | BH4: 0
B6: B | C6: Interest Rate - 9.5% & A&G - 0.20 lakh/MW | D6: Rs Cr. | E6: =SUM(G6:BH6) -> 687.05542 | F6: =NPV($F$1,G6:BH6) -> 184.0747 | G6: 20.883044 | H6: 24.363551 | I6: 40.327968 | J6: 8.1873064 | K6: 11.005074 | L6: 23.101681 | M6: 16.113413 | N6: 16.235173 | O6: 16.047342 | P6: 15.87466 | Q6: 15.702947 | R6: 15.532858 | S6: 15.364395 | T6: 15.197594 | U6: 15.033469 | V6: 14.870069 | W6: 14.708486 | X6: 14.548698 | Y6: 14.390745 | Z6: 14.234663 | AA6: 14.08049 | AB6: 13.928264 | AC6: 13.778023 | AD6: 13.629809 | AE6: 13.483661 | AF6: 13.33962 | AG6: 13.19773 | AH6: 13.058034 | AI6: 12.920575 | AJ6: 12.785398 | AK6: 13.573042 | AL6: 13.393495 | AM6: 13.268062 | AN6: 13.142344 | AO6: 13.019295 | AP6: 0.99282086 | AQ6: 7.4823382 | AR6: 7.3426565 | AS6: 7.4959404 | AT6: 7.6393083 | AU6: 7.7860738 | AV6: 7.9357143 | AW6: 8.0883139 | AX6: 8.2439311 | AY6: 8.4026272 | AZ6: 8.5644644 | BA6: 8.7295064 | BB6: 8.8978181 | BC6: 9.0694659 | BD6: 9.2445173 | BE6: 9.4230414 | BF6: 9.6051088 | BG6: 9.7907913 | BH6: 0
D7: Rs Lakhs/MW | E7: =SUM(G7:BH7) -> 114.50924 | F7: =NPV($F$1,G7:BH7) -> 30.679117 | G7: 3.4805073 | H7: 4.0605918 | I7: 6.721328 | J7: 1.3645511 | K7: 1.8341791 | L7: 3.8502801 | M7: 2.6855689 | N7: 2.7058622 | O7: 2.674557 | P7: 2.6457766 | Q7: 2.6171579 | R7: 2.5888096 | S7: 2.5607325 | T7: 2.5329323 | U7: 2.5055782 | V7: 2.4783449 | W7: 2.4514143 | X7: 2.424783 | Y7: 2.3984575 | Z7: 2.3724439 | AA7: 2.3467483 | AB7: 2.3213773 | AC7: 2.2963372 | AD7: 2.2716348 | AE7: 2.2472768 | AF7: 2.2232701 | AG7: 2.1996217 | AH7: 2.176339 | AI7: 2.1534291 | AJ7: 2.1308997 | AK7: 2.2621736 | AL7: 2.2322492 | AM7: 2.2113436 | AN7: 2.1903907 | AO7: 2.1698826 | AP7: 0.16547014 | AQ7: 1.2470564 | AR7: 1.2237761 | AS7: 1.2493234 | AT7: 1.273218 | AU7: 1.297679 | AV7: 1.3226191 | AW7: 1.3480523 | AX7: 1.3739885 | AY7: 1.4004379 | AZ7: 1.4274107 | BA7: 1.4549177 | BB7: 1.4829697 | BC7: 1.5115776 | BD7: 1.5407529 | BE7: 1.5705069 | BF7: 1.6008515 | BG7: 1.6317985 | BH7: 0
B9: C | C9: Interest Rate - 9.5% & A&G - 0.1 lakh/MW | D9: Rs Cr. | E9: =SUM(G9:BH9) -> 658.31672 | F9: =NPV($F$1,G9:BH9) -> 180.952 | G9: 20.883044 | H9: 24.363551 | I9: 40.327968 | J9: 7.8594408 | K9: 10.702039 | L9: 22.789571 | M9: 15.793819 | N9: 15.907677 | O9: 15.711758 | P9: 15.530789 | Q9: 15.350585 | R9: 15.171793 | S9: 14.994414 | T9: 14.818476 | U9: 14.644819 | V9: 14.471831 | W9: 14.300412 | X9: 14.130547 | Y9: 13.962268 | Z9: 13.795604 | AA9: 13.630589 | AB9: 13.467252 | AC9: 13.305627 | AD9: 13.145746 | AE9: 12.987644 | AF9: 12.831355 | AG9: 12.676913 | AH9: 12.524355 | AI9: 12.373717 | AJ9: 12.225036 | AK9: 12.998841 | AL9: 12.805114 | AM9: 12.665151 | AN9: 12.524544 | AO9: 12.386239 | AP9: 0.3444124 | AQ9: 6.817905 | AR9: 6.6618155 | AS9: 6.798286 | AT9: 6.9244252 | AU9: 7.0535367 | AV9: 7.1850872 | AW9: 7.3191499 | AX9: 7.4557726 | AY9: 7.595005 | AZ9: 7.7368979 | BA9: 7.8815031 | BB9: 8.0288734 | BC9: 8.1790624 | BD9: 8.3321253 | BE9: 8.4881178 | BF9: 8.6470971 | BG9: 8.8091215 | BH9: 0
D10: Rs Lakhs/MW | E10: =SUM(G10:BH10) -> 109.71945 | F10: =NPV($F$1,G10:BH10) -> 30.158667 | G10: 3.4805073 | H10: 4.0605918 | I10: 6.721328 | J10: 1.3099068 | K10: 1.7836731 | L10: 3.7982619 | M10: 2.6323032 | N10: 2.6512795 | O10: 2.6186264 | P10: 2.5884648 | Q10: 2.5584308 | R10: 2.5286322 | S10: 2.499069 | T10: 2.469746 | U10: 2.4408032 | V10: 2.4119718 | W10: 2.383402 | X10: 2.3550912 | Y10: 2.3270446 | Z10: 2.2992674 | AA10: 2.2717648 | AB10: 2.244542 | AC10: 2.2176045 | AD10: 2.1909577 | AE10: 2.1646074 | AF10: 2.1385592 | AG10: 2.1128189 | AH10: 2.0873925 | AI10: 2.0622861 | AJ10: 2.0375059 | AK10: 2.1664735 | AL10: 2.1341857 | AM10: 2.1108584 | AN10: 2.0874241 | AO10: 2.0643732 | AP10: 0.057402067 | AQ10: 1.1363175 | AR10: 1.1103026 | AS10: 1.1330477 | AT10: 1.1540709 | AU10: 1.1755894 | AV10: 1.1975145 | AW10: 1.2198583 | AX10: 1.2426288 | AY10: 1.2658342 | AZ10: 1.289483 | BA10: 1.3135839 | BB10: 1.3381456 | BC10: 1.3631771 | BD10: 1.3886875 | BE10: 1.4146863 | BF10: 1.4411829 | BG10: 1.4681869 | BH10: 0
B12: D | C12: Interest Rate - 9.5% & A&G - 0.0 lakh/MW | D12: Rs Cr. | E12: =SUM(G12:BH12) -> 629.57803 | F12: =NPV($F$1,G12:BH12) -> 177.8293 | G12: 20.883044 | H12: 24.363551 | I12: 40.327968 | J12: 7.5315753 | K12: 10.399003 | L12: 22.477462 | M12: 15.474225 | N12: 15.58018 | O12: 15.376175 | P12: 15.186918 | Q12: 14.998222 | R12: 14.810729 | S12: 14.624433 | T12: 14.439358 | U12: 14.256169 | V12: 14.073592 | W12: 13.892338 | X12: 13.712396 | Y12: 13.53379 | Z12: 13.356546 | AA12: 13.180687 | AB12: 13.00624 | AC12: 12.83323 | AD12: 12.661684 | AE12: 12.491628 | AF12: 12.32309 | AG12: 12.156096 | AH12: 11.990676 | AI12: 11.826859 | AJ12: 11.664673 | AK12: 12.42464 | AL12: 12.216734 | AM12: 12.06224 | AN12: 11.906745 | AO12: 11.753182 | AP12: -0.30399605 | AQ12: 6.1534717 | AR12: 5.9809746 | AS12: 6.1006316 | AT12: 6.2095422 | AU12: 6.3209996 | AV12: 6.43446 | AW12: 6.5499859 | AX12: 6.667614 | AY12: 6.7873828 | AZ12: 6.9093315 | BA12: 7.0334999 | BB12: 7.1599286 | BC12: 7.288659 | BD12: 7.4197332 | BE12: 7.5531942 | BF12: 7.6890855 | BG12: 7.8274517 | BH12: 0
D13: Rs Lakhs/MW | E13: =SUM(G13:BH13) -> 104.92967 | F13: =NPV($F$1,G13:BH13) -> 29.638217 | G13: 3.4805073 | H13: 4.0605918 | I13: 6.721328 | J13: 1.2552625 | K13: 1.7331672 | L13: 3.7462436 | M13: 2.5790374 | N13: 2.5966967 | O13: 2.5626958 | P13: 2.531153 | Q13: 2.4997036 | R13: 2.4684548 | S13: 2.4374055 | T13: 2.4065597 | U13: 2.3760282 | V13: 2.3455986 | W13: 2.3153897 | X13: 2.2853993 | Y13: 2.2556317 | Z13: 2.2260909 | AA13: 2.1967812 | AB13: 2.1677067 | AC13: 2.1388717 | AD13: 2.1102807 | AE13: 2.081938 | AF13: 2.0538483 | AG13: 2.026016 | AH13: 1.9984461 | AI13: 1.9711431 | AJ13: 1.9441121 | AK13: 2.0707733 | AL13: 2.0361223 | AM13: 2.0103733 | AN13: 1.9844574 | AO13: 1.9588637 | AP13: -0.050666009 | AQ13: 1.0255786 | AR13: 0.99682909 | AS13: 1.0167719 | AT13: 1.0349237 | AU13: 1.0534999 | AV13: 1.07241 | AW13: 1.0916643 | AX13: 1.111269 | AY13: 1.1312305 | AZ13: 1.1515552 | BA13: 1.17225 | BB13: 1.1933214 | BC13: 1.2147765 | BD13: 1.2366222 | BE13: 1.2588657 | BF13: 1.2815143 | BG13: 1.3045753 | BH13: 0
B15: E = A - B | C15: Increased Cost due to IDC & Interest Payment | D15: Rs Cr. | E15: =SUM(G15:BH15) -> -23.17877 | F15: =NPV($F$1,G15:BH15) -> -8.4724861 | G15: =G3-G6 -> -0.11215312 | H15: =H3-H6 -> -0.1308453 | I15: =I3-I6 -> -0.2879414 | J15: =J3-J6 -> -2.7381575 | K15: =K3-K6 -> -1.1641184 | L15: =L3-L6 -> -1.2552253 | M15: =M3-M6 -> -1.1574698 | N15: =N3-N6 -> -1.1187593 | ... BH15: =BH3-BH6 -> 0
D16: Rs Lakhs/MW | E16: =SUM(G16:BH16) -> -3.8631284 | F16: =NPV($F$1,G16:BH16) -> -1.412081 | G16: =G4-G7 -> -0.018692186 | H16: =H4-H7 -> -0.02180755 | I16: =I4-I7 -> -0.047990233 | J16: =J4-J7 -> -0.45635958 | K16: =K4-K7 -> -0.19401973 | L16: =L4-L7 -> -0.20920422 | M16: =M4-M7 -> -0.19291163 | N16: =N4-N7 -> -0.18645988 | ... BH16: =BH4-BH7 -> 0
B18: F = A - C | C18: Increased Cost due to IDC & Interest Payment | D18: Rs Cr. | E18: =SUM(G18:BH18) -> 5.5599253 | F18: =NPV($F$1,G18:BH18) -> -5.349785 | G18: =G3-G9 -> -0.11215312 | H18: =H3-H9 -> -0.1308453 | I18: =I3-I9 -> -0.2879414 | J18: =J3-J9 -> -2.4102919 | K18: =K3-K9 -> -0.86108275 | L18: =L3-L9 -> -0.94311581 | M18: =M3-M9 -> -0.83787537 | N18: =N3-N9 -> -0.79126274 | ... BH18: =BH3-BH9 -> 0
D19: Rs Lakhs/MW | E19: =SUM(G19:BH19) -> 0.92665422 | F19: =NPV($F$1,G19:BH19) -> -0.89163084 | G19: =G4-G10 -> -0.018692186 | H19: =H4-H10 -> -0.02180755 | I19: =I4-I10 -> -0.047990233 | J19: =J4-J10 -> -0.40171532 | K19: =K4-K10 -> -0.14351379 | L19: =L4-L10 -> -0.15718597 | M19: =M4-M10 -> -0.1396459 | N19: =N4-N10 -> -0.13187712 | ... BH19: =BH4-BH10 -> 0
B21: G = A - D | C21: Increased Cost due to IDC & Interest Payment | D21: Rs Cr. | E21: =SUM(G21:BH21) -> 34.298621 | F21: =NPV($F$1,G21:BH21) -> -2.2270839 | G21: =G3-G12 -> -0.11215312 | H21: =H3-H12 -> -0.1308453 | I21: =I3-I12 -> -0.2879414 | J21: =J3-J12 -> -2.0824263 | K21: =K3-K12 -> -0.55804711 | L21: =L3-L12 -> -0.63100627 | M21: =M3-M12 -> -0.51828098 | N21: =N3-N12 -> -0.46376619 | ... BH21: =BH3-BH12 -> 0
D22: Rs Lakhs/MW | E22: =SUM(G22:BH22) -> 5.7164368 | F22: =NPV($F$1,G22:BH22) -> -0.37118066 | G22: =G4-G13 -> -0.018692186 | H22: =H4-H13 -> -0.02180755 | I22: =I4-I13 -> -0.047990233 | J22: =J4-J13 -> -0.34707105 | K22: =K4-K13 -> -0.093007851 | L22: =L4-L13 -> -0.10516771 | M22: =M4-M13 -> -0.086380163 | N22: =N4-N13 -> -0.077294366 | ... BH22: =BH4-BH13 -> 0

Sheet Capex
E1: Cost (Rs per unit) | I1: Total Cost | J1: Cost per MW
A2: Infrastructure | C2: Unit | D2: Unit | E2: Base Price | G2: Misc | H2: Net Price | I2: Rs lakh | J2: Rs Lakh /MW
A3: Land Cost
A4: Land | B4: Govt Land | C4: Hectare | D4: =SUMIF($B$81:$B$96,$B4,$D$81:$D$96) -> 58.87 | E4: =IF(D4=0,0,SUMIF($B$81:$B$96,$B4,$I$81:$I$96)/SUMIF($B$81:$B$96,$B4,$D$81:$D$96)*10^5) -> 289665.02 | H4: =SUM(E4:G4) -> 289665.02 | I4: =IF($K4="No",0,D4*H4/10^5) -> 170.5258 | J4: =ROUND(I4/Inputs!$E$3,2) -> 0.28 | K4: Yes
A5: Land | B5: Private Land | C5: Hectare | D5: =SUMIF($B$81:$B$96,$B5,$D$81:$D$96) -> 0 | E5: =IF(D5=0,0,SUMIF($B$81:$B$96,$B5,$I$81:$I$96)/SUMIF($B$81:$B$96,$B5,$D$81:$D$96)*10^5) -> 0 | H5: =SUM(E5:G5) -> 0 | I5: =IF($K5="No",0,D5*H5/10^5) -> 0 | J5: =ROUND(I5/Inputs!$E$3,2) -> 0 | K5: Yes
A6: Land Total | B6: Sub-total | D6: =SUM(D4:D5) -> 58.87 | H6: =ROUND(I6*10^5/D6,0) -> 289665 | I6: =SUM(I4:I5) -> 170.5258 | J6: =SUM(J4:J5) -> 0.28 | M6: =34% -> 0.34 | N6: 0.33 | O6: 0.33 | R6: =M6*$I6 -> 57.978772 | S6: =N6*$I6 -> 56.273514 | T6: =O6*$I6 -> 56.273514
A7: Other Cost | H7: =SUM(E7:G7) -> 0 | I7: =IF($K7="No",0,D7*H7/10^5) -> 0 | J7: =ROUND(I7/Inputs!$E$3,2) -> 0
A8: Land Total | B8: Total | D8: =D6+D7 -> 58.87 | H8: =H6+H7 -> 289665 | I8: =I6+I7 -> 170.5258 | J8: =ROUND(I8/Inputs!$E$3,2) -> 0.28
A10: Road and associated infrastructure
A11: Road length - 5.5 metre | C11: kM | D11: =D70 -> 8.75 | E11: =110*10^5 -> 11000000 | F11: 0 | G11: 0 | H11: =SUM(E11:G11) -> 11000000 | I11: =IF($K11="No",0,D11*H11/10^5) -> 962.5 | J11: =ROUND(I11/Inputs!$E$3,2) -> 1.6
A12: Road length - 3.75 metre | C12: kM | D12: =D76 -> 20.8 | E12: =75*10^5 -> 7500000 | F12: 0 | G12: 0 | H12: =SUM(E12:G12) -> 7500000 | I12: =IF($K12="No",0,D12*H12/10^5) -> 1560 | J12: =ROUND(I12/Inputs!$E$3,2) -> 2.6
A13: Drainage | C13: kM | D13: 0 | E13: =75*10^5 -> 7500000 | F13: 0 | G13: 0 | H13: =SUM(E13:G13) -> 7500000 | I13: =IF($K13="No",0,D13*H13/10^5) -> 0 | J13: =ROUND(I13/Inputs!$E$3,2) -> 0
A14: Roads & Drainage Cost | B14: Total | D14: =SUM(D11:D13) -> 29.55 | H14: =ROUND(I14*10^5/D14,0) -> 8536379 | I14: =SUM(I11:I13) -> 2522.5 | J14: =SUM(J11:J13) -> 4.2 | M14: 0.1 | N14: 0.45 | O14: 0.45 | R14: =M14*$I14 -> 252.25 | S14: =N14*$I14 -> 1135.125 | T14: =O14*$I14 -> 1135.125
A15: Buildings & Civil structures
A16: Building & Civil Structures | C16: Hectare | D16: 0 | E16: 1200000 | F16: 0 | G16: 0 | H16: =SUM(E16:G16) -> 1200000 | I16: =IF($K16="No",0,D16*H16/10^5) -> 0 | J16: =ROUND(I16/Inputs!$E$3,2) -> 0
A17: Water Infrastruture Cost | C17: Rs Lakh | D17: =IF(Inputs!$H$2=1,2,IF(Inputs!$H$2=2,2,4)) -> 4 | E17: 500000 | F17: 0 | G17: 0 | H17: =SUM(E17:G17) -> 500000 | I17: =IF($K17="No",0,D17*H17/10^5) -> 20 | J17: =ROUND(I17/Inputs!$E$3,2) -> 0.03
A18: Storage Area | C18: Hectare | D18: 0 | E18: 1200000 | F18: 0 | G18: 0 | H18: =SUM(E18:G18) -> 1200000 | I18: =IF($K18="No",0,D18*H18/10^5) -> 0 | J18: =ROUND(I18/Inputs!$E$3,2) -> 0
A19: Building & Civil | B19: Total | D19: 0 | H19: =IF(D19=0,0,ROUND(I19*10^5/D19,0)) -> 0 | I19: =SUM(I16:I18) -> 20 | J19: =SUM(J16:J18) -> 0.03 | M19: 1 | R19: =M19*$I19 -> 20 | S19: =N19*$I19 -> 0 | T19: =O19*$I19 -> 0
A21: Substation
A22: Transformer (33/220kV) | B22: 110 MVA | C22: MW | D22: =Inputs!F122 -> 8 | E22: =5.5*10^7 -> 55000000 | F22: 0 | G22: 0 | H22: =SUM(E22:G22) -> 55000000 | I22: =IF($K22="No",0,D22*H22/10^5) -> 4400 | J22: =ROUND(I22/Inputs!$E$3,2) -> 7.33
A23: Bays - Incoming | B23: 33 kV | C23: Nos | D23: =Inputs!F123+Inputs!F124 -> 36 | E23: =0.8*10^7 -> 8000000 | F23: 0 | G23: 0 | H23: =SUM(E23:G23) -> 8000000 | I23: =IF($K23="No",0,D23*H23/10^5) -> 2880 | J23: =ROUND(I23/Inputs!$E$3,2) -> 4.8
A24: Bays - Outgoing | B24: 220 kV | C24: Nos | D24: =Inputs!F125+Inputs!F126+Inputs!F127 -> 14 | E24: =3*10^7 -> 30000000 | F24: 0 | G24: 0 | H24: =SUM(E24:G24) -> 30000000 | I24: =IF($K24="No",0,D24*H24/10^5) -> 4200 | J24: =ROUND(I24/Inputs!$E$3,2) -> 7 | L24: Also include 220kV Bay at STU S/S
A25: Control & Communication | C25: Nos | D25: =Inputs!F128 -> 2 | E25: =100*10^5 -> 10000000 | F25: 0 | G25: 0 | H25: =SUM(E25:G25) -> 10000000 | I25: =IF($K25="No",0,D25*H25/10^5) -> 200 | J25: =ROUND(I25/Inputs!$E$3,2) -> 0.33
A26: Sub-station | B26: Total | D26: =(IF(Inputs!$H$2=1,1,IF(Inputs!$H$2=2,1,2))) -> 2 | H26: =ROUND(I26*10^5/D26,0) -> 584000000 | I26: =SUM(I22:I25) -> 11680 | J26: =SUM(J22:J25) -> 19.46 | M26: 0.25 | N26: 0.45 | O26: 0.3 | R26: =M26*$I26 -> 2920 | S26: =N26*$I26 -> 5256 | T26: =O26*$I26 -> 3504
A28: Transmission Line
A29: Saktapur - Chhegaon | B29: incl M/C line | C29: kM | D29: =IF(Inputs!H$2=2,0,D105+$D$107) -> 40.544 | E29: =IF(Inputs!$H$2=2,0,($D$105*$H$105+$D$107*$H$107)/($D$105+$D$107)) -> 13318881 | F29: 0 | G29: =E29*Inputs!$E$36*0 -> 0 | H29: =SUM(E29:G29) -> 13318881 | I29: =IF($K29="No",0,D29*H29/10^5) -> 5400.0071 | J29: =ROUND(I29/Inputs!$E$3,2) -> 9 | M29: 0.25 | N29: 0.45 | O29: 0.3 | R29: =M29*$I29 -> 1350.0018 | S29: =N29*$I29 -> 2430.0032 | T29: =O29*$I29 -> 1620.0021
A30: Chitramod - Chhegaon | B30: incl M/C line | C30: kM | D30: =IF(Inputs!H$2=1,0,D106+$D$108) -> 54.452 | E30: =IF(Inputs!$H$2=1,0,($D$106*$H$106+$D$108*$H$108)/($D$106+$D$108)) -> 8511967.1 | F30: 0 | G30: =E30*Inputs!$E$36*0 -> 0 | H30: =SUM(E30:G30) -> 8511967.1 | I30: =IF($K30="No",0,D30*H30/10^5) -> 4634.9363 | J30: =ROUND(I30/Inputs!$E$3,2) -> 7.72 | M30: 0.25 | N30: 0.45 | O30: 0.3 | R30: =M30*$I30 -> 1158.7341 | S30: =N30*$I30 -> 2085.7213 | T30: =O30*$I30 -> 1390.4809
A31: ROW | B31: Both lines | C31: kM | D31: =D110 -> 66.085 | E31: =SUMPRODUCT($D$110:$D$111,$E$110:$E$111)/SUM($D$110:$D$111) -> 600000 | F31: 0 | G31: =E31*Inputs!$E$36*0 -> 0 | H31: =SUM(E31:G31) -> 600000 | I31: =IF($K31="No",0,D31*H31/10^5) -> 396.51 | J31: =ROUND(I31/Inputs!$E$3,2) -> 0.66 | M31: 0.25 | N31: 0.45 | O31: 0.3 | R31: =M31*$I31 -> 99.1275 | S31: =N31*$I31 -> 178.4295 | T31: =O31*$I31 -> 118.953
A32: Transmission Line | B32: Total | D32: =D29+D30 -> 94.996 | H32: =ROUND(I32*10^5/D32,0) -> 10980940 | I32: =SUM(I29:I31) -> 10431.453 | J32: =SUM(J29:J31) -> 17.38 | M32: 0.25 | N32: 0.45 | O32: 0.3
A34: Other costs
A35: PMC Cost - Transmission | B35: % of Electric infra | C35: Rs Lakh | D35: =Inputs!$E$14 -> 0.08 | E35: =(I32+I26) -> 22111.453 | F35: 0 | G35: 0 | H35: =SUM(E35:G35) -> 22111.453 | I35: =IF($K35="No",0,D35*H35) -> 1768.9163 | J35: =ROUND(I35/Inputs!$E$3,2) -> 2.95 | M35: 0.25 | N35: 0.45 | O35: 0.3 | R35: =M35*$I35 -> 442.22907 | S35: =N35*$I35 -> 796.01232 | T35: =O35*$I35 -> 530.67488
A36: PMC charges to MPUVNL - Upfront | B36: % of Project Cost | C36: Rs Lakh | D36: =Inputs!$E$16 -> 1 | E36: =ROUND(Working!$D$63*100*Inputs!$E$15,3) -> 0 | F36: 0 | G36: 0 | H36: =SUM(E36:G36) -> 0 | I36: =IF($K36="No",0,D36*H36) -> 0 | J36: =ROUND(I36/Inputs!$E$3,2) -> 0 | L36: Delete - Revised 15-Mar-2022 | M36: 0 | N36: 0.5 | O36: 0.5 | R36: =M36*$I36 -> 0 | S36: =N36*$I36 -> 0 | T36: =O36*$I36 -> 0
A37: Local Area development charges | C37: Rs L/ MW | D37: =Inputs!$E$3 -> 600 | E37: =Inputs!E18*Inputs!E19 -> 2 | F37: 0 | G37: 0 | H37: =SUM(E37:G37) -> 2 | I37: =IF($K37="No",0,D37*H37) -> 1200 | J37: =ROUND(I37/Inputs!$E$3,2) -> 2 | M37: 0 | N37: 0.5 | O37: 0.5 | R37: =M37*$I37 -> 0 | S37: =N37*$I37 -> 600 | T37: =O37*$I37 -> 600
A38: Registration Cost | C38: Rs L/ MW | D38: =Inputs!$E$3 -> 600 | E38: =Inputs!E20 -> 1 | F38: 0 | G38: 0 | H38: =SUM(E38:G38) -> 1 | I38: =IF($K38="No",0,D38*H38) -> 600 | J38: =ROUND(I38/Inputs!$E$3,2) -> 1 | M38: 1 | R38: =M38*$I38 -> 600 | S38: =N38*$I38 -> 0 | T38: =O38*$I38 -> 0
A39: PSF Fees - IREDA | B39: % of MSO | D39: =IF(Inputs!$E$22,Inputs!$E$21,0) -> 0 | E39: =I122 -> 9667.4922 | H39: =SUM(E39:G39) -> 9667.4922 | I39: =IF($K39="No",0,D39*H39) -> 0 | J39: =ROUND(I39/Inputs!$E$3,2) -> 0 | L39: Annual Charges - Revised 15-Mar-2022 | M39: 0 | N39: 0 | O39: 1 | R39: =M39*$I39 -> 0 | S39: =N39*$I39 -> 0 | T39: =O39*$I39 -> 0
A40: Financing costs | B40: % of Debt Cost | C40: Rs Lakh | D40: =Inputs!$E$24 -> 0.0025 | E40: =(Working!D65+Working!D66)*100 -> 16155.137 | F40: 0 | G40: 0 | H40: =SUM(E40:G40) -> 16155.137 | I40: =IF($K40="No",0,MIN(10000,Capex!E40)*Inputs!$E$23+Inputs!$E$24*MAX(Capex!E40-10000,0)) -> 40.387843 | J40: =ROUND(I40/Inputs!$E$3,2) -> 0.07 | M40: 0 | N40: 1 | R40: =M40*$I40 -> 0 | S40: =N40*$I40 -> 40.387843 | T40: =O40*$I40 -> 0
A41: ESIA Charges | D41: =IF(Inputs!$H$2=1,Inputs!$H$3,IF(Inputs!$H$2=2,Inputs!$H$3,1)) -> 1 | E41: =Inputs!E25 -> 69.3 | F41: 0 | G41: 0 | H41: =SUM(E41:G41) -> 69.3 | I41: =IF($K41="No",0,D41*H41) -> 69.3 | J41: =ROUND(I41/Inputs!$E$3,2) -> 0.12 | L41: 1.71 | M41: 1 | R41: =M41*$I41 -> 69.3 | S41: =N41*$I41 -> 0 | T41: =O41*$I41 -> 0
A42: RAP Cost | C42: Rs L/ MW | D42: =Inputs!$E$3 -> 600 | E42: =Inputs!$E$26 -> 2.5 | F42: 0 | G42: 0 | H42: =SUM(E42:G42) -> 2.5 | I42: =IF($K42="No",0,D42*H42) -> 1500 | J42: =ROUND(I42/Inputs!$E$3,2) -> 2.5 | L42: 25.43 | M42: 0.5 | N42: 0.5 | R42: =M42*$I42 -> 750 | S42: =N42*$I42 -> 750 | T42: =O42*$I42 -> 0
A43: ESMP Cost | C43: Rs L/ MW | D43: =Inputs!$E$3 -> 600 | E43: =Inputs!$E$27 -> 1.0833 | F43: 0 | G43: 0 | H43: =SUM(E43:G43) -> 1.0833 | I43: =IF($K43="No",0,D43*H43) -> 649.98 | J43: =ROUND(I43/Inputs!$E$3,2) -> 1.08 | L43: - | M43: 0.5 | N43: 0.5 | R43: =M43*$I43 -> 324.99 | S43: =N43*$I43 -> 324.99 | T43: =O43*$I43 -> 0
A44: Pre operative expenses | D44: =Inputs!$E$3 -> 600 | H44: =ROUND(I44/D44*10^5,0) -> 79676 | I44: =SUM(I45:I52) -> 478.05794 | J44: =ROUND(I44/Inputs!$E$3,2) -> 0.8 | L44: 116.8
A45: Construction power | B45: 33 kV Line | C45: Rs Lakh | D45: =IF(Inputs!$H$2=1,Inputs!$H$3,IF(Inputs!$H$2=2,Inputs!$H$3,1)) -> 1 | E45: 38.38 | F45: 0 | G45: 0 | H45: =SUM(E45:G45) -> 38.38 | I45: =IF($K45="No",0,D45*H45) -> 38.38 | J45: =ROUND(I45/Inputs!$E$3,2) -> 0.06 | L45: 104.32 | M45: 1 | R45: =M45*$I45 -> 38.38 | S45: =N45*$I45 -> 0 | T45: =O45*$I45 -> 0
A46: Boundary Demarcation (Buoys) | C46: Rs Lakh | D46: =INDEX(Inputs!$E$153:$E$155,MATCH(Inputs!$H$2,Inputs!$A$153:$A$155,0),1) -> 64 | E46: =INDEX(Inputs!$F$153:$F$155,MATCH(Inputs!$H$2,Inputs!$A$153:$A$155,0),1)/10^5 -> 1.32275 | F46: 0 | G46: 0 | H46: =SUM(E46:G46) -> 1.32275 | I46: =IF($K46="No",0,D46*H46) -> 84.656 | J46: =ROUND(I46/Inputs!$E$3,2) -> 0.14 | L46: 17.69 | M46: 1 | R46: =M46*$I46 -> 84.656 | S46: =N46*$I46 -> 0 | T46: =O46*$I46 -> 0
A47: Independent Engineer Fee | C47: Rs L/ visit | D47: =IF(Inputs!$H$2=1,Inputs!$H$3,IF(Inputs!$H$2=2,Inputs!$H$3,1))*12 -> 12 | E47: =Inputs!E28 -> 2 | H47: =SUM(E47:G47) -> 2 | I47: =IF($K47="No",0,D47*H47) -> 24 | J47: =ROUND(I47/Inputs!$E$3,2) -> 0.04 | L47: 0.69 | O47: 1 | R47: =M47*$I47 -> 0 | S47: =N47*$I47 -> 0 | T47: =O47*$I47 -> 24
A48: Legal Charges | C48: Rs Lakh | D48: =IF(Inputs!$H$2=1,Inputs!$H$3,IF(Inputs!$H$2=2,Inputs!$H$3,1)) -> 1 | E48: =Inputs!$E$29 -> 15 | H48: =SUM(E48:G48) -> 15 | I48: =IF($K48="No",0,D48*H48) -> 15 | J48: =ROUND(I48/Inputs!$E$3,2) -> 0.03 | K48: 53.54 | L48: 4.78 | M48: 0.25 | N48: 0.25 | O48: 0.5 | R48: =M48*$I48 -> 3.75 | S48: =N48*$I48 -> 3.75 | T48: =O48*$I48 -> 7.5
A49: Connectivity Charges | C49: Rs Lakh | D49: 1 | E49: =Inputs!$E$30 -> 25 | H49: =SUM(E49:G49) -> 25 | I49: =IF($K49="No",0,D49*H49) -> 25 | J49: =ROUND(I49/Inputs!$E$3,2) -> 0.04 | K49: =K48+L53 -> 82.35 | L49: 0.41 | M49: 1 | R49: =M49*$I49 -> 25 | S49: =N49*$I49 -> 0 | T49: =O49*$I49 -> 0
A50: Regulatory Filing Charges | C50: Rs Lakh | D50: 1 | E50: =Inputs!$E$31 -> 35 | H50: =SUM(E50:G50) -> 35 | I50: =IF($K50="No",0,D50*H50) -> 35 | J50: =ROUND(I50/Inputs!$E$3,2) -> 0.06 | L50: 9.12 | M50: 0.25 | N50: 0.25 | O50: 0.5 | R50: =M50*$I50 -> 8.75 | S50: =N50*$I50 -> 8.75 | T50: =O50*$I50 -> 17.5
A51: DPR Preparation | C51: Rs Lakh | D51: 1 | E51: =Inputs!$E$32 -> 50.701935 | H51: =SUM(E51:G51) -> 50.701935 | I51: =IF($K51="No",0,D51*H51) -> 50.701935 | J51: =ROUND(I51/Inputs!$E$3,2) -> 0.08 | L51: 10.21 | M51: 1 | R51: =M51*$I51 -> 50.701935 | S51: =N51*$I51 -> 0 | T51: =O51*$I51 -> 0
A52: TA Consultancy Charges | C52: Rs Lakh | D52: 1 | E52: =Inputs!$E$33 -> 205.32 | H52: =SUM(E52:G52) -> 205.32 | I52: =IF($K52="No",0,D52*H52) -> 205.32 | J52: =ROUND(I52/Inputs!$E$3,2) -> 0.34 | L52: 6 | M52: 0 | N52: 0.5 | O52: 0.5 | R52: =M52*$I52 -> 0 | S52: =N52*$I52 -> 102.66 | T52: =O52*$I52 -> 102.66
A53: Other costs | B53: Total | D53: =Inputs!$E$3 -> 600 | H53: =ROUND(I53/D53*10^5,0) -> 1051107 | I53: =SUM(I35:I44) -> 6306.6421 | J53: =SUM(J35:J44) -> 10.52 | L53: 28.81
A54: Infrastructure Cost | B54: Total | D54: =Inputs!$E$3 -> 600 | I54: =SUM(I6,I14,I19,I26,I32,I53) -> 31131.121 | J54: =SUM(J6,J14,J19,J26,J32,J53) -> 51.87 | L54: 12
A55: Insurance | B55: % of Hard Cost | D55: =Inputs!E92 -> 0.002 | E55: =($I$14+$I$19+$I$26+$I$32-$I$31) -> 24257.443 | H55: =SUM(C55:G55) -> 24257.445 | I55: =IF($K55="No",0,D55*H55) -> 48.514891 | J55: =ROUND(I55/Inputs!$E$3,2) -> 0.08 | L55: 15 | M55: 0 | N55: 0.5 | O55: 0.5 | R55: =M55*$I55 -> 0 | S55: =N55*$I55 -> 24.257445 | T55: =O55*$I55 -> 24.257445
A56: Contingency | B56: % of Hard Cost | D56: =Inputs!E36 -> 0.03 | E56: =($I$14+$I$19+$I$26+$I$32-$I$31+$I$53-$I$35-$I$36) -> 28795.169 | H56: =SUM(C56:G56) -> 28795.199 | I56: =IF($K56="No",0,D56*H56) -> 863.85598 | J56: =ROUND(I56/Inputs!$E$3,2) -> 1.44 | L56: 6.5 | O56: 1 | R56: =M56*$I56 -> 0 | S56: =N56*$I56 -> 0 | T56: =O56*$I56 -> 863.85598
A57: Tax | B57: No separate tax | H57: =SUM(C57:G57) -> 0 | I57: =IF($K57="No",0,D57*H57) -> 0 | J57: =ROUND(I57/Inputs!$E$3,2) -> 0 | K57: No | O57: 1 | R57: =M57*$I57 -> 0 | S57: =N57*$I57 -> 0 | T57: =O57*$I57 -> 0
A58: Insurance & Contingency | B58: Total | D58: =Inputs!$E$3 -> 600 | H58: =ROUND(I58/D58*10^5,0) -> 152062 | I58: =SUM(I55:I57) -> 912.37087 | J58: =SUM(J55:J57) -> 1.52 | L58: 15
A59: Project Cost | B59: Total | I59: =I54+I58 -> 32043.492 | J59: =J54+J58 -> 53.39 | L59: 6.5 | R59: =SUM(R6:R58) -> 8255.8491 | S59: =SUM(S6:S58) -> 13792.36 | T59: =SUM(T6:T58) -> 9995.2828 | U59: =I59-SUM(R59:T59) -> 0
A60: IDC | I60: =Working!$D$62*100 -> 926.17535 | M60: 0 | N60: 0.5 | O60: 0.5
A61: Total Project Cost incl IDC | I61: =I59+I60 -> 32969.667
A63: ROAD - DETAILED BREAKUP
A64: Road Construction Cost
A65: 5.5 m wide road
A66: Saktapur Site - Saktapur Village | B66: S/S 1 | C66: kM | D66: =0.75*(IF(Inputs!$H$2=1,1,IF(Inputs!$H$2=2,0,1))) -> 0.75 | E66: =110*10^5 -> 11000000 | H66: =SUM(E66:G66) -> 11000000 | I66: =D66*H66/10^5 -> 82.5 | J66: =ROUND(I66/Inputs!$E$3,2) -> 0.14
A67: Saktapur Vill - Mohna Main road | B67: S/S 1 | C67: kM | D67: =5.75*(IF(Inputs!$H$2=1,1,IF(Inputs!$H$2=2,0,1))) -> 5.75 | E67: =110*10^5 -> 11000000 | H67: =SUM(E67:G67) -> 11000000 | I67: =IF($K67="No",0,D67*H67/10^5) -> 632.5 | J67: =ROUND(I67/Inputs!$E$3,2) -> 1.05
A68: Chitramod - Chitramod Village | B68: S/S 2 | C68: kM | D68: =1.5*(IF(Inputs!$H$2=1,0,IF(Inputs!$H$2=2,1,1))) -> 1.5 | E68: =110*10^5 -> 11000000 | H68: =SUM(E68:G68) -> 11000000 | I68: =IF($K68="No",0,D68*H68/10^5) -> 165 | J68: =ROUND(I68/Inputs!$E$3,2) -> 0.28
A69: Chitramod Village - Main Road | B69: S/S 2 | C69: kM | D69: =0.75*(IF(Inputs!$H$2=1,0,IF(Inputs!$H$2=2,1,1))) -> 0.75 | E69: =110*10^5 -> 11000000 | H69: =SUM(E69:G69) -> 11000000 | I69: =IF($K69="No",0,D69*H69/10^5) -> 82.5 | J69: =ROUND(I69/Inputs!$E$3,2) -> 0.14
A70: Sub-total | D70: =SUM(D66:D69) -> 8.75 | H70: =I70/D70 -> 110 | I70: =SUM(I66:I69) -> 962.5 | J70: =SUM(J66:J69) -> 1.61
A71: 3.75 m wide Road
A72: Saktapur Village - Ghohalgaon | B72: Assembly | C72: kM | D72: =1.8*(IF(Inputs!$H$2=1,1,IF(Inputs!$H$2=2,0,1))) -> 1.8 | E72: =75*10^5 -> 7500000 | H72: =SUM(E72:G72) -> 7500000 | I72: =IF($K72="No",0,D72*H72/10^5) -> 135 | J72: =ROUND(I72/Inputs!$E$3,2) -> 0.23
A73: Indhawadi Site - Hantiya | B73: Assembly | C73: kM | D73: =9*(IF(Inputs!$H$2=1,1,IF(Inputs!$H$2=2,0,1))) -> 9 | E73: =75*10^5 -> 7500000 | H73: =SUM(E73:G73) -> 7500000 | I73: =IF($K73="No",0,D73*H73/10^5) -> 675 | J73: =ROUND(I73/Inputs!$E$3,2) -> 1.13
A74: Gunjari Site - Main road | B74: Assembly | C74: kM | D74: =1*(IF(Inputs!$H$2=1,0,IF(Inputs!$H$2=2,1,1))) -> 1 | E74: =75*10^5 -> 7500000 | H74: =SUM(E74:G74) -> 7500000 | I74: =IF($K74="No",0,D74*H74/10^5) -> 75 | J74: =ROUND(I74/Inputs!$E$3,2) -> 0.13
A75: Bilaya Site - Main road | B75: Assembly | C75: kM | D75: =9*(IF(Inputs!$H$2=1,0,IF(Inputs!$H$2=2,1,1))) -> 9 | E75: =75*10^5 -> 7500000 | H75: =SUM(E75:G75) -> 7500000 | I75: =IF($K75="No",0,D75*H75/10^5) -> 675 | J75: =ROUND(I75/Inputs!$E$3,2) -> 1.13
A76: Sub-total | D76: =SUM(D72:D75) -> 20.8 | I76: =SUM(I72:I75) -> 1560 | J76: =SUM(J72:J75) -> 2.62
A77: Road - Total | D77: =D76+D70 -> 29.55 | I77: =I76+I70 -> 2522.5 | J77: =J76+J70 -> 4.23
A79: Land Acquisition - Detailed Breakup
A80: Sub-station
A81: Saktapur S/S | B81: Govt Land | C81: Hectare | D81: =ROUND((15*3+25)/2.471,3)*(IF(Inputs!$H$2=1,1,IF(Inputs!$H$2=2,0,1))) -> 28.329 | E81: =Inputs!$E$133*10^5 -> 280000 | H81: =SUM(E81:G81) -> 280000 | I81: =IF($K81="No",0,D81*H81/10^5) -> 79.3212 | J81: =ROUND(I81/Inputs!$E$3,2) -> 0.13
A82: Saktapur S/S | B82: Private Land | C82: Hectare | D82: 0 | E82: =Inputs!$E$133*10^5 -> 280000 | H82: =SUM(E82:G82) -> 280000 | I82: =IF($K82="No",0,D82*H82/10^5) -> 0 | J82: =ROUND(I82/Inputs!$E$3,2) -> 0
A83: Chitramod S/S | B83: Govt Land | C83: Hectare | D83: =ROUND((15*3+25)/2.471,3)*(IF(Inputs!$H$2=1,0,IF(Inputs!$H$2=2,1,1))) -> 28.329 | E83: =Inputs!$E$134*10^5 -> 300000 | H83: =SUM(E83:G83) -> 300000 | I83: =IF($K83="No",0,D83*H83/10^5) -> 84.987 | J83: =ROUND(I83/Inputs!$E$3,2) -> 0.14
A84: Chitramod S/S | B84: Private Land | C84: Hectare | D84: 0 | E84: =Inputs!$E$134*10^5 -> 300000 | H84: =SUM(E84:G84) -> 300000 | I84: =IF($K84="No",0,D84*H84/10^5) -> 0 | J84: =ROUND(I84/Inputs!$E$3,2) -> 0
A85: Sub-total | D85: =SUM(D81:D83) -> 56.658 | E85: =ROUND(I85/D85*10^5,0) -> 290000 | I85: =SUM(I81:I83) -> 164.3082 | J85: =SUM(J81:J83) -> 0.27
A87: Road
A88: Saktapur Site - Saktapur Village | B88: Govt Land | C88: Hectare | D88: =ROUND(2.0995/2.471,3)*(IF(Inputs!$H$2=1,1,IF(Inputs!$H$2=2,0,1))) -> 0.85 | E88: =Inputs!$E$133*10^5 -> 280000 | H88: =SUM(E88:G88) -> 280000 | I88: =IF($K88="No",0,D88*H88/10^5) -> 2.38 | J88: =ROUND(I88/Inputs!$E$3,2) -> 0
A89: Saktapur Site - Saktapur Village | B89: Private Land | C89: Hectare | D89: 0 | E89: =Inputs!$E$133*10^5 -> 280000 | H89: =SUM(E89:G89) -> 280000 | I89: =IF($K89="No",0,D89*H89/10^5) -> 0 | J89: =ROUND(I89/Inputs!$E$3,2) -> 0
A90: Chitramod - Chitramod Village | B90: Govt Land | C90: Hectare | D90: =ROUND(0.2964/2.471,3)*(IF(Inputs!$H$2=1,0,IF(Inputs!$H$2=2,1,1))) -> 0.12 | E90: =Inputs!$E$134*10^5 -> 300000 | H90: =SUM(E90:G90) -> 300000 | I90: =IF($K90="No",0,D90*H90/10^5) -> 0.36 | J90: =ROUND(I90/Inputs!$E$3,2) -> 0
A91: Chitramod - Chitramod Village | B91: Private Land | C91: Hectare | D91: 0 | E91: =Inputs!$E$134*10^5 -> 300000 | H91: =SUM(E91:G91) -> 300000 | I91: =IF($K91="No",0,D91*H91/10^5) -> 0 | J91: =ROUND(I91/Inputs!$E$3,2) -> 0
A92: Indhawadi Site - Hantiya | B92: Govt Land | C92: Hectare | D92: =ROUND(0.8151*3/2/2.471,3)*(IF(Inputs!$H$2=1,0,IF(Inputs!$H$2=2,1,1))) -> 0.495 | E92: =Inputs!$F$135*10^5 -> 280000 | H92: =SUM(E92:G92) -> 280000 | I92: =IF($K92="No",0,D92*H92/10^5) -> 1.386 | J92: =ROUND(I92/Inputs!$E$3,2) -> 0
A93: Indhawadi Site - Hantiya | B93: Private Land | C93: Hectare | D93: 0 | E93: =Inputs!$F$135*10^5 -> 280000 | H93: =SUM(E93:G93) -> 280000 | I93: =IF($K93="No",0,D93*H93/10^5) -> 0 | J93: =ROUND(I93/Inputs!$E$3,2) -> 0
A94: Bilaya Site - Main road | B94: Govt Land | C94: Hectare | D94: =ROUND(1.394*9/6.8/2.471,3)*(IF(Inputs!$H$2=1,0,IF(Inputs!$H$2=2,1,1))) -> 0.747 | E94: =Inputs!$F$135*10^5 -> 280000 | H94: =SUM(E94:G94) -> 280000 | I94: =IF($K94="No",0,D94*H94/10^5) -> 2.0916 | J94: =ROUND(I94/Inputs!$E$3,2) -> 0
A95: Bilaya Site - Main road | B95: Private Land | C95: Hectare | D95: 0 | E95: =Inputs!$F$135*10^5 -> 280000 | H95: =SUM(E95:G95) -> 280000 | I95: =IF($K95="No",0,D95*H95/10^5) -> 0 | J95: =ROUND(I95/Inputs!$E$3,2) -> 0
A96: Sub-total | D96: =SUM(D88:D95) -> 2.212 | E96: =ROUND(I96/D96*10^5,0) -> 281085 | I96: =SUM(I88:I95) -> 6.2176 | J96: =SUM(J88:J95) -> 0
A97: Other Charges - Land
A98: Stamp Duty Charges | B98: Private Land | D98: =Inputs!$E11 -> 0 | E98: =SUMIF($B$81:$B$95,$B$98,$I$81:$I$95) -> 0 | H98: =SUM(E98:G98) -> 0 | I98: =IF($K98="No",0,D98*H98) -> 0 | J98: =ROUND(I98/Inputs!$E$3,2) -> 0
A99: Registration Charges | B99: Private Land | D99: =Inputs!$E12 -> 0 | E99: =SUMIF($B$81:$B$95,$B$98,$I$81:$I$95) -> 0 | H99: =SUM(E99:G99) -> 0 | I99: =IF($K99="No",0,D99*H99) -> 0 | J99: =ROUND(I99/Inputs!$E$3,2) -> 0
A100: Admin Charges | B100: Private Land | D100: =Inputs!$E13 -> 0 | E100: =SUMIF($B$81:$B$95,$B$98,$I$81:$I$95) -> 0 | H100: =SUM(E100:G100) -> 0 | I100: =IF($K100="No",0,D100*H100) -> 0 | J100: =ROUND(I100/Inputs!$E$3,2) -> 0
A101: Sub-total | I101: =SUM(I98:I100) -> 0 | J101: =SUM(J98:J100) -> 0
A102: Total Land Cost | D102: =D85+D96+D101 -> 58.87 | E102: =ROUND(I102/D102*10^5,0) -> 289665 | I102: =I85+I96+I101 -> 170.5258 | J102: =J85+J96+J101 -> 0.27
A104: TRANSMISSION LINE - DETAILED BREAKUP
A105: =Inputs!B138 -> Saktapur - Common Point | C105: kM | D105: =Inputs!C138 -> 11.633 | E105: =(Inputs!D138-Inputs!F138)*10^5*Inputs!G138 -> 13293070 | H105: =SUM(E105:G105) -> 13293070 | I105: =D105*H105/10^5 -> 1546.3828 | J105: =ROUND(I105/Inputs!$E$3,2) -> 2.58
A106: =Inputs!B139 -> Chitramod - Common Point | C106: kM | D106: =Inputs!C139 -> 25.541 | E106: =(Inputs!D139-Inputs!F139)*10^5*Inputs!G139 -> 13237481 | H106: =SUM(E106:G106) -> 13237481 | I106: =D106*H106/10^5 -> 3380.985 | J106: =ROUND(I106/Inputs!$E$3,2) -> 5.63
A107: =Inputs!B140 -> Common Point - Chhegaon (Phase 1) | C107: kM | D107: =Inputs!C140*IF(Inputs!$H$6="Yes",1,2) -> 28.911 | E107: =(Inputs!D140-Inputs!F140)*10^5*Inputs!G140 -> 13329267 | H107: =SUM(E107:G107) -> 13329267 | I107: =D107*H107/10^5 -> 3853.6243 | J107: =ROUND(I107/Inputs!$E$3,2) -> 6.42
A108: =Inputs!B141 -> Common Point - Chhegaon (Phase 2) | C108: kM | D108: =Inputs!C141*IF(Inputs!$H$6="Yes",1,2) -> 28.911 | E108: =(Inputs!D141-Inputs!F141)*10^5*Inputs!G141 -> 4337280.8 | H108: =SUM(E108:G108) -> 4337280.8 | I108: =D108*H108/10^5 -> 1253.9513 | J108: =ROUND(I108/Inputs!$E$3,2) -> 2.09
...

Sheet Working
B1: Particulars | C1: Units | D1: =IF(MONTH(D2)=3,YEAR(D2),YEAR(D2)+1) -> 2021 | E1: =IF(MONTH(E2)=3,YEAR(E2),YEAR(E2)+1) -> 2022 | F1: =IF(MONTH(F2)=3,YEAR(F2),YEAR(F2)+1) -> 2022 | G1: =IF(MONTH(G2)=3,YEAR(G2),YEAR(G2)+1) -> 2023 | H1: =IF(MONTH(H2)=3,YEAR(H2),YEAR(H2)+1) -> 2023 | I1: =IF(MONTH(I2)=3,YEAR(I2),YEAR(I2)+1) -> 2024 | J1: =IF(MONTH(J2)=3,YEAR(J2),YEAR(J2)+1) -> 2024 | K1: =IF(MONTH(K2)=3,YEAR(K2),YEAR(K2)+1) -> 2025 | ... BL1: =IF(MONTH(BL2)=3,YEAR(BL2),YEAR(BL2)+1) -> 2051
D2: 44286 | E2: =EOMONTH(D2,6) -> 44469 | F2: =EOMONTH(E2,6) -> 44651 | G2: =EOMONTH(F2,6) -> 44834 | H2: =EOMONTH(G2,6) -> 45016 | I2: =EOMONTH(H2,6) -> 45199 | J2: =EOMONTH(I2,6) -> 45382 | K2: =EOMONTH(J2,6) -> 45565 | L2: =EOMONTH(K2,6) -> 45747 | ... BL2: =EOMONTH(BK2,6) -> 55243
B3: Financial Year | D3: =DATE(D1,3,31) -> 44286 | E3: =DATE(E1,3,31) -> 44651 | F3: =DATE(F1,3,31) -> 44651 | G3: =DATE(G1,3,31) -> 45016 | H3: =DATE(H1,3,31) -> 45016 | I3: =DATE(I1,3,31) -> 45382 | J3: =DATE(J1,3,31) -> 45382 | K3: =DATE(K1,3,31) -> 45747 | ... BL3: =DATE(BL1,3,31) -> 55243
A4: General
B5: Is Operational ? | E5: =IF(AND(E2>=Inputs!$E$46,E2<=Inputs!$E$47),1,0) -> 0 | F5: =IF(AND(F2>=Inputs!$E$46,F2<=Inputs!$E$47),1,0) -> 0 | G5: =IF(AND(G2>=Inputs!$E$46,G2<=Inputs!$E$47),1,0) -> 0 | H5: =IF(AND(H2>=Inputs!$E$46,H2<=Inputs!$E$47),1,0) -> 0 | I5: =IF(AND(I2>=Inputs!$E$46,I2<=Inputs!$E$47),1,0) -> 0 | J5: =IF(AND(J2>=Inputs!$E$46,J2<=Inputs!$E$47),1,0) -> 1 | K5: =IF(AND(K2>=Inputs!$E$46,K2<=Inputs!$E$47),1,0) -> 1 | L5: =IF(AND(L2>=Inputs!$E$46,L2<=Inputs!$E$47),1,0) -> 1 | ... BL5: =IF(AND(BL2>=Inputs!$E$46,BL2<=Inputs!$E$47),1,0) -> 0
B6: Half Year Number | E6: =SUM($E5:E$5) -> 0 | F6: =SUM($E5:F$5) -> 0 | G6: =SUM($E5:G$5) -> 0 | H6: =SUM($E5:H$5) -> 0 | I6: =SUM($E5:I$5) -> 0 | J6: =SUM($E5:J$5) -> 1 | K6: =SUM($E5:K$5) -> 2 | L6: =SUM($E5:L$5) -> 3 | ... BL6: =SUM($E5:BL$5) -> 50
B7: Days in Half year | E7: =E2-D2 -> 183 | F7: =F2-E2 -> 182 | G7: =G2-F2 -> 183 | H7: =H2-G2 -> 182 | I7: =I2-H2 -> 183 | J7: =J2-I2 -> 183 | K7: =K2-J2 -> 183 | L7: =L2-K2 -> 182 | ... BL7: =BL2-BK2 -> 182
B8: Days in Operations | E8: =IF(E2=Inputs!$E$47,Inputs!$E$44-D2,IF(E2-Inputs!$E$41+1>=182,E2-D2,E2-Inputs!$E$41+1))*E5 -> 0 | F8: =IF(F2=Inputs!$E$47,Inputs!$E$44-E2,IF(F2-Inputs!$E$41+1>=182,F2-E2,F2-Inputs!$E$41+1))*F5 -> 0 | G8: =IF(G2=Inputs!$E$47,Inputs!$E$44-F2,IF(G2-Inputs!$E$41+1>=182,G2-F2,G2-Inputs!$E$41+1))*G5 -> 0 | H8: =IF(H2=Inputs!$E$47,Inputs!$E$44-G2,IF(H2-Inputs!$E$41+1>=182,H2-G2,H2-Inputs!$E$41+1))*H5 -> 0 | I8: =IF(I2=Inputs!$E$47,Inputs!$E$44-H2,IF(I2-Inputs!$E$41+1>=182,I2-H2,I2-Inputs!$E$41+1))*I5 -> 0 | J8: =IF(J2=Inputs!$E$47,Inputs!$E$44-I2,IF(J2-Inputs!$E$41+1>=182,J2-I2,J2-Inputs!$E$41+1))*J5 -> 183 | K8: =IF(K2=Inputs!$E$47,Inputs!$E$44-J2,IF(K2-Inputs!$E$41+1>=182,K2-J2,K2-Inputs!$E$41+1))*K5 -> 183 | L8: =IF(L2=Inputs!$E$47,Inputs!$E$44-K2,IF(L2-Inputs!$E$41+1>=182,L2-K2,L2-Inputs!$E$41+1))*L5 -> 182 | ... BL8: =IF(BL2=Inputs!$E$47,Inputs!$E$44-BK2,IF(BL2-Inputs!$E$41+1>=182,BL2-BK2,BL2-Inputs!$E$41+1))*BL5 -> 0
B9: Proportion of half year in operation | E9: =IF(E7,E8/E7,0) -> 0 | F9: =IF(F7,F8/F7,0) -> 0 | G9: =IF(G7,G8/G7,0) -> 0 | H9: =IF(H7,H8/H7,0) -> 0 | I9: =IF(I7,I8/I7,0) -> 0 | J9: =IF(J7,J8/J7,0) -> 1 | K9: =IF(K7,K8/K7,0) -> 1 | L9: =IF(L7,L8/L7,0) -> 1 | ... BL9: =IF(BL7,BL8/BL7,0) -> 0
B10: Cumulative number of half year in operation | E10: =D10+E9 -> 0 | F10: =E10+F9 -> 0 | G10: =F10+G9 -> 0 | H10: =G10+H9 -> 0 | I10: =H10+I9 -> 0 | J10: =I10+J9 -> 1 | K10: =J10+K9 -> 2 | L10: =K10+L9 -> 3 | ... BL10: =BK10+BL9 -> 50
A11: Half yearly Assumptions for Solar Park (FSP)
A12: Phasing | F12: 44651 | G12: 44834 | H12: 45016 | I12: 45199
B13: Land | F13: 0 | G13: 6 | H13: 6 | I13: 4
B14: Site Development Cost | F14: 1 | G14: 0 | H14: 0 | I14: 0
B15: Park evacuation infrastructure cost | F15: 0.1 | G15: 0.2 | H15: 0.5 | I15: 0.2
B16: Other Costs | F16: 0.05 | G16: 0.2 | H16: 0.3 | I16: 0.45
F17: 0.1 | G17: 0.3 | H17: 0.3 | I17: 0.3
F18: 44651 | G18: 44834 | H18: 45016 | I18: 45199
F19: 0 | G19: 4 | H19: 6 | I19: 6
B20: Land | G20: 1
B21: Site Development Cost | G21: 0.2 | H21: 0.5 | I21: 0.3
B22: Park evacuation infrastructure cost | G22: 0.25 | H22: 0.3 | I22: 0.45
B23: Other Costs | G23: 0.3 | H23: 0.3 | I23: 0.4
A25: Phasing
B26: Land | D26: =SUM(E26:BL26) -> 1 | E26: 0 | F26: 0 | G26: 1 | H26: 0 | I26: 0
B27: Site Development Cost | D27: =SUM(E27:BL27) -> 1 | E27: 0 | F27: 0 | G27: 0.2 | H27: 0.5 | I27: 0.3
B28: Park evacuation infrastructure cost | D28: =SUM(E28:BL28) -> 1 | E28: 0 | F28: 0 | G28: 0.25 | H28: 0.3 | I28: 0.45
B29: Other Costs | D29: =SUM(E29:BL29) -> 1 | E29: 0 | F29: 0 | G29: 0.3 | H29: 0.3 | I29: 0.4
A31: =D31/$D$35 -> 0.0053216984 | B31: Land | C31: Rs Cr | D31: =SUM(E31:BL31) -> 1.705258 | E31: =Capex!$I6/100*E26 -> 0 | F31: =Capex!$I6/100*F26 -> 0 | G31: =Capex!R6/100 -> 0.57978772 | H31: =Capex!S6/100 -> 0.56273514 | I31: =Capex!T6/100 -> 0.56273514 | J31: =Capex!$I6/100*J26 -> 0 | K31: =Capex!$I6/100*K26 -> 0 | L31: =Capex!$I6/100*L26 -> 0 | M31: =Capex!$I6/100*M26 -> 0 | N31: =Capex!$I6/100*N26 -> 0 | O31: =Capex!$I6/100*O26 -> 0 | P31: =Capex!$I6/100*P26 -> 0 | Q31: =Capex!$I6/100*Q26 -> 0 | ... BL31: =Capex!$I6/100*BL26 -> 0
A32: =D32/$D$35 -> 0.079345285 | B32: Site Development - Other infrastructure | C32: Rs Cr | D32: =SUM(E32:BL32) -> 25.425 | E32: =(Capex!$I14+Capex!$I19)/100*E27 -> 0 | F32: =(Capex!$I14+Capex!$I19)/100*F27 -> 0 | G32: =SUM(Capex!R14:R19)/100 -> 2.7225 | H32: =SUM(Capex!S14:S19)/100 -> 11.35125 | I32: =SUM(Capex!T14:T19)/100 -> 11.35125 | J32: =(Capex!$I14+Capex!$I19)/100*J27 -> 0 | K32: =(Capex!$I14+Capex!$I19)/100*K27 -> 0 | L32: =(Capex!$I14+Capex!$I19)/100*L27 -> 0 | M32: =(Capex!$I14+Capex!$I19)/100*M27 -> 0 | N32: =(Capex!$I14+Capex!$I19)/100*N27 -> 0 | O32: =(Capex!$I14+Capex!$I19)/100*O27 -> 0 | P32: =(Capex!$I14+Capex!$I19)/100*P27 -> 0 | Q32: =(Capex!$I14+Capex!$I19)/100*Q27 -> 0 | ... BL32: =(Capex!$I14+Capex!$I19)/100*BL27 -> 0
A33: =D33/$D$35 -> 0.67767094 | B33: Evacuation infrastructure | C33: Rs Cr | D33: =SUM(E33:BL33) -> 217.14943 | E33: =(Capex!$I26+Capex!$I32-Capex!$I31)/100*E28 -> 0 | F33: =(Capex!$I26+Capex!$I32-Capex!$I31)/100*F28 -> 0 | G33: =(Capex!R26+Capex!R29+Capex!R30)/100 -> 54.287359 | H33: =(Capex!S26+Capex!S29+Capex!S30)/100 -> 97.717245 | I33: =(Capex!T26+Capex!T29+Capex!T30)/100 -> 65.14483 | J33: =(Capex!$I26+Capex!$I32-Capex!$I31)/100*J28 -> 0 | K33: =(Capex!$I26+Capex!$I32-Capex!$I31)/100*K28 -> 0 | L33: =(Capex!$I26+Capex!$I32-Capex!$I31)/100*L28 -> 0 | M33: =(Capex!$I26+Capex!$I32-Capex!$I31)/100*M28 -> 0 | N33: =(Capex!$I26+Capex!$I32-Capex!$I31)/100*N28 -> 0 | O33: =(Capex!$I26+Capex!$I32-Capex!$I31)/100*O28 -> 0 | P33: =(Capex!$I26+Capex!$I32-Capex!$I31)/100*P28 -> 0 | Q33: =(Capex!$I26+Capex!$I32-Capex!$I31)/100*Q28 -> 0 | ... BL33: =(Capex!$I26+Capex!$I32-Capex!$I31)/100*BL28 -> 0
A34: =D34/$D$35 -> 0.23766208 | B34: Other Costs | C34: Rs Cr | D34: =SUM(E34:BL34) -> 76.155229 | E34: =(Capex!$I53+Capex!$I58+Capex!$I31)/100*E29 -> 0 | F34: =(Capex!$I53+Capex!$I58+Capex!$I31)/100*F29 -> 0 | G34: =SUM(Capex!R35:R52,Capex!R55:R57,Capex!R31)/100 -> 24.968845 | H34: =SUM(Capex!S35:S52,Capex!S55:S57,Capex!S31)/100 -> 28.292371 | I34: =SUM(Capex!T35:T52,Capex!T55:T57,Capex!T31)/100 -> 22.894013 | J34: =(Capex!$I53+Capex!$I58+Capex!$I31)/100*J29 -> 0 | K34: =(Capex!$I53+Capex!$I58+Capex!$I31)/100*K29 -> 0 | L34: =(Capex!$I53+Capex!$I58+Capex!$I31)/100*L29 -> 0 | M34: =(Capex!$I53+Capex!$I58+Capex!$I31)/100*M29 -> 0 | N34: =(Capex!$I53+Capex!$I58+Capex!$I31)/100*N29 -> 0 | O34: =(Capex!$I53+Capex!$I58+Capex!$I31)/100*O29 -> 0 | P34: =(Capex!$I53+Capex!$I58+Capex!$I31)/100*P29 -> 0 | Q34: =(Capex!$I53+Capex!$I58+Capex!$I31)/100*Q29 -> 0 | ... BL34: =(Capex!$I53+Capex!$I58+Capex!$I31)/100*BL29 -> 0
A35: =D35/$D$35 -> 1 | B35: Total | C35: Rs Cr | D35: =SUM(E35:BL35) -> 320.43492 | E35: =SUM(E31:E34) -> 0 | F35: =SUM(F31:F34) -> 0 | G35: =SUM(G31:G34) -> 82.558491 | H35: =SUM(H31:H34) -> 137.9236 | I35: =SUM(I31:I34) -> 99.952828 | J35: =SUM(J31:J34) -> 0 | K35: =SUM(K31:K34) -> 0 | L35: =SUM(L31:L34) -> 0 | ... BL35: =SUM(BL31:BL34) -> 0
A36: =D36/$D$35 -> 0 | D36: =D35-Capex!I59/100 -> 0
B37: Land | D37: =SUM(E37:BL37) -> 1.705258 | E37: =SUMPRODUCT(Inputs!$E$102:$E$105,E$31:E$34) -> 0 | F37: =SUMPRODUCT(Inputs!$E$102:$E$105,F$31:F$34) -> 0 | G37: =SUMPRODUCT(Inputs!$E$102:$E$105,G$31:G$34) -> 0.57978772 | H37: =SUMPRODUCT(Inputs!$E$102:$E$105,H$31:H$34) -> 0.56273514 | I37: =SUMPRODUCT(Inputs!$E$102:$E$105,I$31:I$34) -> 0.56273514 | J37: =SUMPRODUCT(Inputs!$E$102:$E$105,J$31:J$34) -> 0 | K37: =SUMPRODUCT(Inputs!$E$102:$E$105,K$31:K$34) -> 0 | L37: =SUMPRODUCT(Inputs!$E$102:$E$105,L$31:L$34) -> 0 | ... BL37: =SUMPRODUCT(Inputs!$E$102:$E$105,BL$31:BL$34) -> 0
B38: Civil Works | D38: =SUM(E38:BL38) -> 79.000933 | E38: =SUMPRODUCT(Inputs!$F$102:$F$105,E$31:E$34) -> 0 | F38: =SUMPRODUCT(Inputs!$F$102:$F$105,F$31:F$34) -> 0 | G38: =SUMPRODUCT(Inputs!$F$102:$F$105,G$31:G$34) -> 18.029241 | H38: =SUMPRODUCT(Inputs!$F$102:$F$105,H$31:H$34) -> 34.282923 | I38: =SUMPRODUCT(Inputs!$F$102:$F$105,I$31:I$34) -> 26.688769 | J38: =SUMPRODUCT(Inputs!$F$102:$F$105,J$31:J$34) -> 0 | K38: =SUMPRODUCT(Inputs!$F$102:$F$105,K$31:K$34) -> 0 | L38: =SUMPRODUCT(Inputs!$F$102:$F$105,L$31:L$34) -> 0 | ... BL38: =SUMPRODUCT(Inputs!$F$102:$F$105,BL$31:BL$34) -> 0
B39: Electrical | D39: =SUM(E39:BL39) -> 173.71955 | E39: =SUMPRODUCT(Inputs!$G$102:$G$105,E$31:E$34) -> 0 | F39: =SUMPRODUCT(Inputs!$G$102:$G$105,F$31:F$34) -> 0 | G39: =SUMPRODUCT(Inputs!$G$102:$G$105,G$31:G$34) -> 43.429887 | H39: =SUMPRODUCT(Inputs!$G$102:$G$105,H$31:H$34) -> 78.173796 | I39: =SUMPRODUCT(Inputs!$G$102:$G$105,I$31:I$34) -> 52.115864 | J39: =SUMPRODUCT(Inputs!$G$102:$G$105,J$31:J$34) -> 0 | K39: =SUMPRODUCT(Inputs!$G$102:$G$105,K$31:K$34) -> 0 | L39: =SUMPRODUCT(Inputs!$G$102:$G$105,L$31:L$34) -> 0 | ... BL39: =SUMPRODUCT(Inputs!$G$102:$G$105,BL$31:BL$34) -> 0
B40: Other Assets | D40: =SUM(E40:BL40) -> 66.009183 | E40: =SUMPRODUCT(Inputs!$H$102:$H$105,E$31:E$34) -> 0 | F40: =SUMPRODUCT(Inputs!$H$102:$H$105,F$31:F$34) -> 0 | G40: =SUMPRODUCT(Inputs!$H$102:$H$105,G$31:G$34) -> 20.519576 | H40: =SUMPRODUCT(Inputs!$H$102:$H$105,H$31:H$34) -> 24.904147 | I40: =SUMPRODUCT(Inputs!$H$102:$H$105,I$31:I$34) -> 20.58546 | J40: =SUMPRODUCT(Inputs!$H$102:$H$105,J$31:J$34) -> 0 | K40: =SUMPRODUCT(Inputs!$H$102:$H$105,K$31:K$34) -> 0 | L40: =SUMPRODUCT(Inputs!$H$102:$H$105,L$31:L$34) -> 0 | ... BL40: =SUMPRODUCT(Inputs!$H$102:$H$105,BL$31:BL$34) -> 0
B41: Total | D41: =SUM(E41:BL41) -> 320.43492 | E41: =SUM(E37:E40) -> 0 | F41: =SUM(F37:F40) -> 0 | G41: =SUM(G37:G40) -> 82.558491 | H41: =SUM(H37:H40) -> 137.9236 | I41: =SUM(I37:I40) -> 99.952828 | J41: =SUM(J37:J40) -> 0 | K41: =SUM(K37:K40) -> 0 | L41: =SUM(L37:L40) -> 0 | ... BL41: =SUM(BL37:BL40) -> 0
A42: Funding
B43: Commerical Loan 1 | C43: % | E43: =Inputs!$E$50 -> 0.49 | F43: =Inputs!C165 -> 0 | G43: =Inputs!D165 -> 0.25288569 | H43: =Inputs!E165 -> 0.4274807 | I43: =Inputs!F165 -> 0.31963361 | J43: =Inputs!G165 -> 0 | K43: 0 | L43: 0 | M43: 0 | N43: 0 | O43: 0 | P43: 0 | Q43: 0 | R43: 0 | S43: 0 | T43: 0 | U43: 0 | V43: 0 | W43: 0 | X43: 0 | Y43: 0 | Z43: 0 | AA43: 0 | AB43: 0 | AC43: 0 | AD43: 0 | AE43: 0 | AF43: 0 | AG43: 0 | AH43: 0 | AI43: 0 | AJ43: 0 | AK43: 0 | AL43: 0 | AM43: 0 | AN43: 0 | AO43: 0 | AP43: 0 | AQ43: 0 | AR43: 0 | AS43: 0 | AT43: 0 | AU43: 0 | AV43: 0 | AW43: 0 | AX43: 0 | AY43: 0 | AZ43: 0 | BA43: 0 | BB43: 0 | BC43: 0 | BD43: 0 | BE43: 0 | BF43: 0 | BG43: 0 | BH43: 0 | BI43: 0 | BJ43: 0 | BK43: 0 | BL43: 0
B44: Commerical Loan 2 | C44: % | E44: =Inputs!$E$55 -> 0 | F44: =Inputs!C166 -> 0 | G44: =Inputs!D166 -> 0 | H44: =Inputs!E166 -> 0 | I44: =Inputs!F166 -> 0 | J44: =Inputs!G166 -> 0 | K44: 0 | L44: 0 | M44: 0 | N44: 0 | O44: 0 | P44: 0 | Q44: 0 | R44: 0 | S44: 0 | T44: 0 | U44: 0 | V44: 0 | W44: 0 | X44: 0 | Y44: 0 | Z44: 0 | AA44: 0 | AB44: 0 | AC44: 0 | AD44: 0 | AE44: 0 | AF44: 0 | AG44: 0 | AH44: 0 | AI44: 0 | AJ44: 0 | AK44: 0 | AL44: 0 | AM44: 0 | AN44: 0 | AO44: 0 | AP44: 0 | AQ44: 0 | AR44: 0 | AS44: 0 | AT44: 0 | AU44: 0 | AV44: 0 | AW44: 0 | AX44: 0 | AY44: 0 | AZ44: 0 | BA44: 0 | BB44: 0 | BC44: 0 | BD44: 0 | BE44: 0 | BF44: 0 | BG44: 0 | BH44: 0 | BI44: 0 | BJ44: 0 | BK44: 0 | BL44: 0
B45: Grant/ Capital Subsidy | C45: % | E45: =MIN(30%*Capex!I135,0.2*Inputs!E3)/Capex!I135-E48 -> 0.3 | F45: =Inputs!C167 -> 0 | G45: =Inputs!D167 -> 0.26173539 | H45: =Inputs!E167 -> 0.5733478 | I45: =Inputs!F167 -> 0.16491681 | J45: =Inputs!G167 -> 0 | K45: 0 | L45: 0 | M45: 0 | N45: 0 | O45: 0 | P45: 0 | Q45: 0 | R45: 0 | S45: 0 | T45: 0 | U45: 0 | V45: 0 | W45: 0 | X45: 0 | Y45: 0 | Z45: 0 | AA45: 0 | AB45: 0 | AC45: 0 | AD45: 0 | AE45: 0 | AF45: 0 | AG45: 0 | AH45: 0 | AI45: 0 | AJ45: 0 | AK45: 0 | AL45: 0 | AM45: 0 | AN45: 0 | AO45: 0 | AP45: 0 | AQ45: 0 | AR45: 0 | AS45: 0 | AT45: 0 | AU45: 0 | AV45: 0 | AW45: 0 | AX45: 0 | AY45: 0 | AZ45: 0 | BA45: 0 | BB45: 0 | BC45: 0 | BD45: 0 | BE45: 0 | BF45: 0 | BG45: 0 | BH45: 0 | BI45: 0 | BJ45: 0 | BK45: 0 | BL45: 0
B46: Equity | C46: % | E46: =Inputs!E60 -> 0 | F46: =Inputs!C168 -> 0 | G46: =Inputs!D168 -> 0 | H46: =Inputs!E168 -> 0 | I46: =Inputs!F168 -> 0 | J46: =Inputs!G168 -> 0 | K46: 0 | L46: 0 | M46: 0 | N46: 0 | O46: 0 | P46: 0 | Q46: 0 | R46: 0 | S46: 0 | T46: 0 | U46: 0 | V46: 0 | W46: 0 | X46: 0 | Y46: 0 | Z46: 0 | AA46: 0 | AB46: 0 | AC46: 0 | AD46: 0 | AE46: 0 | AF46: 0 | AG46: 0 | AH46: 0 | AI46: 0 | AJ46: 0 | AK46: 0 | AL46: 0 | AM46: 0 | AN46: 0 | AO46: 0 | AP46: 0 | AQ46: 0 | AR46: 0 | AS46: 0 | AT46: 0 | AU46: 0 | AV46: 0 | AW46: 0 | AX46: 0 | AY46: 0 | AZ46: 0 | BA46: 0 | BB46: 0 | BC46: 0 | BD46: 0 | BE46: 0 | BF46: 0 | BG46: 0 | BH46: 0 | BI46: 0 | BJ46: 0 | BK46: 0 | BL46: 0
B47: Upfront Contribution from Developer | C47: % | E47: =1-SUM(E43:E46) -> 0.21 | F47: =Inputs!C169 -> 0 | G47: =Inputs!D169 -> 0.3 | H47: =Inputs!E169 -> 0.35 | I47: =Inputs!F169 -> 0.35 | J47: =Inputs!G169 -> 0 | K47: 0 | L47: 0 | M47: 0 | N47: 0 | O47: 0 | P47: 0 | Q47: 0 | R47: 0 | S47: 0 | T47: 0 | U47: 0 | V47: 0 | W47: 0 | X47: 0 | Y47: 0 | Z47: 0 | AA47: 0 | AB47: 0 | AC47: 0 | AD47: 0 | AE47: 0 | AF47: 0 | AG47: 0 | AH47: 0 | AI47: 0 | AJ47: 0 | AK47: 0 | AL47: 0 | AM47: 0 | AN47: 0 | AO47: 0 | AP47: 0 | AQ47: 0 | AR47: 0 | AS47: 0 | AT47: 0 | AU47: 0 | AV47: 0 | AW47: 0 | AX47: 0 | AY47: 0 | AZ47: 0 | BA47: 0 | BB47: 0 | BC47: 0 | BD47: 0 | BE47: 0 | BF47: 0 | BG47: 0 | BH47: 0 | BI47: 0 | BJ47: 0 | BK47: 0 | BL47: 0
B48: ="Bridge Finance - "&IF(Inputs!$E$66,"Developer","Loan") -> Bridge Finance - Developer | C48: % | E48: =IF(F$5-E$5=1,Inputs!$E$64,0) -> 0 | F48: =Inputs!C170 -> 0 | G48: =Inputs!D170 -> 0 | H48: =Inputs!E170 -> 0 | I48: =Inputs!F170 -> 0.15 | J48: =Inputs!G170 -> -0.15 | K48: =IF(OR(K5+L5=1,J5+K5=1),IF(K5=0,Inputs!$E$64,IF(K5=1,-Inputs!$E$64,0)),0) -> 0 | L48: =IF(OR(L5+M5=1,K5+L5=1),IF(L5=0,Inputs!$E$64,IF(L5=1,-Inputs!$E$64,0)),0) -> 0 | M48: =IF(OR(M5+N5=1,L5+M5=1),IF(M5=0,Inputs!$E$64,IF(M5=1,-Inputs!$E$64,0)),0) -> 0 | N48: =IF(OR(N5+O5=1,M5+N5=1),IF(N5=0,Inputs!$E$64,IF(N5=1,-Inputs!$E$64,0)),0) -> 0 | O48: =IF(OR(O5+P5=1,N5+O5=1),IF(O5=0,Inputs!$E$64,IF(O5=1,-Inputs!$E$64,0)),0) -> 0 | P48: =IF(OR(P5+Q5=1,O5+P5=1),IF(P5=0,Inputs!$E$64,IF(P5=1,-Inputs!$E$64,0)),0) -> 0 | Q48: =IF(OR(Q5+R5=1,P5+Q5=1),IF(Q5=0,Inputs!$E$64,IF(Q5=1,-Inputs!$E$64,0)),0) -> 0 | R48: =IF(OR(R5+S5=1,Q5+R5=1),IF(R5=0,Inputs!$E$64,IF(R5=1,-Inputs!$E$64,0)),0) -> 0 | ... BF48: =IF(OR(BF5+BG5=1,BE5+BF5=1),IF(BF5=0,Inputs!$E$64,IF(BF5=1,-Inputs!$E$64,0)),0) -> 0 | BG48: =IF(BG5>BH5,0,IF(OR(BG5+BH5=1,BF5+BG5=1),IF(BG5=0,Inputs!$E$64,IF(BG5=1,-Inputs!$E$64,0)),0)) -> 0 | BH48: =IF(BH5>BI5,0,IF(OR(BH5+BI5=1,BG5+BH5=1),IF(BH5=0,Inputs!$E$64,IF(BH5=1,-Inputs!$E$64,0)),0)) -> 0.15 | BI48: =IF(BI5>BJ5,0,IF(OR(BI5+BJ5=1,BH5+BI5=1),IF(BI5=0,Inputs!$E$64,IF(BI5=1,-Inputs!$E$64,0)),0)) -> 0 | BJ48: =IF(BJ5>BK5,0,IF(OR(BJ5+BK5=1,BI5+BJ5=1),IF(BJ5=0,Inputs!$E$64,IF(BJ5=1,-Inputs!$E$64,0)),0)) -> 0 | BK48: =IF(BK5>BL5,0,IF(OR(BK5+BL5=1,BJ5+BK5=1),IF(BK5=0,Inputs!$E$64,IF(BK5=1,-Inputs!$E$64,0)),0)) -> 0 | BL48: =IF(BL5>BM5,0,IF(OR(BL5+BM5=1,BK5+BL5=1),IF(BL5=0,Inputs!$E$64,IF(BL5=1,-Inputs!$E$64,0)),0)) -> 0
A50: Tariff - User Input
B51: Tariff - User Input | C51: Rs Lakhs/ MW | E51: 2.6 | F51: =E51*(1+F52) -> 2.6 | G51: =F51*(1+G52) -> 2.6 | H51: =G51*(1+H52) -> 2.6 | I51: =H51*(1+I52) -> 2.6 | J51: =I51*(1+J52) -> 2.6 | K51: =J51*(1+K52) -> 2.6 | L51: =K51*(1+L52) -> 2.6 | M51: =L51*(1+M52) -> 2.6 | ... BL51: =BK51*(1+BL52) -> 2.6
B52: Growth Rate | C52: % | E52: 0 | F52: 0 | G52: 0 | H52: 0 | I52: 0 | J52: 0 | K52: 0 | L52: 0 | M52: 0 | N52: 0 | O52: 0 | P52: 0 | Q52: 0 | R52: 0 | S52: 0 | T52: 0 | U52: 0 | V52: 0 | W52: 0 | X52: 0 | Y52: 0 | Z52: 0 | AA52: 0 | AB52: 0 | AC52: 0 | AD52: 0 | AE52: 0 | AF52: 0 | AG52: 0 | AH52: 0 | AI52: 0 | AJ52: 0 | AK52: 0 | AL52: 0 | AM52: 0 | AN52: 0 | AO52: 0 | AP52: 0 | AQ52: 0 | AR52: 0 | AS52: 0 | AT52: 0 | AU52: 0 | AV52: 0 | AW52: 0 | AX52: 0 | AY52: 0 | AZ52: 0 | BA52: 0 | BB52: 0 | BC52: 0 | BD52: 0 | BE52: 0 | BF52: 0 | BG52: 0 | BH52: 0 | BI52: 0 | BJ52: 0 | BK52: 0 | BL52: 0
A54: Upfront charges to MPUVNL
B55: Phasing | C55: % | D55: =SUM(F55:BL55) -> 0 | F55: =ROUND(MIN(100%-Inputs!$E$16-SUM($E55:E55),((1-Inputs!$E$16)/Inputs!$E$17/2)*F$9),4) -> 0 | G55: =ROUND(MIN(100%-Inputs!$E$16-SUM($E55:F55),((1-Inputs!$E$16)/Inputs!$E$17/2)*G$9),4) -> 0 | H55: =ROUND(MIN(100%-Inputs!$E$16-SUM($E55:G55),((1-Inputs!$E$16)/Inputs!$E$17/2)*H$9),4) -> 0 | I55: =ROUND(MIN(100%-Inputs!$E$16-SUM($E55:H55),((1-Inputs!$E$16)/Inputs!$E$17/2)*I$9),4) -> 0 | J55: =ROUND(MIN(100%-Inputs!$E$16-SUM($E55:I55),((1-Inputs!$E$16)/Inputs!$E$17/2)*J$9),4) -> 0 | K55: =ROUND(MIN(100%-Inputs!$E$16-SUM($E55:J55),((1-Inputs!$E$16)/Inputs!$E$17/2)*K$9),4) -> 0 | L55: =ROUND(MIN(100%-Inputs!$E$16-SUM($E55:K55),((1-Inputs!$E$16)/Inputs!$E$17/2)*L$9),4) -> 0 | M55: =ROUND(MIN(100%-Inputs!$E$16-SUM($E55:L55),((1-Inputs!$E$16)/Inputs!$E$17/2)*M$9),4) -> 0 | ... BL55: =ROUND(MIN(100%-Inputs!$E$16-SUM($E55:BK55),((1-Inputs!$E$16)/Inputs!$E$17/2)*BL$9),4) -> 0
A57: CapEx
A58: Breakup | B58: =Working!B37 -> Land | C58: Rs Cr | D58: =SUM(E58:BL58) -> 1.705258 | E58: =E37 -> 0 | F58: =F37 -> 0 | G58: =G37 -> 0.57978772 | H58: =H37 -> 0.56273514 | I58: =I37 -> 0.56273514 | J58: =J37 -> 0 | K58: =K37 -> 0 | L58: =L37 -> 0 | ... BL58: =BL37 -> 0
B59: =Working!B38 -> Civil Works | C59: Rs Cr | D59: =SUM(E59:BL59) -> 79.000933 | E59: =E38 -> 0 | F59: =F38 -> 0 | G59: =G38 -> 18.029241 | H59: =H38 -> 34.282923 | I59: =I38 -> 26.688769 | J59: =J38 -> 0 | K59: =K38 -> 0 | L59: =L38 -> 0 | ... BL59: =BL38 -> 0
B60: =Working!B39 -> Electrical | C60: Rs Cr | D60: =SUM(E60:BL60) -> 173.71955 | E60: =E39 -> 0 | F60: =F39 -> 0 | G60: =G39 -> 43.429887 | H60: =H39 -> 78.173796 | I60: =I39 -> 52.115864 | J60: =J39 -> 0 | K60: =K39 -> 0 | L60: =L39 -> 0 | ... BL60: =BL39 -> 0
B61: =Working!B40 -> Other Assets | C61: Rs Cr | D61: =SUM(E61:BL61) -> 66.009183 | E61: =E40 -> 0 | F61: =F40 -> 0 | G61: =G40 -> 20.519576 | H61: =H40 -> 24.904147 | I61: =I40 -> 20.58546 | J61: =J40 -> 0 | K61: =K40 -> 0 | L61: =L40 -> 0 | ... BL61: =BL40 -> 0
B62: IDC | C62: Rs Cr | D62: =SUM(E62:BL62) -> 9.2617535 | E62: =IF(Inputs!$J$1,E117+E107+E97,0) -> 0 | F62: =IF(Inputs!$J$1,F117+F107+F97,0) -> 0 | G62: =IF(Inputs!$J$1,G117+G107+G97,0) -> 0.8170806 | H62: =IF(Inputs!$J$1,H117+H107+H97,0) -> 3.0153631 | I62: =IF(Inputs!$J$1,I117+I107+I97,0) -> 5.4293099 | J62: =IF(Inputs!$J$1,J117+J107+J97,0) -> 0 | K62: =IF(Inputs!$J$1,K117+K107+K97,0) -> 0 | L62: =IF(Inputs!$J$1,L117+L107+L97,0) -> 0 | ... BL62: =IF(Inputs!$J$1,BL117+BL107+BL97,0) -> 0
B63: Capex incld IDC | C63: Rs Cr | D63: =SUM(E63:BL63) -> 329.69667 | E63: =SUM(E58:E62) -> 0 | F63: =SUM(F58:F62) -> 0 | G63: =SUM(G58:G62) -> 83.375572 | H63: =SUM(H58:H62) -> 140.93896 | I63: =SUM(I58:I62) -> 105.38214 | J63: =SUM(J58:J62) -> 0 | K63: =SUM(K58:K62) -> 0 | L63: =SUM(L58:L62) -> 0 | ... BL63: =SUM(BL58:BL62) -> 0
A64: Financing
A65: =D65/$D$71 -> 0.49 | B65: Commerical Loan 1 | C65: Rs Cr | D65: =SUM(E65:BL65) -> 161.55137 | E65: =E$63*E$43 -> 0 | F65: =$D$63*F43*$E43 -> 0 | G65: =$D$63*G43*$E43 -> 40.85403 | H65: =$D$63*H43*$E43 -> 69.060093 | I65: =$D$63*I43*$E43 -> 51.637248 | J65: =$D$63*J43*$E43 -> 0 | K65: =$D$63*K43*$E43 -> 0 | L65: =$D$63*L43*$E43 -> 0 | M65: =$D$63*M43*$E43 -> 0 | ... BL65: =$D$63*BL43*$E43 -> 0
A66: =D66/$D$71 -> 0 | B66: Commerical Loan 2 | C66: Rs Cr | D66: =SUM(E66:BL66) -> 0 | E66: =E$63*E44 -> 0 | F66: =$D$63*F44*$E44 -> 0 | G66: =$D$63*G44*$E44 -> 0 | H66: =$D$63*H44*$E44 -> 0 | I66: =$D$63*I44*$E44 -> 0 | J66: =$D$63*J44*$E44 -> 0 | K66: =$D$63*K44*$E44 -> 0 | L66: =$D$63*L44*$E44 -> 0 | M66: =$D$63*M44*$E44 -> 0 | ... BL66: =$D$63*BL44*$E44 -> 0
A67: =D67/$D$71 -> 0.25205496 | B67: Grant/ Capital Subsidy | C67: Rs Cr | D67: =SUM(E67:BL67) -> 83.101682 | E67: =E63-SUM(E68:E70,E65:E66) -> 0 | F67: =F63-SUM(F68:F70,F65:F66) -> 0 | G67: =G63-SUM(G68:G70,G65:G66) -> 21.750651 | H67: =H63-SUM(H68:H70,H65:H66) -> 47.646166 | I67: =I63-SUM(I68:I70,I65:I66) -> 13.704864 | J67: =J63-SUM(J68:J70,J65:J66) -> 0 | K67: =K63-SUM(K68:K70,K65:K66) -> 0 | L67: =L63-SUM(L68:L70,L65:L66) -> 0 | ... BL67: =BL63-SUM(BL68:BL70,BL65:BL66) -> 0
A68: =D68/$D$71 -> 0 | B68: Equity | C68: Rs Cr | D68: =SUM(E68:BL68) -> 0 | E68: =E$63*E46 -> 0 | F68: =$D$63*F46*$E46 -> 0 | G68: =$D$63*G46*$E46 -> 0 | H68: =$D$63*H46*$E46 -> 0 | I68: =$D$63*I46*$E46 -> 0 | J68: =$D$63*J46*$E46 -> 0 | K68: =$D$63*K46*$E46 -> 0 | L68: =$D$63*L46*$E46 -> 0 | M68: =$D$63*M46*$E46 -> 0 | ... BL68: =$D$63*BL46*$E46 -> 0
A69: =D69/$D$71 -> 0.21 | B69: Upfront Contribution from Developer | C69: Rs Cr | D69: =SUM(E69:BL69) -> 69.236302 | E69: =E$63*E47 -> 0 | F69: =$D$63*F47*$E47 -> 0 | G69: =$D$63*G47*$E47 -> 20.770891 | H69: =$D$63*H47*$E47 -> 24.232706 | I69: =$D$63*I47*$E47 -> 24.232706 | J69: =$D$63*J47*$E47 -> 0 | K69: =$D$63*K47*$E47 -> 0 | L69: =$D$63*L47*$E47 -> 0 | M69: =$D$63*M47*$E47 -> 0 | ... BL69: =$D$63*BL47*$E47 -> 0
A70: =D70/$D$71 -> 0.047945041 | B70: =B48 -> Bridge Finance - Developer | C70: Rs Cr | D70: =SUM(E70:BL70) -> 15.807321 | E70: =E$63*E48 -> 0 | F70: =F$63*F48 -> 0 | G70: =G$63*G48 -> 0 | H70: =H$63*H48 -> 0 | I70: =I$63*I48 -> 15.807321 | J70: =J$63*J48 -> 0 | K70: =K$63*K48 -> 0 | L70: =L$63*L48 -> 0 | ... BL70: =BL$63*BL48 -> 0
B71: Financing Total | C71: Rs Cr | D71: =SUM(D65:D70) -> 329.69667 | E71: =SUM(E65:E70) -> 0 | F71: =SUM(F65:F70) -> 0 | G71: =SUM(G65:G70) -> 83.375572 | H71: =SUM(H65:H70) -> 140.93896 | I71: =SUM(I65:I70) -> 105.38214 | J71: =SUM(J65:J70) -> 0 | K71: =SUM(K65:K70) -> 0 | ... BL71: =SUM(BL65:BL70) -> 0
A72: Grant Schedule
B73: Grant | C73: Rs Cr | D73: =SUM(E73:BL73) -> 98.909002 | E73: =IF(E6=1,$D$70,0)+E67 -> 0 | F73: =IF(F6=1,$D$70,0)+F67 -> 0 | G73: =IF(G6=1,$D$70,0)+G67 -> 21.750651 | H73: =IF(H6=1,$D$70,0)+H67 -> 47.646166 | I73: =IF(I6=1,$D$70,0)+I67 -> 13.704864 | J73: =IF(J6=1,$D$70,0)+J67 -> 15.807321 | K73: =IF(K6=1,$D$70,0)+K67 -> 0 | L73: =IF(L6=1,$D$70,0)+L67 -> 0 | ... BL73: =IF(BL6=1,$D$70,0)+BL67 -> 0
B74: Cumulative Grant | C74: Rs Cr | E74: =D74+E73 -> 0 | F74: =E74+F73 -> 0 | G74: =F74+G73 -> 21.750651 | H74: =G74+H73 -> 69.396818 | I74: =H74+I73 -> 83.101682 | J74: =I74+J73 -> 98.909002 | K74: =J74+K73 -> 98.909002 | L74: =K74+L73 -> 98.909002 | ... BL74: =BK74+BL73 -> 98.909002
A76: Equity Schedule
B77: Equity | C77: Rs Cr | D77: =SUM(E77:BL77) -> 0 | E77: =E68 -> 0 | F77: =F68 -> 0 | G77: =G68 -> 0 | H77: =H68 -> 0 | I77: =I68 -> 0 | J77: =J68 -> 0 | K77: =K68 -> 0 | L77: =L68 -> 0 | ... BL77: =BL68 -> 0
B78: Cumulative Equity | C78: Rs Cr | E78: =D78+E77 -> 0 | F78: =E78+F77 -> 0 | G78: =F78+G77 -> 0 | H78: =G78+H77 -> 0 | I78: =H78+I77 -> 0 | J78: =I78+J77 -> 0 | K78: =J78+K77 -> 0 | L78: =K78+L77 -> 0 | ... BL78: =BK78+BL77 -> 0
A80: =B69 -> Upfront Contribution from Developer
B81: =B69 -> Upfront Contribution from Developer | C81: Rs Cr | D81: =SUM(E81:BL81) -> 69.236302 | E81: =IF(Inputs!$E$66,E86,0)+E69-E87 -> 0 | F81: =IF(Inputs!$E$66,F86,0)+F69-F87 -> 0 | G81: =IF(Inputs!$E$66,G86,0)+G69-G87 -> 20.770891 | H81: =IF(Inputs!$E$66,H86,0)+H69-H87 -> 24.232706 | I81: =IF(Inputs!$E$66,I86,0)+I69-I87 -> 40.040026 | J81: =IF(Inputs!$E$66,J86,0)+J69-J87 -> -15.807321 | K81: =IF(Inputs!$E$66,K86,0)+K69-K87 -> 0 | L81: =IF(Inputs!$E$66,L86,0)+L69-L87 -> 0 | ... BL81: =IF(Inputs!$E$66,BL86,0)+BL69-BL87 -> 0
B82: Cumulative | C82: Rs Cr | E82: =D82+E81 -> 0 | F82: =E82+F81 -> 0 | G82: =F82+G81 -> 20.770891 | H82: =G82+H81 -> 45.003596 | I82: =H82+I81 -> 85.043622 | J82: =I82+J81 -> 69.236302 | K82: =J82+K81 -> 69.236302 | L82: =K82+L81 -> 69.236302 | ... BL82: =BK82+BL81 -> 69.236302
A84: Bridge Finance - Developer
B85: Opening | C85: Rs Cr | E85: =D$88 -> 0 | F85: =E$88 -> 0 | G85: =F$88 -> 0 | H85: =G$88 -> 0 | I85: =H$88 -> 0 | J85: =I$88 -> 15.807321 | K85: =J$88 -> 0 | L85: =K$88 -> 0 | ... BL85: =BK$88 -> 0
B86: Addition | C86: Rs Cr | D86: =SUM(E86:BL86) -> 15.807321 | E86: =IF(Inputs!$E$66,E$70,0) -> 0 | F86: =IF(Inputs!$E$66,F$70,0) -> 0 | G86: =IF(Inputs!$E$66,G$70,0) -> 0 | H86: =IF(Inputs!$E$66,H$70,0) -> 0 | I86: =IF(Inputs!$E$66,I$70,0) -> 15.807321 | J86: =IF(Inputs!$E$66,J$70,0) -> 0 | K86: =IF(Inputs!$E$66,K$70,0) -> 0 | L86: =IF(Inputs!$E$66,L$70,0) -> 0 | ... BL86: =IF(Inputs!$E$66,BL$70,0) -> 0
B87: Repayments | C87: Rs Cr | D87: =SUM(E87:BL87) -> 15.807321 | E87: =IF(E$5=1,E$85,0) -> 0 | F87: =IF(F$5=1,F$85,0) -> 0 | G87: =IF(G$5=1,G$85,0) -> 0 | H87: =IF(H$5=1,H$85,0) -> 0 | I87: =IF(I$5=1,I$85,0) -> 0 | J87: =IF(J$5=1,J$85,0) -> 15.807321 | K87: =IF(K$5=1,K$85,0) -> 0 | L87: =IF(L$5=1,L$85,0) -> 0 | ... BL87: =IF(BL$5=1,BL$85,0) -> 0
B88: Closing | C88: Rs Cr | E88: =E85+E86-E87 -> 0 | F88: =F85+F86-F87 -> 0 | G88: =G85+G86-G87 -> 0 | H88: =H85+H86-H87 -> 0 | I88: =I85+I86-I87 -> 15.807321 | J88: =J85+J86-J87 -> 0 | K88: =K85+K86-K87 -> 0 | L88: =L85+L86-L87 -> 0 | ... BL88: =BL85+BL86-BL87 -> 0
A90: Bridge Finance - Loan
B91: Opening | C91: Rs Cr | E91: =$D$94 -> 0 | F91: =E94 -> 0 | G91: =F94 -> 0 | H91: =G94 -> 0 | I91: =H94 -> 0 | J91: =I94 -> 0 | K91: =J94 -> 0 | L91: =K94 -> 0 | M91: =L94 -> 0 | ... BL91: =BK94 -> 0
B92: Addition | C92: Rs Cr | D92: =SUM(E92:BL92) -> 0 | E92: =IF(Inputs!$E$66,0,E$70) -> 0 | F92: =IF(Inputs!$E$66,0,F70) -> 0 | G92: =IF(Inputs!$E$66,0,G70) -> 0 | H92: =IF(Inputs!$E$66,0,H70) -> 0 | I92: =IF(Inputs!$E$66,0,I70) -> 0 | J92: =IF(Inputs!$E$66,0,J70) -> 0 | K92: =IF(Inputs!$E$66,0,K70) -> 0 | L92: =IF(Inputs!$E$66,0,L70) -> 0 | M92: =IF(Inputs!$E$66,0,M70) -> 0 | ... BL92: =IF(Inputs!$E$66,0,BL70) -> 0
B93: Repayments | C93: Rs Cr | D93: =SUM(E93:BL93) -> 0 | E93: =IF(E$5=1,E$91,0) -> 0 | F93: =IF(F5=1,F91,0) -> 0 | G93: =IF(G5=1,G91,0) -> 0 | H93: =IF(H5=1,H91,0) -> 0 | I93: =IF(I5=1,I91,0) -> 0 | J93: =IF(J5=1,J91,0) -> 0 | K93: =IF(K5=1,K91,0) -> 0 | L93: =IF(L5=1,L91,0) -> 0 | M93: =IF(M5=1,M91,0) -> 0 | ... BL93: =IF(BL5=1,BL91,0) -> 0
B94: Closing | C94: Rs Cr | E94: =E91+E92-E93 -> 0 | F94: =F91+F92-F93 -> 0 | G94: =G91+G92-G93 -> 0 | H94: =H91+H92-H93 -> 0 | I94: =I91+I92-I93 -> 0 | J94: =J91+J92-J93 -> 0 | K94: =K91+K92-K93 -> 0 | L94: =L91+L92-L93 -> 0 | ... BL94: =BL91+BL92-BL93 -> 0
A95: =Inputs!E66 -> TRUE | B95: Interest Rate Applicable | D95: =IF(Inputs!$E$66,0,1) -> 0
B96: Interest Rate | C96: % | E96: =Inputs!$E$65/2*$D$95 -> 0 | F96: =Inputs!$E$65/2*$D$95 -> 0 | G96: =Inputs!$E$65/2*$D$95 -> 0 | H96: =Inputs!$E$65/2*$D$95 -> 0 | I96: =Inputs!$E$65/2*$D$95 -> 0 | J96: =Inputs!$E$65/2*$D$95 -> 0 | K96: =Inputs!$E$65/2*$D$95 -> 0 | L96: =Inputs!$E$65/2*$D$95 -> 0 | ... BL96: =Inputs!$E$65/2*$D$95 -> 0
B97: IDC | C97: Rs Cr | D97: =SUM(E97:BL97) -> 0 | E97: =E91*E96*(1-E9) -> 0 | F97: =F91*F96*(1-F9) -> 0 | G97: =G91*G96*(1-G9) -> 0 | H97: =H91*H96*(1-H9) -> 0 | I97: =I91*I96*(1-I9) -> 0 | J97: =J91*J96*(1-J9) -> 0 | K97: =K91*K96*(1-K9) -> 0 | L97: =L91*L96*(1-L9) -> 0 | ... BL97: =BL91*BL96*(1-BL9) -> 0
B98: Interest Charge | C98: Rs Cr | D98: =SUM(E98:BL98) -> 0 | E98: =E91*E96*E9 -> 0 | F98: =F91*F96*F9 -> 0 | G98: =G91*G96*G9 -> 0 | H98: =H91*H96*H9 -> 0 | I98: =I91*I96*I9 -> 0 | J98: =J91*J96*J9 -> 0 | K98: =K91*K96*K9 -> 0 | L98: =L91*L96*L9 -> 0 | ... BL98: =BL91*BL96*BL9 -> 0
A100: Commerical Loan 1 Schedule
B101: Opening | C101: Rs Cr | E101: =D104 -> 0 | F101: =E104 -> 0 | G101: =F104 -> 0 | H101: =G104 -> 40.85403 | I101: =H104 -> 109.91412 | J101: =I104 -> 161.55137 | K101: =J104 -> 161.55137 | L101: =K104 -> 161.55137 | ... BL101: =BK104 -> 0
B102: Addition | C102: Rs Cr | D102: =SUM(E102:BL102) -> 161.55137 | E102: =E65 -> 0 | F102: =F65 -> 0 | G102: =G65 -> 40.85403 | H102: =H65 -> 69.060093 | I102: =I65 -> 51.637248 | J102: =J65 -> 0 | K102: =K65 -> 0 | L102: =L65 -> 0 | ... BL102: =BL65 -> 0
B103: Repayments | C103: Rs Cr | E103: =IF(E$10/2>Inputs!$E$51,MIN(E101+E102,$D$102/(Inputs!$E$52*2)),0) -> 0 | F103: =IF(F$10/2>Inputs!$E$51,MIN(F101+F102,$D$102/(Inputs!$E$52*2)),0) -> 0 | G103: =IF(G$10/2>Inputs!$E$51,MIN(G101+G102,$D$102/(Inputs!$E$52*2)),0) -> 0 | H103: =IF(H$10/2>Inputs!$E$51,MIN(H101+H102,$D$102/(Inputs!$E$52*2)),0) -> 0 | I103: =IF(I$10/2>Inputs!$E$51,MIN(I101+I102,$D$102/(Inputs!$E$52*2)),0) -> 0 | J103: =IF(J$10/2>Inputs!$E$51,MIN(J101+J102,$D$102/(Inputs!$E$52*2)),0) -> 0 | K103: =IF(K$10/2>Inputs!$E$51,MIN(K101+K102,$D$102/(Inputs!$E$52*2)),0) -> 0 | L103: =IF(L$10/2>Inputs!$E$51,MIN(L101+L102,$D$102/(Inputs!$E$52*2)),0) -> 5.3850457 | ... BL103: =IF(BL$10/2>Inputs!$E$51,MIN(BL101+BL102,$D$102/(Inputs!$E$52*2)),0) -> 0
B104: Closing | C104: Rs Cr | E104: =E101+E102-E103 -> 0 | F104: =F101+F102-F103 -> 0 | G104: =G101+G102-G103 -> 40.85403 | H104: =H101+H102-H103 -> 109.91412 | I104: =I101+I102-I103 -> 161.55137 | J104: =J101+J102-J103 -> 161.55137 | K104: =K101+K102-K103 -> 161.55137 | L104: =L101+L102-L103 -> 156.16632 | ... BL104: =BL101+BL102-BL103 -> 0
B106: Interest Rate | C106: % | E106: =Inputs!$E$53/2 -> 0.04 | F106: =Inputs!$E$53/2 -> 0.04 | G106: =Inputs!$E$53/2 -> 0.04 | H106: =Inputs!$E$53/2 -> 0.04 | I106: =Inputs!$E$53/2 -> 0.04 | J106: =Inputs!$E$53/2 -> 0.04 | K106: =Inputs!$E$53/2 -> 0.04 | L106: =Inputs!$E$53/2 -> 0.04 | ... BL106: =Inputs!$E$53/2 -> 0.04
B107: IDC | C107: Rs Cr | D107: =SUM(E107:BL107) -> 9.2617535 | E107: =AVERAGE(E101,E104)*E106*(1-E9) -> 0 | F107: =AVERAGE(F101,F104)*F106*(1-F9) -> 0 | G107: =AVERAGE(G101,G104)*G106*(1-G9) -> 0.8170806 | H107: =AVERAGE(H101,H104)*H106*(1-H9) -> 3.0153631 | I107: =AVERAGE(I101,I104)*I106*(1-I9) -> 5.4293099 | J107: =AVERAGE(J101,J104)*J106*(1-J9) -> 0 | K107: =AVERAGE(K101,K104)*K106*(1-K9) -> 0 | L107: =AVERAGE(L101,L104)*L106*(1-L9) -> 0 | ... BL107: =AVERAGE(BL101,BL104)*BL106*(1-BL9) -> 0
B108: Interest Charge | C108: Rs Cr | D108: =SUM(E108:BL108) -> 109.85493 | E108: =AVERAGE(E101,E104)*E106*E9 -> 0 | F108: =AVERAGE(F101,F104)*F106*F9 -> 0 | G108: =AVERAGE(G101,G104)*G106*G9 -> 0 | H108: =AVERAGE(H101,H104)*H106*H9 -> 0 | I108: =AVERAGE(I101,I104)*I106*I9 -> 0 | J108: =AVERAGE(J101,J104)*J106*J9 -> 6.4620548 | K108: =AVERAGE(K101,K104)*K106*K9 -> 6.4620548 | L108: =AVERAGE(L101,L104)*L106*L9 -> 6.3543539 | ... BL108: =AVERAGE(BL101,BL104)*BL106*BL9 -> 0
A110: Commercial Loan 2 Schedule
B111: Opening | C111: Rs Cr | E111: =D114 -> 0 | F111: =E114 -> 0 | G111: =F114 -> 0 | H111: =G114 -> 0 | I111: =H114 -> 0 | J111: =I114 -> 0 | K111: =J114 -> 0 | L111: =K114 -> 0 | ... BL111: =BK114 -> 0
B112: Addition | C112: Rs Cr | D112: =SUM(E112:BL112) -> 0 | E112: =E66 -> 0 | F112: =F66 -> 0 | G112: =G66 -> 0 | H112: =H66 -> 0 | I112: =I66 -> 0 | J112: =J66 -> 0 | K112: =K66 -> 0 | L112: =L66 -> 0 | ... BL112: =BL66 -> 0
...

Sheet Statements
B1: Particulars | C1: Units | D1: =IF(MONTH(D2)=3,YEAR(D2),YEAR(D2)+1) -> 2021 | E1: =IF(MONTH(E2)=3,YEAR(E2),YEAR(E2)+1) -> 2022 | F1: =IF(MONTH(F2)=3,YEAR(F2),YEAR(F2)+1) -> 2022 | G1: =IF(MONTH(G2)=3,YEAR(G2),YEAR(G2)+1) -> 2023 | H1: =IF(MONTH(H2)=3,YEAR(H2),YEAR(H2)+1) -> 2023 | I1: =IF(MONTH(I2)=3,YEAR(I2),YEAR(I2)+1) -> 2024 | J1: =IF(MONTH(J2)=3,YEAR(J2),YEAR(J2)+1) -> 2024 | K1: =IF(MONTH(K2)=3,YEAR(K2),YEAR(K2)+1) -> 2025 | ... BL1: =IF(MONTH(BL2)=3,YEAR(BL2),YEAR(BL2)+1) -> 2051
D2: 44286 | E2: =EOMONTH(D2,6) -> 44469 | F2: =EOMONTH(E2,6) -> 44651 | G2: =EOMONTH(F2,6) -> 44834 | H2: =EOMONTH(G2,6) -> 45016 | I2: =EOMONTH(H2,6) -> 45199 | J2: =EOMONTH(I2,6) -> 45382 | K2: =EOMONTH(J2,6) -> 45565 | L2: =EOMONTH(K2,6) -> 45747 | ... BL2: =EOMONTH(BK2,6) -> 55243
B3: Financial Year | D3: =DATE(D1,3,31) -> 44286 | E3: =DATE(E1,3,31) -> 44651 | F3: =DATE(F1,3,31) -> 44651 | G3: =DATE(G1,3,31) -> 45016 | H3: =DATE(H1,3,31) -> 45016 | I3: =DATE(I1,3,31) -> 45382 | J3: =DATE(J1,3,31) -> 45382 | K3: =DATE(K1,3,31) -> 45747 | ... BL3: =DATE(BL1,3,31) -> 55243
A4: Financial Statements & IRR
A5: P&L Account
B7: Revenue | C7: Rs Cr | E7: =Working!E296 -> 0 | F7: =Working!F296 -> 0 | G7: =Working!G296 -> 0 | H7: =Working!H296 -> 0 | I7: =Working!I296 -> 0 | J7: =Working!J296 -> 21.25647 | K7: =Working!K296 -> 9.8409561 | L7: =Working!L296 -> 21.846455 | ... BL7: =Working!BL296 -> 0
B8: Expenditure | C8: Rs Cr
B9: O&M Cost | C9: =SUM(D9:BL9) -> 321.23716 | E9: =Working!E307 -> 0 | F9: =Working!F307 -> 0 | G9: =Working!G307 -> 0 | H9: =Working!H307 -> 0 | I9: =Working!I307 -> 0 | J9: =Working!J307 -> 3.9571487 | K9: =Working!K307 -> 4.0291028 | L9: =Working!L307 -> 4.1024553 | ... BL9: =Working!BL307 -> 0
B10: Charges to MPUVNL | C10: =SUM(D10:BL10) -> 0 | E10: =Working!E313 -> 0 | F10: =Working!F313 -> 0 | G10: =Working!G313 -> 0 | H10: =Working!H313 -> 0 | I10: =Working!I313 -> 0 | J10: =Working!J313 -> 0 | K10: =Working!K313 -> 0 | L10: =Working!L313 -> 0 | ... BL10: =Working!BL313 -> 0
B11: PBITDA | C11: Rs Cr | E11: =E7-E9-E10 -> 0 | F11: =F7-F9-F10 -> 0 | G11: =G7-G9-G10 -> 0 | H11: =H7-H9-H10 -> 0 | I11: =I7-I9-I10 -> 0 | J11: =J7-J9-J10 -> 17.299321 | K11: =K7-K9-K10 -> 5.8118533 | L11: =L7-L9-L10 -> 17.744 | ... BL11: =BL7-BL9-BL10 -> 0
B12: Depreciation | C12: =SUM(D12:BL12) -> 202.9313 | E12: =IF(Inputs!$D$119,Working!E243,Working!E246) -> 0 | F12: =IF(Inputs!$D$119,Working!F243,Working!F246) -> 0 | G12: =IF(Inputs!$D$119,Working!G243,Working!G246) -> 0 | H12: =IF(Inputs!$D$119,Working!H243,Working!H246) -> 0 | I12: =IF(Inputs!$D$119,Working!I243,Working!I246) -> 0 | J12: =IF(Inputs!$D$119,Working!J243,Working!J246) -> 9.0822329 | K12: =IF(Inputs!$D$119,Working!K243,Working!K246) -> 9.0822329 | L12: =IF(Inputs!$D$119,Working!L243,Working!L246) -> 9.0822329 | ... BL12: =IF(Inputs!$D$119,Working!BL243,Working!BL246) -> 0
B13: PBIT | C13: Rs Cr | E13: =E11-E12 -> 0 | F13: =F11-F12 -> 0 | G13: =G11-G12 -> 0 | H13: =H11-H12 -> 0 | I13: =I11-I12 -> 0 | J13: =J11-J12 -> 8.2170881 | K13: =K11-K12 -> -3.2703796 | L13: =L11-L12 -> 8.6617672 | ... BL13: =BL11-BL12 -> 0
B14: Interest on Loan | C14: =SUM(D14:BL14) -> 109.85493 | E14: =Working!E108+Working!E118 -> 0 | F14: =Working!F108+Working!F118 -> 0 | G14: =Working!G108+Working!G118 -> 0 | H14: =Working!H108+Working!H118 -> 0 | I14: =Working!I108+Working!I118 -> 0 | J14: =Working!J108+Working!J118 -> 6.4620548 | K14: =Working!K108+Working!K118 -> 6.4620548 | L14: =Working!L108+Working!L118 -> 6.3543539 | ... BL14: =Working!BL108+Working!BL118 -> 0
B15: Interest on WC Loan | C15: =SUM(D15:BL15) -> 5.7242344 | E15: =Working!E323 -> 0 | F15: =Working!F323 -> 0 | G15: =Working!G323 -> 0 | H15: =Working!H323 -> 0 | I15: =Working!I323 -> 0 | J15: =Working!J323 -> 0.15758511 | K15: =Working!K323 -> 0.086687868 | L15: =Working!L323 -> 0.16218069 | ... BL15: =Working!BL323 -> 0
B16: Interest on Cash Deficit Loan | C16: =SUM(D16:BL16) -> 8.7170271e-14 | E16: =Working!E389 -> 0 | F16: =Working!F389 -> 0 | G16: =Working!G389 -> 0 | H16: =Working!H389 -> 0 | I16: =Working!I389 -> 0 | J16: =Working!J389 -> 0 | K16: =Working!K389 -> 1.5987212e-16 | L16: =Working!L389 -> 1.5987212e-16 | ... BL16: =Working!BL389 -> 0
B17: Interest on Cash Balance | C17: =SUM(D17:BL17) -> 6.615 | E17: =Working!E356 -> 0 | F17: =Working!F356 -> 0 | G17: =Working!G356 -> 0 | H17: =Working!H356 -> 0 | I17: =Working!I356 -> 0 | J17: =Working!J356 -> 0 | K17: =Working!K356 -> 0.135 | L17: =Working!L356 -> 0.135 | ... BL17: =Working!BL356 -> 0
B18: Interest on Bridge Loan | C18: =SUM(D18:BL18) -> 0 | E18: =Working!E98 -> 0 | F18: =Working!F98 -> 0 | G18: =Working!G98 -> 0 | H18: =Working!H98 -> 0 | I18: =Working!I98 -> 0 | J18: =Working!J98 -> 0 | K18: =Working!K98 -> 0 | L18: =Working!L98 -> 0 | ... BL18: =Working!BL98 -> 0
B19: Interest Income on DSRA | C19: =SUM(D19:BL19) -> 5.3182711 | E19: =Working!E336 -> 0 | F19: =Working!F336 -> 0 | G19: =Working!G336 -> 0 | H19: =Working!H336 -> 0 | I19: =Working!I336 -> 0 | J19: =Working!J336 -> 0.1292411 | K19: =Working!K336 -> 0.1292411 | L19: =Working!L336 -> 0.23478799 | ... BL19: =Working!BL336 -> 0
B20: BG Cost on DSRA | C20: =SUM(D20:BL20) -> 0 | E20: =Working!E339 -> 0 | F20: =Working!F339 -> 0 | G20: =Working!G339 -> 0 | H20: =Working!H339 -> 0 | I20: =Working!I339 -> 0 | J20: =Working!J339 -> 0 | K20: =Working!K339 -> 0 | L20: =Working!L339 -> 0 | ... BL20: =Working!BL339 -> 0
B21: Profits Before Tax (PBT) | C21: =SUM(D21:BL21) -> -33.174007 | E21: =E13-SUM(E14:E16)+E17+E19-E20-E18 -> 0 | F21: =F13-SUM(F14:F16)+F17+F19-F20-F18 -> 0 | G21: =G13-SUM(G14:G16)+G17+G19-G20-G18 -> 0 | H21: =H13-SUM(H14:H16)+H17+H19-H20-H18 -> 0 | I21: =I13-SUM(I14:I16)+I17+I19-I20-I18 -> 0 | J21: =J13-SUM(J14:J16)+J17+J19-J20-J18 -> 1.7266893 | K21: =K13-SUM(K14:K16)+K17+K19-K20-K18 -> -9.5548812 | L21: =L13-SUM(L14:L16)+L17+L19-L20-L18 -> 2.5150206 | ... BL21: =BL13-SUM(BL14:BL16)+BL17+BL19-BL20-BL18 -> 0
B22: Tax | C22: =SUM(D22:BL22) -> 4.3902353 | E22: =Working!E486 -> 0 | F22: =Working!F486 -> 0 | G22: =Working!G486 -> 0 | H22: =Working!H486 -> 0 | I22: =Working!I486 -> 0 | J22: =Working!J486 -> 0.29629988 | K22: =Working!K486 -> 0 | L22: =Working!L486 -> 0.43157754 | ... BL22: =Working!BL486 -> 0
B23: Profits After Tax (PAT) | C23: =SUM(D23:BL23) -> -37.564243 | E23: =E21-E22 -> 0 | F23: =F21-F22 -> 0 | G23: =G21-G22 -> 0 | H23: =H21-H22 -> 0 | I23: =I21-I22 -> 0 | J23: =J21-J22 -> 1.4303894 | K23: =K21-K22 -> -9.5548812 | L23: =L21-L22 -> 2.0834431 | ... BL23: =BL21-BL22 -> 0
A25: Cash flow statement
B26: Revenue | C26: Rs Cr | E26: =E7 -> 0 | F26: =F7 -> 0 | G26: =G7 -> 0 | H26: =H7 -> 0 | I26: =I7 -> 0 | J26: =J7 -> 21.25647 | K26: =K7 -> 9.8409561 | L26: =L7 -> 21.846455 | ... BL26: =BL7 -> 0
B27: O&M Cost | C27: Rs Cr | E27: =-E9 -> 0 | F27: =-F9 -> 0 | G27: =-G9 -> 0 | H27: =-H9 -> 0 | I27: =-I9 -> 0 | J27: =-J9 -> -3.9571487 | K27: =-K9 -> -4.0291028 | L27: =-L9 -> -4.1024553 | ... BL27: =-BL9 -> 0
B28: Charges to MPUVNL | C28: Rs Cr | E28: =-E10 -> 0 | F28: =-F10 -> 0 | G28: =-G10 -> 0 | H28: =-H10 -> 0 | I28: =-I10 -> 0 | J28: =-J10 -> 0 | K28: =-K10 -> 0 | L28: =-L10 -> 0 | ... BL28: =-BL10 -> 0
B29: Taxes | C29: Rs Cr | E29: =-E22 -> 0 | F29: =-F22 -> 0 | G29: =-G22 -> 0 | H29: =-H22 -> 0 | I29: =-I22 -> 0 | J29: =-J22 -> -0.29629988 | K29: =-K22 -> 0 | L29: =-L22 -> -0.43157754 | ... BL29: =-BL22 -> 0
B30: Interest on Cash Balance | C30: Rs Cr | E30: =E17 -> 0 | F30: =F17 -> 0 | G30: =G17 -> 0 | H30: =H17 -> 0 | I30: =I17 -> 0 | J30: =J17 -> 0 | K30: =K17 -> 0.135 | L30: =L17 -> 0.135 | ... BL30: =BL17 -> 0
B31: Change in DSRA | C31: Rs Cr | E31: =-Working!E332 -> 0 | F31: =-Working!F332 -> 0 | G31: =-Working!G332 -> 0 | H31: =-Working!H332 -> 0 | I31: =-Working!I332 -> 0 | J31: =-Working!J332 -> -6.4620548 | K31: =-Working!K332 -> 0 | L31: =-Working!L332 -> -5.2773448 | ... BL31: =-Working!BL332 -> 0
B32: Interest Income on DSRA | C32: Rs Cr | E32: =Working!E336 -> 0 | F32: =Working!F336 -> 0 | G32: =Working!G336 -> 0 | H32: =Working!H336 -> 0 | I32: =Working!I336 -> 0 | J32: =Working!J336 -> 0.1292411 | K32: =Working!K336 -> 0.1292411 | L32: =Working!L336 -> 0.23478799 | ... BL32: =Working!BL336 -> 0
B33: BG Cost on DSRA | C33: Rs Cr | E33: =-Working!E339 -> 0 | F33: =-Working!F339 -> 0 | G33: =-Working!G339 -> 0 | H33: =-Working!H339 -> 0 | I33: =-Working!I339 -> 0 | J33: =-Working!J339 -> 0 | K33: =-Working!K339 -> 0 | L33: =-Working!L339 -> 0 | ... BL33: =-Working!BL339 -> 0
B34: Change in WC | C34: Rs Cr | E34: =(Working!D319-Working!E319)*Working!E5 -> 0 | F34: =(Working!E319-Working!F319)*Working!F5 -> 0 | G34: =(Working!F319-Working!G319)*Working!G5 -> 0 | H34: =(Working!G319-Working!H319)*Working!H5 -> 0 | I34: =(Working!H319-Working!I319)*Working!I5 -> 0 | J34: =(Working!I319-Working!J319)*Working!J5 -> -4.2022697 | K34: =(Working!J319-Working!K319)*Working!K5 -> 1.8905932 | L34: =(Working!K319-Working!L319)*Working!L5 -> -2.013142 | ... BL34: =(Working!BK319-Working!BL319)*Working!BL5 -> 0
B35: Cash Flow from Operating Activities | C35: Rs Cr | E35: =SUM(E26:E34) -> 0 | F35: =SUM(F26:F34) -> 0 | G35: =SUM(G26:G34) -> 0 | H35: =SUM(H26:H34) -> 0 | I35: =SUM(I26:I34) -> 0 | J35: =SUM(J26:J34) -> 6.4679376 | K35: =SUM(K26:K34) -> 7.9666876 | L35: =SUM(L26:L34) -> 10.391724 | ... BL35: =SUM(BL26:BL34) -> 0
B37: Capital Expenditure | C37: Rs Cr | E37: =-Working!E63 -> 0 | F37: =-Working!F63 -> 0 | G37: =-Working!G63 -> -83.375572 | H37: =-Working!H63 -> -140.93896 | I37: =-Working!I63 -> -105.38214 | J37: =-Working!J63 -> 0 | K37: =-Working!K63 -> 0 | L37: =-Working!L63 -> 0 | ... BL37: =-Working!BL63 -> 0
B38: Cash Flow from Investing Activities | C38: Rs Cr | E38: =E37 -> 0 | F38: =F37 -> 0 | G38: =G37 -> -83.375572 | H38: =H37 -> -140.93896 | I38: =I37 -> -105.38214 | J38: =J37 -> 0 | K38: =K37 -> 0 | L38: =L37 -> 0 | ... BL38: =BL37 -> 0
A40: =SUM(E40:BL40) -> 161.55137 | B40: Commerical Loan 1 - Additions | C40: Rs Cr | E40: =Working!E102 -> 0 | F40: =Working!F102 -> 0 | G40: =Working!G102 -> 40.85403 | H40: =Working!H102 -> 69.060093 | I40: =Working!I102 -> 51.637248 | J40: =Working!J102 -> 0 | K40: =Working!K102 -> 0 | L40: =Working!L102 -> 0 | ... BL40: =Working!BL102 -> 0
A41: =SUM(E41:BL41) -> 0 | B41: Commercial Loan 2 - Additions | C41: Rs Cr | E41: =Working!E112 -> 0 | F41: =Working!F112 -> 0 | G41: =Working!G112 -> 0 | H41: =Working!H112 -> 0 | I41: =Working!I112 -> 0 | J41: =Working!J112 -> 0 | K41: =Working!K112 -> 0 | L41: =Working!L112 -> 0 | ... BL41: =Working!BL112 -> 0
A42: =SUM(E42:BL42) -> 98.909002 | B42: Grant | C42: Rs Cr | E42: =Working!E73 -> 0 | F42: =Working!F73 -> 0 | G42: =Working!G73 -> 21.750651 | H42: =Working!H73 -> 47.646166 | I42: =Working!I73 -> 13.704864 | J42: =Working!J73 -> 15.807321 | K42: =Working!K73 -> 0 | L42: =Working!L73 -> 0 | ... BL42: =Working!BL73 -> 0
A43: =SUM(E43:BL43) -> 0 | B43: Equity | C43: Rs Cr | E43: =Working!E371 -> 0 | F43: =Working!F371 -> 0 | G43: =Working!G371 -> 0 | H43: =Working!H371 -> 0 | I43: =Working!I371 -> 0 | J43: =Working!J371 -> 0 | K43: =Working!K371 -> 0 | L43: =Working!L371 -> 0 | ... BL43: =Working!BL371 -> 0
A44: =SUM(E44:BL44) -> 69.236302 | B44: Upfront Contribution from Developer | E44: =Working!E81 -> 0 | F44: =Working!F81 -> 0 | G44: =Working!G81 -> 20.770891 | H44: =Working!H81 -> 24.232706 | I44: =Working!I81 -> 40.040026 | J44: =Working!J81 -> -15.807321 | K44: =Working!K81 -> 0 | L44: =Working!L81 -> 0 | ... BL44: =Working!BL81 -> 0
A45: =SUM(E45:BL45) -> 1.0835777e-13 | B45: Cash Deficit Loan | C45: Rs Cr | E45: =Working!E384 -> 0 | F45: =Working!F384 -> 0 | G45: =Working!G384 -> 0 | H45: =Working!H384 -> 0 | I45: =Working!I384 -> 0 | J45: =Working!J384 -> 3.5527137e-15 | K45: =Working!K384 -> 0 | L45: =Working!L384 -> 4.4408921e-16 | ... BL45: =Working!BL384 -> 0
A46: =SUM(E46:BL46) -> -161.55137 | B46: Commerical Loan 1 - Repayment | C46: Rs Cr | E46: =-Working!E103 -> 0 | F46: =-Working!F103 -> 0 | G46: =-Working!G103 -> 0 | H46: =-Working!H103 -> 0 | I46: =-Working!I103 -> 0 | J46: =-Working!J103 -> 0 | K46: =-Working!K103 -> 0 | L46: =-Working!L103 -> -5.3850457 | ... BL46: =-Working!BL103 -> 0
A47: =SUM(E47:BL47) -> 0 | B47: Commercial Loan 2 - Repayment | C47: Rs Cr | E47: =-Working!E113 -> 0 | F47: =-Working!F113 -> 0 | G47: =-Working!G113 -> 0 | H47: =-Working!H113 -> 0 | I47: =-Working!I113 -> 0 | J47: =-Working!J113 -> 0 | K47: =-Working!K113 -> 0 | L47: =-Working!L113 -> 0 | ... BL47: =-Working!BL113 -> 0
A48: =SUM(E48:BL48) -> 0 | B48: Bridge Loan | C48: Rs Cr | E48: =Working!E92 -> 0 | F48: =Working!F92 -> 0 | G48: =Working!G92 -> 0 | H48: =Working!H92 -> 0 | I48: =Working!I92 -> 0 | J48: =Working!J92 -> 0 | K48: =Working!K92 -> 0 | L48: =Working!L92 -> 0 | ... BL48: =Working!BL92 -> 0
A49: =SUM(E49:BL49) -> 0 | B49: Bridge Loan - Repayment | C49: Rs Cr | E49: =-Working!E93 -> 0 | F49: =-Working!F93 -> 0 | G49: =-Working!G93 -> 0 | H49: =-Working!H93 -> 0 | I49: =-Working!I93 -> 0 | J49: =-Working!J93 -> 0 | K49: =-Working!K93 -> 0 | L49: =-Working!L93 -> 0 | ... BL49: =-Working!BL93 -> 0
A50: =SUM(E50:BL50) -> 0 | B50: Interest on Bridge Loan | C50: Rs Cr | E50: =-Working!E98 -> 0 | F50: =-Working!F98 -> 0 | G50: =-Working!G98 -> 0 | H50: =-Working!H98 -> 0 | I50: =-Working!I98 -> 0 | J50: =-Working!J98 -> 0 | K50: =-Working!K98 -> 0 | L50: =-Working!L98 -> 0 | ... BL50: =-Working!BL98 -> 0
A51: =SUM(E51:BL51) -> -1.0835777e-13 | B51: Cash Deficit Loan Repayment | C51: Rs Cr | E51: =Working!E385 -> 0 | F51: =Working!F385 -> 0 | G51: =Working!G385 -> 0 | H51: =Working!H385 -> 0 | I51: =Working!I385 -> 0 | J51: =Working!J385 -> 0 | K51: =Working!K385 -> 0 | L51: =Working!L385 -> 0 | ... BL51: =Working!BL385 -> 0
A52: =SUM(E52:BL52) -> 2.4470499 | B52: Change in WC Loan | C52: Rs Cr | E52: =(Working!E321-Working!D321)*Working!E5 -> 0 | F52: =(Working!F321-Working!E321)*Working!F5 -> 0 | G52: =(Working!G321-Working!F321)*Working!G5 -> 0 | H52: =(Working!H321-Working!G321)*Working!H5 -> 0 | I52: =(Working!I321-Working!H321)*Working!I5 -> 0 | J52: =(Working!J321-Working!I321)*Working!J5 -> 3.1517023 | K52: =(Working!K321-Working!J321)*Working!K5 -> -1.4179449 | L52: =(Working!L321-Working!K321)*Working!L5 -> 1.5098565 | ... BL52: =(Working!BL321-Working!BK321)*Working!BL5 -> 0
A53: =SUM(E53:BL53) -> -109.85493 | B53: Interest on Debt | C53: Rs Cr | E53: =-E14 -> 0 | F53: =-F14 -> 0 | G53: =-G14 -> 0 | H53: =-H14 -> 0 | I53: =-I14 -> 0 | J53: =-J14 -> -6.4620548 | K53: =-K14 -> -6.4620548 | L53: =-L14 -> -6.3543539 | ... BL53: =-BL14 -> 0
A54: =SUM(E54:BL54) -> -5.7242344 | B54: Interest on WC Loan | C54: Rs Cr | E54: =-E15 -> 0 | F54: =-F15 -> 0 | G54: =-G15 -> 0 | H54: =-H15 -> 0 | I54: =-I15 -> 0 | J54: =-J15 -> -0.15758511 | K54: =-K15 -> -0.086687868 | L54: =-L15 -> -0.16218069 | ... BL54: =-BL15 -> 0
A55: =SUM(E55:BL55) -> -8.7170271e-14 | B55: Interest on Cash Deficit Loan | C55: Rs Cr | E55: =-E16 -> 0 | F55: =-F16 -> 0 | G55: =-G16 -> 0 | H55: =-H16 -> 0 | I55: =-I16 -> 0 | J55: =-J16 -> 0 | K55: =-K16 -> -1.5987212e-16 | L55: =-L16 -> -1.5987212e-16 | ... BL55: =-BL16 -> 0
B56: Cash Flow from Financing Activities | C56: Rs Cr | E56: =SUM(E40:E55) -> 0 | F56: =SUM(F40:F55) -> 0 | G56: =SUM(G40:G55) -> 83.375572 | H56: =SUM(H40:H55) -> 140.93896 | I56: =SUM(I40:I55) -> 105.38214 | J56: =SUM(J40:J55) -> -3.4679376 | K56: =SUM(K40:K55) -> -7.9666876 | L56: =SUM(L40:L55) -> -10.391724 | ... BL56: =SUM(BL40:BL55) -> 0
B58: Cash Schedule
B59: Opening cash balance | C59: Rs Cr | E59: =D61 -> 0 | F59: =E61 -> 0 | G59: =F61 -> 0 | H59: =G61 -> 0 | I59: =H61 -> 0 | J59: =I61 -> 0 | K59: =J61 -> 3 | L59: =K61 -> 3 | ... BL59: =BK61 -> 3
B60: Cash generated during the year | C60: Rs Cr | E60: =E35+E38+E56 -> 0 | F60: =F35+F38+F56 -> 0 | G60: =G35+G38+G56 -> 0 | H60: =H35+H38+H56 -> 0 | I60: =I35+I38+I56 -> 0 | J60: =J35+J38+J56 -> 3 | K60: =K35+K38+K56 -> 0 | L60: =L35+L38+L56 -> 0 | ... BL60: =BL35+BL38+BL56 -> 0
B61: Closing Cash Balance | C61: Rs Cr | E61: =E59+E60 -> 0 | F61: =F59+F60 -> 0 | G61: =G59+G60 -> 0 | H61: =H59+H60 -> 0 | I61: =I59+I60 -> 0 | J61: =J59+J60 -> 3 | K61: =K59+K60 -> 3 | L61: =L59+L60 -> 3 | ... BL61: =BL59+BL60 -> 3
A63: Balance Sheet Statement
A64: Assets
B65: GFA | C65: Rs Cr | E65: =Working!E233 -> 0 | F65: =Working!F233 -> 0 | G65: =Working!G233 -> 0 | H65: =Working!H233 -> 0 | I65: =Working!I233 -> 0 | J65: =Working!J233 -> 329.69667 | K65: =Working!K233 -> 329.69667 | L65: =Working!L233 -> 329.69667 | ... BL65: =Working!BL233 -> 329.69667
B66: Accumulated Depreciation | C66: Rs Cr | E66: =D66+E12 -> 0 | F66: =E66+F12 -> 0 | G66: =F66+G12 -> 0 | H66: =G66+H12 -> 0 | I66: =H66+I12 -> 0 | J66: =I66+J12 -> 9.0822329 | K66: =J66+K12 -> 18.164466 | L66: =K66+L12 -> 27.246699 | ... BL66: =BK66+BL12 -> 202.9313
B67: Net Fixed Assets | C67: Rs Cr | E67: =E65-E66 -> 0 | F67: =F65-F66 -> 0 | G67: =G65-G66 -> 0 | H67: =H65-H66 -> 0 | I67: =I65-I66 -> 0 | J67: =J65-J66 -> 320.61444 | K67: =K65-K66 -> 311.53221 | L67: =L65-L66 -> 302.44998 | ... BL67: =BL65-BL66 -> 126.76538
B68: CWIP | C68: Rs Cr | E68: =Working!E226 -> 0 | F68: =Working!F226 -> 0 | G68: =Working!G226 -> 83.375572 | H68: =Working!H226 -> 224.31454 | I68: =Working!I226 -> 329.69667 | J68: =Working!J226 -> 0 | K68: =Working!K226 -> 0 | L68: =Working!L226 -> 0 | ... BL68: =Working!BL226 -> 0
B70: Current Assets | C70: Rs Cr | E70: =D70-E34 -> 0 | F70: =E70-F34 -> 0 | G70: =F70-G34 -> 0 | H70: =G70-H34 -> 0 | I70: =H70-I34 -> 0 | J70: =I70-J34 -> 4.2022697 | K70: =J70-K34 -> 2.3116765 | L70: =K70-L34 -> 4.3248185 | ... BL70: =BK70-BL34 -> 3.2627332
B71: DSRA | C71: Rs Cr | E71: =D71-E31 -> 0 | F71: =E71-F31 -> 0 | G71: =F71-G31 -> 0 | H71: =G71-H31 -> 0 | I71: =H71-I31 -> 0 | J71: =I71-J31 -> 6.4620548 | K71: =J71-K31 -> 6.4620548 | L71: =K71-L31 -> 11.7394 | ... BL71: =BK71-BL31 -> 0
B72: Cash & Bank Balance | C72: Rs Cr | E72: =E61 -> 0 | F72: =F61 -> 0 | G72: =G61 -> 0 | H72: =H61 -> 0 | I72: =I61 -> 0 | J72: =J61 -> 3 | K72: =K61 -> 3 | L72: =L61 -> 3 | ... BL72: =BL61 -> 3
B74: TOTAL ASSETS | C74: Rs Cr | E74: =SUM(E67:E72) -> 0 | F74: =SUM(F67:F72) -> 0 | G74: =SUM(G67:G72) -> 83.375572 | H74: =SUM(H67:H72) -> 224.31454 | I74: =SUM(I67:I72) -> 329.69667 | J74: =SUM(J67:J72) -> 334.27877 | K74: =SUM(K67:K72) -> 323.30594 | L74: =SUM(L67:L72) -> 321.51419 | ... BL74: =SUM(BL67:BL72) -> 133.02811
A76: Liabilities
B77: Equity | C77: Rs Cr | E77: =D77+E43 -> 0 | F77: =E77+F43 -> 0 | G77: =F77+G43 -> 0 | H77: =G77+H43 -> 0 | I77: =H77+I43 -> 0 | J77: =I77+J43 -> 0 | K77: =J77+K43 -> 0 | L77: =K77+L43 -> 0 | ... BL77: =BK77+BL43 -> 0
B78: Reserve and Surplus | C78: Rs Cr | E78: =D78+E23 -> 0 | F78: =E78+F23 -> 0 | G78: =F78+G23 -> 0 | H78: =G78+H23 -> 0 | I78: =H78+I23 -> 0 | J78: =I78+J23 -> 1.4303894 | K78: =J78+K23 -> -8.1244918 | L78: =K78+L23 -> -6.0410487 | ... BL78: =BK78+BL23 -> -37.564243
B80: Grants | C80: Rs Cr | E80: =D80+E42 -> 0 | F80: =E80+F42 -> 0 | G80: =F80+G42 -> 21.750651 | H80: =G80+H42 -> 69.396818 | I80: =H80+I42 -> 83.101682 | J80: =I80+J42 -> 98.909002 | K80: =J80+K42 -> 98.909002 | L80: =K80+L42 -> 98.909002 | ... BL80: =BK80+BL42 -> 98.909002
B81: Upfront contribution from developer | C81: Rs Cr | E81: =D81+E44 -> 0 | F81: =E81+F44 -> 0 | G81: =F81+G44 -> 20.770891 | H81: =G81+H44 -> 45.003596 | I81: =H81+I44 -> 85.043622 | J81: =I81+J44 -> 69.236302 | K81: =J81+K44 -> 69.236302 | L81: =K81+L44 -> 69.236302 | ... BL81: =BK81+BL44 -> 69.236302
B82: Commercial Loan 1 | C82: Rs Cr | E82: =Working!E104 -> 0 | F82: =Working!F104 -> 0 | G82: =Working!G104 -> 40.85403 | H82: =Working!H104 -> 109.91412 | I82: =Working!I104 -> 161.55137 | J82: =Working!J104 -> 161.55137 | K82: =Working!K104 -> 161.55137 | L82: =Working!L104 -> 156.16632 | ... BL82: =Working!BL104 -> 0
B83: Commercial Loan 2 | C83: Rs Cr | E83: =Working!E114 -> 0 | F83: =Working!F114 -> 0 | G83: =Working!G114 -> 0 | H83: =Working!H114 -> 0 | I83: =Working!I114 -> 0 | J83: =Working!J114 -> 0 | K83: =Working!K114 -> 0 | L83: =Working!L114 -> 0 | ... BL83: =Working!BL114 -> 0
B84: Bridge Loan | C84: Rs Cr | E84: =D84+E48+E49 -> 0 | F84: =E84+F48+F49 -> 0 | G84: =F84+G48+G49 -> 0 | H84: =G84+H48+H49 -> 0 | I84: =H84+I48+I49 -> 0 | J84: =I84+J48+J49 -> 0 | K84: =J84+K48+K49 -> 0 | L84: =K84+L48+L49 -> 0 | ... BL84: =BK84+BL48+BL49 -> 0
B86: Working Capital Loan | C86: Rs Cr | E86: =D86+E52 -> 0 | F86: =E86+F52 -> 0 | G86: =F86+G52 -> 0 | H86: =G86+H52 -> 0 | I86: =H86+I52 -> 0 | J86: =I86+J52 -> 3.1517023 | K86: =J86+K52 -> 1.7337574 | L86: =K86+L52 -> 3.2436138 | ... BL86: =BK86+BL52 -> 2.4470499
B87: Cash Deficit Loan | C87: Rs Cr | E87: =Working!E386 -> 0 | F87: =Working!F386 -> 0 | G87: =Working!G386 -> 0 | H87: =Working!H386 -> 0 | I87: =Working!I386 -> 0 | J87: =Working!J386 -> 3.5527137e-15 | K87: =Working!K386 -> 3.5527137e-15 | L87: =Working!L386 -> 3.9968029e-15 | ... BL87: =Working!BL386 -> 0
B89: TOTAL LIABILITIES | C89: Rs Cr | E89: =SUM(E77:E87) -> 0 | F89: =SUM(F77:F87) -> 0 | G89: =SUM(G77:G87) -> 83.375572 | H89: =SUM(H77:H87) -> 224.31454 | I89: =SUM(I77:I87) -> 329.69667 | J89: =SUM(J77:J87) -> 334.27877 | K89: =SUM(K77:K87) -> 323.30594 | L89: =SUM(L77:L87) -> 321.51419 | ... BL89: =SUM(BL77:BL87) -> 133.02811
B91: Check | C91: Rs Cr | E91: =E74-E89 -> 0 | F91: =F74-F89 -> 0 | G91: =G74-G89 -> 0 | H91: =H74-H89 -> 0 | I91: =I74-I89 -> 0 | J91: =J74-J89 -> 0 | K91: =K74-K89 -> 0 | L91: =L74-L89 -> 0 | ... BL91: =BL74-BL89 -> 3.126388e-13
A93: DSCR
B94: PAT | C94: Rs Cr | D94: =SUM(E94:BL94) -> -37.564243 | E94: =E23 -> 0 | F94: =F23 -> 0 | G94: =G23 -> 0 | H94: =H23 -> 0 | I94: =I23 -> 0 | J94: =J23 -> 1.4303894 | K94: =K23 -> -9.5548812 | L94: =L23 -> 2.0834431 | ... BL94: =BL23 -> 0
B95: Depreciation | C95: Rs Cr | D95: =SUM(E95:BL95) -> 202.9313 | E95: =E12 -> 0 | F95: =F12 -> 0 | G95: =G12 -> 0 | H95: =H12 -> 0 | I95: =I12 -> 0 | J95: =J12 -> 9.0822329 | K95: =K12 -> 9.0822329 | L95: =L12 -> 9.0822329 | ... BL95: =BL12 -> 0
B96: Interest on Debt | C96: Rs Cr | D96: =SUM(E96:BL96) -> 109.85493 | E96: =E14 -> 0 | F96: =F14 -> 0 | G96: =G14 -> 0 | H96: =H14 -> 0 | I96: =I14 -> 0 | J96: =J14 -> 6.4620548 | K96: =K14 -> 6.4620548 | L96: =L14 -> 6.3543539 | ... BL96: =BL14 -> 0
B97: Total | C97: Rs Cr | D97: =SUM(E97:BL97) -> 275.22199 | E97: =SUM(E94:E96) -> 0 | F97: =SUM(F94:F96) -> 0 | G97: =SUM(G94:G96) -> 0 | H97: =SUM(H94:H96) -> 0 | I97: =SUM(I94:I96) -> 0 | J97: =SUM(J94:J96) -> 16.974677 | K97: =SUM(K94:K96) -> 5.9894065 | L97: =SUM(L94:L96) -> 17.52003 | ... BL97: =SUM(BL94:BL96) -> 0
B99: Interest on Debt | C99: Rs Cr | D99: =SUM(E99:BL99) -> 109.85493 | E99: =E14 -> 0 | F99: =F14 -> 0 | G99: =G14 -> 0 | H99: =H14 -> 0 | I99: =I14 -> 0 | J99: =J14 -> 6.4620548 | K99: =K14 -> 6.4620548 | L99: =L14 -> 6.3543539 | ... BL99: =BL14 -> 0
B100: Debt Repayment | C100: Rs Cr | D100: =SUM(E100:BL100) -> 161.55137 | E100: =-E46-E47 -> 0 | F100: =-F46-F47 -> 0 | G100: =-G46-G47 -> 0 | H100: =-H46-H47 -> 0 | I100: =-I46-I47 -> 0 | J100: =-J46-J47 -> 0 | K100: =-K46-K47 -> 0 | L100: =-L46-L47 -> 5.3850457 | ... BL100: =-BL46-BL47 -> 0
B101: Total | C101: Rs Cr | D101: =SUM(E101:BL101) -> 271 | E101: =ROUND(SUM(E99:E100),0) -> 0 | F101: =ROUND(SUM(F99:F100),0) -> 0 | G101: =ROUND(SUM(G99:G100),0) -> 0 | H101: =ROUND(SUM(H99:H100),0) -> 0 | I101: =ROUND(SUM(I99:I100),0) -> 0 | J101: =ROUND(SUM(J99:J100),0) -> 6 | K101: =ROUND(SUM(K99:K100),0) -> 6 | L101: =ROUND(SUM(L99:L100),0) -> 12 | ... BL101: =ROUND(SUM(BL99:BL100),0) -> 0
B103: DSCR | C103: # | E103: =IF(E101,E97/E101,0) -> 0 | F103: =IF(F101,F97/F101,0) -> 0 | G103: =IF(G101,G97/G101,0) -> 0 | H103: =IF(H101,H97/H101,0) -> 0 | I103: =IF(I101,I97/I101,0) -> 0 | J103: =IF(J101,J97/J101,0) -> 2.8291128 | K103: =IF(K101,K97/K101,0) -> 0.99823442 | L103: =IF(L101,L97/L101,0) -> 1.4600025 | ... BL103: =IF(BL101,BL97/BL101,0) -> 0
B104: Average DSCR | C104: # | D104: =SUMIFS(E97:BL97,E101:BL101,">0")/SUM(E101:BL101) -> 1.014634
B105: Minimum DSCR | C105: # | D105: =_xlfn.MINIFS($E$103:$BL$103,Working!$E$6:$BL$6,">0",Working!$E$6:$BL$6,"<="&((Inputs!$E$52+Inputs!$E$51)*2)) -> -0.097456772
A110: Comprehensive Charges
B111: Payment from Developer | E111: =E2 -> 44469 | F111: =F2 -> 44651 | G111: =G2 -> 44834 | H111: =H2 -> 45016 | I111: =I2 -> 45199 | J111: =J2 -> 45382 | K111: =K2 -> 45565 | L111: =L2 -> 45747 | ... BL111: =BL2 -> 55243
B112: Upfront Charges | C112: =SUM(E112:BL112) -> 69.236302 | E112: =E44 -> 0 | F112: =F44 -> 0 | G112: =G44 -> 20.770891 | H112: =H44 -> 24.232706 | I112: =I44 -> 40.040026 | J112: =J44 -> -15.807321 | K112: =K44 -> 0 | L112: =L44 -> 0 | ... BL112: =BL44 -> 0
B113: Solar Park Charges | C113: =SUM(E113:BL113) -> 594.64035 | E113: =E26 -> 0 | F113: =F26 -> 0 | G113: =G26 -> 0 | H113: =H26 -> 0 | I113: =I26 -> 0 | J113: =J26 -> 21.25647 | K113: =K26 -> 9.8409561 | L113: =L26 -> 21.846455 | ... BL113: =BL26 -> 0
B114: Total | C114: =SUM(C112:C113) -> 663.87665
B115: Capex including IDC | C115: =SUM(E115:BL115) -> 329.69667 | E115: =Dashboard!G14 -> 329.69667
A117: Modified Comprehensive Charges
B118: Payment from Developer | E118: =E111 -> 44469 | F118: =F111 -> 44651 | G118: =G111 -> 44834 | H118: =H111 -> 45016 | I118: =I111 -> 45199 | J118: =J111 -> 45382 | K118: =K111 -> 45565 | L118: =L111 -> 45747 | ... BL118: =BL111 -> 55243
B119: less: A&G Charges | C119: =SUM(E119:BL119) -> -56.582387 | E119: =-Working!E303 -> 0 | F119: =-Working!F303 -> 0 | G119: =-Working!G303 -> 0 | H119: =-Working!H303 -> 0 | I119: =-Working!I303 -> 0 | J119: =-Working!J303 -> -0.58554004 | K119: =-Working!K303 -> -0.6 | L119: =-Working!L303 -> -0.61481705 | ... BL119: =-Working!BL303 -> 0
B120: Upfront Charges | C120: =SUM(E120:BL120) -> 69.236302 | E120: =E112 -> 0 | F120: =F112 -> 0 | G120: =G112 -> 20.770891 | H120: =H112 -> 24.232706 | I120: =I112 -> 40.040026 | J120: =J112 -> -15.807321 | K120: =K112 -> 0 | L120: =L112 -> 0 | ... BL120: =BL112 -> 0
B121: Solar Park Charges | C121: =SUM(E121:BL121) -> 538.05796 | E121: =E113+E119 -> 0 | F121: =F113+F119 -> 0 | G121: =G113+G119 -> 0 | H121: =H113+H119 -> 0 | I121: =I113+I119 -> 0 | J121: =J113+J119 -> 20.67093 | K121: =K113+K119 -> 9.2409561 | L121: =L113+L119 -> 21.231638 | ... BL121: =BL113+BL119 -> 0
...

Sheet Charges_Schedule
B2: Comprehensive Park Charges | D2: Modified Comprehensive Park Charges
A3: Semi-annual park charges post CoD in INR lakhs | B3: Charges (INR Lakhs) | D3: Charges (INR Lakhs)
A4: Execution Date + 15 days | B4: =Dashboard!K5*100 -> 2077.0891 | D4: =Dashboard!O5*100 -> 2077.0891 | F4: =D4+D5+D6 -> 8504.3622
A5: Execution Date + 0.5 years | B5: =Dashboard!K6*100 -> 2423.2706 | D5: =Dashboard!O6*100 -> 2423.2706 | F5: =F4/600 -> 14.173937
A6: Execution Date + 1 year | B6: =Dashboard!K7*100 -> 4004.0026 | D6: =Dashboard!O7*100 -> 4004.0026
A7: COD | G7: 0 | H7: =G7+0.5 -> 0.5 | I7: =H7+0.5 -> 1 | J7: =I7+0.5 -> 1.5 | K7: =J7+0.5 -> 2 | L7: =K7+0.5 -> 2.5 | M7: =L7+0.5 -> 3 | N7: =M7+0.5 -> 3.5 | O7: =N7+0.5 -> 4 | ... BD7: =BC7+0.5 -> 24.5
A8: Unit CoD + 1 day | B8: =Dashboard!K10*100 -> 544.91489 | D8: =Dashboard!O10*100 -> 486.36089 | G8: 632.02868 | H8: 986.02739 | I8: 2189.945 | J8: 1494.1735 | K8: 1506.6054 | L8: 1488.1606 | M8: 1471.1861 | N8: 1454.2684 | O8: 1437.4717 | P8: 1420.7953 | Q8: 1404.2416 | R8: 1388.3443 | S8: 1372.0176 | T8: 1355.8502 | U8: 1339.8132 | V8: 1323.9107 | W8: 1308.1451 | X8: 1292.5189 | Y8: 1277.0346 | Z8: 1261.6948 | AA8: 1246.5022 | AB8: 1231.4595 | AC8: 1216.5694 | AD8: 1201.8347 | AE8: 1187.2583 | AF8: 1172.843 | AG8: 1158.5919 | AH8: 1236.3274 | AI8: 1217.5185 | AJ8: 1204.0389 | AK8: 1190.461 | AL8: 517.37072 | AM8: 582.45327 | AN8: 590.46672 | AO8: 601.17558 | AP8: 611.96794 | AQ8: 622.96182 | AR8: 634.1558 | AS8: 645.55379 | AT8: 657.1595 | AU8: 668.97676 | AV8: 681.00944 | AW8: 693.26148 | AX8: 705.73691 | AY8: 718.43983 | AZ8: 731.37441 | BA8: 744.5449 | BB8: 757.95562 | BC8: 771.61098 | BD8: 785.51546
A9: Unit CoD + 0.5 years + 1 day | B9: =Dashboard!K11*100 -> 984.09561 | D9: =Dashboard!O11*100 -> 924.09561 | G9: =IF(G7<1,1,1/(1+8%)^(G7-1)) -> 1 | H9: =IF(H7<1,1,1/(1+8%)^(H7-1)) -> 1 | I9: =IF(I7<1,1,1/(1+8%)^(I7-1)) -> 1 | J9: =IF(J7<1,1,1/(1+8%)^(J7-1)) -> 0.96225045 | K9: =IF(K7<1,1,1/(1+8%)^(K7-1)) -> 0.92592593 | L9: =IF(L7<1,1,1/(1+8%)^(L7-1)) -> 0.89097264 | M9: =IF(M7<1,1,1/(1+8%)^(M7-1)) -> 0.85733882 | N9: =IF(N7<1,1,1/(1+8%)^(N7-1)) -> 0.82497466 | ... BD9: =IF(BD7<1,1,1/(1+8%)^(BD7-1)) -> 0.16388596
A10: Unit CoD + 1 years + 1 day | B10: =Dashboard!K12*100 -> 2184.6455 | D10: =Dashboard!O12*100 -> 2123.1638 | G10: =G8*G9 -> 632.02868 | H10: =H8*H9 -> 986.02739 | I10: =I8*I9 -> 2189.945 | J10: =J8*J9 -> 1437.7691 | K10: =K8*K9 -> 1395.005 | L10: =L8*L9 -> 1325.9104 | M10: =M8*M9 -> 1261.3049 | N10: =N8*N9 -> 1199.7346 | ... BD10: =BD8*BD9 -> 128.73495
A11: Unit CoD + 1.5 years + 1 day | B11: =Dashboard!K13*100 -> 1495.5944 | D11: =Dashboard!O13*100 -> 1432.5944 | G11: =SUM(G10:BD10) -> 29439.91
A12: Unit CoD + 2 years + 1 day | B12: =Dashboard!K14*100 -> 1511.6414 | D12: =Dashboard!O14*100 -> 1447.0856 | G12: =G11/600 -> 49.066516
A13: Unit CoD + 2.5 years + 1 day | B13: =Dashboard!K15*100 -> 1496.9877 | D13: =Dashboard!O15*100 -> 1430.8377
A14: Unit CoD + 3 years + 1 day | B14: =Dashboard!K16*100 -> 1483.8376 | D14: =Dashboard!O16*100 -> 1416.0541 | G14: 486.36089
A15: Unit CoD + 3.5 years + 1 day | B15: =Dashboard!K17*100 -> 1470.785 | D15: =Dashboard!O17*100 -> 1401.3275 | G15: 924.09561
A16: Unit CoD + 4 years + 1 day | B16: =Dashboard!K18*100 -> 1457.8947 | D16: =Dashboard!O18*100 -> 1386.7219 | G16: 2123.1638
A17: Unit CoD + 4.5 years + 1 day | B17: =Dashboard!K19*100 -> 1445.167 | D17: =Dashboard!O19*100 -> 1372.2366 | G17: 1432.5944
A18: Unit CoD + 5 years + 1 day | B18: =Dashboard!K20*100 -> 1432.6055 | D18: =Dashboard!O20*100 -> 1357.8741 | G18: 1447.0856
A19: Unit CoD + 5.5 years + 1 day | B19: =Dashboard!K21*100 -> 1421.2371 | D19: =Dashboard!O21*100 -> 1344.6602 | G19: 1430.8377
A20: Unit CoD + 6 years + 1 day | B20: =Dashboard!K22*100 -> 1408.9664 | D20: =Dashboard!O22*100 -> 1330.4984 | G20: 1416.0541
A21: Unit CoD + 6.5 years + 1 day | B21: =Dashboard!K23*100 -> 1396.9293 | D21: =Dashboard!O23*100 -> 1316.5235 | G21: 1401.3275
A22: Unit CoD + 7 years + 1 day | B22: =Dashboard!K24*100 -> 1385.069 | D22: =Dashboard!O24*100 -> 1302.6776 | G22: 1386.7219
A23: Unit CoD + 7.5 years + 1 day | B23: =Dashboard!K25*100 -> 1373.3922 | D23: =Dashboard!O25*100 -> 1288.9662 | G23: 1372.2366
A24: Unit CoD + 8 years + 1 day | B24: =Dashboard!K26*100 -> 1361.9026 | D24: =Dashboard!O26*100 -> 1275.3917 | G24: 1357.8741
A25: Unit CoD + 8.5 years + 1 day | B25: =Dashboard!K27*100 -> 1350.6039 | D25: =Dashboard!O27*100 -> 1261.9566 | G25: 1344.6602
... A57: Unit CoD + 24.5 years + 1 day | B57: =Dashboard!K59*100 -> 978.9558 | D57: =Dashboard!O59*100 -> 785.4498 | G57: 705.67318
G58: 718.37578
G59: 731.31004
G60: 744.48021
G61: 757.89061
G62: 771.54564
G63: 785.4498
